Workbook

Sheet Read Me
A1: FleetPods Alberta Phase 1 - PPP Financial Model (BASIC / WORKING VERSION)
A4: Built to maximize institutional credibility using this engagement's available inputs and standard Canadian project-finance conventions. See below for exactly what was added.
A7: SITE-LEVEL DETAIL
A8: All 8 sites are modelled individually (Site Detail tab).
A9: Capex is the Business Case's exact per-site figure. Stall/pod counts and opex were scaled from the typology averages by each site's capex share (e.g. a site 8% above its typology's average capex gets 8% more stalls/pods/opex) this is this model's own estimate, not client-confirmed per-site data (none exists yet), and should be replaced once real site-level surveys exist.
A13: SENIOR + MEZZANINE DEBT
A14: Debt is split 55% senior (6.0%) / 15% mezzanine (11.5%, senior + 550bps, per the Business Case's stated mezzanine pricing convention) / 30% equity, blended to ~7.2%. This is a BLENDED-RATE simplification (both tranches amortise on the same schedule) rather than two fully separate schedules with different tenors/priorities a full build would size and amortise each tranche separately once real lenders are engaged.
A20: DSRA, WORKING CAPITAL, TERMINAL VALUE
A21: DSRA: 6 months of debt service, funded by an additional equity call at Year 4, released back to equity at the end of the debt tenor (Year 26).
A23: Working capital: 5% of annual opex, built up from first year of operations and fully released in Year 30, flowing through CFADS.
A25: Terminal value: 6.0x final-year EBITDA, paid to equity in Year 30 a standard simplified proxy for the network's ongoing value beyond the 30-year concession (no formal residual valuationhas been done; this multiple is this model's own placeholder assumption, flagged for review).
A29: SCULPTED DEBT REPAYMENT
... A67: Red = flagged/solved cell needing validation

Sheet Executive Summary
A1: EXECUTIVE SUMMARY : FleetPods Alberta Phase 1 Financial Model
A4: Overview
A5: FleetPods proposes an 8-site truck parking, rest-pod, and driver-service network across Alberta's principal freight corridors, with a total program capital cost of CAD 155.1M (2026 real terms). The network combines one flagship Mega Hub (Calgary-Airdrie), three Regional Hubs (West Edmonton-Acheson, Red Deer, Fort McMurray-Suncor), and four lighter Infill Gateway Hubs (Seebe-Cochrane, Brooks, Medicine Hat, Whitecourt-Fox Creek), financed on a 70% debt / 30% equity structure over a 30-year concession.
A10: The Core Question: Can User Fees Alone Make This Bankable?
A11: No. This model tests two funding structures side by side and finds that commercial revenue (parking, recovery pods, fleet subscriptions, digital platform, ancillary services) cannot on its own service the debt required to build the network. Under a user-funded-only structure (Case A), minimum DSCR is negative and averages 0.13x across the concession that is far below the 1.0x break-even threshold lenders require, let alone the 1.35x typically needed for investment-grade project debt.
A16: The Case for an Availability Payment
A17: Introducing a government availability payment (Case B), sized to deliver both a 1.35x minimum DSCR and a 12-15% equity IRR, restores the project to bankable metrics: 1.56x minimum DSCR, 13.5% equity IRR. The steady-state availability payment required is approximately CAD 18.4M/year consistent with the range the client's own Business Case had anticipated (CAD 15-25M/year).
A21: Sensitivity testing confirms this conclusion holds under downside scenarios (weaker traffic/occupancy,higher capex, higher interest rates):
A22: Case A remains unbankable in every scenario tested, while
A23: Case B remains resilient because the availability payment mechanism flexes with underlying performance.
A25: Status of This Model
A26: This is a working financial model built using Business Case figures, the original project brief, and standard Canadian project-finance and CCA/tax conventions. Every assumption is clearly flagged (see Assumptions tab and Read Me tab) and colour-coded (blue = input, red = flagged/solved). Two items in particular should be confirmed or refined before this goes to government:
... A39: Case B minimum DSCR 1.50x, equity IRR 13.5%, steady-state availability payment ~CAD 20.3M/year, present value of availability payments to the public authority ~CAD 212.2M over 30 years. See Read Me for full detail on every addition and the one remaining structuring concern (LLCR dips to 0.78x near debt maturity).

Sheet Dashboard
A1: FLEETPODS ALBERTA PHASE 1 : RESULTS DASHBOARD
A3: $155.1M program - 8 sites - 30-year concession - Case A vs Case B (PPP + Availability Payment)
B5: TOTAL PROGRAM CAPEX | D5: DEBT / EQUITY SPLIT | F5: MIN DSCR - CASE A (no AP) | H5: MIN DSCR - CASE B (with AP)
B6: =Summary!B4 -> 155 | D6: =Summary!B5&" / "&Summary!B6 -> 108.5 / 46.5 | F6: =Summary!B10 -> -1.0731362 | H6: =Summary!C10 -> 1.5046072
B8: EQUITY IRR - CASE A | D8: EQUITY IRR - CASE B | F8: STEADY-STATE AVAIL. PAYMENT | H8: DISCOUNTED PAYBACK - CASE B
B9: =Summary!B12 -> -0.12159604 | D9: =Summary!C12 -> 0.13503208 | F9: =Summary!B16 -> 20.277156 | H9: =Summary!C32 -> 30
B11: WHY AN AVAILABILITY PAYMENT IS REQUIRED
B12: Under Case A (user-fees only), the project cannot service its own debt: DSCR is negative in most operating years and averages well below the 1.0x break-even line across the 30-year concession.
B14: Under Case B, an availability payment sized to deliver both a 1.35x minimum DSCR AND a 12-15% equity IRR restores the project to bankable, investment-grade metrics without relying on user fees.
B17: DSCR PROFILE, CASE A vs CASE B (Years 5-30)

Sheet Assumptions
A1: ASSUMPTIONS
A3: 1. GENERAL & TIMING
A5: Study year | B5: 2026
A6: Concession start year | B6: 2027
A7: Concession life (years) | B7: 30
A8: Construction period (years) | B8: 4
A9: Gateway sites operational from Year | B9: 3
A10: Regional & Corridor-support sites operational from Year | B10: 4
A12: 2. SITE COUNTS & TYPOLOGY (Business Case Reference Case, $155M)
A14: Typology | B14: Count | C14: Capex/site $M | D14: Opex/site $M/yr
A15: Mega Hub (Calgary-Airdrie) | B15: 1 | C15: 53 | D15: 12
A16: Regional Hub (avg of 3) | B16: 3 | C16: 16.7 | D16: 3.73
A17: Infill Gateway Hub (avg of 4) | B17: 4 | C17: 7.85 | D17: 1.84
A18: Platform/Network Opex (steady-state) | B18: 2.6 | C18: $M/yr
A20: 3. CAPEX PHASING (% of site capex spent each construction year)
A22: Year of construction -> | B22: Year 1 | C22: Year 2 | D22: Year 3 | E22: Year 4
A23: Mega Hub phasing | B23: 0.2 | C23: 0.4 | D23: 0.4 | E23: 0
A24: Regional / Infill phasing | B24: 0.1 | C24: 0.3 | D24: 0.4 | E24: 0.2
A26: 4. PARKING REVENUE (steady-state; network total = 1,380 spaces per Business Case)
A28: Typology | B28: Stalls/site | C28: Occupancy % | D28: Rate $/stall-hr
A29: Mega Hub | B29: 460 | C29: 0.6 | D29: 8.5
A30: Regional (avg) | B30: 180 | C30: 0.5 | D30: 8.5
A31: Infill (avg) | B31: 80 | C31: 0.4 | D31: 8.5
A33: 5. RECOVERY POD REVENUE
A35: Typology | B35: Pods/site | C35: Occ. Yr5 of ops | D35: Occ. Yr10+ of ops | E35: Rate $/session
A36: Mega Hub | B36: 50 | C36: 0.45 | D36: 0.7 | E36: 125
A37: Regional (avg) | B37: 35 | C37: 0.4 | D37: 0.65 | E37: 125
A38: Infill (avg) | B38: 20 | C38: 0.35 | D38: 0.6 | E38: 125
A40: 6. FLEET SUBSCRIPTIONS & DIGITAL PLATFORM (network-level)
A42: Fleet count - Year 3 of concession | B42: 50
A43: Fleet count - Year 10+ of concession | B43: 140
A44: Average fee ($/fleet/month) | B44: 3250
A45: Digital platform revenue - Year 3 ($M) | B45: 0.6
A46: Digital platform revenue - Year 10+ ($M) | B46: 1.85
A48: 7. OTHER / ANCILLARY REVENUE (fuel, EV, food - simplified single line, $M/site/yr steady-state)
A50: Gateway | B50: 1.5
A51: Regional | B51: 0.5
A52: Corridor-support | B52: 0.2
A54: 8. RAMP-UP PROFILE (parking & ancillary revenue - % of steady-state, by years since site opened)
A56: Years since opening -> | B56: Yr 1 | C56: Yr 2 | D56: Yr 3 | E56: Yr 4 | F56: Yr 5+
A57: Ramp factor | B57: 0.6 | C57: 0.7 | D57: 0.85 | E57: 0.95 | F57: 1
A59: 9. FINANCING STRUCTURE
A61: Equity % | B61: 0.3
A62: Debt % | B62: 0.7
A63: Blended debt rate (auto-calculated from Senior + Mezzanine below) | B63: =(B102*B103+B104*B105)/(B102+B104) -> 0.071785714
A64: Debt tenor (years, from Year 5) | B64: 22
A65: Grace period (years, interest capitalised) | B65: 4
A66: Target minimum DSCR | B66: 1.35
A68: 10. TAX & INFLATION
A70: Corporate tax rate (Alberta + Federal, combined) | B70: 0.25
A71: Revenue / cost indexation (annual) | B71: 0.025
A73: 11. SCENARIO TOGGLES (sensitivity switches - 0 = base case)
A75: Traffic / occupancy adjustment | B75: 0
A76: Capex adjustment | B76: 0
A77: Interest rate adjustment (bps) | B77: 0
A79: 12. REVENUE CALIBRATION FACTOR (FLAG - see Read Me)
A80: Parking + Pod revenue calibration factor | B80: 0.42
A82: 13. PROGRAMWIDE CAPEX (client-requested separate line items, per Business Case)
A84: Digital Platform & Program Management ($M) | B84: 11.6
A85: Contingency / 9th-site reserve ($M) | B85: 9
A87: 14. CCA / DEPRECIATION CLASSES (standard CRA classes, declining balance, half-year rule)
A89: Class | B89: Rate | C89: % of Total Capex
A90: Class 1 - Buildings | B90: 0.04 | C90: 0.4
A91: Class 17 - Paving/parking lots | B91: 0.08 | C91: 0.25
A92: Class 8 - Furniture/fixtures/pod units | B92: 0.2 | C92: 0.2
A93: Class 43.1 - Clean energy/EV equipment | B93: 0.3 | C93: 0.1
A94: Class 50 - Computer/digital equipment | B94: 0.55 | C94: 0.05
A96: 15. AVAILABILITY PAYMENT : EQUITY IRR FLOOR (client requirement: DSCR AND equity IRR)
A98: Target equity IRR (midpoint of 12-15% range) | B98: 0.135
A99: AP flat top-up ($M/yr, operating years SOLVED, see Read Me) | B99: 6.44
A101: 16. SENIOR + MEZZANINE DEBT STRUCTURE (per Business Case)
A102: Senior debt % of total capital | B102: 0.55
A103: Senior debt rate (nominal) | B103: 0.06
A104: Mezzanine debt % of total capital | B104: 0.15
A105: Mezzanine debt rate (nominal, senior + 550bps) | B105: 0.115
A107: 17. DSRA / WORKING CAPITAL / TERMINAL VALUE (added for high-level build)
A108: DSRA target (months of debt service, funded from debt/equity at Yr4) | B108: 6
A109: Working capital (% of annual opex, held from first year of ops) | B109: 0.05
A110: Terminal value (x of final-year EBITDA, paid to equity in Yr 30) | B110: 6

Sheet Site Detail
A1: SITE-BY-SITE DETAIL (8 sites individually, per Business Case Reference Case)
A2: Stall/pod counts scaled from typology averages by each site's capex share (blue = input, editable per site).
A4: Site | B4: Capex $M | C4: Open Yr | D4: Stalls | E4: Park Occ% | F4: Park Rate | G4: Pods | H4: Pod Occ5 | I4: Pod Occ10 | J4: Pod Rate | K4: Opex $M/yr | L4: Other $M/yr
A5: Calgary-Airdrie (Mega) | B5: 53 | C5: 3 | D5: 460 | E5: 0.6 | F5: 8.5 | G5: 50 | H5: 0.45 | I5: 0.7 | J5: 125 | K5: 12 | L5: 1.5
A6: West Edmonton-Acheson | B6: 18 | C6: 4 | D6: 194 | E6: 0.5 | F6: 8.5 | G6: 38 | H6: 0.4 | I6: 0.65 | J6: 125 | K6: 4.028 | L6: 0.54
A7: Red Deer | B7: 16 | C7: 4 | D7: 173 | E7: 0.5 | F7: 8.5 | G7: 34 | H7: 0.4 | I7: 0.65 | J7: 125 | K7: 3.581 | L7: 0.48
A8: Fort McMurray-Suncor | B8: 16 | C8: 4 | D8: 173 | E8: 0.5 | F8: 8.5 | G8: 34 | H8: 0.4 | I8: 0.65 | J8: 125 | K8: 3.581 | L8: 0.48
A9: Seebe-Cochrane | B9: 8.2 | C9: 4 | D9: 84 | E9: 0.4 | F9: 8.5 | G9: 21 | H9: 0.35 | I9: 0.6 | J9: 125 | K9: 1.922 | L9: 0.209
A10: Brooks | B10: 7.7 | C10: 4 | D10: 79 | E10: 0.4 | F10: 8.5 | G10: 20 | H10: 0.35 | I10: 0.6 | J10: 125 | K10: 1.805 | L10: 0.196
A11: Medicine Hat | B11: 7.7 | C11: 4 | D11: 79 | E11: 0.4 | F11: 8.5 | G11: 20 | H11: 0.35 | I11: 0.6 | J11: 125 | K11: 1.805 | L11: 0.196
A12: Whitecourt-Fox Creek | B12: 7.8 | C12: 4 | D12: 80 | E12: 0.4 | F12: 8.5 | G12: 20 | H12: 0.35 | I12: 0.6 | J12: 125 | K12: 1.828 | L12: 0.199
A14: PER-SITE 30-YEAR SCHEDULES ($M)
A16: Calgary-Airdrie (Mega) - Years since opening | D16: =IF(Model!D3>=$C$5,Model!D3-$C$5+1,0) -> 0 | E16: =IF(Model!E3>=$C$5,Model!E3-$C$5+1,0) -> 0 | F16: =IF(Model!F3>=$C$5,Model!F3-$C$5+1,0) -> 1 | G16: =IF(Model!G3>=$C$5,Model!G3-$C$5+1,0) -> 2 | H16: =IF(Model!H3>=$C$5,Model!H3-$C$5+1,0) -> 3 | I16: =IF(Model!I3>=$C$5,Model!I3-$C$5+1,0) -> 4 | J16: =IF(Model!J3>=$C$5,Model!J3-$C$5+1,0) -> 5 | K16: =IF(Model!K3>=$C$5,Model!K3-$C$5+1,0) -> 6 | ... AG16: =IF(Model!AG3>=$C$5,Model!AG3-$C$5+1,0) -> 28
A17: Calgary-Airdrie (Mega) - Capex | D17: =IF(Model!D3<=4,$B$5*INDEX(Assumptions!$B$23:$E$23,Model!D3),0)*(1+Assumptions!$B$76) -> 10.6 | E17: =IF(Model!E3<=4,$B$5*INDEX(Assumptions!$B$23:$E$23,Model!E3),0)*(1+Assumptions!$B$76) -> 21.2 | F17: =IF(Model!F3<=4,$B$5*INDEX(Assumptions!$B$23:$E$23,Model!F3),0)*(1+Assumptions!$B$76) -> 21.2 | G17: =IF(Model!G3<=4,$B$5*INDEX(Assumptions!$B$23:$E$23,Model!G3),0)*(1+Assumptions!$B$76) -> 0 | H17: =IF(Model!H3<=4,$B$5*INDEX(Assumptions!$B$23:$E$23,Model!H3),0)*(1+Assumptions!$B$76) -> 0 | I17: =IF(Model!I3<=4,$B$5*INDEX(Assumptions!$B$23:$E$23,Model!I3),0)*(1+Assumptions!$B$76) -> 0 | J17: =IF(Model!J3<=4,$B$5*INDEX(Assumptions!$B$23:$E$23,Model!J3),0)*(1+Assumptions!$B$76) -> 0 | K17: =IF(Model!K3<=4,$B$5*INDEX(Assumptions!$B$23:$E$23,Model!K3),0)*(1+Assumptions!$B$76) -> 0 | ... AG17: =IF(Model!AG3<=4,$B$5*INDEX(Assumptions!$B$23:$E$23,Model!AG3),0)*(1+Assumptions!$B$76) -> 0
A18: Calgary-Airdrie (Mega) - Parking Revenue | D18: =$D$5*$E$5*(1+Assumptions!$B$75)*IF(D16<=0,0,INDEX(Assumptions!$B$57:$F$57,MIN(D16,5)))*8760*$F$5*(1+Assumptions!$B$71)^(Model!D3-1)*Assumptions!$B$80/1000000 -> 0 | E18: =$D$5*$E$5*(1+Assumptions!$B$75)*IF(E16<=0,0,INDEX(Assumptions!$B$57:$F$57,MIN(E16,5)))*8760*$F$5*(1+Assumptions!$B$71)^(Model!E3-1)*Assumptions!$B$80/1000000 -> 0 | F18: =$D$5*$E$5*(1+Assumptions!$B$75)*IF(F16<=0,0,INDEX(Assumptions!$B$57:$F$57,MIN(F16,5)))*8760*$F$5*(1+Assumptions!$B$71)^(Model!F3-1)*Assumptions!$B$80/1000000 -> 5.4410208 | G18: =$D$5*$E$5*(1+Assumptions!$B$75)*IF(G16<=0,0,INDEX(Assumptions!$B$57:$F$57,MIN(G16,5)))*8760*$F$5*(1+Assumptions!$B$71)^(Model!G3-1)*Assumptions!$B$80/1000000 -> 6.506554 | H18: =$D$5*$E$5*(1+Assumptions!$B$75)*IF(H16<=0,0,INDEX(Assumptions!$B$57:$F$57,MIN(H16,5)))*8760*$F$5*(1+Assumptions!$B$71)^(Model!H3-1)*Assumptions!$B$80/1000000 -> 8.098336 | I18: =$D$5*$E$5*(1+Assumptions!$B$75)*IF(I16<=0,0,INDEX(Assumptions!$B$57:$F$57,MIN(I16,5)))*8760*$F$5*(1+Assumptions!$B$71)^(Model!I3-1)*Assumptions!$B$80/1000000 -> 9.2773584 | J18: =$D$5*$E$5*(1+Assumptions!$B$75)*IF(J16<=0,0,INDEX(Assumptions!$B$57:$F$57,MIN(J16,5)))*8760*$F$5*(1+Assumptions!$B$71)^(Model!J3-1)*Assumptions!$B$80/1000000 -> 10.009781 | K18: =$D$5*$E$5*(1+Assumptions!$B$75)*IF(K16<=0,0,INDEX(Assumptions!$B$57:$F$57,MIN(K16,5)))*8760*$F$5*(1+Assumptions!$B$71)^(Model!K3-1)*Assumptions!$B$80/1000000 -> 10.260026 | ... AG18: =$D$5*$E$5*(1+Assumptions!$B$75)*IF(AG16<=0,0,INDEX(Assumptions!$B$57:$F$57,MIN(AG16,5)))*8760*$F$5*(1+Assumptions!$B$71)^(Model!AG3-1)*Assumptions!$B$80/1000000 -> 17.663367
A19: Calgary-Airdrie (Mega) - Pod Revenue | D19: =$G$5*(IF(D16<=0,0,IF(D16<=5,$H$5/5*D16,IF(D16<=10,$H$5+($I$5-$H$5)*(D16-5)/5,$I$5))))*365*(1+Assumptions!$B$75)*$J$5*(1+Assumptions!$B$71)^(Model!D3-1)*Assumptions!$B$80/1000000 -> 0 | E19: =$G$5*(IF(E16<=0,0,IF(E16<=5,$H$5/5*E16,IF(E16<=10,$H$5+($I$5-$H$5)*(E16-5)/5,$I$5))))*365*(1+Assumptions!$B$75)*$J$5*(1+Assumptions!$B$71)^(Model!E3-1)*Assumptions!$B$80/1000000 -> 0 | F19: =$G$5*(IF(F16<=0,0,IF(F16<=5,$H$5/5*F16,IF(F16<=10,$H$5+($I$5-$H$5)*(F16-5)/5,$I$5))))*365*(1+Assumptions!$B$75)*$J$5*(1+Assumptions!$B$71)^(Model!F3-1)*Assumptions!$B$80/1000000 -> 0.090596707 | G19: =$G$5*(IF(G16<=0,0,IF(G16<=5,$H$5/5*G16,IF(G16<=10,$H$5+($I$5-$H$5)*(G16-5)/5,$I$5))))*365*(1+Assumptions!$B$75)*$J$5*(1+Assumptions!$B$71)^(Model!G3-1)*Assumptions!$B$80/1000000 -> 0.18572325 | H19: =$G$5*(IF(H16<=0,0,IF(H16<=5,$H$5/5*H16,IF(H16<=10,$H$5+($I$5-$H$5)*(H16-5)/5,$I$5))))*365*(1+Assumptions!$B$75)*$J$5*(1+Assumptions!$B$71)^(Model!H3-1)*Assumptions!$B$80/1000000 -> 0.2855495 | I19: =$G$5*(IF(I16<=0,0,IF(I16<=5,$H$5/5*I16,IF(I16<=10,$H$5+($I$5-$H$5)*(I16-5)/5,$I$5))))*365*(1+Assumptions!$B$75)*$J$5*(1+Assumptions!$B$71)^(Model!I3-1)*Assumptions!$B$80/1000000 -> 0.39025098 | J19: =$G$5*(IF(J16<=0,0,IF(J16<=5,$H$5/5*J16,IF(J16<=10,$H$5+($I$5-$H$5)*(J16-5)/5,$I$5))))*365*(1+Assumptions!$B$75)*$J$5*(1+Assumptions!$B$71)^(Model!J3-1)*Assumptions!$B$80/1000000 -> 0.50000907 | K19: =$G$5*(IF(K16<=0,0,IF(K16<=5,$H$5/5*K16,IF(K16<=10,$H$5+($I$5-$H$5)*(K16-5)/5,$I$5))))*365*(1+Assumptions!$B$75)*$J$5*(1+Assumptions!$B$71)^(Model!K3-1)*Assumptions!$B$80/1000000 -> 0.56945477 | ... AG19: =$G$5*(IF(AG16<=0,0,IF(AG16<=5,$H$5/5*AG16,IF(AG16<=10,$H$5+($I$5-$H$5)*(AG16-5)/5,$I$5))))*365*(1+Assumptions!$B$75)*$J$5*(1+Assumptions!$B$71)^(Model!AG3-1)*Assumptions!$B$80/1000000 -> 1.3724999
A20: Calgary-Airdrie (Mega) - Other/Ancillary Revenue | D20: =$L$5*IF(D16<=0,0,INDEX(Assumptions!$B$57:$F$57,MIN(D16,5)))*(1+Assumptions!$B$71)^(Model!D3-1) -> 0 | E20: =$L$5*IF(E16<=0,0,INDEX(Assumptions!$B$57:$F$57,MIN(E16,5)))*(1+Assumptions!$B$71)^(Model!E3-1) -> 0 | F20: =$L$5*IF(F16<=0,0,INDEX(Assumptions!$B$57:$F$57,MIN(F16,5)))*(1+Assumptions!$B$71)^(Model!F3-1) -> 0.9455625 | G20: =$L$5*IF(G16<=0,0,INDEX(Assumptions!$B$57:$F$57,MIN(G16,5)))*(1+Assumptions!$B$71)^(Model!G3-1) -> 1.1307352 | H20: =$L$5*IF(H16<=0,0,INDEX(Assumptions!$B$57:$F$57,MIN(H16,5)))*(1+Assumptions!$B$71)^(Model!H3-1) -> 1.4073614 | I20: =$L$5*IF(I16<=0,0,INDEX(Assumptions!$B$57:$F$57,MIN(I16,5)))*(1+Assumptions!$B$71)^(Model!I3-1) -> 1.6122567 | J20: =$L$5*IF(J16<=0,0,INDEX(Assumptions!$B$57:$F$57,MIN(J16,5)))*(1+Assumptions!$B$71)^(Model!J3-1) -> 1.7395401 | K20: =$L$5*IF(K16<=0,0,INDEX(Assumptions!$B$57:$F$57,MIN(K16,5)))*(1+Assumptions!$B$71)^(Model!K3-1) -> 1.7830286 | ... AG20: =$L$5*IF(AG16<=0,0,INDEX(Assumptions!$B$57:$F$57,MIN(AG16,5)))*(1+Assumptions!$B$71)^(Model!AG3-1) -> 3.0696111
A21: Calgary-Airdrie (Mega) - Opex | D21: =IF(D16>0,$K$5*(1+Assumptions!$B$71)^(Model!D3-1),0) -> 0 | E21: =IF(E16>0,$K$5*(1+Assumptions!$B$71)^(Model!E3-1),0) -> 0 | F21: =IF(F16>0,$K$5*(1+Assumptions!$B$71)^(Model!F3-1),0) -> 12.6075 | G21: =IF(G16>0,$K$5*(1+Assumptions!$B$71)^(Model!G3-1),0) -> 12.922687 | H21: =IF(H16>0,$K$5*(1+Assumptions!$B$71)^(Model!H3-1),0) -> 13.245755 | I21: =IF(I16>0,$K$5*(1+Assumptions!$B$71)^(Model!I3-1),0) -> 13.576899 | J21: =IF(J16>0,$K$5*(1+Assumptions!$B$71)^(Model!J3-1),0) -> 13.916321 | K21: =IF(K16>0,$K$5*(1+Assumptions!$B$71)^(Model!K3-1),0) -> 14.264229 | ... AG21: =IF(AG16>0,$K$5*(1+Assumptions!$B$71)^(Model!AG3-1),0) -> 24.556889
A23: West Edmonton-Acheson - Years since opening | D23: =IF(Model!D3>=$C$6,Model!D3-$C$6+1,0) -> 0 | E23: =IF(Model!E3>=$C$6,Model!E3-$C$6+1,0) -> 0 | F23: =IF(Model!F3>=$C$6,Model!F3-$C$6+1,0) -> 0 | G23: =IF(Model!G3>=$C$6,Model!G3-$C$6+1,0) -> 1 | H23: =IF(Model!H3>=$C$6,Model!H3-$C$6+1,0) -> 2 | I23: =IF(Model!I3>=$C$6,Model!I3-$C$6+1,0) -> 3 | J23: =IF(Model!J3>=$C$6,Model!J3-$C$6+1,0) -> 4 | K23: =IF(Model!K3>=$C$6,Model!K3-$C$6+1,0) -> 5 | ... AG23: =IF(Model!AG3>=$C$6,Model!AG3-$C$6+1,0) -> 27
A24: West Edmonton-Acheson - Capex | D24: =IF(Model!D3<=4,$B$6*INDEX(Assumptions!$B$24:$E$24,Model!D3),0)*(1+Assumptions!$B$76) -> 1.8 | E24: =IF(Model!E3<=4,$B$6*INDEX(Assumptions!$B$24:$E$24,Model!E3),0)*(1+Assumptions!$B$76) -> 5.4 | F24: =IF(Model!F3<=4,$B$6*INDEX(Assumptions!$B$24:$E$24,Model!F3),0)*(1+Assumptions!$B$76) -> 7.2 | G24: =IF(Model!G3<=4,$B$6*INDEX(Assumptions!$B$24:$E$24,Model!G3),0)*(1+Assumptions!$B$76) -> 3.6 | H24: =IF(Model!H3<=4,$B$6*INDEX(Assumptions!$B$24:$E$24,Model!H3),0)*(1+Assumptions!$B$76) -> 0 | I24: =IF(Model!I3<=4,$B$6*INDEX(Assumptions!$B$24:$E$24,Model!I3),0)*(1+Assumptions!$B$76) -> 0 | J24: =IF(Model!J3<=4,$B$6*INDEX(Assumptions!$B$24:$E$24,Model!J3),0)*(1+Assumptions!$B$76) -> 0 | K24: =IF(Model!K3<=4,$B$6*INDEX(Assumptions!$B$24:$E$24,Model!K3),0)*(1+Assumptions!$B$76) -> 0 | ... AG24: =IF(Model!AG3<=4,$B$6*INDEX(Assumptions!$B$24:$E$24,Model!AG3),0)*(1+Assumptions!$B$76) -> 0
A25: West Edmonton-Acheson - Parking Revenue | D25: =$D$6*$E$6*(1+Assumptions!$B$75)*IF(D23<=0,0,INDEX(Assumptions!$B$57:$F$57,MIN(D23,5)))*8760*$F$6*(1+Assumptions!$B$71)^(Model!D3-1)*Assumptions!$B$80/1000000 -> 0 | E25: =$D$6*$E$6*(1+Assumptions!$B$75)*IF(E23<=0,0,INDEX(Assumptions!$B$57:$F$57,MIN(E23,5)))*8760*$F$6*(1+Assumptions!$B$71)^(Model!E3-1)*Assumptions!$B$80/1000000 -> 0 | F25: =$D$6*$E$6*(1+Assumptions!$B$75)*IF(F23<=0,0,INDEX(Assumptions!$B$57:$F$57,MIN(F23,5)))*8760*$F$6*(1+Assumptions!$B$71)^(Model!F3-1)*Assumptions!$B$80/1000000 -> 0 | G25: =$D$6*$E$6*(1+Assumptions!$B$75)*IF(G23<=0,0,INDEX(Assumptions!$B$57:$F$57,MIN(G23,5)))*8760*$F$6*(1+Assumptions!$B$71)^(Model!G3-1)*Assumptions!$B$80/1000000 -> 1.9600489 | H25: =$D$6*$E$6*(1+Assumptions!$B$75)*IF(H23<=0,0,INDEX(Assumptions!$B$57:$F$57,MIN(H23,5)))*8760*$F$6*(1+Assumptions!$B$71)^(Model!H3-1)*Assumptions!$B$80/1000000 -> 2.3438918 | I25: =$D$6*$E$6*(1+Assumptions!$B$75)*IF(I23<=0,0,INDEX(Assumptions!$B$57:$F$57,MIN(I23,5)))*8760*$F$6*(1+Assumptions!$B$71)^(Model!I3-1)*Assumptions!$B$80/1000000 -> 2.9173082 | J25: =$D$6*$E$6*(1+Assumptions!$B$75)*IF(J23<=0,0,INDEX(Assumptions!$B$57:$F$57,MIN(J23,5)))*8760*$F$6*(1+Assumptions!$B$71)^(Model!J3-1)*Assumptions!$B$80/1000000 -> 3.3420339 | K25: =$D$6*$E$6*(1+Assumptions!$B$75)*IF(K23<=0,0,INDEX(Assumptions!$B$57:$F$57,MIN(K23,5)))*8760*$F$6*(1+Assumptions!$B$71)^(Model!K3-1)*Assumptions!$B$80/1000000 -> 3.6058787 | ... AG25: =$D$6*$E$6*(1+Assumptions!$B$75)*IF(AG23<=0,0,INDEX(Assumptions!$B$57:$F$57,MIN(AG23,5)))*8760*$F$6*(1+Assumptions!$B$71)^(Model!AG3-1)*Assumptions!$B$80/1000000 -> 6.2077776
A26: West Edmonton-Acheson - Pod Revenue | D26: =$G$6*(IF(D23<=0,0,IF(D23<=5,$H$6/5*D23,IF(D23<=10,$H$6+($I$6-$H$6)*(D23-5)/5,$I$6))))*365*(1+Assumptions!$B$75)*$J$6*(1+Assumptions!$B$71)^(Model!D3-1)*Assumptions!$B$80/1000000 -> 0 | E26: =$G$6*(IF(E23<=0,0,IF(E23<=5,$H$6/5*E23,IF(E23<=10,$H$6+($I$6-$H$6)*(E23-5)/5,$I$6))))*365*(1+Assumptions!$B$75)*$J$6*(1+Assumptions!$B$71)^(Model!E3-1)*Assumptions!$B$80/1000000 -> 0 | F26: =$G$6*(IF(F23<=0,0,IF(F23<=5,$H$6/5*F23,IF(F23<=10,$H$6+($I$6-$H$6)*(F23-5)/5,$I$6))))*365*(1+Assumptions!$B$75)*$J$6*(1+Assumptions!$B$71)^(Model!F3-1)*Assumptions!$B$80/1000000 -> 0 | G26: =$G$6*(IF(G23<=0,0,IF(G23<=5,$H$6/5*G23,IF(G23<=10,$H$6+($I$6-$H$6)*(G23-5)/5,$I$6))))*365*(1+Assumptions!$B$75)*$J$6*(1+Assumptions!$B$71)^(Model!G3-1)*Assumptions!$B$80/1000000 -> 0.062733186 | H26: =$G$6*(IF(H23<=0,0,IF(H23<=5,$H$6/5*H23,IF(H23<=10,$H$6+($I$6-$H$6)*(H23-5)/5,$I$6))))*365*(1+Assumptions!$B$75)*$J$6*(1+Assumptions!$B$71)^(Model!H3-1)*Assumptions!$B$80/1000000 -> 0.12860303 | I26: =$G$6*(IF(I23<=0,0,IF(I23<=5,$H$6/5*I23,IF(I23<=10,$H$6+($I$6-$H$6)*(I23-5)/5,$I$6))))*365*(1+Assumptions!$B$75)*$J$6*(1+Assumptions!$B$71)^(Model!I3-1)*Assumptions!$B$80/1000000 -> 0.19772716 | J26: =$G$6*(IF(J23<=0,0,IF(J23<=5,$H$6/5*J23,IF(J23<=10,$H$6+($I$6-$H$6)*(J23-5)/5,$I$6))))*365*(1+Assumptions!$B$75)*$J$6*(1+Assumptions!$B$71)^(Model!J3-1)*Assumptions!$B$80/1000000 -> 0.27022712 | K26: =$G$6*(IF(K23<=0,0,IF(K23<=5,$H$6/5*K23,IF(K23<=10,$H$6+($I$6-$H$6)*(K23-5)/5,$I$6))))*365*(1+Assumptions!$B$75)*$J$6*(1+Assumptions!$B$71)^(Model!K3-1)*Assumptions!$B$80/1000000 -> 0.3462285 | ... AG26: =$G$6*(IF(AG23<=0,0,IF(AG23<=5,$H$6/5*AG23,IF(AG23<=10,$H$6+($I$6-$H$6)*(AG23-5)/5,$I$6))))*365*(1+Assumptions!$B$75)*$J$6*(1+Assumptions!$B$71)^(Model!AG3-1)*Assumptions!$B$80/1000000 -> 0.96859276
A27: West Edmonton-Acheson - Other/Ancillary Revenue | D27: =$L$6*IF(D23<=0,0,INDEX(Assumptions!$B$57:$F$57,MIN(D23,5)))*(1+Assumptions!$B$71)^(Model!D3-1) -> 0 | E27: =$L$6*IF(E23<=0,0,INDEX(Assumptions!$B$57:$F$57,MIN(E23,5)))*(1+Assumptions!$B$71)^(Model!E3-1) -> 0 | F27: =$L$6*IF(F23<=0,0,INDEX(Assumptions!$B$57:$F$57,MIN(F23,5)))*(1+Assumptions!$B$71)^(Model!F3-1) -> 0 | G27: =$L$6*IF(G23<=0,0,INDEX(Assumptions!$B$57:$F$57,MIN(G23,5)))*(1+Assumptions!$B$71)^(Model!G3-1) -> 0.34891256 | H27: =$L$6*IF(H23<=0,0,INDEX(Assumptions!$B$57:$F$57,MIN(H23,5)))*(1+Assumptions!$B$71)^(Model!H3-1) -> 0.41724127 | I27: =$L$6*IF(I23<=0,0,INDEX(Assumptions!$B$57:$F$57,MIN(I23,5)))*(1+Assumptions!$B$71)^(Model!I3-1) -> 0.51931637 | J27: =$L$6*IF(J23<=0,0,INDEX(Assumptions!$B$57:$F$57,MIN(J23,5)))*(1+Assumptions!$B$71)^(Model!J3-1) -> 0.59492272 | K27: =$L$6*IF(K23<=0,0,INDEX(Assumptions!$B$57:$F$57,MIN(K23,5)))*(1+Assumptions!$B$71)^(Model!K3-1) -> 0.64189031 | ... AG27: =$L$6*IF(AG23<=0,0,INDEX(Assumptions!$B$57:$F$57,MIN(AG23,5)))*(1+Assumptions!$B$71)^(Model!AG3-1) -> 1.10506
A28: West Edmonton-Acheson - Opex | D28: =IF(D23>0,$K$6*(1+Assumptions!$B$71)^(Model!D3-1),0) -> 0 | E28: =IF(E23>0,$K$6*(1+Assumptions!$B$71)^(Model!E3-1),0) -> 0 | F28: =IF(F23>0,$K$6*(1+Assumptions!$B$71)^(Model!F3-1),0) -> 0 | G28: =IF(G23>0,$K$6*(1+Assumptions!$B$71)^(Model!G3-1),0) -> 4.3377154 | H28: =IF(H23>0,$K$6*(1+Assumptions!$B$71)^(Model!H3-1),0) -> 4.4461583 | I28: =IF(I23>0,$K$6*(1+Assumptions!$B$71)^(Model!I3-1),0) -> 4.5573123 | J28: =IF(J23>0,$K$6*(1+Assumptions!$B$71)^(Model!J3-1),0) -> 4.6712451 | K28: =IF(K23>0,$K$6*(1+Assumptions!$B$71)^(Model!K3-1),0) -> 4.7880262 | ... AG28: =IF(AG23>0,$K$6*(1+Assumptions!$B$71)^(Model!AG3-1),0) -> 8.242929
A30: Red Deer - Years since opening | D30: =IF(Model!D3>=$C$7,Model!D3-$C$7+1,0) -> 0 | E30: =IF(Model!E3>=$C$7,Model!E3-$C$7+1,0) -> 0 | F30: =IF(Model!F3>=$C$7,Model!F3-$C$7+1,0) -> 0 | G30: =IF(Model!G3>=$C$7,Model!G3-$C$7+1,0) -> 1 | H30: =IF(Model!H3>=$C$7,Model!H3-$C$7+1,0) -> 2 | I30: =IF(Model!I3>=$C$7,Model!I3-$C$7+1,0) -> 3 | J30: =IF(Model!J3>=$C$7,Model!J3-$C$7+1,0) -> 4 | K30: =IF(Model!K3>=$C$7,Model!K3-$C$7+1,0) -> 5 | ... AG30: =IF(Model!AG3>=$C$7,Model!AG3-$C$7+1,0) -> 27
A31: Red Deer - Capex | D31: =IF(Model!D3<=4,$B$7*INDEX(Assumptions!$B$24:$E$24,Model!D3),0)*(1+Assumptions!$B$76) -> 1.6 | E31: =IF(Model!E3<=4,$B$7*INDEX(Assumptions!$B$24:$E$24,Model!E3),0)*(1+Assumptions!$B$76) -> 4.8 | F31: =IF(Model!F3<=4,$B$7*INDEX(Assumptions!$B$24:$E$24,Model!F3),0)*(1+Assumptions!$B$76) -> 6.4 | G31: =IF(Model!G3<=4,$B$7*INDEX(Assumptions!$B$24:$E$24,Model!G3),0)*(1+Assumptions!$B$76) -> 3.2 | H31: =IF(Model!H3<=4,$B$7*INDEX(Assumptions!$B$24:$E$24,Model!H3),0)*(1+Assumptions!$B$76) -> 0 | I31: =IF(Model!I3<=4,$B$7*INDEX(Assumptions!$B$24:$E$24,Model!I3),0)*(1+Assumptions!$B$76) -> 0 | J31: =IF(Model!J3<=4,$B$7*INDEX(Assumptions!$B$24:$E$24,Model!J3),0)*(1+Assumptions!$B$76) -> 0 | K31: =IF(Model!K3<=4,$B$7*INDEX(Assumptions!$B$24:$E$24,Model!K3),0)*(1+Assumptions!$B$76) -> 0 | ... AG31: =IF(Model!AG3<=4,$B$7*INDEX(Assumptions!$B$24:$E$24,Model!AG3),0)*(1+Assumptions!$B$76) -> 0
A32: Red Deer - Parking Revenue | D32: =$D$7*$E$7*(1+Assumptions!$B$75)*IF(D30<=0,0,INDEX(Assumptions!$B$57:$F$57,MIN(D30,5)))*8760*$F$7*(1+Assumptions!$B$71)^(Model!D3-1)*Assumptions!$B$80/1000000 -> 0 | E32: =$D$7*$E$7*(1+Assumptions!$B$75)*IF(E30<=0,0,INDEX(Assumptions!$B$57:$F$57,MIN(E30,5)))*8760*$F$7*(1+Assumptions!$B$71)^(Model!E3-1)*Assumptions!$B$80/1000000 -> 0 | F32: =$D$7*$E$7*(1+Assumptions!$B$75)*IF(F30<=0,0,INDEX(Assumptions!$B$57:$F$57,MIN(F30,5)))*8760*$F$7*(1+Assumptions!$B$71)^(Model!F3-1)*Assumptions!$B$80/1000000 -> 0 | G32: =$D$7*$E$7*(1+Assumptions!$B$75)*IF(G30<=0,0,INDEX(Assumptions!$B$57:$F$57,MIN(G30,5)))*8760*$F$7*(1+Assumptions!$B$71)^(Model!G3-1)*Assumptions!$B$80/1000000 -> 1.7478786 | H32: =$D$7*$E$7*(1+Assumptions!$B$75)*IF(H30<=0,0,INDEX(Assumptions!$B$57:$F$57,MIN(H30,5)))*8760*$F$7*(1+Assumptions!$B$71)^(Model!H3-1)*Assumptions!$B$80/1000000 -> 2.0901715 | I32: =$D$7*$E$7*(1+Assumptions!$B$75)*IF(I30<=0,0,INDEX(Assumptions!$B$57:$F$57,MIN(I30,5)))*8760*$F$7*(1+Assumptions!$B$71)^(Model!I3-1)*Assumptions!$B$80/1000000 -> 2.6015171 | J32: =$D$7*$E$7*(1+Assumptions!$B$75)*IF(J30<=0,0,INDEX(Assumptions!$B$57:$F$57,MIN(J30,5)))*8760*$F$7*(1+Assumptions!$B$71)^(Model!J3-1)*Assumptions!$B$80/1000000 -> 2.9802674 | K32: =$D$7*$E$7*(1+Assumptions!$B$75)*IF(K30<=0,0,INDEX(Assumptions!$B$57:$F$57,MIN(K30,5)))*8760*$F$7*(1+Assumptions!$B$71)^(Model!K3-1)*Assumptions!$B$80/1000000 -> 3.2155516 | ... AG32: =$D$7*$E$7*(1+Assumptions!$B$75)*IF(AG30<=0,0,INDEX(Assumptions!$B$57:$F$57,MIN(AG30,5)))*8760*$F$7*(1+Assumptions!$B$71)^(Model!AG3-1)*Assumptions!$B$80/1000000 -> 5.5358017
A33: Red Deer - Pod Revenue | D33: =$G$7*(IF(D30<=0,0,IF(D30<=5,$H$7/5*D30,IF(D30<=10,$H$7+($I$7-$H$7)*(D30-5)/5,$I$7))))*365*(1+Assumptions!$B$75)*$J$7*(1+Assumptions!$B$71)^(Model!D3-1)*Assumptions!$B$80/1000000 -> 0 | E33: =$G$7*(IF(E30<=0,0,IF(E30<=5,$H$7/5*E30,IF(E30<=10,$H$7+($I$7-$H$7)*(E30-5)/5,$I$7))))*365*(1+Assumptions!$B$75)*$J$7*(1+Assumptions!$B$71)^(Model!E3-1)*Assumptions!$B$80/1000000 -> 0 | F33: =$G$7*(IF(F30<=0,0,IF(F30<=5,$H$7/5*F30,IF(F30<=10,$H$7+($I$7-$H$7)*(F30-5)/5,$I$7))))*365*(1+Assumptions!$B$75)*$J$7*(1+Assumptions!$B$71)^(Model!F3-1)*Assumptions!$B$80/1000000 -> 0 | G33: =$G$7*(IF(G30<=0,0,IF(G30<=5,$H$7/5*G30,IF(G30<=10,$H$7+($I$7-$H$7)*(G30-5)/5,$I$7))))*365*(1+Assumptions!$B$75)*$J$7*(1+Assumptions!$B$71)^(Model!G3-1)*Assumptions!$B$80/1000000 -> 0.056129693 | H33: =$G$7*(IF(H30<=0,0,IF(H30<=5,$H$7/5*H30,IF(H30<=10,$H$7+($I$7-$H$7)*(H30-5)/5,$I$7))))*365*(1+Assumptions!$B$75)*$J$7*(1+Assumptions!$B$71)^(Model!H3-1)*Assumptions!$B$80/1000000 -> 0.11506587 | I33: =$G$7*(IF(I30<=0,0,IF(I30<=5,$H$7/5*I30,IF(I30<=10,$H$7+($I$7-$H$7)*(I30-5)/5,$I$7))))*365*(1+Assumptions!$B$75)*$J$7*(1+Assumptions!$B$71)^(Model!I3-1)*Assumptions!$B$80/1000000 -> 0.17691378 | J33: =$G$7*(IF(J30<=0,0,IF(J30<=5,$H$7/5*J30,IF(J30<=10,$H$7+($I$7-$H$7)*(J30-5)/5,$I$7))))*365*(1+Assumptions!$B$75)*$J$7*(1+Assumptions!$B$71)^(Model!J3-1)*Assumptions!$B$80/1000000 -> 0.24178216 | K33: =$G$7*(IF(K30<=0,0,IF(K30<=5,$H$7/5*K30,IF(K30<=10,$H$7+($I$7-$H$7)*(K30-5)/5,$I$7))))*365*(1+Assumptions!$B$75)*$J$7*(1+Assumptions!$B$71)^(Model!K3-1)*Assumptions!$B$80/1000000 -> 0.30978339 | ... AG33: =$G$7*(IF(AG30<=0,0,IF(AG30<=5,$H$7/5*AG30,IF(AG30<=10,$H$7+($I$7-$H$7)*(AG30-5)/5,$I$7))))*365*(1+Assumptions!$B$75)*$J$7*(1+Assumptions!$B$71)^(Model!AG3-1)*Assumptions!$B$80/1000000 -> 0.86663563
A34: Red Deer - Other/Ancillary Revenue | D34: =$L$7*IF(D30<=0,0,INDEX(Assumptions!$B$57:$F$57,MIN(D30,5)))*(1+Assumptions!$B$71)^(Model!D3-1) -> 0 | E34: =$L$7*IF(E30<=0,0,INDEX(Assumptions!$B$57:$F$57,MIN(E30,5)))*(1+Assumptions!$B$71)^(Model!E3-1) -> 0 | F34: =$L$7*IF(F30<=0,0,INDEX(Assumptions!$B$57:$F$57,MIN(F30,5)))*(1+Assumptions!$B$71)^(Model!F3-1) -> 0 | G34: =$L$7*IF(G30<=0,0,INDEX(Assumptions!$B$57:$F$57,MIN(G30,5)))*(1+Assumptions!$B$71)^(Model!G3-1) -> 0.3101445 | H34: =$L$7*IF(H30<=0,0,INDEX(Assumptions!$B$57:$F$57,MIN(H30,5)))*(1+Assumptions!$B$71)^(Model!H3-1) -> 0.37088113 | I34: =$L$7*IF(I30<=0,0,INDEX(Assumptions!$B$57:$F$57,MIN(I30,5)))*(1+Assumptions!$B$71)^(Model!I3-1) -> 0.46161455 | J34: =$L$7*IF(J30<=0,0,INDEX(Assumptions!$B$57:$F$57,MIN(J30,5)))*(1+Assumptions!$B$71)^(Model!J3-1) -> 0.5288202 | K34: =$L$7*IF(K30<=0,0,INDEX(Assumptions!$B$57:$F$57,MIN(K30,5)))*(1+Assumptions!$B$71)^(Model!K3-1) -> 0.57056916 | ... AG34: =$L$7*IF(AG30<=0,0,INDEX(Assumptions!$B$57:$F$57,MIN(AG30,5)))*(1+Assumptions!$B$71)^(Model!AG3-1) -> 0.98227555
A35: Red Deer - Opex | D35: =IF(D30>0,$K$7*(1+Assumptions!$B$71)^(Model!D3-1),0) -> 0 | E35: =IF(E30>0,$K$7*(1+Assumptions!$B$71)^(Model!E3-1),0) -> 0 | F35: =IF(F30>0,$K$7*(1+Assumptions!$B$71)^(Model!F3-1),0) -> 0 | G35: =IF(G30>0,$K$7*(1+Assumptions!$B$71)^(Model!G3-1),0) -> 3.8563453 | H35: =IF(H30>0,$K$7*(1+Assumptions!$B$71)^(Model!H3-1),0) -> 3.952754 | I35: =IF(I30>0,$K$7*(1+Assumptions!$B$71)^(Model!I3-1),0) -> 4.0515728 | J35: =IF(J30>0,$K$7*(1+Assumptions!$B$71)^(Model!J3-1),0) -> 4.1528621 | K35: =IF(K30>0,$K$7*(1+Assumptions!$B$71)^(Model!K3-1),0) -> 4.2566837 | ... AG35: =IF(AG30>0,$K$7*(1+Assumptions!$B$71)^(Model!AG3-1),0) -> 7.3281849
A37: Fort McMurray-Suncor - Years since opening | D37: =IF(Model!D3>=$C$8,Model!D3-$C$8+1,0) -> 0 | E37: =IF(Model!E3>=$C$8,Model!E3-$C$8+1,0) -> 0 | F37: =IF(Model!F3>=$C$8,Model!F3-$C$8+1,0) -> 0 | G37: =IF(Model!G3>=$C$8,Model!G3-$C$8+1,0) -> 1 | H37: =IF(Model!H3>=$C$8,Model!H3-$C$8+1,0) -> 2 | I37: =IF(Model!I3>=$C$8,Model!I3-$C$8+1,0) -> 3 | J37: =IF(Model!J3>=$C$8,Model!J3-$C$8+1,0) -> 4 | K37: =IF(Model!K3>=$C$8,Model!K3-$C$8+1,0) -> 5 | ... AG37: =IF(Model!AG3>=$C$8,Model!AG3-$C$8+1,0) -> 27
A38: Fort McMurray-Suncor - Capex | D38: =IF(Model!D3<=4,$B$8*INDEX(Assumptions!$B$24:$E$24,Model!D3),0)*(1+Assumptions!$B$76) -> 1.6 | E38: =IF(Model!E3<=4,$B$8*INDEX(Assumptions!$B$24:$E$24,Model!E3),0)*(1+Assumptions!$B$76) -> 4.8 | F38: =IF(Model!F3<=4,$B$8*INDEX(Assumptions!$B$24:$E$24,Model!F3),0)*(1+Assumptions!$B$76) -> 6.4 | G38: =IF(Model!G3<=4,$B$8*INDEX(Assumptions!$B$24:$E$24,Model!G3),0)*(1+Assumptions!$B$76) -> 3.2 | H38: =IF(Model!H3<=4,$B$8*INDEX(Assumptions!$B$24:$E$24,Model!H3),0)*(1+Assumptions!$B$76) -> 0 | I38: =IF(Model!I3<=4,$B$8*INDEX(Assumptions!$B$24:$E$24,Model!I3),0)*(1+Assumptions!$B$76) -> 0 | J38: =IF(Model!J3<=4,$B$8*INDEX(Assumptions!$B$24:$E$24,Model!J3),0)*(1+Assumptions!$B$76) -> 0 | K38: =IF(Model!K3<=4,$B$8*INDEX(Assumptions!$B$24:$E$24,Model!K3),0)*(1+Assumptions!$B$76) -> 0 | ... AG38: =IF(Model!AG3<=4,$B$8*INDEX(Assumptions!$B$24:$E$24,Model!AG3),0)*(1+Assumptions!$B$76) -> 0
A39: Fort McMurray-Suncor - Parking Revenue | D39: =$D$8*$E$8*(1+Assumptions!$B$75)*IF(D37<=0,0,INDEX(Assumptions!$B$57:$F$57,MIN(D37,5)))*8760*$F$8*(1+Assumptions!$B$71)^(Model!D3-1)*Assumptions!$B$80/1000000 -> 0 | E39: =$D$8*$E$8*(1+Assumptions!$B$75)*IF(E37<=0,0,INDEX(Assumptions!$B$57:$F$57,MIN(E37,5)))*8760*$F$8*(1+Assumptions!$B$71)^(Model!E3-1)*Assumptions!$B$80/1000000 -> 0 | F39: =$D$8*$E$8*(1+Assumptions!$B$75)*IF(F37<=0,0,INDEX(Assumptions!$B$57:$F$57,MIN(F37,5)))*8760*$F$8*(1+Assumptions!$B$71)^(Model!F3-1)*Assumptions!$B$80/1000000 -> 0 | G39: =$D$8*$E$8*(1+Assumptions!$B$75)*IF(G37<=0,0,INDEX(Assumptions!$B$57:$F$57,MIN(G37,5)))*8760*$F$8*(1+Assumptions!$B$71)^(Model!G3-1)*Assumptions!$B$80/1000000 -> 1.7478786 | H39: =$D$8*$E$8*(1+Assumptions!$B$75)*IF(H37<=0,0,INDEX(Assumptions!$B$57:$F$57,MIN(H37,5)))*8760*$F$8*(1+Assumptions!$B$71)^(Model!H3-1)*Assumptions!$B$80/1000000 -> 2.0901715 | I39: =$D$8*$E$8*(1+Assumptions!$B$75)*IF(I37<=0,0,INDEX(Assumptions!$B$57:$F$57,MIN(I37,5)))*8760*$F$8*(1+Assumptions!$B$71)^(Model!I3-1)*Assumptions!$B$80/1000000 -> 2.6015171 | J39: =$D$8*$E$8*(1+Assumptions!$B$75)*IF(J37<=0,0,INDEX(Assumptions!$B$57:$F$57,MIN(J37,5)))*8760*$F$8*(1+Assumptions!$B$71)^(Model!J3-1)*Assumptions!$B$80/1000000 -> 2.9802674 | K39: =$D$8*$E$8*(1+Assumptions!$B$75)*IF(K37<=0,0,INDEX(Assumptions!$B$57:$F$57,MIN(K37,5)))*8760*$F$8*(1+Assumptions!$B$71)^(Model!K3-1)*Assumptions!$B$80/1000000 -> 3.2155516 | ... AG39: =$D$8*$E$8*(1+Assumptions!$B$75)*IF(AG37<=0,0,INDEX(Assumptions!$B$57:$F$57,MIN(AG37,5)))*8760*$F$8*(1+Assumptions!$B$71)^(Model!AG3-1)*Assumptions!$B$80/1000000 -> 5.5358017
A40: Fort McMurray-Suncor - Pod Revenue | D40: =$G$8*(IF(D37<=0,0,IF(D37<=5,$H$8/5*D37,IF(D37<=10,$H$8+($I$8-$H$8)*(D37-5)/5,$I$8))))*365*(1+Assumptions!$B$75)*$J$8*(1+Assumptions!$B$71)^(Model!D3-1)*Assumptions!$B$80/1000000 -> 0 | E40: =$G$8*(IF(E37<=0,0,IF(E37<=5,$H$8/5*E37,IF(E37<=10,$H$8+($I$8-$H$8)*(E37-5)/5,$I$8))))*365*(1+Assumptions!$B$75)*$J$8*(1+Assumptions!$B$71)^(Model!E3-1)*Assumptions!$B$80/1000000 -> 0 | F40: =$G$8*(IF(F37<=0,0,IF(F37<=5,$H$8/5*F37,IF(F37<=10,$H$8+($I$8-$H$8)*(F37-5)/5,$I$8))))*365*(1+Assumptions!$B$75)*$J$8*(1+Assumptions!$B$71)^(Model!F3-1)*Assumptions!$B$80/1000000 -> 0 | G40: =$G$8*(IF(G37<=0,0,IF(G37<=5,$H$8/5*G37,IF(G37<=10,$H$8+($I$8-$H$8)*(G37-5)/5,$I$8))))*365*(1+Assumptions!$B$75)*$J$8*(1+Assumptions!$B$71)^(Model!G3-1)*Assumptions!$B$80/1000000 -> 0.056129693 | H40: =$G$8*(IF(H37<=0,0,IF(H37<=5,$H$8/5*H37,IF(H37<=10,$H$8+($I$8-$H$8)*(H37-5)/5,$I$8))))*365*(1+Assumptions!$B$75)*$J$8*(1+Assumptions!$B$71)^(Model!H3-1)*Assumptions!$B$80/1000000 -> 0.11506587 | I40: =$G$8*(IF(I37<=0,0,IF(I37<=5,$H$8/5*I37,IF(I37<=10,$H$8+($I$8-$H$8)*(I37-5)/5,$I$8))))*365*(1+Assumptions!$B$75)*$J$8*(1+Assumptions!$B$71)^(Model!I3-1)*Assumptions!$B$80/1000000 -> 0.17691378 | J40: =$G$8*(IF(J37<=0,0,IF(J37<=5,$H$8/5*J37,IF(J37<=10,$H$8+($I$8-$H$8)*(J37-5)/5,$I$8))))*365*(1+Assumptions!$B$75)*$J$8*(1+Assumptions!$B$71)^(Model!J3-1)*Assumptions!$B$80/1000000 -> 0.24178216 | K40: =$G$8*(IF(K37<=0,0,IF(K37<=5,$H$8/5*K37,IF(K37<=10,$H$8+($I$8-$H$8)*(K37-5)/5,$I$8))))*365*(1+Assumptions!$B$75)*$J$8*(1+Assumptions!$B$71)^(Model!K3-1)*Assumptions!$B$80/1000000 -> 0.30978339 | ... AG40: =$G$8*(IF(AG37<=0,0,IF(AG37<=5,$H$8/5*AG37,IF(AG37<=10,$H$8+($I$8-$H$8)*(AG37-5)/5,$I$8))))*365*(1+Assumptions!$B$75)*$J$8*(1+Assumptions!$B$71)^(Model!AG3-1)*Assumptions!$B$80/1000000 -> 0.86663563
A41: Fort McMurray-Suncor - Other/Ancillary Revenue | D41: =$L$8*IF(D37<=0,0,INDEX(Assumptions!$B$57:$F$57,MIN(D37,5)))*(1+Assumptions!$B$71)^(Model!D3-1) -> 0 | E41: =$L$8*IF(E37<=0,0,INDEX(Assumptions!$B$57:$F$57,MIN(E37,5)))*(1+Assumptions!$B$71)^(Model!E3-1) -> 0 | F41: =$L$8*IF(F37<=0,0,INDEX(Assumptions!$B$57:$F$57,MIN(F37,5)))*(1+Assumptions!$B$71)^(Model!F3-1) -> 0 | G41: =$L$8*IF(G37<=0,0,INDEX(Assumptions!$B$57:$F$57,MIN(G37,5)))*(1+Assumptions!$B$71)^(Model!G3-1) -> 0.3101445 | H41: =$L$8*IF(H37<=0,0,INDEX(Assumptions!$B$57:$F$57,MIN(H37,5)))*(1+Assumptions!$B$71)^(Model!H3-1) -> 0.37088113 | I41: =$L$8*IF(I37<=0,0,INDEX(Assumptions!$B$57:$F$57,MIN(I37,5)))*(1+Assumptions!$B$71)^(Model!I3-1) -> 0.46161455 | J41: =$L$8*IF(J37<=0,0,INDEX(Assumptions!$B$57:$F$57,MIN(J37,5)))*(1+Assumptions!$B$71)^(Model!J3-1) -> 0.5288202 | K41: =$L$8*IF(K37<=0,0,INDEX(Assumptions!$B$57:$F$57,MIN(K37,5)))*(1+Assumptions!$B$71)^(Model!K3-1) -> 0.57056916 | ... AG41: =$L$8*IF(AG37<=0,0,INDEX(Assumptions!$B$57:$F$57,MIN(AG37,5)))*(1+Assumptions!$B$71)^(Model!AG3-1) -> 0.98227555
A42: Fort McMurray-Suncor - Opex | D42: =IF(D37>0,$K$8*(1+Assumptions!$B$71)^(Model!D3-1),0) -> 0 | E42: =IF(E37>0,$K$8*(1+Assumptions!$B$71)^(Model!E3-1),0) -> 0 | F42: =IF(F37>0,$K$8*(1+Assumptions!$B$71)^(Model!F3-1),0) -> 0 | G42: =IF(G37>0,$K$8*(1+Assumptions!$B$71)^(Model!G3-1),0) -> 3.8563453 | H42: =IF(H37>0,$K$8*(1+Assumptions!$B$71)^(Model!H3-1),0) -> 3.952754 | I42: =IF(I37>0,$K$8*(1+Assumptions!$B$71)^(Model!I3-1),0) -> 4.0515728 | J42: =IF(J37>0,$K$8*(1+Assumptions!$B$71)^(Model!J3-1),0) -> 4.1528621 | K42: =IF(K37>0,$K$8*(1+Assumptions!$B$71)^(Model!K3-1),0) -> 4.2566837 | ... AG42: =IF(AG37>0,$K$8*(1+Assumptions!$B$71)^(Model!AG3-1),0) -> 7.3281849
A44: Seebe-Cochrane - Years since opening | D44: =IF(Model!D3>=$C$9,Model!D3-$C$9+1,0) -> 0 | E44: =IF(Model!E3>=$C$9,Model!E3-$C$9+1,0) -> 0 | F44: =IF(Model!F3>=$C$9,Model!F3-$C$9+1,0) -> 0 | G44: =IF(Model!G3>=$C$9,Model!G3-$C$9+1,0) -> 1 | H44: =IF(Model!H3>=$C$9,Model!H3-$C$9+1,0) -> 2 | I44: =IF(Model!I3>=$C$9,Model!I3-$C$9+1,0) -> 3 | J44: =IF(Model!J3>=$C$9,Model!J3-$C$9+1,0) -> 4 | K44: =IF(Model!K3>=$C$9,Model!K3-$C$9+1,0) -> 5 | ... AG44: =IF(Model!AG3>=$C$9,Model!AG3-$C$9+1,0) -> 27
A45: Seebe-Cochrane - Capex | D45: =IF(Model!D3<=4,$B$9*INDEX(Assumptions!$B$24:$E$24,Model!D3),0)*(1+Assumptions!$B$76) -> 0.82 | E45: =IF(Model!E3<=4,$B$9*INDEX(Assumptions!$B$24:$E$24,Model!E3),0)*(1+Assumptions!$B$76) -> 2.46 | F45: =IF(Model!F3<=4,$B$9*INDEX(Assumptions!$B$24:$E$24,Model!F3),0)*(1+Assumptions!$B$76) -> 3.28 | G45: =IF(Model!G3<=4,$B$9*INDEX(Assumptions!$B$24:$E$24,Model!G3),0)*(1+Assumptions!$B$76) -> 1.64 | H45: =IF(Model!H3<=4,$B$9*INDEX(Assumptions!$B$24:$E$24,Model!H3),0)*(1+Assumptions!$B$76) -> 0 | I45: =IF(Model!I3<=4,$B$9*INDEX(Assumptions!$B$24:$E$24,Model!I3),0)*(1+Assumptions!$B$76) -> 0 | J45: =IF(Model!J3<=4,$B$9*INDEX(Assumptions!$B$24:$E$24,Model!J3),0)*(1+Assumptions!$B$76) -> 0 | K45: =IF(Model!K3<=4,$B$9*INDEX(Assumptions!$B$24:$E$24,Model!K3),0)*(1+Assumptions!$B$76) -> 0 | ... AG45: =IF(Model!AG3<=4,$B$9*INDEX(Assumptions!$B$24:$E$24,Model!AG3),0)*(1+Assumptions!$B$76) -> 0
A46: Seebe-Cochrane - Parking Revenue | D46: =$D$9*$E$9*(1+Assumptions!$B$75)*IF(D44<=0,0,INDEX(Assumptions!$B$57:$F$57,MIN(D44,5)))*8760*$F$9*(1+Assumptions!$B$71)^(Model!D3-1)*Assumptions!$B$80/1000000 -> 0 | E46: =$D$9*$E$9*(1+Assumptions!$B$75)*IF(E44<=0,0,INDEX(Assumptions!$B$57:$F$57,MIN(E44,5)))*8760*$F$9*(1+Assumptions!$B$71)^(Model!E3-1)*Assumptions!$B$80/1000000 -> 0 | F46: =$D$9*$E$9*(1+Assumptions!$B$75)*IF(F44<=0,0,INDEX(Assumptions!$B$57:$F$57,MIN(F44,5)))*8760*$F$9*(1+Assumptions!$B$71)^(Model!F3-1)*Assumptions!$B$80/1000000 -> 0 | G46: =$D$9*$E$9*(1+Assumptions!$B$75)*IF(G44<=0,0,INDEX(Assumptions!$B$57:$F$57,MIN(G44,5)))*8760*$F$9*(1+Assumptions!$B$71)^(Model!G3-1)*Assumptions!$B$80/1000000 -> 0.67894477 | H46: =$D$9*$E$9*(1+Assumptions!$B$75)*IF(H44<=0,0,INDEX(Assumptions!$B$57:$F$57,MIN(H44,5)))*8760*$F$9*(1+Assumptions!$B$71)^(Model!H3-1)*Assumptions!$B$80/1000000 -> 0.81190479 | I46: =$D$9*$E$9*(1+Assumptions!$B$75)*IF(I44<=0,0,INDEX(Assumptions!$B$57:$F$57,MIN(I44,5)))*8760*$F$9*(1+Assumptions!$B$71)^(Model!I3-1)*Assumptions!$B$80/1000000 -> 1.0105315 | J46: =$D$9*$E$9*(1+Assumptions!$B$75)*IF(J44<=0,0,INDEX(Assumptions!$B$57:$F$57,MIN(J44,5)))*8760*$F$9*(1+Assumptions!$B$71)^(Model!J3-1)*Assumptions!$B$80/1000000 -> 1.157653 | K46: =$D$9*$E$9*(1+Assumptions!$B$75)*IF(K44<=0,0,INDEX(Assumptions!$B$57:$F$57,MIN(K44,5)))*8760*$F$9*(1+Assumptions!$B$71)^(Model!K3-1)*Assumptions!$B$80/1000000 -> 1.2490466 | ... AG46: =$D$9*$E$9*(1+Assumptions!$B$75)*IF(AG44<=0,0,INDEX(Assumptions!$B$57:$F$57,MIN(AG44,5)))*8760*$F$9*(1+Assumptions!$B$71)^(Model!AG3-1)*Assumptions!$B$80/1000000 -> 2.150323
A47: Seebe-Cochrane - Pod Revenue | D47: =$G$9*(IF(D44<=0,0,IF(D44<=5,$H$9/5*D44,IF(D44<=10,$H$9+($I$9-$H$9)*(D44-5)/5,$I$9))))*365*(1+Assumptions!$B$75)*$J$9*(1+Assumptions!$B$71)^(Model!D3-1)*Assumptions!$B$80/1000000 -> 0 | E47: =$G$9*(IF(E44<=0,0,IF(E44<=5,$H$9/5*E44,IF(E44<=10,$H$9+($I$9-$H$9)*(E44-5)/5,$I$9))))*365*(1+Assumptions!$B$75)*$J$9*(1+Assumptions!$B$71)^(Model!E3-1)*Assumptions!$B$80/1000000 -> 0 | F47: =$G$9*(IF(F44<=0,0,IF(F44<=5,$H$9/5*F44,IF(F44<=10,$H$9+($I$9-$H$9)*(F44-5)/5,$I$9))))*365*(1+Assumptions!$B$75)*$J$9*(1+Assumptions!$B$71)^(Model!F3-1)*Assumptions!$B$80/1000000 -> 0 | G47: =$G$9*(IF(G44<=0,0,IF(G44<=5,$H$9/5*G44,IF(G44<=10,$H$9+($I$9-$H$9)*(G44-5)/5,$I$9))))*365*(1+Assumptions!$B$75)*$J$9*(1+Assumptions!$B$71)^(Model!G3-1)*Assumptions!$B$80/1000000 -> 0.030334797 | H47: =$G$9*(IF(H44<=0,0,IF(H44<=5,$H$9/5*H44,IF(H44<=10,$H$9+($I$9-$H$9)*(H44-5)/5,$I$9))))*365*(1+Assumptions!$B$75)*$J$9*(1+Assumptions!$B$71)^(Model!H3-1)*Assumptions!$B$80/1000000 -> 0.062186335 | I47: =$G$9*(IF(I44<=0,0,IF(I44<=5,$H$9/5*I44,IF(I44<=10,$H$9+($I$9-$H$9)*(I44-5)/5,$I$9))))*365*(1+Assumptions!$B$75)*$J$9*(1+Assumptions!$B$71)^(Model!I3-1)*Assumptions!$B$80/1000000 -> 0.09561149 | J47: =$G$9*(IF(J44<=0,0,IF(J44<=5,$H$9/5*J44,IF(J44<=10,$H$9+($I$9-$H$9)*(J44-5)/5,$I$9))))*365*(1+Assumptions!$B$75)*$J$9*(1+Assumptions!$B$71)^(Model!J3-1)*Assumptions!$B$80/1000000 -> 0.13066904 | K47: =$G$9*(IF(K44<=0,0,IF(K44<=5,$H$9/5*K44,IF(K44<=10,$H$9+($I$9-$H$9)*(K44-5)/5,$I$9))))*365*(1+Assumptions!$B$75)*$J$9*(1+Assumptions!$B$71)^(Model!K3-1)*Assumptions!$B$80/1000000 -> 0.1674197 | ... AG47: =$G$9*(IF(AG44<=0,0,IF(AG44<=5,$H$9/5*AG44,IF(AG44<=10,$H$9+($I$9-$H$9)*(AG44-5)/5,$I$9))))*365*(1+Assumptions!$B$75)*$J$9*(1+Assumptions!$B$71)^(Model!AG3-1)*Assumptions!$B$80/1000000 -> 0.49409995
A48: Seebe-Cochrane - Other/Ancillary Revenue | D48: =$L$9*IF(D44<=0,0,INDEX(Assumptions!$B$57:$F$57,MIN(D44,5)))*(1+Assumptions!$B$71)^(Model!D3-1) -> 0 | E48: =$L$9*IF(E44<=0,0,INDEX(Assumptions!$B$57:$F$57,MIN(E44,5)))*(1+Assumptions!$B$71)^(Model!E3-1) -> 0 | F48: =$L$9*IF(F44<=0,0,INDEX(Assumptions!$B$57:$F$57,MIN(F44,5)))*(1+Assumptions!$B$71)^(Model!F3-1) -> 0 | G48: =$L$9*IF(G44<=0,0,INDEX(Assumptions!$B$57:$F$57,MIN(G44,5)))*(1+Assumptions!$B$71)^(Model!G3-1) -> 0.13504208 | H48: =$L$9*IF(H44<=0,0,INDEX(Assumptions!$B$57:$F$57,MIN(H44,5)))*(1+Assumptions!$B$71)^(Model!H3-1) -> 0.16148783 | I48: =$L$9*IF(I44<=0,0,INDEX(Assumptions!$B$57:$F$57,MIN(I44,5)))*(1+Assumptions!$B$71)^(Model!I3-1) -> 0.20099467 | J48: =$L$9*IF(J44<=0,0,INDEX(Assumptions!$B$57:$F$57,MIN(J44,5)))*(1+Assumptions!$B$71)^(Model!J3-1) -> 0.23025713 | K48: =$L$9*IF(K44<=0,0,INDEX(Assumptions!$B$57:$F$57,MIN(K44,5)))*(1+Assumptions!$B$71)^(Model!K3-1) -> 0.24843532 | ... AG48: =$L$9*IF(AG44<=0,0,INDEX(Assumptions!$B$57:$F$57,MIN(AG44,5)))*(1+Assumptions!$B$71)^(Model!AG3-1) -> 0.42769915
A49: Seebe-Cochrane - Opex | D49: =IF(D44>0,$K$9*(1+Assumptions!$B$71)^(Model!D3-1),0) -> 0 | E49: =IF(E44>0,$K$9*(1+Assumptions!$B$71)^(Model!E3-1),0) -> 0 | F49: =IF(F44>0,$K$9*(1+Assumptions!$B$71)^(Model!F3-1),0) -> 0 | G49: =IF(G44>0,$K$9*(1+Assumptions!$B$71)^(Model!G3-1),0) -> 2.0697838 | H49: =IF(H44>0,$K$9*(1+Assumptions!$B$71)^(Model!H3-1),0) -> 2.1215284 | I49: =IF(I44>0,$K$9*(1+Assumptions!$B$71)^(Model!I3-1),0) -> 2.1745666 | J49: =IF(J44>0,$K$9*(1+Assumptions!$B$71)^(Model!J3-1),0) -> 2.2289307 | K49: =IF(K44>0,$K$9*(1+Assumptions!$B$71)^(Model!K3-1),0) -> 2.284654 | ... AG49: =IF(AG44>0,$K$9*(1+Assumptions!$B$71)^(Model!AG3-1),0) -> 3.933195
A51: Brooks - Years since opening | D51: =IF(Model!D3>=$C$10,Model!D3-$C$10+1,0) -> 0 | E51: =IF(Model!E3>=$C$10,Model!E3-$C$10+1,0) -> 0 | F51: =IF(Model!F3>=$C$10,Model!F3-$C$10+1,0) -> 0 | G51: =IF(Model!G3>=$C$10,Model!G3-$C$10+1,0) -> 1 | H51: =IF(Model!H3>=$C$10,Model!H3-$C$10+1,0) -> 2 | I51: =IF(Model!I3>=$C$10,Model!I3-$C$10+1,0) -> 3 | J51: =IF(Model!J3>=$C$10,Model!J3-$C$10+1,0) -> 4 | K51: =IF(Model!K3>=$C$10,Model!K3-$C$10+1,0) -> 5 | ... AG51: =IF(Model!AG3>=$C$10,Model!AG3-$C$10+1,0) -> 27
A52: Brooks - Capex | D52: =IF(Model!D3<=4,$B$10*INDEX(Assumptions!$B$24:$E$24,Model!D3),0)*(1+Assumptions!$B$76) -> 0.77 | E52: =IF(Model!E3<=4,$B$10*INDEX(Assumptions!$B$24:$E$24,Model!E3),0)*(1+Assumptions!$B$76) -> 2.31 | F52: =IF(Model!F3<=4,$B$10*INDEX(Assumptions!$B$24:$E$24,Model!F3),0)*(1+Assumptions!$B$76) -> 3.08 | G52: =IF(Model!G3<=4,$B$10*INDEX(Assumptions!$B$24:$E$24,Model!G3),0)*(1+Assumptions!$B$76) -> 1.54 | H52: =IF(Model!H3<=4,$B$10*INDEX(Assumptions!$B$24:$E$24,Model!H3),0)*(1+Assumptions!$B$76) -> 0 | I52: =IF(Model!I3<=4,$B$10*INDEX(Assumptions!$B$24:$E$24,Model!I3),0)*(1+Assumptions!$B$76) -> 0 | J52: =IF(Model!J3<=4,$B$10*INDEX(Assumptions!$B$24:$E$24,Model!J3),0)*(1+Assumptions!$B$76) -> 0 | K52: =IF(Model!K3<=4,$B$10*INDEX(Assumptions!$B$24:$E$24,Model!K3),0)*(1+Assumptions!$B$76) -> 0 | ... AG52: =IF(Model!AG3<=4,$B$10*INDEX(Assumptions!$B$24:$E$24,Model!AG3),0)*(1+Assumptions!$B$76) -> 0
A53: Brooks - Parking Revenue | D53: =$D$10*$E$10*(1+Assumptions!$B$75)*IF(D51<=0,0,INDEX(Assumptions!$B$57:$F$57,MIN(D51,5)))*8760*$F$10*(1+Assumptions!$B$71)^(Model!D3-1)*Assumptions!$B$80/1000000 -> 0 | E53: =$D$10*$E$10*(1+Assumptions!$B$75)*IF(E51<=0,0,INDEX(Assumptions!$B$57:$F$57,MIN(E51,5)))*8760*$F$10*(1+Assumptions!$B$71)^(Model!E3-1)*Assumptions!$B$80/1000000 -> 0 | F53: =$D$10*$E$10*(1+Assumptions!$B$75)*IF(F51<=0,0,INDEX(Assumptions!$B$57:$F$57,MIN(F51,5)))*8760*$F$10*(1+Assumptions!$B$71)^(Model!F3-1)*Assumptions!$B$80/1000000 -> 0 | G53: =$D$10*$E$10*(1+Assumptions!$B$75)*IF(G51<=0,0,INDEX(Assumptions!$B$57:$F$57,MIN(G51,5)))*8760*$F$10*(1+Assumptions!$B$71)^(Model!G3-1)*Assumptions!$B$80/1000000 -> 0.63853139 | H53: =$D$10*$E$10*(1+Assumptions!$B$75)*IF(H51<=0,0,INDEX(Assumptions!$B$57:$F$57,MIN(H51,5)))*8760*$F$10*(1+Assumptions!$B$71)^(Model!H3-1)*Assumptions!$B$80/1000000 -> 0.76357712 | I53: =$D$10*$E$10*(1+Assumptions!$B$75)*IF(I51<=0,0,INDEX(Assumptions!$B$57:$F$57,MIN(I51,5)))*8760*$F$10*(1+Assumptions!$B$71)^(Model!I3-1)*Assumptions!$B$80/1000000 -> 0.95038081 | J53: =$D$10*$E$10*(1+Assumptions!$B$75)*IF(J51<=0,0,INDEX(Assumptions!$B$57:$F$57,MIN(J51,5)))*8760*$F$10*(1+Assumptions!$B$71)^(Model!J3-1)*Assumptions!$B$80/1000000 -> 1.0887451 | K53: =$D$10*$E$10*(1+Assumptions!$B$75)*IF(K51<=0,0,INDEX(Assumptions!$B$57:$F$57,MIN(K51,5)))*8760*$F$10*(1+Assumptions!$B$71)^(Model!K3-1)*Assumptions!$B$80/1000000 -> 1.1746986 | ... AG53: =$D$10*$E$10*(1+Assumptions!$B$75)*IF(AG51<=0,0,INDEX(Assumptions!$B$57:$F$57,MIN(AG51,5)))*8760*$F$10*(1+Assumptions!$B$71)^(Model!AG3-1)*Assumptions!$B$80/1000000 -> 2.0223276
A54: Brooks - Pod Revenue | D54: =$G$10*(IF(D51<=0,0,IF(D51<=5,$H$10/5*D51,IF(D51<=10,$H$10+($I$10-$H$10)*(D51-5)/5,$I$10))))*365*(1+Assumptions!$B$75)*$J$10*(1+Assumptions!$B$71)^(Model!D3-1)*Assumptions!$B$80/1000000 -> 0 | E54: =$G$10*(IF(E51<=0,0,IF(E51<=5,$H$10/5*E51,IF(E51<=10,$H$10+($I$10-$H$10)*(E51-5)/5,$I$10))))*365*(1+Assumptions!$B$75)*$J$10*(1+Assumptions!$B$71)^(Model!E3-1)*Assumptions!$B$80/1000000 -> 0 | F54: =$G$10*(IF(F51<=0,0,IF(F51<=5,$H$10/5*F51,IF(F51<=10,$H$10+($I$10-$H$10)*(F51-5)/5,$I$10))))*365*(1+Assumptions!$B$75)*$J$10*(1+Assumptions!$B$71)^(Model!F3-1)*Assumptions!$B$80/1000000 -> 0 | G54: =$G$10*(IF(G51<=0,0,IF(G51<=5,$H$10/5*G51,IF(G51<=10,$H$10+($I$10-$H$10)*(G51-5)/5,$I$10))))*365*(1+Assumptions!$B$75)*$J$10*(1+Assumptions!$B$71)^(Model!G3-1)*Assumptions!$B$80/1000000 -> 0.028890283 | H54: =$G$10*(IF(H51<=0,0,IF(H51<=5,$H$10/5*H51,IF(H51<=10,$H$10+($I$10-$H$10)*(H51-5)/5,$I$10))))*365*(1+Assumptions!$B$75)*$J$10*(1+Assumptions!$B$71)^(Model!H3-1)*Assumptions!$B$80/1000000 -> 0.059225081 | I54: =$G$10*(IF(I51<=0,0,IF(I51<=5,$H$10/5*I51,IF(I51<=10,$H$10+($I$10-$H$10)*(I51-5)/5,$I$10))))*365*(1+Assumptions!$B$75)*$J$10*(1+Assumptions!$B$71)^(Model!I3-1)*Assumptions!$B$80/1000000 -> 0.091058561 | J54: =$G$10*(IF(J51<=0,0,IF(J51<=5,$H$10/5*J51,IF(J51<=10,$H$10+($I$10-$H$10)*(J51-5)/5,$I$10))))*365*(1+Assumptions!$B$75)*$J$10*(1+Assumptions!$B$71)^(Model!J3-1)*Assumptions!$B$80/1000000 -> 0.1244467 | K54: =$G$10*(IF(K51<=0,0,IF(K51<=5,$H$10/5*K51,IF(K51<=10,$H$10+($I$10-$H$10)*(K51-5)/5,$I$10))))*365*(1+Assumptions!$B$75)*$J$10*(1+Assumptions!$B$71)^(Model!K3-1)*Assumptions!$B$80/1000000 -> 0.15944734 | ... AG54: =$G$10*(IF(AG51<=0,0,IF(AG51<=5,$H$10/5*AG51,IF(AG51<=10,$H$10+($I$10-$H$10)*(AG51-5)/5,$I$10))))*365*(1+Assumptions!$B$75)*$J$10*(1+Assumptions!$B$71)^(Model!AG3-1)*Assumptions!$B$80/1000000 -> 0.47057138
A55: Brooks - Other/Ancillary Revenue | D55: =$L$10*IF(D51<=0,0,INDEX(Assumptions!$B$57:$F$57,MIN(D51,5)))*(1+Assumptions!$B$71)^(Model!D3-1) -> 0 | E55: =$L$10*IF(E51<=0,0,INDEX(Assumptions!$B$57:$F$57,MIN(E51,5)))*(1+Assumptions!$B$71)^(Model!E3-1) -> 0 | F55: =$L$10*IF(F51<=0,0,INDEX(Assumptions!$B$57:$F$57,MIN(F51,5)))*(1+Assumptions!$B$71)^(Model!F3-1) -> 0 | G55: =$L$10*IF(G51<=0,0,INDEX(Assumptions!$B$57:$F$57,MIN(G51,5)))*(1+Assumptions!$B$71)^(Model!G3-1) -> 0.12664234 | H55: =$L$10*IF(H51<=0,0,INDEX(Assumptions!$B$57:$F$57,MIN(H51,5)))*(1+Assumptions!$B$71)^(Model!H3-1) -> 0.15144313 | I55: =$L$10*IF(I51<=0,0,INDEX(Assumptions!$B$57:$F$57,MIN(I51,5)))*(1+Assumptions!$B$71)^(Model!I3-1) -> 0.18849261 | J55: =$L$10*IF(J51<=0,0,INDEX(Assumptions!$B$57:$F$57,MIN(J51,5)))*(1+Assumptions!$B$71)^(Model!J3-1) -> 0.21593491 | K55: =$L$10*IF(K51<=0,0,INDEX(Assumptions!$B$57:$F$57,MIN(K51,5)))*(1+Assumptions!$B$71)^(Model!K3-1) -> 0.23298241 | ... AG55: =$L$10*IF(AG51<=0,0,INDEX(Assumptions!$B$57:$F$57,MIN(AG51,5)))*(1+Assumptions!$B$71)^(Model!AG3-1) -> 0.40109585
A56: Brooks - Opex | D56: =IF(D51>0,$K$10*(1+Assumptions!$B$71)^(Model!D3-1),0) -> 0 | E56: =IF(E51>0,$K$10*(1+Assumptions!$B$71)^(Model!E3-1),0) -> 0 | F56: =IF(F51>0,$K$10*(1+Assumptions!$B$71)^(Model!F3-1),0) -> 0 | G56: =IF(G51>0,$K$10*(1+Assumptions!$B$71)^(Model!G3-1),0) -> 1.9437876 | H56: =IF(H51>0,$K$10*(1+Assumptions!$B$71)^(Model!H3-1),0) -> 1.9923823 | I56: =IF(I51>0,$K$10*(1+Assumptions!$B$71)^(Model!I3-1),0) -> 2.0421918 | J56: =IF(J51>0,$K$10*(1+Assumptions!$B$71)^(Model!J3-1),0) -> 2.0932466 | K56: =IF(K51>0,$K$10*(1+Assumptions!$B$71)^(Model!K3-1),0) -> 2.1455778 | ... AG56: =IF(AG51>0,$K$10*(1+Assumptions!$B$71)^(Model!AG3-1),0) -> 3.6937653
A58: Medicine Hat - Years since opening | D58: =IF(Model!D3>=$C$11,Model!D3-$C$11+1,0) -> 0 | E58: =IF(Model!E3>=$C$11,Model!E3-$C$11+1,0) -> 0 | F58: =IF(Model!F3>=$C$11,Model!F3-$C$11+1,0) -> 0 | G58: =IF(Model!G3>=$C$11,Model!G3-$C$11+1,0) -> 1 | H58: =IF(Model!H3>=$C$11,Model!H3-$C$11+1,0) -> 2 | I58: =IF(Model!I3>=$C$11,Model!I3-$C$11+1,0) -> 3 | J58: =IF(Model!J3>=$C$11,Model!J3-$C$11+1,0) -> 4 | K58: =IF(Model!K3>=$C$11,Model!K3-$C$11+1,0) -> 5 | ... AG58: =IF(Model!AG3>=$C$11,Model!AG3-$C$11+1,0) -> 27
A59: Medicine Hat - Capex | D59: =IF(Model!D3<=4,$B$11*INDEX(Assumptions!$B$24:$E$24,Model!D3),0)*(1+Assumptions!$B$76) -> 0.77 | E59: =IF(Model!E3<=4,$B$11*INDEX(Assumptions!$B$24:$E$24,Model!E3),0)*(1+Assumptions!$B$76) -> 2.31 | F59: =IF(Model!F3<=4,$B$11*INDEX(Assumptions!$B$24:$E$24,Model!F3),0)*(1+Assumptions!$B$76) -> 3.08 | G59: =IF(Model!G3<=4,$B$11*INDEX(Assumptions!$B$24:$E$24,Model!G3),0)*(1+Assumptions!$B$76) -> 1.54 | H59: =IF(Model!H3<=4,$B$11*INDEX(Assumptions!$B$24:$E$24,Model!H3),0)*(1+Assumptions!$B$76) -> 0 | I59: =IF(Model!I3<=4,$B$11*INDEX(Assumptions!$B$24:$E$24,Model!I3),0)*(1+Assumptions!$B$76) -> 0 | J59: =IF(Model!J3<=4,$B$11*INDEX(Assumptions!$B$24:$E$24,Model!J3),0)*(1+Assumptions!$B$76) -> 0 | K59: =IF(Model!K3<=4,$B$11*INDEX(Assumptions!$B$24:$E$24,Model!K3),0)*(1+Assumptions!$B$76) -> 0 | ... AG59: =IF(Model!AG3<=4,$B$11*INDEX(Assumptions!$B$24:$E$24,Model!AG3),0)*(1+Assumptions!$B$76) -> 0
A60: Medicine Hat - Parking Revenue | D60: =$D$11*$E$11*(1+Assumptions!$B$75)*IF(D58<=0,0,INDEX(Assumptions!$B$57:$F$57,MIN(D58,5)))*8760*$F$11*(1+Assumptions!$B$71)^(Model!D3-1)*Assumptions!$B$80/1000000 -> 0 | E60: =$D$11*$E$11*(1+Assumptions!$B$75)*IF(E58<=0,0,INDEX(Assumptions!$B$57:$F$57,MIN(E58,5)))*8760*$F$11*(1+Assumptions!$B$71)^(Model!E3-1)*Assumptions!$B$80/1000000 -> 0 | F60: =$D$11*$E$11*(1+Assumptions!$B$75)*IF(F58<=0,0,INDEX(Assumptions!$B$57:$F$57,MIN(F58,5)))*8760*$F$11*(1+Assumptions!$B$71)^(Model!F3-1)*Assumptions!$B$80/1000000 -> 0 | G60: =$D$11*$E$11*(1+Assumptions!$B$75)*IF(G58<=0,0,INDEX(Assumptions!$B$57:$F$57,MIN(G58,5)))*8760*$F$11*(1+Assumptions!$B$71)^(Model!G3-1)*Assumptions!$B$80/1000000 -> 0.63853139 | H60: =$D$11*$E$11*(1+Assumptions!$B$75)*IF(H58<=0,0,INDEX(Assumptions!$B$57:$F$57,MIN(H58,5)))*8760*$F$11*(1+Assumptions!$B$71)^(Model!H3-1)*Assumptions!$B$80/1000000 -> 0.76357712 | I60: =$D$11*$E$11*(1+Assumptions!$B$75)*IF(I58<=0,0,INDEX(Assumptions!$B$57:$F$57,MIN(I58,5)))*8760*$F$11*(1+Assumptions!$B$71)^(Model!I3-1)*Assumptions!$B$80/1000000 -> 0.95038081 | J60: =$D$11*$E$11*(1+Assumptions!$B$75)*IF(J58<=0,0,INDEX(Assumptions!$B$57:$F$57,MIN(J58,5)))*8760*$F$11*(1+Assumptions!$B$71)^(Model!J3-1)*Assumptions!$B$80/1000000 -> 1.0887451 | K60: =$D$11*$E$11*(1+Assumptions!$B$75)*IF(K58<=0,0,INDEX(Assumptions!$B$57:$F$57,MIN(K58,5)))*8760*$F$11*(1+Assumptions!$B$71)^(Model!K3-1)*Assumptions!$B$80/1000000 -> 1.1746986 | ... AG60: =$D$11*$E$11*(1+Assumptions!$B$75)*IF(AG58<=0,0,INDEX(Assumptions!$B$57:$F$57,MIN(AG58,5)))*8760*$F$11*(1+Assumptions!$B$71)^(Model!AG3-1)*Assumptions!$B$80/1000000 -> 2.0223276
A61: Medicine Hat - Pod Revenue | D61: =$G$11*(IF(D58<=0,0,IF(D58<=5,$H$11/5*D58,IF(D58<=10,$H$11+($I$11-$H$11)*(D58-5)/5,$I$11))))*365*(1+Assumptions!$B$75)*$J$11*(1+Assumptions!$B$71)^(Model!D3-1)*Assumptions!$B$80/1000000 -> 0 | E61: =$G$11*(IF(E58<=0,0,IF(E58<=5,$H$11/5*E58,IF(E58<=10,$H$11+($I$11-$H$11)*(E58-5)/5,$I$11))))*365*(1+Assumptions!$B$75)*$J$11*(1+Assumptions!$B$71)^(Model!E3-1)*Assumptions!$B$80/1000000 -> 0 | F61: =$G$11*(IF(F58<=0,0,IF(F58<=5,$H$11/5*F58,IF(F58<=10,$H$11+($I$11-$H$11)*(F58-5)/5,$I$11))))*365*(1+Assumptions!$B$75)*$J$11*(1+Assumptions!$B$71)^(Model!F3-1)*Assumptions!$B$80/1000000 -> 0 | G61: =$G$11*(IF(G58<=0,0,IF(G58<=5,$H$11/5*G58,IF(G58<=10,$H$11+($I$11-$H$11)*(G58-5)/5,$I$11))))*365*(1+Assumptions!$B$75)*$J$11*(1+Assumptions!$B$71)^(Model!G3-1)*Assumptions!$B$80/1000000 -> 0.028890283 | H61: =$G$11*(IF(H58<=0,0,IF(H58<=5,$H$11/5*H58,IF(H58<=10,$H$11+($I$11-$H$11)*(H58-5)/5,$I$11))))*365*(1+Assumptions!$B$75)*$J$11*(1+Assumptions!$B$71)^(Model!H3-1)*Assumptions!$B$80/1000000 -> 0.059225081 | I61: =$G$11*(IF(I58<=0,0,IF(I58<=5,$H$11/5*I58,IF(I58<=10,$H$11+($I$11-$H$11)*(I58-5)/5,$I$11))))*365*(1+Assumptions!$B$75)*$J$11*(1+Assumptions!$B$71)^(Model!I3-1)*Assumptions!$B$80/1000000 -> 0.091058561 | J61: =$G$11*(IF(J58<=0,0,IF(J58<=5,$H$11/5*J58,IF(J58<=10,$H$11+($I$11-$H$11)*(J58-5)/5,$I$11))))*365*(1+Assumptions!$B$75)*$J$11*(1+Assumptions!$B$71)^(Model!J3-1)*Assumptions!$B$80/1000000 -> 0.1244467 | K61: =$G$11*(IF(K58<=0,0,IF(K58<=5,$H$11/5*K58,IF(K58<=10,$H$11+($I$11-$H$11)*(K58-5)/5,$I$11))))*365*(1+Assumptions!$B$75)*$J$11*(1+Assumptions!$B$71)^(Model!K3-1)*Assumptions!$B$80/1000000 -> 0.15944734 | ... AG61: =$G$11*(IF(AG58<=0,0,IF(AG58<=5,$H$11/5*AG58,IF(AG58<=10,$H$11+($I$11-$H$11)*(AG58-5)/5,$I$11))))*365*(1+Assumptions!$B$75)*$J$11*(1+Assumptions!$B$71)^(Model!AG3-1)*Assumptions!$B$80/1000000 -> 0.47057138
A62: Medicine Hat - Other/Ancillary Revenue | D62: =$L$11*IF(D58<=0,0,INDEX(Assumptions!$B$57:$F$57,MIN(D58,5)))*(1+Assumptions!$B$71)^(Model!D3-1) -> 0 | E62: =$L$11*IF(E58<=0,0,INDEX(Assumptions!$B$57:$F$57,MIN(E58,5)))*(1+Assumptions!$B$71)^(Model!E3-1) -> 0 | F62: =$L$11*IF(F58<=0,0,INDEX(Assumptions!$B$57:$F$57,MIN(F58,5)))*(1+Assumptions!$B$71)^(Model!F3-1) -> 0 | G62: =$L$11*IF(G58<=0,0,INDEX(Assumptions!$B$57:$F$57,MIN(G58,5)))*(1+Assumptions!$B$71)^(Model!G3-1) -> 0.12664234 | H62: =$L$11*IF(H58<=0,0,INDEX(Assumptions!$B$57:$F$57,MIN(H58,5)))*(1+Assumptions!$B$71)^(Model!H3-1) -> 0.15144313 | I62: =$L$11*IF(I58<=0,0,INDEX(Assumptions!$B$57:$F$57,MIN(I58,5)))*(1+Assumptions!$B$71)^(Model!I3-1) -> 0.18849261 | J62: =$L$11*IF(J58<=0,0,INDEX(Assumptions!$B$57:$F$57,MIN(J58,5)))*(1+Assumptions!$B$71)^(Model!J3-1) -> 0.21593491 | K62: =$L$11*IF(K58<=0,0,INDEX(Assumptions!$B$57:$F$57,MIN(K58,5)))*(1+Assumptions!$B$71)^(Model!K3-1) -> 0.23298241 | ... AG62: =$L$11*IF(AG58<=0,0,INDEX(Assumptions!$B$57:$F$57,MIN(AG58,5)))*(1+Assumptions!$B$71)^(Model!AG3-1) -> 0.40109585
A63: Medicine Hat - Opex | D63: =IF(D58>0,$K$11*(1+Assumptions!$B$71)^(Model!D3-1),0) -> 0 | E63: =IF(E58>0,$K$11*(1+Assumptions!$B$71)^(Model!E3-1),0) -> 0 | F63: =IF(F58>0,$K$11*(1+Assumptions!$B$71)^(Model!F3-1),0) -> 0 | G63: =IF(G58>0,$K$11*(1+Assumptions!$B$71)^(Model!G3-1),0) -> 1.9437876 | H63: =IF(H58>0,$K$11*(1+Assumptions!$B$71)^(Model!H3-1),0) -> 1.9923823 | I63: =IF(I58>0,$K$11*(1+Assumptions!$B$71)^(Model!I3-1),0) -> 2.0421918 | J63: =IF(J58>0,$K$11*(1+Assumptions!$B$71)^(Model!J3-1),0) -> 2.0932466 | K63: =IF(K58>0,$K$11*(1+Assumptions!$B$71)^(Model!K3-1),0) -> 2.1455778 | ... AG63: =IF(AG58>0,$K$11*(1+Assumptions!$B$71)^(Model!AG3-1),0) -> 3.6937653
A65: Whitecourt-Fox Creek - Years since opening | D65: =IF(Model!D3>=$C$12,Model!D3-$C$12+1,0) -> 0 | E65: =IF(Model!E3>=$C$12,Model!E3-$C$12+1,0) -> 0 | F65: =IF(Model!F3>=$C$12,Model!F3-$C$12+1,0) -> 0 | G65: =IF(Model!G3>=$C$12,Model!G3-$C$12+1,0) -> 1 | H65: =IF(Model!H3>=$C$12,Model!H3-$C$12+1,0) -> 2 | I65: =IF(Model!I3>=$C$12,Model!I3-$C$12+1,0) -> 3 | J65: =IF(Model!J3>=$C$12,Model!J3-$C$12+1,0) -> 4 | K65: =IF(Model!K3>=$C$12,Model!K3-$C$12+1,0) -> 5 | ... AG65: =IF(Model!AG3>=$C$12,Model!AG3-$C$12+1,0) -> 27
A66: Whitecourt-Fox Creek - Capex | D66: =IF(Model!D3<=4,$B$12*INDEX(Assumptions!$B$24:$E$24,Model!D3),0)*(1+Assumptions!$B$76) -> 0.78 | E66: =IF(Model!E3<=4,$B$12*INDEX(Assumptions!$B$24:$E$24,Model!E3),0)*(1+Assumptions!$B$76) -> 2.34 | F66: =IF(Model!F3<=4,$B$12*INDEX(Assumptions!$B$24:$E$24,Model!F3),0)*(1+Assumptions!$B$76) -> 3.12 | G66: =IF(Model!G3<=4,$B$12*INDEX(Assumptions!$B$24:$E$24,Model!G3),0)*(1+Assumptions!$B$76) -> 1.56 | H66: =IF(Model!H3<=4,$B$12*INDEX(Assumptions!$B$24:$E$24,Model!H3),0)*(1+Assumptions!$B$76) -> 0 | I66: =IF(Model!I3<=4,$B$12*INDEX(Assumptions!$B$24:$E$24,Model!I3),0)*(1+Assumptions!$B$76) -> 0 | J66: =IF(Model!J3<=4,$B$12*INDEX(Assumptions!$B$24:$E$24,Model!J3),0)*(1+Assumptions!$B$76) -> 0 | K66: =IF(Model!K3<=4,$B$12*INDEX(Assumptions!$B$24:$E$24,Model!K3),0)*(1+Assumptions!$B$76) -> 0 | ... AG66: =IF(Model!AG3<=4,$B$12*INDEX(Assumptions!$B$24:$E$24,Model!AG3),0)*(1+Assumptions!$B$76) -> 0
A67: Whitecourt-Fox Creek - Parking Revenue | D67: =$D$12*$E$12*(1+Assumptions!$B$75)*IF(D65<=0,0,INDEX(Assumptions!$B$57:$F$57,MIN(D65,5)))*8760*$F$12*(1+Assumptions!$B$71)^(Model!D3-1)*Assumptions!$B$80/1000000 -> 0 | E67: =$D$12*$E$12*(1+Assumptions!$B$75)*IF(E65<=0,0,INDEX(Assumptions!$B$57:$F$57,MIN(E65,5)))*8760*$F$12*(1+Assumptions!$B$71)^(Model!E3-1)*Assumptions!$B$80/1000000 -> 0 | F67: =$D$12*$E$12*(1+Assumptions!$B$75)*IF(F65<=0,0,INDEX(Assumptions!$B$57:$F$57,MIN(F65,5)))*8760*$F$12*(1+Assumptions!$B$71)^(Model!F3-1)*Assumptions!$B$80/1000000 -> 0 | G67: =$D$12*$E$12*(1+Assumptions!$B$75)*IF(G65<=0,0,INDEX(Assumptions!$B$57:$F$57,MIN(G65,5)))*8760*$F$12*(1+Assumptions!$B$71)^(Model!G3-1)*Assumptions!$B$80/1000000 -> 0.64661407 | H67: =$D$12*$E$12*(1+Assumptions!$B$75)*IF(H65<=0,0,INDEX(Assumptions!$B$57:$F$57,MIN(H65,5)))*8760*$F$12*(1+Assumptions!$B$71)^(Model!H3-1)*Assumptions!$B$80/1000000 -> 0.77324265 | I67: =$D$12*$E$12*(1+Assumptions!$B$75)*IF(I65<=0,0,INDEX(Assumptions!$B$57:$F$57,MIN(I65,5)))*8760*$F$12*(1+Assumptions!$B$71)^(Model!I3-1)*Assumptions!$B$80/1000000 -> 0.96241094 | J67: =$D$12*$E$12*(1+Assumptions!$B$75)*IF(J65<=0,0,INDEX(Assumptions!$B$57:$F$57,MIN(J65,5)))*8760*$F$12*(1+Assumptions!$B$71)^(Model!J3-1)*Assumptions!$B$80/1000000 -> 1.1025267 | K67: =$D$12*$E$12*(1+Assumptions!$B$75)*IF(K65<=0,0,INDEX(Assumptions!$B$57:$F$57,MIN(K65,5)))*8760*$F$12*(1+Assumptions!$B$71)^(Model!K3-1)*Assumptions!$B$80/1000000 -> 1.1895682 | ... AG67: =$D$12*$E$12*(1+Assumptions!$B$75)*IF(AG65<=0,0,INDEX(Assumptions!$B$57:$F$57,MIN(AG65,5)))*8760*$F$12*(1+Assumptions!$B$71)^(Model!AG3-1)*Assumptions!$B$80/1000000 -> 2.0479266
A68: Whitecourt-Fox Creek - Pod Revenue | D68: =$G$12*(IF(D65<=0,0,IF(D65<=5,$H$12/5*D65,IF(D65<=10,$H$12+($I$12-$H$12)*(D65-5)/5,$I$12))))*365*(1+Assumptions!$B$75)*$J$12*(1+Assumptions!$B$71)^(Model!D3-1)*Assumptions!$B$80/1000000 -> 0 | E68: =$G$12*(IF(E65<=0,0,IF(E65<=5,$H$12/5*E65,IF(E65<=10,$H$12+($I$12-$H$12)*(E65-5)/5,$I$12))))*365*(1+Assumptions!$B$75)*$J$12*(1+Assumptions!$B$71)^(Model!E3-1)*Assumptions!$B$80/1000000 -> 0 | F68: =$G$12*(IF(F65<=0,0,IF(F65<=5,$H$12/5*F65,IF(F65<=10,$H$12+($I$12-$H$12)*(F65-5)/5,$I$12))))*365*(1+Assumptions!$B$75)*$J$12*(1+Assumptions!$B$71)^(Model!F3-1)*Assumptions!$B$80/1000000 -> 0 | G68: =$G$12*(IF(G65<=0,0,IF(G65<=5,$H$12/5*G65,IF(G65<=10,$H$12+($I$12-$H$12)*(G65-5)/5,$I$12))))*365*(1+Assumptions!$B$75)*$J$12*(1+Assumptions!$B$71)^(Model!G3-1)*Assumptions!$B$80/1000000 -> 0.028890283 | H68: =$G$12*(IF(H65<=0,0,IF(H65<=5,$H$12/5*H65,IF(H65<=10,$H$12+($I$12-$H$12)*(H65-5)/5,$I$12))))*365*(1+Assumptions!$B$75)*$J$12*(1+Assumptions!$B$71)^(Model!H3-1)*Assumptions!$B$80/1000000 -> 0.059225081 | I68: =$G$12*(IF(I65<=0,0,IF(I65<=5,$H$12/5*I65,IF(I65<=10,$H$12+($I$12-$H$12)*(I65-5)/5,$I$12))))*365*(1+Assumptions!$B$75)*$J$12*(1+Assumptions!$B$71)^(Model!I3-1)*Assumptions!$B$80/1000000 -> 0.091058561 | J68: =$G$12*(IF(J65<=0,0,IF(J65<=5,$H$12/5*J65,IF(J65<=10,$H$12+($I$12-$H$12)*(J65-5)/5,$I$12))))*365*(1+Assumptions!$B$75)*$J$12*(1+Assumptions!$B$71)^(Model!J3-1)*Assumptions!$B$80/1000000 -> 0.1244467 | K68: =$G$12*(IF(K65<=0,0,IF(K65<=5,$H$12/5*K65,IF(K65<=10,$H$12+($I$12-$H$12)*(K65-5)/5,$I$12))))*365*(1+Assumptions!$B$75)*$J$12*(1+Assumptions!$B$71)^(Model!K3-1)*Assumptions!$B$80/1000000 -> 0.15944734 | ... AG68: =$G$12*(IF(AG65<=0,0,IF(AG65<=5,$H$12/5*AG65,IF(AG65<=10,$H$12+($I$12-$H$12)*(AG65-5)/5,$I$12))))*365*(1+Assumptions!$B$75)*$J$12*(1+Assumptions!$B$71)^(Model!AG3-1)*Assumptions!$B$80/1000000 -> 0.47057138
A69: Whitecourt-Fox Creek - Other/Ancillary Revenue | D69: =$L$12*IF(D65<=0,0,INDEX(Assumptions!$B$57:$F$57,MIN(D65,5)))*(1+Assumptions!$B$71)^(Model!D3-1) -> 0 | E69: =$L$12*IF(E65<=0,0,INDEX(Assumptions!$B$57:$F$57,MIN(E65,5)))*(1+Assumptions!$B$71)^(Model!E3-1) -> 0 | F69: =$L$12*IF(F65<=0,0,INDEX(Assumptions!$B$57:$F$57,MIN(F65,5)))*(1+Assumptions!$B$71)^(Model!F3-1) -> 0 | G69: =$L$12*IF(G65<=0,0,INDEX(Assumptions!$B$57:$F$57,MIN(G65,5)))*(1+Assumptions!$B$71)^(Model!G3-1) -> 0.12858074 | H69: =$L$12*IF(H65<=0,0,INDEX(Assumptions!$B$57:$F$57,MIN(H65,5)))*(1+Assumptions!$B$71)^(Model!H3-1) -> 0.15376114 | I69: =$L$12*IF(I65<=0,0,INDEX(Assumptions!$B$57:$F$57,MIN(I65,5)))*(1+Assumptions!$B$71)^(Model!I3-1) -> 0.1913777 | J69: =$L$12*IF(J65<=0,0,INDEX(Assumptions!$B$57:$F$57,MIN(J65,5)))*(1+Assumptions!$B$71)^(Model!J3-1) -> 0.21924004 | K69: =$L$12*IF(K65<=0,0,INDEX(Assumptions!$B$57:$F$57,MIN(K65,5)))*(1+Assumptions!$B$71)^(Model!K3-1) -> 0.23654846 | ... AG69: =$L$12*IF(AG65<=0,0,INDEX(Assumptions!$B$57:$F$57,MIN(AG65,5)))*(1+Assumptions!$B$71)^(Model!AG3-1) -> 0.40723507
A70: Whitecourt-Fox Creek - Opex | D70: =IF(D65>0,$K$12*(1+Assumptions!$B$71)^(Model!D3-1),0) -> 0 | E70: =IF(E65>0,$K$12*(1+Assumptions!$B$71)^(Model!E3-1),0) -> 0 | F70: =IF(F65>0,$K$12*(1+Assumptions!$B$71)^(Model!F3-1),0) -> 0 | G70: =IF(G65>0,$K$12*(1+Assumptions!$B$71)^(Model!G3-1),0) -> 1.9685561 | H70: =IF(H65>0,$K$12*(1+Assumptions!$B$71)^(Model!H3-1),0) -> 2.01777 | I70: =IF(I65>0,$K$12*(1+Assumptions!$B$71)^(Model!I3-1),0) -> 2.0682142 | J70: =IF(J65>0,$K$12*(1+Assumptions!$B$71)^(Model!J3-1),0) -> 2.1199196 | K70: =IF(K65>0,$K$12*(1+Assumptions!$B$71)^(Model!K3-1),0) -> 2.1729176 | ... AG70: =IF(AG65>0,$K$12*(1+Assumptions!$B$71)^(Model!AG3-1),0) -> 3.7408327
A72: NETWORK TOTALS (sum of all 8 sites)
A74: TOTAL SITE CAPEX | D74: =D17+D24+D31+D38+D45+D52+D59+D66 -> 18.74 | E74: =E17+E24+E31+E38+E45+E52+E59+E66 -> 45.62 | F74: =F17+F24+F31+F38+F45+F52+F59+F66 -> 53.76 | G74: =G17+G24+G31+G38+G45+G52+G59+G66 -> 16.28 | H74: =H17+H24+H31+H38+H45+H52+H59+H66 -> 0 | I74: =I17+I24+I31+I38+I45+I52+I59+I66 -> 0 | J74: =J17+J24+J31+J38+J45+J52+J59+J66 -> 0 | K74: =K17+K24+K31+K38+K45+K52+K59+K66 -> 0 | ... AG74: =AG17+AG24+AG31+AG38+AG45+AG52+AG59+AG66 -> 0
A75: TOTAL PARKING REVENUE | D75: =D18+D25+D32+D39+D46+D53+D60+D67 -> 0 | E75: =E18+E25+E32+E39+E46+E53+E60+E67 -> 0 | F75: =F18+F25+F32+F39+F46+F53+F60+F67 -> 5.4410208 | G75: =G18+G25+G32+G39+G46+G53+G60+G67 -> 14.564982 | H75: =H18+H25+H32+H39+H46+H53+H60+H67 -> 17.734873 | I75: =I18+I25+I32+I39+I46+I53+I60+I67 -> 21.271405 | J75: =J18+J25+J32+J39+J46+J53+J60+J67 -> 23.75002 | K75: =K18+K25+K32+K39+K46+K53+K60+K67 -> 25.08502 | ... AG75: =AG18+AG25+AG32+AG39+AG46+AG53+AG60+AG67 -> 43.185653
A76: TOTAL POD REVENUE | D76: =D19+D26+D33+D40+D47+D54+D61+D68 -> 0 | E76: =E19+E26+E33+E40+E47+E54+E61+E68 -> 0 | F76: =F19+F26+F33+F40+F47+F54+F61+F68 -> 0.090596707 | G76: =G19+G26+G33+G40+G47+G54+G61+G68 -> 0.47772147 | H76: =H19+H26+H33+H40+H47+H54+H61+H68 -> 0.88414585 | I76: =I19+I26+I33+I40+I47+I54+I61+I68 -> 1.3105929 | J76: =J19+J26+J33+J40+J47+J54+J61+J68 -> 1.7578096 | K76: =K19+K26+K33+K40+K47+K54+K61+K68 -> 2.1810118 | ... AG76: =AG19+AG26+AG33+AG40+AG47+AG54+AG61+AG68 -> 5.980178
A77: TOTAL OTHER/ANCILLARY REVENUE | D77: =D20+D27+D34+D41+D48+D55+D62+D69 -> 0 | E77: =E20+E27+E34+E41+E48+E55+E62+E69 -> 0 | F77: =F20+F27+F34+F41+F48+F55+F62+F69 -> 0.9455625 | G77: =G20+G27+G34+G41+G48+G55+G62+G69 -> 2.6168442 | H77: =H20+H27+H34+H41+H48+H55+H62+H69 -> 3.1845002 | I77: =I20+I27+I34+I41+I48+I55+I62+I69 -> 3.8241598 | J77: =J20+J27+J34+J41+J48+J55+J62+J69 -> 4.2734702 | K77: =K20+K27+K34+K41+K48+K55+K62+K69 -> 4.5170059 | ... AG77: =AG20+AG27+AG34+AG41+AG48+AG55+AG62+AG69 -> 7.7763481
A78: TOTAL SITE OPEX (excl. platform) | D78: =D21+D28+D35+D42+D49+D56+D63+D70 -> 0 | E78: =E21+E28+E35+E42+E49+E56+E63+E70 -> 0 | F78: =F21+F28+F35+F42+F49+F56+F63+F70 -> 12.6075 | G78: =G21+G28+G35+G42+G49+G56+G63+G70 -> 32.899009 | H78: =H21+H28+H35+H42+H49+H56+H63+H70 -> 33.721484 | I78: =I21+I28+I35+I42+I49+I56+I63+I70 -> 34.564521 | J78: =J21+J28+J35+J42+J49+J56+J63+J70 -> 35.428634 | K78: =K21+K28+K35+K42+K49+K56+K63+K70 -> 36.31435 | ... AG78: =AG21+AG28+AG35+AG42+AG49+AG56+AG63+AG70 -> 62.517746

Sheet Model
A1: MODEL - 30 YEAR CASH FLOW (all figures $M unless noted)
A3: Year # | D3: 1 | E3: 2 | F3: 3 | G3: 4 | H3: 5 | I3: 6 | J3: 7 | K3: 8 | L3: 9 | M3: 10 | N3: 11 | O3: 12 | P3: 13 | Q3: 14 | R3: 15 | S3: 16 | T3: 17 | U3: 18 | V3: 19 | W3: 20 | X3: 21 | Y3: 22 | Z3: 23 | AA3: 24 | AB3: 25 | AC3: 26 | AD3: 27 | AE3: 28 | AF3: 29 | AG3: 30
A4: Calendar Year | D4: =Assumptions!$B$6+D3-1 -> 2027 | E4: =Assumptions!$B$6+E3-1 -> 2028 | F4: =Assumptions!$B$6+F3-1 -> 2029 | G4: =Assumptions!$B$6+G3-1 -> 2030 | H4: =Assumptions!$B$6+H3-1 -> 2031 | I4: =Assumptions!$B$6+I3-1 -> 2032 | J4: =Assumptions!$B$6+J3-1 -> 2033 | K4: =Assumptions!$B$6+K3-1 -> 2034 | ... AG4: =Assumptions!$B$6+AG3-1 -> 2056
A5: Mega Hub - years since opening | D5: =IF(D3>=Assumptions!$B$9,D3-Assumptions!$B$9+1,0) -> 0 | E5: =IF(E3>=Assumptions!$B$9,E3-Assumptions!$B$9+1,0) -> 0 | F5: =IF(F3>=Assumptions!$B$9,F3-Assumptions!$B$9+1,0) -> 1 | G5: =IF(G3>=Assumptions!$B$9,G3-Assumptions!$B$9+1,0) -> 2 | H5: =IF(H3>=Assumptions!$B$9,H3-Assumptions!$B$9+1,0) -> 3 | I5: =IF(I3>=Assumptions!$B$9,I3-Assumptions!$B$9+1,0) -> 4 | J5: =IF(J3>=Assumptions!$B$9,J3-Assumptions!$B$9+1,0) -> 5 | K5: =IF(K3>=Assumptions!$B$9,K3-Assumptions!$B$9+1,0) -> 6 | ... AG5: =IF(AG3>=Assumptions!$B$9,AG3-Assumptions!$B$9+1,0) -> 28
A6: Regional/Infill - years since opening | D6: =IF(D3>=Assumptions!$B$10,D3-Assumptions!$B$10+1,0) -> 0 | E6: =IF(E3>=Assumptions!$B$10,E3-Assumptions!$B$10+1,0) -> 0 | F6: =IF(F3>=Assumptions!$B$10,F3-Assumptions!$B$10+1,0) -> 0 | G6: =IF(G3>=Assumptions!$B$10,G3-Assumptions!$B$10+1,0) -> 1 | H6: =IF(H3>=Assumptions!$B$10,H3-Assumptions!$B$10+1,0) -> 2 | I6: =IF(I3>=Assumptions!$B$10,I3-Assumptions!$B$10+1,0) -> 3 | J6: =IF(J3>=Assumptions!$B$10,J3-Assumptions!$B$10+1,0) -> 4 | K6: =IF(K3>=Assumptions!$B$10,K3-Assumptions!$B$10+1,0) -> 5 | ... AG6: =IF(AG3>=Assumptions!$B$10,AG3-Assumptions!$B$10+1,0) -> 27
A8: CAPEX ($M)
A10: Mega Hub capex | D10: =IF(D3<=4,Assumptions!$B$15*Assumptions!$C$15*INDEX(Assumptions!$B$23:$E$23,D3),0)*(1+Assumptions!$B$76) -> 10.6 | E10: =IF(E3<=4,Assumptions!$B$15*Assumptions!$C$15*INDEX(Assumptions!$B$23:$E$23,E3),0)*(1+Assumptions!$B$76) -> 21.2 | F10: =IF(F3<=4,Assumptions!$B$15*Assumptions!$C$15*INDEX(Assumptions!$B$23:$E$23,F3),0)*(1+Assumptions!$B$76) -> 21.2 | G10: =IF(G3<=4,Assumptions!$B$15*Assumptions!$C$15*INDEX(Assumptions!$B$23:$E$23,G3),0)*(1+Assumptions!$B$76) -> 0 | H10: =IF(H3<=4,Assumptions!$B$15*Assumptions!$C$15*INDEX(Assumptions!$B$23:$E$23,H3),0)*(1+Assumptions!$B$76) -> 0 | I10: =IF(I3<=4,Assumptions!$B$15*Assumptions!$C$15*INDEX(Assumptions!$B$23:$E$23,I3),0)*(1+Assumptions!$B$76) -> 0 | J10: =IF(J3<=4,Assumptions!$B$15*Assumptions!$C$15*INDEX(Assumptions!$B$23:$E$23,J3),0)*(1+Assumptions!$B$76) -> 0 | K10: =IF(K3<=4,Assumptions!$B$15*Assumptions!$C$15*INDEX(Assumptions!$B$23:$E$23,K3),0)*(1+Assumptions!$B$76) -> 0 | ... AG10: =IF(AG3<=4,Assumptions!$B$15*Assumptions!$C$15*INDEX(Assumptions!$B$23:$E$23,AG3),0)*(1+Assumptions!$B$76) -> 0
A11: Regional capex (3 sites) | D11: =IF(D3<=4,Assumptions!$B$16*Assumptions!$C$16*INDEX(Assumptions!$B$24:$E$24,D3),0)*(1+Assumptions!$B$76) -> 5.01 | E11: =IF(E3<=4,Assumptions!$B$16*Assumptions!$C$16*INDEX(Assumptions!$B$24:$E$24,E3),0)*(1+Assumptions!$B$76) -> 15.03 | F11: =IF(F3<=4,Assumptions!$B$16*Assumptions!$C$16*INDEX(Assumptions!$B$24:$E$24,F3),0)*(1+Assumptions!$B$76) -> 20.04 | G11: =IF(G3<=4,Assumptions!$B$16*Assumptions!$C$16*INDEX(Assumptions!$B$24:$E$24,G3),0)*(1+Assumptions!$B$76) -> 10.02 | H11: =IF(H3<=4,Assumptions!$B$16*Assumptions!$C$16*INDEX(Assumptions!$B$24:$E$24,H3),0)*(1+Assumptions!$B$76) -> 0 | I11: =IF(I3<=4,Assumptions!$B$16*Assumptions!$C$16*INDEX(Assumptions!$B$24:$E$24,I3),0)*(1+Assumptions!$B$76) -> 0 | J11: =IF(J3<=4,Assumptions!$B$16*Assumptions!$C$16*INDEX(Assumptions!$B$24:$E$24,J3),0)*(1+Assumptions!$B$76) -> 0 | K11: =IF(K3<=4,Assumptions!$B$16*Assumptions!$C$16*INDEX(Assumptions!$B$24:$E$24,K3),0)*(1+Assumptions!$B$76) -> 0 | ... AG11: =IF(AG3<=4,Assumptions!$B$16*Assumptions!$C$16*INDEX(Assumptions!$B$24:$E$24,AG3),0)*(1+Assumptions!$B$76) -> 0
A12: Infill capex (4 sites) | D12: =IF(D3<=4,Assumptions!$B$17*Assumptions!$C$17*INDEX(Assumptions!$B$24:$E$24,D3),0)*(1+Assumptions!$B$76) -> 3.14 | E12: =IF(E3<=4,Assumptions!$B$17*Assumptions!$C$17*INDEX(Assumptions!$B$24:$E$24,E3),0)*(1+Assumptions!$B$76) -> 9.42 | F12: =IF(F3<=4,Assumptions!$B$17*Assumptions!$C$17*INDEX(Assumptions!$B$24:$E$24,F3),0)*(1+Assumptions!$B$76) -> 12.56 | G12: =IF(G3<=4,Assumptions!$B$17*Assumptions!$C$17*INDEX(Assumptions!$B$24:$E$24,G3),0)*(1+Assumptions!$B$76) -> 6.28 | H12: =IF(H3<=4,Assumptions!$B$17*Assumptions!$C$17*INDEX(Assumptions!$B$24:$E$24,H3),0)*(1+Assumptions!$B$76) -> 0 | I12: =IF(I3<=4,Assumptions!$B$17*Assumptions!$C$17*INDEX(Assumptions!$B$24:$E$24,I3),0)*(1+Assumptions!$B$76) -> 0 | J12: =IF(J3<=4,Assumptions!$B$17*Assumptions!$C$17*INDEX(Assumptions!$B$24:$E$24,J3),0)*(1+Assumptions!$B$76) -> 0 | K12: =IF(K3<=4,Assumptions!$B$17*Assumptions!$C$17*INDEX(Assumptions!$B$24:$E$24,K3),0)*(1+Assumptions!$B$76) -> 0 | ... AG12: =IF(AG3<=4,Assumptions!$B$17*Assumptions!$C$17*INDEX(Assumptions!$B$24:$E$24,AG3),0)*(1+Assumptions!$B$76) -> 0
A13: Total Capex | D13: ='Site Detail'!D74 -> 18.74 | E13: ='Site Detail'!E74 -> 45.62 | F13: ='Site Detail'!F74 -> 53.76 | G13: ='Site Detail'!G74 -> 16.28 | H13: ='Site Detail'!H74 -> 0 | I13: ='Site Detail'!I74 -> 0 | J13: ='Site Detail'!J74 -> 0 | K13: ='Site Detail'!K74 -> 0 | ... AG13: ='Site Detail'!AG74 -> 0
A14: Debt Draw (70%) | D14: =D73*Assumptions!$B$62 -> 16.723 | E14: =E73*Assumptions!$B$62 -> 35.539 | F14: =F73*Assumptions!$B$62 -> 41.237 | G14: =G73*Assumptions!$B$62 -> 15.001 | H14: =H73*Assumptions!$B$62 -> 0 | I14: =I73*Assumptions!$B$62 -> 0 | J14: =J73*Assumptions!$B$62 -> 0 | K14: =K73*Assumptions!$B$62 -> 0 | ... AG14: =AG73*Assumptions!$B$62 -> 0
A15: Equity Draw (30%) | D15: =D73*Assumptions!$B$61 -> 7.167 | E15: =E73*Assumptions!$B$61 -> 15.231 | F15: =F73*Assumptions!$B$61 -> 17.673 | G15: =G73*Assumptions!$B$61 -> 6.429 | H15: =H73*Assumptions!$B$61 -> 0 | I15: =I73*Assumptions!$B$61 -> 0 | J15: =J73*Assumptions!$B$61 -> 0 | K15: =K73*Assumptions!$B$61 -> 0 | ... AG15: =AG73*Assumptions!$B$61 -> 0
A17: DEBT SCHEDULE ($M) - interest capitalised during Yrs 1-4 (grace); amortising P+I from Yr 5
A19: Opening balance | D19: 0 | E19: =D25 -> 17.323236 | F19: =E25 -> 55.381393 | G19: =F25 -> 102.0741 | H19: =G25 -> 124.94099 | I19: =H25 -> 122.4468 | J19: =I25 -> 119.77356 | K19: =J25 -> 116.90843 | L19: =K25 -> 113.83762 | ... AG19: =AF25 -> 5.2488643e-14
A20: Draw | D20: =D14 -> 16.723 | E20: =E14 -> 35.539 | F20: =F14 -> 41.237 | G20: =G14 -> 15.001 | H20: =H14 -> 0 | I20: =I14 -> 0 | J20: =J14 -> 0 | K20: =K14 -> 0 | ... AG20: =AG14 -> 0
A21: Interest | D21: =(D19+D20/2)*(Assumptions!$B$63+Assumptions!$B$77/10000) -> 0.60023625 | E21: =(E19+E20/2)*(Assumptions!$B$63+Assumptions!$B$77/10000) -> 2.5191571 | F21: =(F19+F20/2)*(Assumptions!$B$63+Assumptions!$B$77/10000) -> 5.4557066 | G21: =(G19+G20/2)*(Assumptions!$B$63+Assumptions!$B$77/10000) -> 7.8658909 | H21: =(H19+H20/2)*(Assumptions!$B$63+Assumptions!$B$77/10000) -> 8.9689783 | I21: =(I19+I20/2)*(Assumptions!$B$63+Assumptions!$B$77/10000) -> 8.7899311 | J21: =(J19+J20/2)*(Assumptions!$B$63+Assumptions!$B$77/10000) -> 8.5980309 | K21: =(K19+K20/2)*(Assumptions!$B$63+Assumptions!$B$77/10000) -> 8.392355 | ... AG21: =(AG19+AG20/2)*(Assumptions!$B$63+Assumptions!$B$77/10000) -> 3.7679347e-15
A22: Capitalised interest (Yrs 1-4) | D22: =IF(D3<=Assumptions!$B$65,D21,0) -> 0.60023625 | E22: =IF(E3<=Assumptions!$B$65,E21,0) -> 2.5191571 | F22: =IF(F3<=Assumptions!$B$65,F21,0) -> 5.4557066 | G22: =IF(G3<=Assumptions!$B$65,G21,0) -> 7.8658909 | H22: =IF(H3<=Assumptions!$B$65,H21,0) -> 0 | I22: =IF(I3<=Assumptions!$B$65,I21,0) -> 0 | J22: =IF(J3<=Assumptions!$B$65,J21,0) -> 0 | K22: =IF(K3<=Assumptions!$B$65,K21,0) -> 0 | ... AG22: =IF(AG3<=Assumptions!$B$65,AG21,0) -> 0
A23: Scheduled debt service (P+I) | D23: =IF(AND(D3>Assumptions!$B$65,D3<=Assumptions!$B$65+Assumptions!$B$64),-PMT((Assumptions!$B$63+Assumptions!$B$77/10000),Assumptions!$B$64,G25),0) -> 0 | E23: =IF(AND(E3>Assumptions!$B$65,E3<=Assumptions!$B$65+Assumptions!$B$64),-PMT((Assumptions!$B$63+Assumptions!$B$77/10000),Assumptions!$B$64,G25),0) -> 0 | F23: =IF(AND(F3>Assumptions!$B$65,F3<=Assumptions!$B$65+Assumptions!$B$64),-PMT((Assumptions!$B$63+Assumptions!$B$77/10000),Assumptions!$B$64,G25),0) -> 0 | G23: =IF(AND(G3>Assumptions!$B$65,G3<=Assumptions!$B$65+Assumptions!$B$64),-PMT((Assumptions!$B$63+Assumptions!$B$77/10000),Assumptions!$B$64,G25),0) -> 0 | H23: =IF(AND(H3>Assumptions!$B$65,H3<=Assumptions!$B$65+Assumptions!$B$64),-PMT((Assumptions!$B$63+Assumptions!$B$77/10000),Assumptions!$B$64,G25),0) -> 11.463168 | I23: =IF(AND(I3>Assumptions!$B$65,I3<=Assumptions!$B$65+Assumptions!$B$64),-PMT((Assumptions!$B$63+Assumptions!$B$77/10000),Assumptions!$B$64,G25),0) -> 11.463168 | J23: =IF(AND(J3>Assumptions!$B$65,J3<=Assumptions!$B$65+Assumptions!$B$64),-PMT((Assumptions!$B$63+Assumptions!$B$77/10000),Assumptions!$B$64,G25),0) -> 11.463168 | K23: =IF(AND(K3>Assumptions!$B$65,K3<=Assumptions!$B$65+Assumptions!$B$64),-PMT((Assumptions!$B$63+Assumptions!$B$77/10000),Assumptions!$B$64,G25),0) -> 11.463168 | L23: =IF(AND(L3>Assumptions!$B$65,L3<=Assumptions!$B$65+Assumptions!$B$64),-PMT((Assumptions!$B$63+Assumptions!$B$77/10000),Assumptions!$B$64,G25),0) -> 11.463168 | M23: =IF(AND(M3>Assumptions!$B$65,M3<=Assumptions!$B$65+Assumptions!$B$64),-PMT((Assumptions!$B$63+Assumptions!$B$77/10000),Assumptions!$B$64,G25),0) -> 11.463168 | N23: =IF(AND(N3>Assumptions!$B$65,N3<=Assumptions!$B$65+Assumptions!$B$64),-PMT((Assumptions!$B$63+Assumptions!$B$77/10000),Assumptions!$B$64,G25),0) -> 11.463168 | O23: =IF(AND(O3>Assumptions!$B$65,O3<=Assumptions!$B$65+Assumptions!$B$64),-PMT((Assumptions!$B$63+Assumptions!$B$77/10000),Assumptions!$B$64,G25),0) -> 11.463168 | P23: =IF(AND(P3>Assumptions!$B$65,P3<=Assumptions!$B$65+Assumptions!$B$64),-PMT((Assumptions!$B$63+Assumptions!$B$77/10000),Assumptions!$B$64,G25),0) -> 11.463168 | Q23: =IF(AND(Q3>Assumptions!$B$65,Q3<=Assumptions!$B$65+Assumptions!$B$64),-PMT((Assumptions!$B$63+Assumptions!$B$77/10000),Assumptions!$B$64,G25),0) -> 11.463168 | R23: =IF(AND(R3>Assumptions!$B$65,R3<=Assumptions!$B$65+Assumptions!$B$64),-PMT((Assumptions!$B$63+Assumptions!$B$77/10000),Assumptions!$B$64,G25),0) -> 11.463168 | S23: =IF(AND(S3>Assumptions!$B$65,S3<=Assumptions!$B$65+Assumptions!$B$64),-PMT((Assumptions!$B$63+Assumptions!$B$77/10000),Assumptions!$B$64,G25),0) -> 11.463168 | T23: =IF(AND(T3>Assumptions!$B$65,T3<=Assumptions!$B$65+Assumptions!$B$64),-PMT((Assumptions!$B$63+Assumptions!$B$77/10000),Assumptions!$B$64,G25),0) -> 11.463168 | U23: =IF(AND(U3>Assumptions!$B$65,U3<=Assumptions!$B$65+Assumptions!$B$64),-PMT((Assumptions!$B$63+Assumptions!$B$77/10000),Assumptions!$B$64,G25),0) -> 11.463168 | V23: =IF(AND(V3>Assumptions!$B$65,V3<=Assumptions!$B$65+Assumptions!$B$64),-PMT((Assumptions!$B$63+Assumptions!$B$77/10000),Assumptions!$B$64,G25),0) -> 11.463168 | W23: =IF(AND(W3>Assumptions!$B$65,W3<=Assumptions!$B$65+Assumptions!$B$64),-PMT((Assumptions!$B$63+Assumptions!$B$77/10000),Assumptions!$B$64,G25),0) -> 11.463168 | X23: =IF(AND(X3>Assumptions!$B$65,X3<=Assumptions!$B$65+Assumptions!$B$64),-PMT((Assumptions!$B$63+Assumptions!$B$77/10000),Assumptions!$B$64,G25),0) -> 11.463168 | Y23: =IF(AND(Y3>Assumptions!$B$65,Y3<=Assumptions!$B$65+Assumptions!$B$64),-PMT((Assumptions!$B$63+Assumptions!$B$77/10000),Assumptions!$B$64,G25),0) -> 11.463168 | Z23: =IF(AND(Z3>Assumptions!$B$65,Z3<=Assumptions!$B$65+Assumptions!$B$64),-PMT((Assumptions!$B$63+Assumptions!$B$77/10000),Assumptions!$B$64,G25),0) -> 11.463168 | AA23: =IF(AND(AA3>Assumptions!$B$65,AA3<=Assumptions!$B$65+Assumptions!$B$64),-PMT((Assumptions!$B$63+Assumptions!$B$77/10000),Assumptions!$B$64,G25),0) -> 11.463168 | AB23: =IF(AND(AB3>Assumptions!$B$65,AB3<=Assumptions!$B$65+Assumptions!$B$64),-PMT((Assumptions!$B$63+Assumptions!$B$77/10000),Assumptions!$B$64,G25),0) -> 11.463168 | AC23: =IF(AND(AC3>Assumptions!$B$65,AC3<=Assumptions!$B$65+Assumptions!$B$64),-PMT((Assumptions!$B$63+Assumptions!$B$77/10000),Assumptions!$B$64,G25),0) -> 11.463168 | AD23: =IF(AND(AD3>Assumptions!$B$65,AD3<=Assumptions!$B$65+Assumptions!$B$64),-PMT((Assumptions!$B$63+Assumptions!$B$77/10000),Assumptions!$B$64,G25),0) -> 0 | AE23: =IF(AND(AE3>Assumptions!$B$65,AE3<=Assumptions!$B$65+Assumptions!$B$64),-PMT((Assumptions!$B$63+Assumptions!$B$77/10000),Assumptions!$B$64,G25),0) -> 0 | AF23: =IF(AND(AF3>Assumptions!$B$65,AF3<=Assumptions!$B$65+Assumptions!$B$64),-PMT((Assumptions!$B$63+Assumptions!$B$77/10000),Assumptions!$B$64,G25),0) -> 0 | AG23: =IF(AND(AG3>Assumptions!$B$65,AG3<=Assumptions!$B$65+Assumptions!$B$64),-PMT((Assumptions!$B$63+Assumptions!$B$77/10000),Assumptions!$B$64,G25),0) -> 0
A24: Principal repayment | D24: =IF(D3>Assumptions!$B$65,MIN(D19,D23-D21),0) -> 0 | E24: =IF(E3>Assumptions!$B$65,MIN(E19,E23-E21),0) -> 0 | F24: =IF(F3>Assumptions!$B$65,MIN(F19,F23-F21),0) -> 0 | G24: =IF(G3>Assumptions!$B$65,MIN(G19,G23-G21),0) -> 0 | H24: =IF(H3>Assumptions!$B$65,MIN(H19,H23-H21),0) -> 2.4941894 | I24: =IF(I3>Assumptions!$B$65,MIN(I19,I23-I21),0) -> 2.6732366 | J24: =IF(J3>Assumptions!$B$65,MIN(J19,J23-J21),0) -> 2.8651368 | K24: =IF(K3>Assumptions!$B$65,MIN(K19,K23-K21),0) -> 3.0708127 | ... AG24: =IF(AG3>Assumptions!$B$65,MIN(AG19,AG23-AG21),0) -> -3.7679347e-15
A25: Closing balance | D25: =MAX(0,D19+D20+D22-D24) -> 17.323236 | E25: =MAX(0,E19+E20+E22-E24) -> 55.381393 | F25: =MAX(0,F19+F20+F22-F24) -> 102.0741 | G25: =MAX(0,G19+G20+G22-G24) -> 124.94099 | H25: =MAX(0,H19+H20+H22-H24) -> 122.4468 | I25: =MAX(0,I19+I20+I22-I24) -> 119.77356 | J25: =MAX(0,J19+J20+J22-J24) -> 116.90843 | K25: =MAX(0,K19+K20+K22-K24) -> 113.83762 | ... AG25: =MAX(0,AG19+AG20+AG22-AG24) -> 5.6256578e-14
A27: COMMERCIAL REVENUE ($M)
A29: Parking - Mega Hub | D29: =Assumptions!$B$15*Assumptions!$B$29*Assumptions!$C$29*(1+Assumptions!$B$75)*IF(D5<=0,0,INDEX(Assumptions!$B$57:$F$57,MIN(D5,5)))*8760*Assumptions!$D$29*(1+Assumptions!$B$71)^(D3-1)/1000000*Assumptions!$B$80 -> 0 | E29: =Assumptions!$B$15*Assumptions!$B$29*Assumptions!$C$29*(1+Assumptions!$B$75)*IF(E5<=0,0,INDEX(Assumptions!$B$57:$F$57,MIN(E5,5)))*8760*Assumptions!$D$29*(1+Assumptions!$B$71)^(E3-1)/1000000*Assumptions!$B$80 -> 0 | F29: =Assumptions!$B$15*Assumptions!$B$29*Assumptions!$C$29*(1+Assumptions!$B$75)*IF(F5<=0,0,INDEX(Assumptions!$B$57:$F$57,MIN(F5,5)))*8760*Assumptions!$D$29*(1+Assumptions!$B$71)^(F3-1)/1000000*Assumptions!$B$80 -> 5.4410208 | G29: =Assumptions!$B$15*Assumptions!$B$29*Assumptions!$C$29*(1+Assumptions!$B$75)*IF(G5<=0,0,INDEX(Assumptions!$B$57:$F$57,MIN(G5,5)))*8760*Assumptions!$D$29*(1+Assumptions!$B$71)^(G3-1)/1000000*Assumptions!$B$80 -> 6.506554 | H29: =Assumptions!$B$15*Assumptions!$B$29*Assumptions!$C$29*(1+Assumptions!$B$75)*IF(H5<=0,0,INDEX(Assumptions!$B$57:$F$57,MIN(H5,5)))*8760*Assumptions!$D$29*(1+Assumptions!$B$71)^(H3-1)/1000000*Assumptions!$B$80 -> 8.098336 | I29: =Assumptions!$B$15*Assumptions!$B$29*Assumptions!$C$29*(1+Assumptions!$B$75)*IF(I5<=0,0,INDEX(Assumptions!$B$57:$F$57,MIN(I5,5)))*8760*Assumptions!$D$29*(1+Assumptions!$B$71)^(I3-1)/1000000*Assumptions!$B$80 -> 9.2773584 | J29: =Assumptions!$B$15*Assumptions!$B$29*Assumptions!$C$29*(1+Assumptions!$B$75)*IF(J5<=0,0,INDEX(Assumptions!$B$57:$F$57,MIN(J5,5)))*8760*Assumptions!$D$29*(1+Assumptions!$B$71)^(J3-1)/1000000*Assumptions!$B$80 -> 10.009781 | K29: =Assumptions!$B$15*Assumptions!$B$29*Assumptions!$C$29*(1+Assumptions!$B$75)*IF(K5<=0,0,INDEX(Assumptions!$B$57:$F$57,MIN(K5,5)))*8760*Assumptions!$D$29*(1+Assumptions!$B$71)^(K3-1)/1000000*Assumptions!$B$80 -> 10.260026 | ... AG29: =Assumptions!$B$15*Assumptions!$B$29*Assumptions!$C$29*(1+Assumptions!$B$75)*IF(AG5<=0,0,INDEX(Assumptions!$B$57:$F$57,MIN(AG5,5)))*8760*Assumptions!$D$29*(1+Assumptions!$B$71)^(AG3-1)/1000000*Assumptions!$B$80 -> 17.663367
A30: Parking - Regional (3) | D30: =Assumptions!$B$16*Assumptions!$B$30*Assumptions!$C$30*(1+Assumptions!$B$75)*IF(D6<=0,0,INDEX(Assumptions!$B$57:$F$57,MIN(D6,5)))*8760*Assumptions!$D$30*(1+Assumptions!$B$71)^(D3-1)/1000000*Assumptions!$B$80 -> 0 | E30: =Assumptions!$B$16*Assumptions!$B$30*Assumptions!$C$30*(1+Assumptions!$B$75)*IF(E6<=0,0,INDEX(Assumptions!$B$57:$F$57,MIN(E6,5)))*8760*Assumptions!$D$30*(1+Assumptions!$B$71)^(E3-1)/1000000*Assumptions!$B$80 -> 0 | F30: =Assumptions!$B$16*Assumptions!$B$30*Assumptions!$C$30*(1+Assumptions!$B$75)*IF(F6<=0,0,INDEX(Assumptions!$B$57:$F$57,MIN(F6,5)))*8760*Assumptions!$D$30*(1+Assumptions!$B$71)^(F3-1)/1000000*Assumptions!$B$80 -> 0 | G30: =Assumptions!$B$16*Assumptions!$B$30*Assumptions!$C$30*(1+Assumptions!$B$75)*IF(G6<=0,0,INDEX(Assumptions!$B$57:$F$57,MIN(G6,5)))*8760*Assumptions!$D$30*(1+Assumptions!$B$71)^(G3-1)/1000000*Assumptions!$B$80 -> 5.4558062 | H30: =Assumptions!$B$16*Assumptions!$B$30*Assumptions!$C$30*(1+Assumptions!$B$75)*IF(H6<=0,0,INDEX(Assumptions!$B$57:$F$57,MIN(H6,5)))*8760*Assumptions!$D$30*(1+Assumptions!$B$71)^(H3-1)/1000000*Assumptions!$B$80 -> 6.5242349 | I30: =Assumptions!$B$16*Assumptions!$B$30*Assumptions!$C$30*(1+Assumptions!$B$75)*IF(I6<=0,0,INDEX(Assumptions!$B$57:$F$57,MIN(I6,5)))*8760*Assumptions!$D$30*(1+Assumptions!$B$71)^(I3-1)/1000000*Assumptions!$B$80 -> 8.1203423 | J30: =Assumptions!$B$16*Assumptions!$B$30*Assumptions!$C$30*(1+Assumptions!$B$75)*IF(J6<=0,0,INDEX(Assumptions!$B$57:$F$57,MIN(J6,5)))*8760*Assumptions!$D$30*(1+Assumptions!$B$71)^(J3-1)/1000000*Assumptions!$B$80 -> 9.3025687 | K30: =Assumptions!$B$16*Assumptions!$B$30*Assumptions!$C$30*(1+Assumptions!$B$75)*IF(K6<=0,0,INDEX(Assumptions!$B$57:$F$57,MIN(K6,5)))*8760*Assumptions!$D$30*(1+Assumptions!$B$71)^(K3-1)/1000000*Assumptions!$B$80 -> 10.036982 | ... AG30: =Assumptions!$B$16*Assumptions!$B$30*Assumptions!$C$30*(1+Assumptions!$B$75)*IF(AG6<=0,0,INDEX(Assumptions!$B$57:$F$57,MIN(AG6,5)))*8760*Assumptions!$D$30*(1+Assumptions!$B$71)^(AG3-1)/1000000*Assumptions!$B$80 -> 17.279381
A31: Parking - Infill (4) | D31: =Assumptions!$B$17*Assumptions!$B$31*Assumptions!$C$31*(1+Assumptions!$B$75)*IF(D6<=0,0,INDEX(Assumptions!$B$57:$F$57,MIN(D6,5)))*8760*Assumptions!$D$31*(1+Assumptions!$B$71)^(D3-1)/1000000*Assumptions!$B$80 -> 0 | E31: =Assumptions!$B$17*Assumptions!$B$31*Assumptions!$C$31*(1+Assumptions!$B$75)*IF(E6<=0,0,INDEX(Assumptions!$B$57:$F$57,MIN(E6,5)))*8760*Assumptions!$D$31*(1+Assumptions!$B$71)^(E3-1)/1000000*Assumptions!$B$80 -> 0 | F31: =Assumptions!$B$17*Assumptions!$B$31*Assumptions!$C$31*(1+Assumptions!$B$75)*IF(F6<=0,0,INDEX(Assumptions!$B$57:$F$57,MIN(F6,5)))*8760*Assumptions!$D$31*(1+Assumptions!$B$71)^(F3-1)/1000000*Assumptions!$B$80 -> 0 | G31: =Assumptions!$B$17*Assumptions!$B$31*Assumptions!$C$31*(1+Assumptions!$B$75)*IF(G6<=0,0,INDEX(Assumptions!$B$57:$F$57,MIN(G6,5)))*8760*Assumptions!$D$31*(1+Assumptions!$B$71)^(G3-1)/1000000*Assumptions!$B$80 -> 2.5864563 | H31: =Assumptions!$B$17*Assumptions!$B$31*Assumptions!$C$31*(1+Assumptions!$B$75)*IF(H6<=0,0,INDEX(Assumptions!$B$57:$F$57,MIN(H6,5)))*8760*Assumptions!$D$31*(1+Assumptions!$B$71)^(H3-1)/1000000*Assumptions!$B$80 -> 3.0929706 | I31: =Assumptions!$B$17*Assumptions!$B$31*Assumptions!$C$31*(1+Assumptions!$B$75)*IF(I6<=0,0,INDEX(Assumptions!$B$57:$F$57,MIN(I6,5)))*8760*Assumptions!$D$31*(1+Assumptions!$B$71)^(I3-1)/1000000*Assumptions!$B$80 -> 3.8496438 | J31: =Assumptions!$B$17*Assumptions!$B$31*Assumptions!$C$31*(1+Assumptions!$B$75)*IF(J6<=0,0,INDEX(Assumptions!$B$57:$F$57,MIN(J6,5)))*8760*Assumptions!$D$31*(1+Assumptions!$B$71)^(J3-1)/1000000*Assumptions!$B$80 -> 4.4101066 | K31: =Assumptions!$B$17*Assumptions!$B$31*Assumptions!$C$31*(1+Assumptions!$B$75)*IF(K6<=0,0,INDEX(Assumptions!$B$57:$F$57,MIN(K6,5)))*8760*Assumptions!$D$31*(1+Assumptions!$B$71)^(K3-1)/1000000*Assumptions!$B$80 -> 4.7582729 | ... AG31: =Assumptions!$B$17*Assumptions!$B$31*Assumptions!$C$31*(1+Assumptions!$B$75)*IF(AG6<=0,0,INDEX(Assumptions!$B$57:$F$57,MIN(AG6,5)))*8760*Assumptions!$D$31*(1+Assumptions!$B$71)^(AG3-1)/1000000*Assumptions!$B$80 -> 8.1917066
A32: Recovery Pods - Mega Hub | D32: =Assumptions!$B$15*Assumptions!$B$36*(IF(D5<=0,0,IF(D5<=5,Assumptions!$C$36/5*D5,IF(D5<=10,Assumptions!$C$36+(Assumptions!$D$36-Assumptions!$C$36)*(D5-5)/5,Assumptions!$D$36))))*365*(1+Assumptions!$B$75)*Assumptions!$E$36*(1+Assumptions!$B$71)^(D3-1)/1000000*Assumptions!$B$80 -> 0 | E32: =Assumptions!$B$15*Assumptions!$B$36*(IF(E5<=0,0,IF(E5<=5,Assumptions!$C$36/5*E5,IF(E5<=10,Assumptions!$C$36+(Assumptions!$D$36-Assumptions!$C$36)*(E5-5)/5,Assumptions!$D$36))))*365*(1+Assumptions!$B$75)*Assumptions!$E$36*(1+Assumptions!$B$71)^(E3-1)/1000000*Assumptions!$B$80 -> 0 | F32: =Assumptions!$B$15*Assumptions!$B$36*(IF(F5<=0,0,IF(F5<=5,Assumptions!$C$36/5*F5,IF(F5<=10,Assumptions!$C$36+(Assumptions!$D$36-Assumptions!$C$36)*(F5-5)/5,Assumptions!$D$36))))*365*(1+Assumptions!$B$75)*Assumptions!$E$36*(1+Assumptions!$B$71)^(F3-1)/1000000*Assumptions!$B$80 -> 0.090596707 | G32: =Assumptions!$B$15*Assumptions!$B$36*(IF(G5<=0,0,IF(G5<=5,Assumptions!$C$36/5*G5,IF(G5<=10,Assumptions!$C$36+(Assumptions!$D$36-Assumptions!$C$36)*(G5-5)/5,Assumptions!$D$36))))*365*(1+Assumptions!$B$75)*Assumptions!$E$36*(1+Assumptions!$B$71)^(G3-1)/1000000*Assumptions!$B$80 -> 0.18572325 | H32: =Assumptions!$B$15*Assumptions!$B$36*(IF(H5<=0,0,IF(H5<=5,Assumptions!$C$36/5*H5,IF(H5<=10,Assumptions!$C$36+(Assumptions!$D$36-Assumptions!$C$36)*(H5-5)/5,Assumptions!$D$36))))*365*(1+Assumptions!$B$75)*Assumptions!$E$36*(1+Assumptions!$B$71)^(H3-1)/1000000*Assumptions!$B$80 -> 0.2855495 | I32: =Assumptions!$B$15*Assumptions!$B$36*(IF(I5<=0,0,IF(I5<=5,Assumptions!$C$36/5*I5,IF(I5<=10,Assumptions!$C$36+(Assumptions!$D$36-Assumptions!$C$36)*(I5-5)/5,Assumptions!$D$36))))*365*(1+Assumptions!$B$75)*Assumptions!$E$36*(1+Assumptions!$B$71)^(I3-1)/1000000*Assumptions!$B$80 -> 0.39025098 | J32: =Assumptions!$B$15*Assumptions!$B$36*(IF(J5<=0,0,IF(J5<=5,Assumptions!$C$36/5*J5,IF(J5<=10,Assumptions!$C$36+(Assumptions!$D$36-Assumptions!$C$36)*(J5-5)/5,Assumptions!$D$36))))*365*(1+Assumptions!$B$75)*Assumptions!$E$36*(1+Assumptions!$B$71)^(J3-1)/1000000*Assumptions!$B$80 -> 0.50000907 | K32: =Assumptions!$B$15*Assumptions!$B$36*(IF(K5<=0,0,IF(K5<=5,Assumptions!$C$36/5*K5,IF(K5<=10,Assumptions!$C$36+(Assumptions!$D$36-Assumptions!$C$36)*(K5-5)/5,Assumptions!$D$36))))*365*(1+Assumptions!$B$75)*Assumptions!$E$36*(1+Assumptions!$B$71)^(K3-1)/1000000*Assumptions!$B$80 -> 0.56945477 | ... AG32: =Assumptions!$B$15*Assumptions!$B$36*(IF(AG5<=0,0,IF(AG5<=5,Assumptions!$C$36/5*AG5,IF(AG5<=10,Assumptions!$C$36+(Assumptions!$D$36-Assumptions!$C$36)*(AG5-5)/5,Assumptions!$D$36))))*365*(1+Assumptions!$B$75)*Assumptions!$E$36*(1+Assumptions!$B$71)^(AG3-1)/1000000*Assumptions!$B$80 -> 1.3724999
A33: Recovery Pods - Regional (3) | D33: =Assumptions!$B$16*Assumptions!$B$37*(IF(D6<=0,0,IF(D6<=5,Assumptions!$C$37/5*D6,IF(D6<=10,Assumptions!$C$37+(Assumptions!$D$37-Assumptions!$C$37)*(D6-5)/5,Assumptions!$D$37))))*365*(1+Assumptions!$B$75)*Assumptions!$E$37*(1+Assumptions!$B$71)^(D3-1)/1000000*Assumptions!$B$80 -> 0 | E33: =Assumptions!$B$16*Assumptions!$B$37*(IF(E6<=0,0,IF(E6<=5,Assumptions!$C$37/5*E6,IF(E6<=10,Assumptions!$C$37+(Assumptions!$D$37-Assumptions!$C$37)*(E6-5)/5,Assumptions!$D$37))))*365*(1+Assumptions!$B$75)*Assumptions!$E$37*(1+Assumptions!$B$71)^(E3-1)/1000000*Assumptions!$B$80 -> 0 | F33: =Assumptions!$B$16*Assumptions!$B$37*(IF(F6<=0,0,IF(F6<=5,Assumptions!$C$37/5*F6,IF(F6<=10,Assumptions!$C$37+(Assumptions!$D$37-Assumptions!$C$37)*(F6-5)/5,Assumptions!$D$37))))*365*(1+Assumptions!$B$75)*Assumptions!$E$37*(1+Assumptions!$B$71)^(F3-1)/1000000*Assumptions!$B$80 -> 0 | G33: =Assumptions!$B$16*Assumptions!$B$37*(IF(G6<=0,0,IF(G6<=5,Assumptions!$C$37/5*G6,IF(G6<=10,Assumptions!$C$37+(Assumptions!$D$37-Assumptions!$C$37)*(G6-5)/5,Assumptions!$D$37))))*365*(1+Assumptions!$B$75)*Assumptions!$E$37*(1+Assumptions!$B$71)^(G3-1)/1000000*Assumptions!$B$80 -> 0.1733417 | H33: =Assumptions!$B$16*Assumptions!$B$37*(IF(H6<=0,0,IF(H6<=5,Assumptions!$C$37/5*H6,IF(H6<=10,Assumptions!$C$37+(Assumptions!$D$37-Assumptions!$C$37)*(H6-5)/5,Assumptions!$D$37))))*365*(1+Assumptions!$B$75)*Assumptions!$E$37*(1+Assumptions!$B$71)^(H3-1)/1000000*Assumptions!$B$80 -> 0.35535048 | I33: =Assumptions!$B$16*Assumptions!$B$37*(IF(I6<=0,0,IF(I6<=5,Assumptions!$C$37/5*I6,IF(I6<=10,Assumptions!$C$37+(Assumptions!$D$37-Assumptions!$C$37)*(I6-5)/5,Assumptions!$D$37))))*365*(1+Assumptions!$B$75)*Assumptions!$E$37*(1+Assumptions!$B$71)^(I3-1)/1000000*Assumptions!$B$80 -> 0.54635137 | J33: =Assumptions!$B$16*Assumptions!$B$37*(IF(J6<=0,0,IF(J6<=5,Assumptions!$C$37/5*J6,IF(J6<=10,Assumptions!$C$37+(Assumptions!$D$37-Assumptions!$C$37)*(J6-5)/5,Assumptions!$D$37))))*365*(1+Assumptions!$B$75)*Assumptions!$E$37*(1+Assumptions!$B$71)^(J3-1)/1000000*Assumptions!$B$80 -> 0.7466802 | K33: =Assumptions!$B$16*Assumptions!$B$37*(IF(K6<=0,0,IF(K6<=5,Assumptions!$C$37/5*K6,IF(K6<=10,Assumptions!$C$37+(Assumptions!$D$37-Assumptions!$C$37)*(K6-5)/5,Assumptions!$D$37))))*365*(1+Assumptions!$B$75)*Assumptions!$E$37*(1+Assumptions!$B$71)^(K3-1)/1000000*Assumptions!$B$80 -> 0.95668401 | ... AG33: =Assumptions!$B$16*Assumptions!$B$37*(IF(AG6<=0,0,IF(AG6<=5,Assumptions!$C$37/5*AG6,IF(AG6<=10,Assumptions!$C$37+(Assumptions!$D$37-Assumptions!$C$37)*(AG6-5)/5,Assumptions!$D$37))))*365*(1+Assumptions!$B$75)*Assumptions!$E$37*(1+Assumptions!$B$71)^(AG3-1)/1000000*Assumptions!$B$80 -> 2.6763747
A34: Recovery Pods - Infill (4) | D34: =Assumptions!$B$17*Assumptions!$B$38*(IF(D6<=0,0,IF(D6<=5,Assumptions!$C$38/5*D6,IF(D6<=10,Assumptions!$C$38+(Assumptions!$D$38-Assumptions!$C$38)*(D6-5)/5,Assumptions!$D$38))))*365*(1+Assumptions!$B$75)*Assumptions!$E$38*(1+Assumptions!$B$71)^(D3-1)/1000000*Assumptions!$B$80 -> 0 | E34: =Assumptions!$B$17*Assumptions!$B$38*(IF(E6<=0,0,IF(E6<=5,Assumptions!$C$38/5*E6,IF(E6<=10,Assumptions!$C$38+(Assumptions!$D$38-Assumptions!$C$38)*(E6-5)/5,Assumptions!$D$38))))*365*(1+Assumptions!$B$75)*Assumptions!$E$38*(1+Assumptions!$B$71)^(E3-1)/1000000*Assumptions!$B$80 -> 0 | F34: =Assumptions!$B$17*Assumptions!$B$38*(IF(F6<=0,0,IF(F6<=5,Assumptions!$C$38/5*F6,IF(F6<=10,Assumptions!$C$38+(Assumptions!$D$38-Assumptions!$C$38)*(F6-5)/5,Assumptions!$D$38))))*365*(1+Assumptions!$B$75)*Assumptions!$E$38*(1+Assumptions!$B$71)^(F3-1)/1000000*Assumptions!$B$80 -> 0 | G34: =Assumptions!$B$17*Assumptions!$B$38*(IF(G6<=0,0,IF(G6<=5,Assumptions!$C$38/5*G6,IF(G6<=10,Assumptions!$C$38+(Assumptions!$D$38-Assumptions!$C$38)*(G6-5)/5,Assumptions!$D$38))))*365*(1+Assumptions!$B$75)*Assumptions!$E$38*(1+Assumptions!$B$71)^(G3-1)/1000000*Assumptions!$B$80 -> 0.11556113 | H34: =Assumptions!$B$17*Assumptions!$B$38*(IF(H6<=0,0,IF(H6<=5,Assumptions!$C$38/5*H6,IF(H6<=10,Assumptions!$C$38+(Assumptions!$D$38-Assumptions!$C$38)*(H6-5)/5,Assumptions!$D$38))))*365*(1+Assumptions!$B$75)*Assumptions!$E$38*(1+Assumptions!$B$71)^(H3-1)/1000000*Assumptions!$B$80 -> 0.23690032 | I34: =Assumptions!$B$17*Assumptions!$B$38*(IF(I6<=0,0,IF(I6<=5,Assumptions!$C$38/5*I6,IF(I6<=10,Assumptions!$C$38+(Assumptions!$D$38-Assumptions!$C$38)*(I6-5)/5,Assumptions!$D$38))))*365*(1+Assumptions!$B$75)*Assumptions!$E$38*(1+Assumptions!$B$71)^(I3-1)/1000000*Assumptions!$B$80 -> 0.36423425 | J34: =Assumptions!$B$17*Assumptions!$B$38*(IF(J6<=0,0,IF(J6<=5,Assumptions!$C$38/5*J6,IF(J6<=10,Assumptions!$C$38+(Assumptions!$D$38-Assumptions!$C$38)*(J6-5)/5,Assumptions!$D$38))))*365*(1+Assumptions!$B$75)*Assumptions!$E$38*(1+Assumptions!$B$71)^(J3-1)/1000000*Assumptions!$B$80 -> 0.4977868 | K34: =Assumptions!$B$17*Assumptions!$B$38*(IF(K6<=0,0,IF(K6<=5,Assumptions!$C$38/5*K6,IF(K6<=10,Assumptions!$C$38+(Assumptions!$D$38-Assumptions!$C$38)*(K6-5)/5,Assumptions!$D$38))))*365*(1+Assumptions!$B$75)*Assumptions!$E$38*(1+Assumptions!$B$71)^(K3-1)/1000000*Assumptions!$B$80 -> 0.63778934 | ... AG34: =Assumptions!$B$17*Assumptions!$B$38*(IF(AG6<=0,0,IF(AG6<=5,Assumptions!$C$38/5*AG6,IF(AG6<=10,Assumptions!$C$38+(Assumptions!$D$38-Assumptions!$C$38)*(AG6-5)/5,Assumptions!$D$38))))*365*(1+Assumptions!$B$75)*Assumptions!$E$38*(1+Assumptions!$B$71)^(AG3-1)/1000000*Assumptions!$B$80 -> 1.8822855
A35: Fleet Subscriptions (network) | D35: =IF(D3<3,0,IF(D3<=10,Assumptions!$B$42+(Assumptions!$B$43-Assumptions!$B$42)*(D3-3)/7,Assumptions!$B$43))*Assumptions!$B$44*12*(1+Assumptions!$B$75)*(1+Assumptions!$B$71)^(D3-1)/1000000 -> 0 | E35: =IF(E3<3,0,IF(E3<=10,Assumptions!$B$42+(Assumptions!$B$43-Assumptions!$B$42)*(E3-3)/7,Assumptions!$B$43))*Assumptions!$B$44*12*(1+Assumptions!$B$75)*(1+Assumptions!$B$71)^(E3-1)/1000000 -> 0 | F35: =IF(F3<3,0,IF(F3<=10,Assumptions!$B$42+(Assumptions!$B$43-Assumptions!$B$42)*(F3-3)/7,Assumptions!$B$43))*Assumptions!$B$44*12*(1+Assumptions!$B$75)*(1+Assumptions!$B$71)^(F3-1)/1000000 -> 2.0487187 | G35: =IF(G3<3,0,IF(G3<=10,Assumptions!$B$42+(Assumptions!$B$43-Assumptions!$B$42)*(G3-3)/7,Assumptions!$B$43))*Assumptions!$B$44*12*(1+Assumptions!$B$75)*(1+Assumptions!$B$71)^(G3-1)/1000000 -> 2.6399204 | H35: =IF(H3<3,0,IF(H3<=10,Assumptions!$B$42+(Assumptions!$B$43-Assumptions!$B$42)*(H3-3)/7,Assumptions!$B$43))*Assumptions!$B$44*12*(1+Assumptions!$B$75)*(1+Assumptions!$B$71)^(H3-1)/1000000 -> 3.2594018 | I35: =IF(I3<3,0,IF(I3<=10,Assumptions!$B$42+(Assumptions!$B$43-Assumptions!$B$42)*(I3-3)/7,Assumptions!$B$43))*Assumptions!$B$44*12*(1+Assumptions!$B$75)*(1+Assumptions!$B$71)^(I3-1)/1000000 -> 3.9082072 | J35: =IF(J3<3,0,IF(J3<=10,Assumptions!$B$42+(Assumptions!$B$43-Assumptions!$B$42)*(J3-3)/7,Assumptions!$B$43))*Assumptions!$B$44*12*(1+Assumptions!$B$75)*(1+Assumptions!$B$71)^(J3-1)/1000000 -> 4.5874158 | K35: =IF(K3<3,0,IF(K3<=10,Assumptions!$B$42+(Assumptions!$B$43-Assumptions!$B$42)*(K3-3)/7,Assumptions!$B$43))*Assumptions!$B$44*12*(1+Assumptions!$B$75)*(1+Assumptions!$B$71)^(K3-1)/1000000 -> 5.2981422 | ... AG35: =IF(AG3<3,0,IF(AG3<=10,Assumptions!$B$42+(Assumptions!$B$43-Assumptions!$B$42)*(AG3-3)/7,Assumptions!$B$43))*Assumptions!$B$44*12*(1+Assumptions!$B$75)*(1+Assumptions!$B$71)^(AG3-1)/1000000 -> 11.173384
A36: Digital Platform (network) | D36: =IF(D3<3,0,IF(D3<=10,Assumptions!$B$45+(Assumptions!$B$46-Assumptions!$B$45)*(D3-3)/7,Assumptions!$B$46))*(1+Assumptions!$B$71)^(D3-1) -> 0 | E36: =IF(E3<3,0,IF(E3<=10,Assumptions!$B$45+(Assumptions!$B$46-Assumptions!$B$45)*(E3-3)/7,Assumptions!$B$46))*(1+Assumptions!$B$71)^(E3-1) -> 0 | F36: =IF(F3<3,0,IF(F3<=10,Assumptions!$B$45+(Assumptions!$B$46-Assumptions!$B$45)*(F3-3)/7,Assumptions!$B$46))*(1+Assumptions!$B$71)^(F3-1) -> 0.630375 | G36: =IF(G3<3,0,IF(G3<=10,Assumptions!$B$45+(Assumptions!$B$46-Assumptions!$B$45)*(G3-3)/7,Assumptions!$B$46))*(1+Assumptions!$B$71)^(G3-1) -> 0.83843627 | H36: =IF(H3<3,0,IF(H3<=10,Assumptions!$B$45+(Assumptions!$B$46-Assumptions!$B$45)*(H3-3)/7,Assumptions!$B$46))*(1+Assumptions!$B$71)^(H3-1) -> 1.0565066 | I36: =IF(I3<3,0,IF(I3<=10,Assumptions!$B$45+(Assumptions!$B$46-Assumptions!$B$45)*(I3-3)/7,Assumptions!$B$46))*(1+Assumptions!$B$71)^(I3-1) -> 1.2849565 | J36: =IF(J3<3,0,IF(J3<=10,Assumptions!$B$45+(Assumptions!$B$46-Assumptions!$B$45)*(J3-3)/7,Assumptions!$B$46))*(1+Assumptions!$B$71)^(J3-1) -> 1.5241685 | K36: =IF(K3<3,0,IF(K3<=10,Assumptions!$B$45+(Assumptions!$B$46-Assumptions!$B$45)*(K3-3)/7,Assumptions!$B$46))*(1+Assumptions!$B$71)^(K3-1) -> 1.774538 | ... AG36: =IF(AG3<3,0,IF(AG3<=10,Assumptions!$B$45+(Assumptions!$B$46-Assumptions!$B$45)*(AG3-3)/7,Assumptions!$B$46))*(1+Assumptions!$B$71)^(AG3-1) -> 3.7858537
A37: Other/Ancillary - Mega Hub | D37: =Assumptions!$B$15*Assumptions!$B$50*IF(D5<=0,0,INDEX(Assumptions!$B$57:$F$57,MIN(D5,5)))*(1+Assumptions!$B$71)^(D3-1) -> 0 | E37: =Assumptions!$B$15*Assumptions!$B$50*IF(E5<=0,0,INDEX(Assumptions!$B$57:$F$57,MIN(E5,5)))*(1+Assumptions!$B$71)^(E3-1) -> 0 | F37: =Assumptions!$B$15*Assumptions!$B$50*IF(F5<=0,0,INDEX(Assumptions!$B$57:$F$57,MIN(F5,5)))*(1+Assumptions!$B$71)^(F3-1) -> 0.9455625 | G37: =Assumptions!$B$15*Assumptions!$B$50*IF(G5<=0,0,INDEX(Assumptions!$B$57:$F$57,MIN(G5,5)))*(1+Assumptions!$B$71)^(G3-1) -> 1.1307352 | H37: =Assumptions!$B$15*Assumptions!$B$50*IF(H5<=0,0,INDEX(Assumptions!$B$57:$F$57,MIN(H5,5)))*(1+Assumptions!$B$71)^(H3-1) -> 1.4073614 | I37: =Assumptions!$B$15*Assumptions!$B$50*IF(I5<=0,0,INDEX(Assumptions!$B$57:$F$57,MIN(I5,5)))*(1+Assumptions!$B$71)^(I3-1) -> 1.6122567 | J37: =Assumptions!$B$15*Assumptions!$B$50*IF(J5<=0,0,INDEX(Assumptions!$B$57:$F$57,MIN(J5,5)))*(1+Assumptions!$B$71)^(J3-1) -> 1.7395401 | K37: =Assumptions!$B$15*Assumptions!$B$50*IF(K5<=0,0,INDEX(Assumptions!$B$57:$F$57,MIN(K5,5)))*(1+Assumptions!$B$71)^(K3-1) -> 1.7830286 | ... AG37: =Assumptions!$B$15*Assumptions!$B$50*IF(AG5<=0,0,INDEX(Assumptions!$B$57:$F$57,MIN(AG5,5)))*(1+Assumptions!$B$71)^(AG3-1) -> 3.0696111
A38: Other/Ancillary - Regional (3) | D38: =Assumptions!$B$16*Assumptions!$B$51*IF(D6<=0,0,INDEX(Assumptions!$B$57:$F$57,MIN(D6,5)))*(1+Assumptions!$B$71)^(D3-1) -> 0 | E38: =Assumptions!$B$16*Assumptions!$B$51*IF(E6<=0,0,INDEX(Assumptions!$B$57:$F$57,MIN(E6,5)))*(1+Assumptions!$B$71)^(E3-1) -> 0 | F38: =Assumptions!$B$16*Assumptions!$B$51*IF(F6<=0,0,INDEX(Assumptions!$B$57:$F$57,MIN(F6,5)))*(1+Assumptions!$B$71)^(F3-1) -> 0 | G38: =Assumptions!$B$16*Assumptions!$B$51*IF(G6<=0,0,INDEX(Assumptions!$B$57:$F$57,MIN(G6,5)))*(1+Assumptions!$B$71)^(G3-1) -> 0.96920156 | H38: =Assumptions!$B$16*Assumptions!$B$51*IF(H6<=0,0,INDEX(Assumptions!$B$57:$F$57,MIN(H6,5)))*(1+Assumptions!$B$71)^(H3-1) -> 1.1590035 | I38: =Assumptions!$B$16*Assumptions!$B$51*IF(I6<=0,0,INDEX(Assumptions!$B$57:$F$57,MIN(I6,5)))*(1+Assumptions!$B$71)^(I3-1) -> 1.4425455 | J38: =Assumptions!$B$16*Assumptions!$B$51*IF(J6<=0,0,INDEX(Assumptions!$B$57:$F$57,MIN(J6,5)))*(1+Assumptions!$B$71)^(J3-1) -> 1.6525631 | K38: =Assumptions!$B$16*Assumptions!$B$51*IF(K6<=0,0,INDEX(Assumptions!$B$57:$F$57,MIN(K6,5)))*(1+Assumptions!$B$71)^(K3-1) -> 1.7830286 | ... AG38: =Assumptions!$B$16*Assumptions!$B$51*IF(AG6<=0,0,INDEX(Assumptions!$B$57:$F$57,MIN(AG6,5)))*(1+Assumptions!$B$71)^(AG3-1) -> 3.0696111
A39: Other/Ancillary - Infill (4) | D39: =Assumptions!$B$17*Assumptions!$B$52*IF(D6<=0,0,INDEX(Assumptions!$B$57:$F$57,MIN(D6,5)))*(1+Assumptions!$B$71)^(D3-1) -> 0 | E39: =Assumptions!$B$17*Assumptions!$B$52*IF(E6<=0,0,INDEX(Assumptions!$B$57:$F$57,MIN(E6,5)))*(1+Assumptions!$B$71)^(E3-1) -> 0 | F39: =Assumptions!$B$17*Assumptions!$B$52*IF(F6<=0,0,INDEX(Assumptions!$B$57:$F$57,MIN(F6,5)))*(1+Assumptions!$B$71)^(F3-1) -> 0 | G39: =Assumptions!$B$17*Assumptions!$B$52*IF(G6<=0,0,INDEX(Assumptions!$B$57:$F$57,MIN(G6,5)))*(1+Assumptions!$B$71)^(G3-1) -> 0.5169075 | H39: =Assumptions!$B$17*Assumptions!$B$52*IF(H6<=0,0,INDEX(Assumptions!$B$57:$F$57,MIN(H6,5)))*(1+Assumptions!$B$71)^(H3-1) -> 0.61813522 | I39: =Assumptions!$B$17*Assumptions!$B$52*IF(I6<=0,0,INDEX(Assumptions!$B$57:$F$57,MIN(I6,5)))*(1+Assumptions!$B$71)^(I3-1) -> 0.76935758 | J39: =Assumptions!$B$17*Assumptions!$B$52*IF(J6<=0,0,INDEX(Assumptions!$B$57:$F$57,MIN(J6,5)))*(1+Assumptions!$B$71)^(J3-1) -> 0.881367 | K39: =Assumptions!$B$17*Assumptions!$B$52*IF(K6<=0,0,INDEX(Assumptions!$B$57:$F$57,MIN(K6,5)))*(1+Assumptions!$B$71)^(K3-1) -> 0.9509486 | ... AG39: =Assumptions!$B$17*Assumptions!$B$52*IF(AG6<=0,0,INDEX(Assumptions!$B$57:$F$57,MIN(AG6,5)))*(1+Assumptions!$B$71)^(AG3-1) -> 1.6371259
A40: TOTAL COMMERCIAL REVENUE | D40: ='Site Detail'!D75+'Site Detail'!D76+D35+D36+'Site Detail'!D77 -> 0 | E40: ='Site Detail'!E75+'Site Detail'!E76+E35+E36+'Site Detail'!E77 -> 0 | F40: ='Site Detail'!F75+'Site Detail'!F76+F35+F36+'Site Detail'!F77 -> 9.1562737 | G40: ='Site Detail'!G75+'Site Detail'!G76+G35+G36+'Site Detail'!G77 -> 21.137904 | H40: ='Site Detail'!H75+'Site Detail'!H76+H35+H36+'Site Detail'!H77 -> 26.119427 | I40: ='Site Detail'!I75+'Site Detail'!I76+I35+I36+'Site Detail'!I77 -> 31.599321 | J40: ='Site Detail'!J75+'Site Detail'!J76+J35+J36+'Site Detail'!J77 -> 35.892884 | K40: ='Site Detail'!K75+'Site Detail'!K76+K35+K36+'Site Detail'!K77 -> 38.855718 | ... AG40: ='Site Detail'!AG75+'Site Detail'!AG76+AG35+AG36+'Site Detail'!AG77 -> 71.901417
A42: OPERATING COSTS ($M)
A44: Mega Hub Opex | D44: =IF(D5>0,Assumptions!$B$15*Assumptions!$D$15*(1+Assumptions!$B$71)^(D3-1),0) -> 0 | E44: =IF(E5>0,Assumptions!$B$15*Assumptions!$D$15*(1+Assumptions!$B$71)^(E3-1),0) -> 0 | F44: =IF(F5>0,Assumptions!$B$15*Assumptions!$D$15*(1+Assumptions!$B$71)^(F3-1),0) -> 12.6075 | G44: =IF(G5>0,Assumptions!$B$15*Assumptions!$D$15*(1+Assumptions!$B$71)^(G3-1),0) -> 12.922687 | H44: =IF(H5>0,Assumptions!$B$15*Assumptions!$D$15*(1+Assumptions!$B$71)^(H3-1),0) -> 13.245755 | I44: =IF(I5>0,Assumptions!$B$15*Assumptions!$D$15*(1+Assumptions!$B$71)^(I3-1),0) -> 13.576899 | J44: =IF(J5>0,Assumptions!$B$15*Assumptions!$D$15*(1+Assumptions!$B$71)^(J3-1),0) -> 13.916321 | K44: =IF(K5>0,Assumptions!$B$15*Assumptions!$D$15*(1+Assumptions!$B$71)^(K3-1),0) -> 14.264229 | ... AG44: =IF(AG5>0,Assumptions!$B$15*Assumptions!$D$15*(1+Assumptions!$B$71)^(AG3-1),0) -> 24.556889
A45: Regional Opex (3 sites) | D45: =IF(D6>0,Assumptions!$B$16*Assumptions!$D$16*(1+Assumptions!$B$71)^(D3-1),0) -> 0 | E45: =IF(E6>0,Assumptions!$B$16*Assumptions!$D$16*(1+Assumptions!$B$71)^(E3-1),0) -> 0 | F45: =IF(F6>0,Assumptions!$B$16*Assumptions!$D$16*(1+Assumptions!$B$71)^(F3-1),0) -> 0 | G45: =IF(G6>0,Assumptions!$B$16*Assumptions!$D$16*(1+Assumptions!$B$71)^(G3-1),0) -> 12.050406 | H45: =IF(H6>0,Assumptions!$B$16*Assumptions!$D$16*(1+Assumptions!$B$71)^(H3-1),0) -> 12.351666 | I45: =IF(I6>0,Assumptions!$B$16*Assumptions!$D$16*(1+Assumptions!$B$71)^(I3-1),0) -> 12.660458 | J45: =IF(J6>0,Assumptions!$B$16*Assumptions!$D$16*(1+Assumptions!$B$71)^(J3-1),0) -> 12.976969 | K45: =IF(K6>0,Assumptions!$B$16*Assumptions!$D$16*(1+Assumptions!$B$71)^(K3-1),0) -> 13.301394 | ... AG45: =IF(AG6>0,Assumptions!$B$16*Assumptions!$D$16*(1+Assumptions!$B$71)^(AG3-1),0) -> 22.899299
A46: Infill Opex (4 sites) | D46: =IF(D6>0,Assumptions!$B$17*Assumptions!$D$17*(1+Assumptions!$B$71)^(D3-1),0) -> 0 | E46: =IF(E6>0,Assumptions!$B$17*Assumptions!$D$17*(1+Assumptions!$B$71)^(E3-1),0) -> 0 | F46: =IF(F6>0,Assumptions!$B$17*Assumptions!$D$17*(1+Assumptions!$B$71)^(F3-1),0) -> 0 | G46: =IF(G6>0,Assumptions!$B$17*Assumptions!$D$17*(1+Assumptions!$B$71)^(G3-1),0) -> 7.925915 | H46: =IF(H6>0,Assumptions!$B$17*Assumptions!$D$17*(1+Assumptions!$B$71)^(H3-1),0) -> 8.1240629 | I46: =IF(I6>0,Assumptions!$B$17*Assumptions!$D$17*(1+Assumptions!$B$71)^(I3-1),0) -> 8.3271644 | J46: =IF(J6>0,Assumptions!$B$17*Assumptions!$D$17*(1+Assumptions!$B$71)^(J3-1),0) -> 8.5353436 | K46: =IF(K6>0,Assumptions!$B$17*Assumptions!$D$17*(1+Assumptions!$B$71)^(K3-1),0) -> 8.7487271 | ... AG46: =IF(AG6>0,Assumptions!$B$17*Assumptions!$D$17*(1+Assumptions!$B$71)^(AG3-1),0) -> 15.061558
A47: Platform/Network Opex | D47: =IF(D3>=Assumptions!$B$9,Assumptions!$B$18*(1+Assumptions!$B$71)^(D3-1),0) -> 0 | E47: =IF(E3>=Assumptions!$B$9,Assumptions!$B$18*(1+Assumptions!$B$71)^(E3-1),0) -> 0 | F47: =IF(F3>=Assumptions!$B$9,Assumptions!$B$18*(1+Assumptions!$B$71)^(F3-1),0) -> 2.731625 | G47: =IF(G3>=Assumptions!$B$9,Assumptions!$B$18*(1+Assumptions!$B$71)^(G3-1),0) -> 2.7999156 | H47: =IF(H3>=Assumptions!$B$9,Assumptions!$B$18*(1+Assumptions!$B$71)^(H3-1),0) -> 2.8699135 | I47: =IF(I3>=Assumptions!$B$9,Assumptions!$B$18*(1+Assumptions!$B$71)^(I3-1),0) -> 2.9416614 | J47: =IF(J3>=Assumptions!$B$9,Assumptions!$B$18*(1+Assumptions!$B$71)^(J3-1),0) -> 3.0152029 | K47: =IF(K3>=Assumptions!$B$9,Assumptions!$B$18*(1+Assumptions!$B$71)^(K3-1),0) -> 3.090583 | ... AG47: =IF(AG3>=Assumptions!$B$9,Assumptions!$B$18*(1+Assumptions!$B$71)^(AG3-1),0) -> 5.3206592
A48: TOTAL OPEX | D48: ='Site Detail'!D78+D47 -> 0 | E48: ='Site Detail'!E78+E47 -> 0 | F48: ='Site Detail'!F78+F47 -> 15.339125 | G48: ='Site Detail'!G78+G47 -> 35.698924 | H48: ='Site Detail'!H78+H47 -> 36.591397 | I48: ='Site Detail'!I78+I47 -> 37.506182 | J48: ='Site Detail'!J78+J47 -> 38.443837 | K48: ='Site Detail'!K78+K47 -> 39.404933 | ... AG48: ='Site Detail'!AG78+AG47 -> 67.838405
A50: CASE A - USER-FUNDED ONLY (no availability payment)
A52: EBITDA | D52: =D40-D48 -> 0 | E52: =E40-E48 -> 0 | F52: =F40-F48 -> -6.1828513 | G52: =G40-G48 -> -14.56102 | H52: =H40-H48 -> -10.47197 | I52: =I40-I48 -> -5.9068611 | J52: =J40-J48 -> -2.5509527 | K52: =K40-K48 -> -0.54921474 | ... AG52: =AG40-AG48 -> 4.0630122
A53: Tax | D53: =MAX(0,(D52-IF(D3>Assumptions!$B$65,D21,0)-D97)*Assumptions!$B$70) -> 0 | E53: =MAX(0,(E52-IF(E3>Assumptions!$B$65,E21,0)-E97)*Assumptions!$B$70) -> 0 | F53: =MAX(0,(F52-IF(F3>Assumptions!$B$65,F21,0)-F97)*Assumptions!$B$70) -> 0 | G53: =MAX(0,(G52-IF(G3>Assumptions!$B$65,G21,0)-G97)*Assumptions!$B$70) -> 0 | H53: =MAX(0,(H52-IF(H3>Assumptions!$B$65,H21,0)-H97)*Assumptions!$B$70) -> 0 | I53: =MAX(0,(I52-IF(I3>Assumptions!$B$65,I21,0)-I97)*Assumptions!$B$70) -> 0 | J53: =MAX(0,(J52-IF(J3>Assumptions!$B$65,J21,0)-J97)*Assumptions!$B$70) -> 0 | K53: =MAX(0,(K52-IF(K3>Assumptions!$B$65,K21,0)-K97)*Assumptions!$B$70) -> 0 | ... AG53: =MAX(0,(AG52-IF(AG3>Assumptions!$B$65,AG21,0)-AG97)*Assumptions!$B$70) -> 0.72378256
A54: CFADS | D54: =D52-D53+D113 -> 0 | E54: =E52-E53+E113 -> 0 | F54: =F52-F53+F113 -> -6.1828513 | G54: =G52-G53+G113 -> -14.56102 | H54: =H52-H53+H113 -> -12.30154 | I54: =I52-I53+I113 -> -5.9526003 | J54: =J52-J53+J113 -> -2.5978354 | K54: =K52-K53+K113 -> -0.59726953 | ... AG54: =AG52-AG53+AG113 -> 6.6484201
A55: Debt Service | D55: =D23 -> 0 | E55: =E23 -> 0 | F55: =F23 -> 0 | G55: =G23 -> 0 | H55: =H23 -> 11.463168 | I55: =I23 -> 11.463168 | J55: =J23 -> 11.463168 | K55: =K23 -> 11.463168 | ... AG55: =AG23 -> 0
A56: DSCR | D56: =IF(D55=0,"-",D54/D55) -> - | E56: =IF(E55=0,"-",E54/E55) -> - | F56: =IF(F55=0,"-",F54/F55) -> - | G56: =IF(G55=0,"-",G54/G55) -> - | H56: =IF(H55=0,"-",H54/H55) -> -1.0731362 | I56: =IF(I55=0,"-",I54/I55) -> -0.51928058 | J56: =IF(J55=0,"-",J54/J55) -> -0.22662457 | K56: =IF(K55=0,"-",K54/K55) -> -0.052103358 | ... AG56: =IF(AG55=0,"-",AG54/AG55) -> -
A57: Equity Cash Flow | D57: =IF(D3<=Assumptions!$B$65,-D15,D54-D55)+D115+D116 -> -7.167 | E57: =IF(E3<=Assumptions!$B$65,-E15,E54-E55)+E115+E116 -> -15.231 | F57: =IF(F3<=Assumptions!$B$65,-F15,F54-F55)+F115+F116 -> -17.673 | G57: =IF(G3<=Assumptions!$B$65,-G15,G54-G55)+G115+G116 -> -12.160584 | H57: =IF(H3<=Assumptions!$B$65,-H15,H54-H55)+H115+H116 -> -23.764708 | I57: =IF(I3<=Assumptions!$B$65,-I15,I54-I55)+I115+I116 -> -17.415768 | J57: =IF(J3<=Assumptions!$B$65,-J15,J54-J55)+J115+J116 -> -14.061003 | K57: =IF(K3<=Assumptions!$B$65,-K15,K54-K55)+K115+K116 -> -12.060437 | ... AG57: =IF(AG3<=Assumptions!$B$65,-AG15,AG54-AG55)+AG115+AG116 -> 31.026493
A59: CASE B - PPP WITH AVAILABILITY PAYMENT (endogenous, targets min DSCR)
A61: Availability Payment (gross) | D61: =IF(D3<=Assumptions!$B$65,0,MAX(0,D55*Assumptions!$B$66-D54)+Assumptions!$B$99) -> 0 | E61: =IF(E3<=Assumptions!$B$65,0,MAX(0,E55*Assumptions!$B$66-E54)+Assumptions!$B$99) -> 0 | F61: =IF(F3<=Assumptions!$B$65,0,MAX(0,F55*Assumptions!$B$66-F54)+Assumptions!$B$99) -> 0 | G61: =IF(G3<=Assumptions!$B$65,0,MAX(0,G55*Assumptions!$B$66-G54)+Assumptions!$B$99) -> 0 | H61: =IF(H3<=Assumptions!$B$65,0,MAX(0,H55*Assumptions!$B$66-H54)+Assumptions!$B$99) -> 34.216817 | I61: =IF(I3<=Assumptions!$B$65,0,MAX(0,I55*Assumptions!$B$66-I54)+Assumptions!$B$99) -> 27.867877 | J61: =IF(J3<=Assumptions!$B$65,0,MAX(0,J55*Assumptions!$B$66-J54)+Assumptions!$B$99) -> 24.513112 | K61: =IF(K3<=Assumptions!$B$65,0,MAX(0,K55*Assumptions!$B$66-K54)+Assumptions!$B$99) -> 22.512546 | ... AG61: =IF(AG3<=Assumptions!$B$65,0,MAX(0,AG55*Assumptions!$B$66-AG54)+Assumptions!$B$99) -> 6.44
A62: EBITDA | D62: =D40+D61-D48 -> 0 | E62: =E40+E61-E48 -> 0 | F62: =F40+F61-F48 -> -6.1828513 | G62: =G40+G61-G48 -> -14.56102 | H62: =H40+H61-H48 -> 23.744846 | I62: =I40+I61-I48 -> 21.961016 | J62: =J40+J61-J48 -> 21.962159 | K62: =K40+K61-K48 -> 21.963331 | ... AG62: =AG40+AG61-AG48 -> 10.503012
A63: Tax | D63: =MAX(0,(D62-IF(D3>Assumptions!$B$65,D21,0)-D97)*Assumptions!$B$70) -> 0 | E63: =MAX(0,(E62-IF(E3>Assumptions!$B$65,E21,0)-E97)*Assumptions!$B$70) -> 0 | F63: =MAX(0,(F62-IF(F3>Assumptions!$B$65,F21,0)-F97)*Assumptions!$B$70) -> 0 | G63: =MAX(0,(G62-IF(G3>Assumptions!$B$65,G21,0)-G97)*Assumptions!$B$70) -> 0 | H63: =MAX(0,(H62-IF(H3>Assumptions!$B$65,H21,0)-H97)*Assumptions!$B$70) -> 0.5325139 | I63: =MAX(0,(I62-IF(I3>Assumptions!$B$65,I21,0)-I97)*Assumptions!$B$70) -> 0.75946444 | J63: =MAX(0,(J62-IF(J3>Assumptions!$B$65,J21,0)-J97)*Assumptions!$B$70) -> 1.2439645 | K63: =MAX(0,(K62-IF(K3>Assumptions!$B$65,K21,0)-K97)*Assumptions!$B$70) -> 1.6151035 | ... AG63: =MAX(0,(AG62-IF(AG3>Assumptions!$B$65,AG21,0)-AG97)*Assumptions!$B$70) -> 2.3337826
A64: CFADS | D64: =D62-D63+D113 -> 0 | E64: =E62-E63+E113 -> 0 | F64: =F62-F63+F113 -> -6.1828513 | G64: =G62-G63+G113 -> -14.56102 | H64: =H62-H63+H113 -> 21.382763 | I64: =I62-I63+I113 -> 21.155812 | J64: =J62-J63+J113 -> 20.671312 | K64: =K62-K63+K113 -> 20.300173 | ... AG64: =AG62-AG63+AG113 -> 11.47842
A65: Debt Service | D65: =D23 -> 0 | E65: =E23 -> 0 | F65: =F23 -> 0 | G65: =G23 -> 0 | H65: =H23 -> 11.463168 | I65: =I23 -> 11.463168 | J65: =J23 -> 11.463168 | K65: =K23 -> 11.463168 | ... AG65: =AG23 -> 0
A66: DSCR | D66: =IF(D65=0,"-",D64/D65) -> - | E66: =IF(E65=0,"-",E64/E65) -> - | F66: =IF(F65=0,"-",F64/F65) -> - | G66: =IF(G65=0,"-",G64/G65) -> - | H66: =IF(H65=0,"-",H64/H65) -> 1.865345 | I66: =IF(I65=0,"-",I64/I65) -> 1.8455468 | J66: =IF(J65=0,"-",J64/J65) -> 1.8032809 | K66: =IF(K65=0,"-",K64/K65) -> 1.7709043 | ... AG66: =IF(AG65=0,"-",AG64/AG65) -> -
A67: Equity Cash Flow | D67: =IF(D3<=Assumptions!$B$65,-D15,D64-D65)+D115+D117 -> -7.167 | E67: =IF(E3<=Assumptions!$B$65,-E15,E64-E65)+E115+E117 -> -15.231 | F67: =IF(F3<=Assumptions!$B$65,-F15,F64-F65)+F115+F117 -> -17.673 | G67: =IF(G3<=Assumptions!$B$65,-G15,G64-G65)+G115+G117 -> -12.160584 | H67: =IF(H3<=Assumptions!$B$65,-H15,H64-H65)+H115+H117 -> 9.9195948 | I67: =IF(I3<=Assumptions!$B$65,-I15,I64-I65)+I115+I117 -> 9.6926443 | J67: =IF(J3<=Assumptions!$B$65,-J15,J64-J65)+J115+J117 -> 9.2081442 | K67: =IF(K3<=Assumptions!$B$65,-K15,K64-K65)+K115+K117 -> 8.8370052 | ... AG67: =IF(AG3<=Assumptions!$B$65,-AG15,AG64-AG65)+AG115+AG117 -> 74.496493
A69: PROGRAMWIDE CAPEX (Spread evenly Yrs 1-4, $M)
A71: Digital Platform & PM | D71: =IF(D3<=4,Assumptions!$B$84/4,0) -> 2.9 | E71: =IF(E3<=4,Assumptions!$B$84/4,0) -> 2.9 | F71: =IF(F3<=4,Assumptions!$B$84/4,0) -> 2.9 | G71: =IF(G3<=4,Assumptions!$B$84/4,0) -> 2.9 | H71: =IF(H3<=4,Assumptions!$B$84/4,0) -> 0 | I71: =IF(I3<=4,Assumptions!$B$84/4,0) -> 0 | J71: =IF(J3<=4,Assumptions!$B$84/4,0) -> 0 | K71: =IF(K3<=4,Assumptions!$B$84/4,0) -> 0 | ... AG71: =IF(AG3<=4,Assumptions!$B$84/4,0) -> 0
A72: Contingency / 9th-site reserve | D72: =IF(D3<=4,Assumptions!$B$85/4,0) -> 2.25 | E72: =IF(E3<=4,Assumptions!$B$85/4,0) -> 2.25 | F72: =IF(F3<=4,Assumptions!$B$85/4,0) -> 2.25 | G72: =IF(G3<=4,Assumptions!$B$85/4,0) -> 2.25 | H72: =IF(H3<=4,Assumptions!$B$85/4,0) -> 0 | I72: =IF(I3<=4,Assumptions!$B$85/4,0) -> 0 | J72: =IF(J3<=4,Assumptions!$B$85/4,0) -> 0 | K72: =IF(K3<=4,Assumptions!$B$85/4,0) -> 0 | ... AG72: =IF(AG3<=4,Assumptions!$B$85/4,0) -> 0
A73: TOTAL PROGRAM CAPEX (sites + programwide) | D73: =D13+D71+D72 -> 23.89 | E73: =E13+E71+E72 -> 50.77 | F73: =F13+F71+F72 -> 58.91 | G73: =G13+G71+G72 -> 21.43 | H73: =H13+H71+H72 -> 0 | I73: =I13+I71+I72 -> 0 | J73: =J13+J71+J72 -> 0 | K73: =K13+K71+K72 -> 0 | ... AG73: =AG13+AG71+AG72 -> 0
A75: CCA / DEPRECIATION SCHEDULE (CRA declining-balance classes, half-year rule, $M)
A77: Class 1 (Buildings, 4%) - Additions | D77: =D73*Assumptions!$C$90 -> 9.556 | E77: =E73*Assumptions!$C$90 -> 20.308 | F77: =F73*Assumptions!$C$90 -> 23.564 | G77: =G73*Assumptions!$C$90 -> 8.572 | H77: =H73*Assumptions!$C$90 -> 0 | I77: =I73*Assumptions!$C$90 -> 0 | J77: =J73*Assumptions!$C$90 -> 0 | K77: =K73*Assumptions!$C$90 -> 0 | ... AG77: =AG73*Assumptions!$C$90 -> 0
A78: Class 1 (Buildings, 4%) - CCA claimed | D78: =(0+D77/2)*Assumptions!$B$90 -> 0.19112 | E78: =(D79+E77/2)*Assumptions!$B$90 -> 0.7807552 | F78: =(E79+F77/2)*Assumptions!$B$90 -> 1.626965 | G78: =(F79+G77/2)*Assumptions!$B$90 -> 2.2046064 | H78: =(G79+H77/2)*Assumptions!$B$90 -> 2.2878621 | I78: =(H79+I77/2)*Assumptions!$B$90 -> 2.1963477 | J78: =(I79+J77/2)*Assumptions!$B$90 -> 2.1084937 | K78: =(J79+K77/2)*Assumptions!$B$90 -> 2.024154 | L78: =(K79+L77/2)*Assumptions!$B$90 -> 1.9431878 | ... AG78: =(AF79+AG77/2)*Assumptions!$B$90 -> 0.824538
A79: Class 1 (Buildings, 4%) - Closing UCC | D79: =(0)+D77-D78 -> 9.36488 | E79: =(D79)+E77-E78 -> 28.892125 | F79: =(E79)+F77-F78 -> 50.82916 | G79: =(F79)+G77-G78 -> 57.196553 | H79: =(G79)+H77-H78 -> 54.908691 | I79: =(H79)+I77-I78 -> 52.712344 | J79: =(I79)+J77-J78 -> 50.60385 | K79: =(J79)+K77-K78 -> 48.579696 | L79: =(K79)+L77-L78 -> 46.636508 | ... AG79: =(AF79)+AG77-AG78 -> 19.788912
A81: Class 17 (Paving, 8%) - Additions | D81: =D73*Assumptions!$C$91 -> 5.9725 | E81: =E73*Assumptions!$C$91 -> 12.6925 | F81: =F73*Assumptions!$C$91 -> 14.7275 | G81: =G73*Assumptions!$C$91 -> 5.3575 | H81: =H73*Assumptions!$C$91 -> 0 | I81: =I73*Assumptions!$C$91 -> 0 | J81: =J73*Assumptions!$C$91 -> 0 | K81: =K73*Assumptions!$C$91 -> 0 | ... AG81: =AG73*Assumptions!$C$91 -> 0
A82: Class 17 (Paving, 8%) - CCA claimed | D82: =(0+D81/2)*Assumptions!$B$91 -> 0.2389 | E82: =(D83+E81/2)*Assumptions!$B$91 -> 0.966388 | F82: =(E83+F81/2)*Assumptions!$B$91 -> 1.985877 | G82: =(F83+G81/2)*Assumptions!$B$91 -> 2.6304068 | H82: =(G83+H81/2)*Assumptions!$B$91 -> 2.6342743 | I82: =(H83+I81/2)*Assumptions!$B$91 -> 2.4235323 | J82: =(I83+J81/2)*Assumptions!$B$91 -> 2.2296497 | K82: =(J83+K81/2)*Assumptions!$B$91 -> 2.0512778 | L82: =(K83+L81/2)*Assumptions!$B$91 -> 1.8871755 | ... AG82: =(AF83+AG81/2)*Assumptions!$B$91 -> 0.32760964
A83: Class 17 (Paving, 8%) - Closing UCC | D83: =(0)+D81-D82 -> 5.7336 | E83: =(D83)+E81-E82 -> 17.459712 | F83: =(E83)+F81-F82 -> 30.201335 | G83: =(F83)+G81-G82 -> 32.928428 | H83: =(G83)+H81-H82 -> 30.294154 | I83: =(H83)+I81-I82 -> 27.870622 | J83: =(I83)+J81-J82 -> 25.640972 | K83: =(J83)+K81-K82 -> 23.589694 | L83: =(K83)+L81-L82 -> 21.702519 | ... AG83: =(AF83)+AG81-AG82 -> 3.7675109
A85: Class 8 (Furniture/Pods, 20%) - Additions | D85: =D73*Assumptions!$C$92 -> 4.778 | E85: =E73*Assumptions!$C$92 -> 10.154 | F85: =F73*Assumptions!$C$92 -> 11.782 | G85: =G73*Assumptions!$C$92 -> 4.286 | H85: =H73*Assumptions!$C$92 -> 0 | I85: =I73*Assumptions!$C$92 -> 0 | J85: =J73*Assumptions!$C$92 -> 0 | K85: =K73*Assumptions!$C$92 -> 0 | ... AG85: =AG73*Assumptions!$C$92 -> 0
A86: Class 8 (Furniture/Pods, 20%) - CCA claimed | D86: =(0+D85/2)*Assumptions!$B$92 -> 0.4778 | E86: =(D87+E85/2)*Assumptions!$B$92 -> 1.87544 | F86: =(E87+F85/2)*Assumptions!$B$92 -> 3.693952 | G86: =(F87+G85/2)*Assumptions!$B$92 -> 4.5619616 | H86: =(G87+H85/2)*Assumptions!$B$92 -> 4.0781693 | I86: =(H87+I85/2)*Assumptions!$B$92 -> 3.2625354 | J86: =(I87+J85/2)*Assumptions!$B$92 -> 2.6100283 | K86: =(J87+K85/2)*Assumptions!$B$92 -> 2.0880227 | L86: =(K87+L85/2)*Assumptions!$B$92 -> 1.6704181 | ... AG86: =(AF87+AG85/2)*Assumptions!$B$92 -> 0.015406888
A87: Class 8 (Furniture/Pods, 20%) - Closing UCC | D87: =(0)+D85-D86 -> 4.3002 | E87: =(D87)+E85-E86 -> 12.57876 | F87: =(E87)+F85-F86 -> 20.666808 | G87: =(F87)+G85-G86 -> 20.390846 | H87: =(G87)+H85-H86 -> 16.312677 | I87: =(H87)+I85-I86 -> 13.050142 | J87: =(I87)+J85-J86 -> 10.440113 | K87: =(J87)+K85-K86 -> 8.3520907 | L87: =(K87)+L85-L86 -> 6.6816725 | ... AG87: =(AF87)+AG85-AG86 -> 0.061627552
A89: Class 43.1 (Clean energy/EV, 30%) - Additions | D89: =D73*Assumptions!$C$93 -> 2.389 | E89: =E73*Assumptions!$C$93 -> 5.077 | F89: =F73*Assumptions!$C$93 -> 5.891 | G89: =G73*Assumptions!$C$93 -> 2.143 | H89: =H73*Assumptions!$C$93 -> 0 | I89: =I73*Assumptions!$C$93 -> 0 | J89: =J73*Assumptions!$C$93 -> 0 | K89: =K73*Assumptions!$C$93 -> 0 | ... AG89: =AG73*Assumptions!$C$93 -> 0
A90: Class 43.1 (Clean energy/EV, 30%) - CCA claimed | D90: =(0+D89/2)*Assumptions!$B$93 -> 0.35835 | E90: =(D91+E89/2)*Assumptions!$B$93 -> 1.370745 | F90: =(E91+F89/2)*Assumptions!$B$93 -> 2.6047215 | G90: =(F91+G89/2)*Assumptions!$B$93 -> 3.0284051 | H90: =(G91+H89/2)*Assumptions!$B$93 -> 2.4413335 | I90: =(H91+I89/2)*Assumptions!$B$93 -> 1.7089335 | J90: =(I91+J89/2)*Assumptions!$B$93 -> 1.1962534 | K90: =(J91+K89/2)*Assumptions!$B$93 -> 0.8373774 | L90: =(K91+L89/2)*Assumptions!$B$93 -> 0.58616418 | ... AG90: =(AF91+AG89/2)*Assumptions!$B$93 -> 0.00032739958
A91: Class 43.1 (Clean energy/EV, 30%) - Closing UCC | D91: =(0)+D89-D90 -> 2.03065 | E91: =(D91)+E89-E90 -> 5.736905 | F91: =(E91)+F89-F90 -> 9.0231835 | G91: =(F91)+G89-G90 -> 8.1377785 | H91: =(G91)+H89-H90 -> 5.6964449 | I91: =(H91)+I89-I90 -> 3.9875114 | J91: =(I91)+J89-J90 -> 2.791258 | K91: =(J91)+K89-K90 -> 1.9538806 | L91: =(K91)+L89-L90 -> 1.3677164 | ... AG91: =(AF91)+AG89-AG90 -> 0.00076393235
A93: Class 50 (Digital/IT, 55%) - Additions | D93: =D73*Assumptions!$C$94 -> 1.1945 | E93: =E73*Assumptions!$C$94 -> 2.5385 | F93: =F73*Assumptions!$C$94 -> 2.9455 | G93: =G73*Assumptions!$C$94 -> 1.0715 | H93: =H73*Assumptions!$C$94 -> 0 | I93: =I73*Assumptions!$C$94 -> 0 | J93: =J73*Assumptions!$C$94 -> 0 | K93: =K73*Assumptions!$C$94 -> 0 | ... AG93: =AG73*Assumptions!$C$94 -> 0
A94: Class 50 (Digital/IT, 55%) - CCA claimed | D94: =(0+D93/2)*Assumptions!$B$94 -> 0.3284875 | E94: =(D95+E93/2)*Assumptions!$B$94 -> 1.1743944 | F94: =(E95+F93/2)*Assumptions!$B$94 -> 2.0365775 | G94: =(F95+G93/2)*Assumptions!$B$94 -> 2.0211349 | H94: =(G95+H93/2)*Assumptions!$B$94 -> 1.2041732 | I94: =(H95+I93/2)*Assumptions!$B$94 -> 0.54187793 | J94: =(I95+J93/2)*Assumptions!$B$94 -> 0.24384507 | K94: =(J95+K93/2)*Assumptions!$B$94 -> 0.10973028 | L94: =(K95+L93/2)*Assumptions!$B$94 -> 0.049378627 | ... AG94: =(AF95+AG93/2)*Assumptions!$B$94 -> 2.5763318e-09
A95: Class 50 (Digital/IT, 55%) - Closing UCC | D95: =(0)+D93-D94 -> 0.8660125 | E95: =(D95)+E93-E94 -> 2.2301181 | F95: =(E95)+F93-F94 -> 3.1390407 | G95: =(F95)+G93-G94 -> 2.1894058 | H95: =(G95)+H93-H94 -> 0.98523261 | I95: =(H95)+I93-I94 -> 0.44335467 | J95: =(I95)+J93-J94 -> 0.1995096 | K95: =(J95)+K93-K94 -> 0.089779321 | L95: =(K95)+L93-L94 -> 0.040400695 | ... AG95: =(AF95)+AG93-AG94 -> 2.1079079e-09
A97: TOTAL CCA CLAIMED | D97: =D78+D82+D86+D90+D94 -> 1.5946575 | E97: =E78+E82+E86+E90+E94 -> 6.1677226 | F97: =F78+F82+F86+F90+F94 -> 11.948093 | G97: =G78+G82+G86+G90+G94 -> 14.446515 | H97: =H78+H82+H86+H90+H94 -> 12.645812 | I97: =I78+I82+I86+I90+I94 -> 10.133227 | J97: =J78+J82+J86+J90+J94 -> 8.3882703 | K97: =K78+K82+K86+K90+K94 -> 7.1105621 | ... AG97: =AG78+AG82+AG86+AG90+AG94 -> 1.1678819
A99: PAYBACK HELPERS (cumulative equity cash flow, $M)
A101: Cumulative Equity CF - Case A (undiscounted) | D101: =0+D57 -> -7.167 | E101: =D101+E57 -> -22.398 | F101: =E101+F57 -> -40.071 | G101: =F101+G57 -> -52.231584 | H101: =G101+H57 -> -75.996292 | I101: =H101+I57 -> -93.41206 | J101: =I101+J57 -> -107.47306 | K101: =J101+K57 -> -119.5335 | L101: =K101+L57 -> -130.50369 | ... AG101: =AF101+AG57 -> -230.53495
A102: Cumulative Equity CF - Case B (undiscounted) | D102: =0+D67 -> -7.167 | E102: =D102+E67 -> -22.398 | F102: =E102+F67 -> -40.071 | G102: =F102+G67 -> -52.231584 | H102: =G102+H67 -> -42.311989 | I102: =H102+I67 -> -32.619345 | J102: =I102+J67 -> -23.411201 | K102: =J102+K67 -> -14.574195 | L102: =K102+L67 -> -6.0361601 | ... AG102: =AF102+AG67 -> 215.79786
A103: Cumulative Discounted Equity CF - Case B (@ target IRR) | D103: =0+D67/(1+Assumptions!$B$98)^D3 -> -6.3145374 | E103: =D103+E67/(1+Assumptions!$B$98)^E3 -> -18.137783 | F103: =E103+F67/(1+Assumptions!$B$98)^F3 -> -30.224899 | G103: =F103+G67/(1+Assumptions!$B$98)^G3 -> -37.552654 | H103: =G103+H67/(1+Assumptions!$B$98)^H3 -> -32.286245 | I103: =H103+I67/(1+Assumptions!$B$98)^I3 -> -27.752395 | J103: =I103+J67/(1+Assumptions!$B$98)^J3 -> -23.957489 | K103: =J103+K67/(1+Assumptions!$B$98)^K3 -> -20.748722 | L103: =K103+L67/(1+Assumptions!$B$98)^L3 -> -18.017259 | ... AG103: =AF103+AG67/(1+Assumptions!$B$98)^AG3 -> 0.009538916
A105: BANKABILITY RATIOS : LLCR & PLCR (Case B, standard PPP lender metrics)
A107: LLCR (Loan Life Coverage Ratio) | D107: =IF(OR(D3<=Assumptions!$B$65,D3>=(Assumptions!$B$65+Assumptions!$B$64),D19=0),"-",SUMPRODUCT(($D$3:$AG$3>D3)*($D$3:$AG$3<=(Assumptions!$B$65+Assumptions!$B$64))*$D$64:$AG$64/(1+(Assumptions!$B$63+Assumptions!$B$77/10000))^($D$3:$AG$3-D3))/D19) -> - | E107: =IF(OR(E3<=Assumptions!$B$65,E3>=(Assumptions!$B$65+Assumptions!$B$64),E19=0),"-",SUMPRODUCT(($D$3:$AG$3>E3)*($D$3:$AG$3<=(Assumptions!$B$65+Assumptions!$B$64))*$D$64:$AG$64/(1+(Assumptions!$B$63+Assumptions!$B$77/10000))^($D$3:$AG$3-E3))/E19) -> - | F107: =IF(OR(F3<=Assumptions!$B$65,F3>=(Assumptions!$B$65+Assumptions!$B$64),F19=0),"-",SUMPRODUCT(($D$3:$AG$3>F3)*($D$3:$AG$3<=(Assumptions!$B$65+Assumptions!$B$64))*$D$64:$AG$64/(1+(Assumptions!$B$63+Assumptions!$B$77/10000))^($D$3:$AG$3-F3))/F19) -> - | G107: =IF(OR(G3<=Assumptions!$B$65,G3>=(Assumptions!$B$65+Assumptions!$B$64),G19=0),"-",SUMPRODUCT(($D$3:$AG$3>G3)*($D$3:$AG$3<=(Assumptions!$B$65+Assumptions!$B$64))*$D$64:$AG$64/(1+(Assumptions!$B$63+Assumptions!$B$77/10000))^($D$3:$AG$3-G3))/G19) -> - | H107: =IF(OR(H3<=Assumptions!$B$65,H3>=(Assumptions!$B$65+Assumptions!$B$64),H19=0),"-",SUMPRODUCT(($D$3:$AG$3>H3)*($D$3:$AG$3<=(Assumptions!$B$65+Assumptions!$B$64))*$D$64:$AG$64/(1+(Assumptions!$B$63+Assumptions!$B$77/10000))^($D$3:$AG$3-H3))/H19) -> 1.6459389 | I107: =IF(OR(I3<=Assumptions!$B$65,I3>=(Assumptions!$B$65+Assumptions!$B$64),I19=0),"-",SUMPRODUCT(($D$3:$AG$3>I3)*($D$3:$AG$3<=(Assumptions!$B$65+Assumptions!$B$64))*$D$64:$AG$64/(1+(Assumptions!$B$63+Assumptions!$B$77/10000))^($D$3:$AG$3-I3))/I19) -> 1.6272521 | J107: =IF(OR(J3<=Assumptions!$B$65,J3>=(Assumptions!$B$65+Assumptions!$B$64),J19=0),"-",SUMPRODUCT(($D$3:$AG$3>J3)*($D$3:$AG$3<=(Assumptions!$B$65+Assumptions!$B$64))*$D$64:$AG$64/(1+(Assumptions!$B$63+Assumptions!$B$77/10000))^($D$3:$AG$3-J3))/J19) -> 1.6104049 | K107: =IF(OR(K3<=Assumptions!$B$65,K3>=(Assumptions!$B$65+Assumptions!$B$64),K19=0),"-",SUMPRODUCT(($D$3:$AG$3>K3)*($D$3:$AG$3<=(Assumptions!$B$65+Assumptions!$B$64))*$D$64:$AG$64/(1+(Assumptions!$B$63+Assumptions!$B$77/10000))^($D$3:$AG$3-K3))/K19) -> 1.5946675 | ... AG107: =IF(OR(AG3<=Assumptions!$B$65,AG3>=(Assumptions!$B$65+Assumptions!$B$64),AG19=0),"-",SUMPRODUCT(($D$3:$AG$3>AG3)*($D$3:$AG$3<=(Assumptions!$B$65+Assumptions!$B$64))*$D$64:$AG$64/(1+(Assumptions!$B$63+Assumptions!$B$77/10000))^($D$3:$AG$3-AG3))/AG19) -> -
A108: PLCR (Project Life Coverage Ratio) | D108: =IF(OR(D3<=Assumptions!$B$65,D3>=(Assumptions!$B$65+Assumptions!$B$64),D19=0),"-",SUMPRODUCT(($D$3:$AG$3>D3)*$D$64:$AG$64/(1+(Assumptions!$B$63+Assumptions!$B$77/10000))^($D$3:$AG$3-D3))/D19) -> - | E108: =IF(OR(E3<=Assumptions!$B$65,E3>=(Assumptions!$B$65+Assumptions!$B$64),E19=0),"-",SUMPRODUCT(($D$3:$AG$3>E3)*$D$64:$AG$64/(1+(Assumptions!$B$63+Assumptions!$B$77/10000))^($D$3:$AG$3-E3))/E19) -> - | F108: =IF(OR(F3<=Assumptions!$B$65,F3>=(Assumptions!$B$65+Assumptions!$B$64),F19=0),"-",SUMPRODUCT(($D$3:$AG$3>F3)*$D$64:$AG$64/(1+(Assumptions!$B$63+Assumptions!$B$77/10000))^($D$3:$AG$3-F3))/F19) -> - | G108: =IF(OR(G3<=Assumptions!$B$65,G3>=(Assumptions!$B$65+Assumptions!$B$64),G19=0),"-",SUMPRODUCT(($D$3:$AG$3>G3)*$D$64:$AG$64/(1+(Assumptions!$B$63+Assumptions!$B$77/10000))^($D$3:$AG$3-G3))/G19) -> - | H108: =IF(OR(H3<=Assumptions!$B$65,H3>=(Assumptions!$B$65+Assumptions!$B$64),H19=0),"-",SUMPRODUCT(($D$3:$AG$3>H3)*$D$64:$AG$64/(1+(Assumptions!$B$63+Assumptions!$B$77/10000))^($D$3:$AG$3-H3))/H19) -> 1.7011212 | I108: =IF(OR(I3<=Assumptions!$B$65,I3>=(Assumptions!$B$65+Assumptions!$B$64),I19=0),"-",SUMPRODUCT(($D$3:$AG$3>I3)*$D$64:$AG$64/(1+(Assumptions!$B$63+Assumptions!$B$77/10000))^($D$3:$AG$3-I3))/I19) -> 1.6876005 | J108: =IF(OR(J3<=Assumptions!$B$65,J3>=(Assumptions!$B$65+Assumptions!$B$64),J19=0),"-",SUMPRODUCT(($D$3:$AG$3>J3)*$D$64:$AG$64/(1+(Assumptions!$B$63+Assumptions!$B$77/10000))^($D$3:$AG$3-J3))/J19) -> 1.676529 | K108: =IF(OR(K3<=Assumptions!$B$65,K3>=(Assumptions!$B$65+Assumptions!$B$64),K19=0),"-",SUMPRODUCT(($D$3:$AG$3>K3)*$D$64:$AG$64/(1+(Assumptions!$B$63+Assumptions!$B$77/10000))^($D$3:$AG$3-K3))/K19) -> 1.6672753 | ... AG108: =IF(OR(AG3<=Assumptions!$B$65,AG3>=(Assumptions!$B$65+Assumptions!$B$64),AG19=0),"-",SUMPRODUCT(($D$3:$AG$3>AG3)*$D$64:$AG$64/(1+(Assumptions!$B$63+Assumptions!$B$77/10000))^($D$3:$AG$3-AG3))/AG19) -> -
A110: WORKING CAPITAL, DSRA & TERMINAL VALUE (high-level additions)
A112: Working Capital Balance | D112: =IF(D3>Assumptions!$B$65,Assumptions!$B$109*D48,0) -> 0 | E112: =IF(E3>Assumptions!$B$65,Assumptions!$B$109*E48,0) -> 0 | F112: =IF(F3>Assumptions!$B$65,Assumptions!$B$109*F48,0) -> 0 | G112: =IF(G3>Assumptions!$B$65,Assumptions!$B$109*G48,0) -> 0 | H112: =IF(H3>Assumptions!$B$65,Assumptions!$B$109*H48,0) -> 1.8295699 | I112: =IF(I3>Assumptions!$B$65,Assumptions!$B$109*I48,0) -> 1.8753091 | J112: =IF(J3>Assumptions!$B$65,Assumptions!$B$109*J48,0) -> 1.9221918 | K112: =IF(K3>Assumptions!$B$65,Assumptions!$B$109*K48,0) -> 1.9702466 | ... AF112: =IF(AF3>Assumptions!$B$65,Assumptions!$B$109*AF48,0) -> 3.3091905 | AG112: 0
A113: Working Capital Delta (cash impact) | D113: =-(D112-0) -> 0 | E113: =-(E112-D112) -> 0 | F113: =-(F112-E112) -> 0 | G113: =-(G112-F112) -> 0 | H113: =-(H112-G112) -> -1.8295699 | I113: =-(I112-H112) -> -0.045739247 | J113: =-(J112-I112) -> -0.046882728 | K113: =-(K112-J112) -> -0.048054796 | L113: =-(L112-K112) -> -0.049256166 | ... AG113: =-(AG112-AF112) -> 3.3091905
A114: DSRA Required ($M, 6mo debt service) | D114: =Assumptions!$B$108/12*H23 -> 5.7315839 | E114: =Assumptions!$B$108/12*H23 -> 5.7315839 | F114: =Assumptions!$B$108/12*H23 -> 5.7315839 | G114: =Assumptions!$B$108/12*H23 -> 5.7315839 | H114: =Assumptions!$B$108/12*H23 -> 5.7315839 | I114: =Assumptions!$B$108/12*H23 -> 5.7315839 | J114: =Assumptions!$B$108/12*H23 -> 5.7315839 | K114: =Assumptions!$B$108/12*H23 -> 5.7315839 | L114: =Assumptions!$B$108/12*H23 -> 5.7315839 | M114: =Assumptions!$B$108/12*H23 -> 5.7315839 | N114: =Assumptions!$B$108/12*H23 -> 5.7315839 | O114: =Assumptions!$B$108/12*H23 -> 5.7315839 | P114: =Assumptions!$B$108/12*H23 -> 5.7315839 | Q114: =Assumptions!$B$108/12*H23 -> 5.7315839 | R114: =Assumptions!$B$108/12*H23 -> 5.7315839 | S114: =Assumptions!$B$108/12*H23 -> 5.7315839 | T114: =Assumptions!$B$108/12*H23 -> 5.7315839 | U114: =Assumptions!$B$108/12*H23 -> 5.7315839 | V114: =Assumptions!$B$108/12*H23 -> 5.7315839 | W114: =Assumptions!$B$108/12*H23 -> 5.7315839 | X114: =Assumptions!$B$108/12*H23 -> 5.7315839 | Y114: =Assumptions!$B$108/12*H23 -> 5.7315839 | Z114: =Assumptions!$B$108/12*H23 -> 5.7315839 | AA114: =Assumptions!$B$108/12*H23 -> 5.7315839 | AB114: =Assumptions!$B$108/12*H23 -> 5.7315839 | AC114: =Assumptions!$B$108/12*H23 -> 5.7315839 | AD114: =Assumptions!$B$108/12*H23 -> 5.7315839 | AE114: =Assumptions!$B$108/12*H23 -> 5.7315839 | AF114: =Assumptions!$B$108/12*H23 -> 5.7315839 | AG114: =Assumptions!$B$108/12*H23 -> 5.7315839
A115: DSRA Funding (Yr4) / Release (end of tenor) | D115: =IF(D3=4,-D114,IF(D3=Assumptions!$B$65+Assumptions!$B$64,D114,0)) -> 0 | E115: =IF(E3=4,-E114,IF(E3=Assumptions!$B$65+Assumptions!$B$64,E114,0)) -> 0 | F115: =IF(F3=4,-F114,IF(F3=Assumptions!$B$65+Assumptions!$B$64,F114,0)) -> 0 | G115: =IF(G3=4,-G114,IF(G3=Assumptions!$B$65+Assumptions!$B$64,G114,0)) -> -5.7315839 | H115: =IF(H3=4,-H114,IF(H3=Assumptions!$B$65+Assumptions!$B$64,H114,0)) -> 0 | I115: =IF(I3=4,-I114,IF(I3=Assumptions!$B$65+Assumptions!$B$64,I114,0)) -> 0 | J115: =IF(J3=4,-J114,IF(J3=Assumptions!$B$65+Assumptions!$B$64,J114,0)) -> 0 | K115: =IF(K3=4,-K114,IF(K3=Assumptions!$B$65+Assumptions!$B$64,K114,0)) -> 0 | ... AG115: =IF(AG3=4,-AG114,IF(AG3=Assumptions!$B$65+Assumptions!$B$64,AG114,0)) -> 0
A116: Terminal Value - Case A (Yr30, x final EBITDA) | D116: =IF(D3=30,Assumptions!$B$110*D52,0) -> 0 | E116: =IF(E3=30,Assumptions!$B$110*E52,0) -> 0 | F116: =IF(F3=30,Assumptions!$B$110*F52,0) -> 0 | G116: =IF(G3=30,Assumptions!$B$110*G52,0) -> 0 | H116: =IF(H3=30,Assumptions!$B$110*H52,0) -> 0 | I116: =IF(I3=30,Assumptions!$B$110*I52,0) -> 0 | J116: =IF(J3=30,Assumptions!$B$110*J52,0) -> 0 | K116: =IF(K3=30,Assumptions!$B$110*K52,0) -> 0 | ... AG116: =IF(AG3=30,Assumptions!$B$110*AG52,0) -> 24.378073
A117: Terminal Value - Case B (Yr30, x final EBITDA) | D117: =IF(D3=30,Assumptions!$B$110*D62,0) -> 0 | E117: =IF(E3=30,Assumptions!$B$110*E62,0) -> 0 | F117: =IF(F3=30,Assumptions!$B$110*F62,0) -> 0 | G117: =IF(G3=30,Assumptions!$B$110*G62,0) -> 0 | H117: =IF(H3=30,Assumptions!$B$110*H62,0) -> 0 | I117: =IF(I3=30,Assumptions!$B$110*I62,0) -> 0 | J117: =IF(J3=30,Assumptions!$B$110*J62,0) -> 0 | K117: =IF(K3=30,Assumptions!$B$110*K62,0) -> 0 | ... AG117: =IF(AG3=30,Assumptions!$B$110*AG62,0) -> 63.018073

Sheet P&L (Case B)
A1: INCOME STATEMENT : CASE B (PPP with Availability Payment), $M
A2: Illustrative / simplified : see Read Me for basis. Case B shown as this is the recommended structure.
A4: Year # | D4: =Model!D3 -> 1 | E4: =Model!E3 -> 2 | F4: =Model!F3 -> 3 | G4: =Model!G3 -> 4 | H4: =Model!H3 -> 5 | I4: =Model!I3 -> 6 | J4: =Model!J3 -> 7 | K4: =Model!K3 -> 8 | ... AG4: =Model!AG3 -> 30
A5: Calendar Year | D5: =Model!D4 -> 2027 | E5: =Model!E4 -> 2028 | F5: =Model!F4 -> 2029 | G5: =Model!G4 -> 2030 | H5: =Model!H4 -> 2031 | I5: =Model!I4 -> 2032 | J5: =Model!J4 -> 2033 | K5: =Model!K4 -> 2034 | ... AG5: =Model!AG4 -> 2056
A7: Commercial Revenue | D7: =Model!D40 -> 0 | E7: =Model!E40 -> 0 | F7: =Model!F40 -> 9.1562737 | G7: =Model!G40 -> 21.137904 | H7: =Model!H40 -> 26.119427 | I7: =Model!I40 -> 31.599321 | J7: =Model!J40 -> 35.892884 | K7: =Model!K40 -> 38.855718 | ... AG7: =Model!AG40 -> 71.901417
A8: Availability Payment | D8: =Model!D61 -> 0 | E8: =Model!E61 -> 0 | F8: =Model!F61 -> 0 | G8: =Model!G61 -> 0 | H8: =Model!H61 -> 34.216817 | I8: =Model!I61 -> 27.867877 | J8: =Model!J61 -> 24.513112 | K8: =Model!K61 -> 22.512546 | ... AG8: =Model!AG61 -> 6.44
A9: TOTAL REVENUE | D9: =D7+D8 -> 0 | E9: =E7+E8 -> 0 | F9: =F7+F8 -> 9.1562737 | G9: =G7+G8 -> 21.137904 | H9: =H7+H8 -> 60.336244 | I9: =I7+I8 -> 59.467198 | J9: =J7+J8 -> 60.405996 | K9: =K7+K8 -> 61.368264 | ... AG9: =AG7+AG8 -> 78.341417
A10: Operating Costs | D10: =-Model!D48 -> 0 | E10: =-Model!E48 -> 0 | F10: =-Model!F48 -> -15.339125 | G10: =-Model!G48 -> -35.698924 | H10: =-Model!H48 -> -36.591397 | I10: =-Model!I48 -> -37.506182 | J10: =-Model!J48 -> -38.443837 | K10: =-Model!K48 -> -39.404933 | ... AG10: =-Model!AG48 -> -67.838405
A11: EBITDA | D11: =D9+D10 -> 0 | E11: =E9+E10 -> 0 | F11: =F9+F10 -> -6.1828513 | G11: =G9+G10 -> -14.56102 | H11: =H9+H10 -> 23.744846 | I11: =I9+I10 -> 21.961016 | J11: =J9+J10 -> 21.962159 | K11: =K9+K10 -> 21.963331 | ... AG11: =AG9+AG10 -> 10.503012
A13: Depreciation (CCA proxy) | D13: =-Model!D97 -> -1.5946575 | E13: =-Model!E97 -> -6.1677226 | F13: =-Model!F97 -> -11.948093 | G13: =-Model!G97 -> -14.446515 | H13: =-Model!H97 -> -12.645812 | I13: =-Model!I97 -> -10.133227 | J13: =-Model!J97 -> -8.3882703 | K13: =-Model!K97 -> -7.1105621 | ... AG13: =-Model!AG97 -> -1.1678819
A14: EBIT | D14: =D11+D13 -> -1.5946575 | E14: =E11+E13 -> -6.1677226 | F14: =F11+F13 -> -18.130944 | G14: =G11+G13 -> -29.007535 | H14: =H11+H13 -> 11.099034 | I14: =I11+I13 -> 11.827789 | J14: =J11+J13 -> 13.573889 | K14: =K11+K13 -> 14.852769 | ... AG14: =AG11+AG13 -> 9.3351302
A15: Interest Expense (post-Yr4) | D15: =-IF(Model!D3>Assumptions!$B$65,Model!D21,0) -> 0 | E15: =-IF(Model!E3>Assumptions!$B$65,Model!E21,0) -> 0 | F15: =-IF(Model!F3>Assumptions!$B$65,Model!F21,0) -> 0 | G15: =-IF(Model!G3>Assumptions!$B$65,Model!G21,0) -> 0 | H15: =-IF(Model!H3>Assumptions!$B$65,Model!H21,0) -> -8.9689783 | I15: =-IF(Model!I3>Assumptions!$B$65,Model!I21,0) -> -8.7899311 | J15: =-IF(Model!J3>Assumptions!$B$65,Model!J21,0) -> -8.5980309 | K15: =-IF(Model!K3>Assumptions!$B$65,Model!K21,0) -> -8.392355 | ... AG15: =-IF(Model!AG3>Assumptions!$B$65,Model!AG21,0) -> -3.7679347e-15
A16: EBT (pre-tax profit) | D16: =D14+D15 -> -1.5946575 | E16: =E14+E15 -> -6.1677226 | F16: =F14+F15 -> -18.130944 | G16: =G14+G15 -> -29.007535 | H16: =H14+H15 -> 2.1300556 | I16: =I14+I15 -> 3.0378578 | J16: =J14+J15 -> 4.9758579 | K16: =K14+K15 -> 6.4604141 | ... AG16: =AG14+AG15 -> 9.3351302
A17: Tax | D17: =-Model!D63 -> 0 | E17: =-Model!E63 -> 0 | F17: =-Model!F63 -> 0 | G17: =-Model!G63 -> 0 | H17: =-Model!H63 -> -0.5325139 | I17: =-Model!I63 -> -0.75946444 | J17: =-Model!J63 -> -1.2439645 | K17: =-Model!K63 -> -1.6151035 | ... AG17: =-Model!AG63 -> -2.3337826
A18: NET INCOME | D18: =D16+D17 -> -1.5946575 | E18: =E16+E17 -> -6.1677226 | F18: =F16+F17 -> -18.130944 | G18: =G16+G17 -> -29.007535 | H18: =H16+H17 -> 1.5975417 | I18: =I16+I17 -> 2.2783933 | J18: =J16+J17 -> 3.7318934 | K18: =K16+K17 -> 4.8453106 | ... AG18: =AG16+AG17 -> 7.0013477

Sheet Balance Sheet (Case B)
A1: BALANCE SHEET - CASE B (simplified/summary presentation), $M
A2: Simplified: no working capital, no DSRA cash, cash assumed fully distributed each year. See Read Me.
A4: Year # | D4: =Model!D3 -> 1 | E4: =Model!E3 -> 2 | F4: =Model!F3 -> 3 | G4: =Model!G3 -> 4 | H4: =Model!H3 -> 5 | I4: =Model!I3 -> 6 | J4: =Model!J3 -> 7 | K4: =Model!K3 -> 8 | ... AG4: =Model!AG3 -> 30
A6: ASSETS
A8: Cumulative Program Capex | D8: =0+Model!D73 -> 23.89 | E8: =D8+Model!E73 -> 74.66 | F8: =E8+Model!F73 -> 133.57 | G8: =F8+Model!G73 -> 155 | H8: =G8+Model!H73 -> 155 | I8: =H8+Model!I73 -> 155 | J8: =I8+Model!J73 -> 155 | K8: =J8+Model!K73 -> 155 | L8: =K8+Model!L73 -> 155 | ... AG8: =AF8+Model!AG73 -> 155
A9: less: Cumulative CCA / Depreciation | D9: =0+Model!D97 -> 1.5946575 | E9: =D9+Model!E97 -> 7.7623801 | F9: =E9+Model!F97 -> 19.710473 | G9: =F9+Model!G97 -> 34.156988 | H9: =G9+Model!H97 -> 46.8028 | I9: =H9+Model!I97 -> 56.936027 | J9: =I9+Model!J97 -> 65.324297 | K9: =J9+Model!K97 -> 72.434859 | L9: =K9+Model!L97 -> 78.571184 | ... AG9: =AF9+Model!AG97 -> 131.38119
A10: Net PP&E | D10: =D8-D9 -> 22.295343 | E10: =E8-E9 -> 66.89762 | F10: =F8-F9 -> 113.85953 | G10: =G8-G9 -> 120.84301 | H10: =H8-H9 -> 108.1972 | I10: =I8-I9 -> 98.063973 | J10: =J8-J9 -> 89.675703 | K10: =K8-K9 -> 82.565141 | ... AG10: =AG8-AG9 -> 23.618814
A11: Cash (assumed nil - fully distributed) | D11: 0 | E11: 0 | F11: 0 | G11: 0 | H11: 0 | I11: 0 | J11: 0 | K11: 0 | L11: 0 | M11: 0 | N11: 0 | O11: 0 | P11: 0 | Q11: 0 | R11: 0 | S11: 0 | T11: 0 | U11: 0 | V11: 0 | W11: 0 | X11: 0 | Y11: 0 | Z11: 0 | AA11: 0 | AB11: 0 | AC11: 0 | AD11: 0 | AE11: 0 | AF11: 0 | AG11: 0
A12: TOTAL ASSETS | D12: =D10+D11 -> 22.295343 | E12: =E10+E11 -> 66.89762 | F12: =F10+F11 -> 113.85953 | G12: =G10+G11 -> 120.84301 | H12: =H10+H11 -> 108.1972 | I12: =I10+I11 -> 98.063973 | J12: =J10+J11 -> 89.675703 | K12: =K10+K11 -> 82.565141 | ... AG12: =AG10+AG11 -> 23.618814
A14: LIABILITIES & EQUITY
A16: Debt (closing balance) | D16: =Model!D25 -> 17.323236 | E16: =Model!E25 -> 55.381393 | F16: =Model!F25 -> 102.0741 | G16: =Model!G25 -> 124.94099 | H16: =Model!H25 -> 122.4468 | I16: =Model!I25 -> 119.77356 | J16: =Model!J25 -> 116.90843 | K16: =Model!K25 -> 113.83762 | ... AG16: =Model!AG25 -> 5.6256578e-14
A17: Equity (paid-in + retained, plug) | D17: =D12-D16 -> 4.9721063 | E17: =E12-E16 -> 11.516227 | F17: =F12-F16 -> 11.785427 | G17: =G12-G16 -> -4.0979787 | H17: =H12-H16 -> -14.249602 | I17: =I12-I16 -> -21.709592 | J17: =J12-J16 -> -27.232725 | K17: =K12-K16 -> -31.272475 | ... AG17: =AG12-AG16 -> 23.618814
A18: TOTAL LIABILITIES & EQUITY | D18: =D16+D17 -> 22.295343 | E18: =E16+E17 -> 66.89762 | F18: =F16+F17 -> 113.85953 | G18: =G16+G17 -> 120.84301 | H18: =H16+H17 -> 108.1972 | I18: =I16+I17 -> 98.063973 | J18: =J16+J17 -> 89.675703 | K18: =K16+K17 -> 82.565141 | ... AG18: =AG16+AG17 -> 23.618814

Sheet Summary
A1: SUMMARY OUTPUTS - FleetPods Alberta Phase 1
A3: CAPITAL STACK
A4: Total Capex ($M) | B4: =SUM(Model!D73:AG73) -> 155
A5: Debt (70%) ($M) | B5: =B4*Assumptions!$B$62 -> 108.5
A6: Equity (30%) ($M) | B6: =B4*Assumptions!$B$61 -> 46.5
A8: CASE A vs CASE B - KEY RESULTS
B9: Case A | C9: Case B
A10: Minimum DSCR (Yrs 5-30) | B10: =MIN(Model!D56:AG56) -> -1.0731362 | C10: =MIN(Model!D66:AG66) -> 1.5046072
A11: Average DSCR (Yrs 5-30) | B11: =AVERAGE(Model!D56:AG56) -> 0.10975962 | C11: =AVERAGE(Model!D66:AG66) -> 1.6497624
A12: Equity IRR (nominal, 30-yr) | B12: =IFERROR(IRR(Model!D57:AG57,-0.5),"N/M (neg. equity CF for 25+ yrs)") -> -0.12159604 | C12: =IFERROR(IRR(Model!D67:AG67,-0.2),"N/M") -> 0.13503208
A13: Cumulative Equity Distributions ($M) | B13: =SUMIF(Model!D57:AG57,">0") -> 40.474491 | C13: =SUMIF(Model!D67:AG67,">0") -> 268.02944
A15: AVAILABILITY PAYMENT (CASE B)
A16: Steady-state annual Availability Payment ($M, Yr 10) | B16: =INDEX(Model!D61:AG61,10) -> 20.277156
A17: Peak annual Availability Payment ($M) | B17: =MAX(Model!D61:AG61) -> 34.216817
A18: Total Availability Payments over concession ($M, nominal) | B18: =SUM(Model!D61:AG61) -> 480.21584
A20: REVENUE MIX - STEADY STATE (Year 15, $M)
A21: Total Commercial Revenue | B21: =INDEX(Model!D40:AG40,15) -> 49.645452
A22: Total Opex | B22: =INDEX(Model!D48:AG48,15) -> 46.840082
A24: Note: this Summary pulls live from the Model tab. Change any Assumptions input and every number above recalculates automatically.
A27: NPV, IRR & PAYBACK
B28: Case A | C28: Case B
A29: Equity NPV @ target IRR (13.5%) ($M) | B29: =NPV(Assumptions!$B$98,Model!D57:AG57) -> -89.434493 | C29: =NPV(Assumptions!$B$98,Model!D67:AG67) -> 0.009538916
A30: Equity IRR (nominal) | B30: =B12 -> -0.12159604 | C30: =C12 -> 0.13503208
A31: Simple Payback (undiscounted, years) | B31: =IFERROR(MATCH(TRUE(),INDEX(Model!D101:AG101>0,0),0),"N/M (never)") -> N/M (never) | C31: =MATCH(TRUE(),INDEX(Model!D102:AG102>0,0),0) -> 10
A32: Discounted Payback @ target IRR (years, Case B) | C32: =MATCH(TRUE(),INDEX(Model!D103:AG103>0,0),0) -> 30
A34: BANKABILITY RATIOS (Case B) - standard PPP lender metrics
A35: Minimum LLCR (Yrs 5-26, debt tenor) | B35: =MIN(Model!D107:AG107) -> 0.77837032
A36: Minimum PLCR (Yrs 5-26, full remaining project life) | B36: =MIN(Model!D108:AG108) -> 1.6369775
A37: PV of Availability Payments (public authority cost, @6% discount) | B37: =NPV(0.06,Model!D61:AG61) -> 212.21157

Sheet Sensitivity Analysis
A1: SENSITIVITY ANALYSIS
A4: Scenario | B4: Min DSCR - Case A | C4: Min DSCR - Case B | D4: Equity IRR - Case B | E4: Steady-state AP ($M/yr)
A5: Base Case | B5: -1.0731362 | C5: 1.5046072 | D5: 0.13503208 | E5: 20.277156
A7: Traffic/Occupancy -20% | B7: -1.454853 | C7: 1.4809547 | D7: 0.12999126 | E7: 27.483624
A9: Capex +20% | B9: -0.91456178 | C9: 1.4336905 | D9: 0.12359836 | E9: 22.96039
A11: Interest +150bps | B11: -0.92553392 | C11: 1.438302 | D11: 0.14051922 | E11: 22.745122
A14: RESULTS
A15: Case A's DSCR stays deeply negative to marginally-negative across every downside scenario tested under no scenario modelled does user-fee revenue alone come close to covering debt service.
A17: Case B's DSCR and equity IRR stay resilient because the availability payment mechanism is designed to flex: the DSCR-driven component scales automatically with debt service and CFADS shortfalls. The flat top-up is NOT re-solved per scenario here (a live re-solve would need the iteration script re-run) - so Case B equity IRR drifts modestly (12.2%-14.3%) rather than sitting exactly on 13.5% in each downside case.
A22: Downside scenarios generally require a LARGER availability payment (up to ~$25.6M/yr steady-state under the traffic downside), reinforcing that the payment mechanism not user fees is what keeps the project bankable under stress.
A27: Static snapshot : Each scenario recalculated in full (not a live Excel data table). To re-run: change the Scenario Toggles on the Assumptions tab and read the Summary tab, then restore to 0/0/0 for base case. See Read Me.

Sheet Conclusion & Recommendations
A1: CONCLUSION & RECOMMENDATIONS
A4: Conclusion
A5: The financial model demonstrates a clear and quantified case that the FleetPods Alberta Phase 1 network is not commercially bankable on user fees alone, and that a government availability payment of approximately CAD 18-20M/year (steady-state) is both necessary and sufficient to bring the project to standard infrastructure investment metrics (1.35x+ DSCR, 12-15% equity IRR). This holds up under stress testing across traffic, capex, and interest-rate downside scenarios.
A11: Recommendations for Next Steps
A12: 1. Reconcile the site list
A13: The Demand Analysis (traffic study) and the Business Case (capex source) name different sites for 3 of the 8 nodes. Confirm one authoritative Phase 1 site list before this model or the underlying business case goes to government a reviewer will likely notice the inconsistency.
A17: 2. Validate parking and pod pricing/occupancy assumptions
A18: The brief's own bottom-up unit assumptions (stall counts x occupancy x blended $/hour) produced revenue materially above its own top-down steady-state anchor. A 0.42 calibration factor has been applied to bring the two in line, but this should be replaced with validated market rates from comparable Alberta/Canadian truck-parking and rest-stop operators.
A23: 3. Confirm the operating cost basis
A24: The original brief (CAD 30-40M/yr) and the Business Case Appendix (CAD 2.8-3.9M/yr) disagree by roughly 9x. This model uses the higher figure as the more defensible basis, but the client should confirm which cost basis and which cost categories it intends to stand behind publicly.
A28: 4. Engage lenders to firm up financing terms
A29: The model currently uses a simplified single-tranche 70/30 debt/equity structure at a flat 6%. The Business Case references a more realistic senior + mezzanine structure (200-300bps and 400-700bps over GoC bonds respectively). Firming this up will change the DSCR and IRR outputs meaningfully and should be prioritized once the model moves beyond this working draft stage.
... A59: 8. Confirm the mezzanine pricing and DSRA/working capital/terminal value assumptions The 55/15 senior/mezzanine split, 11.5% mezzanine rate, 6-month DSRA, 5% working capital, and 6.0x terminal value multiple are this model's own placeholder assumptions (not client-provided), included to reach a credible 'full' institutional structure. Each should be confirmed or replaced with real terms as lenders, tax advisors, and asset valuators are engaged.
