Workbook

Sheet Stats
A1: Stats | C1: As of Apr 20
A2: Reviewer | B2: Total Jobs | C2: Assigned | D2: Jobs to Assign | E2: Stuck Jobs | F2: Actual Jobs Reviewed | G2: Attempts submitted to the agent | H2: Turn 0 Assigned on Slack | I2: Attempts Reviewed | J2: Threads Left to Review | K2: Turn 0 Success | L2: Overall Pass Rate | M2: Remaining Evals to process for Turn 1 | N2: Turn 1 Change Requested | O2: Review Ready - Turn 1 - Assigned in Slack | P2: Attempts Reviewed Turn 1 | Q2: Turn 1 Success | R2: Overall Pass Rate Turn 1 | S2: Turn 2 Change Requested | T2: Review Ready - Turn 2 - Assigned in Slack | U2: Attempts Reviewed Turn 2 | V2: Turn 2 Success
A3: Sanjeev | B3: =COUNTIF(assignments!B:B, A3) -> 26 | C3: =IFERROR(__xludf.DUMMYFUNCTION("IFERROR(COUNTUNIQUE(FILTER(job_status!A:A, job_status!C:C=A28)),0)"),26.0) -> 26 | D3: =B3-C3 -> 0 | E3: 0 | F3: =IFERROR(__xludf.DUMMYFUNCTION("IFERROR(COUNTUNIQUE(FILTER(job_status!A:A, job_status!C:C = A28, job_status!E:E = ""up:Reviewed"")), 0)"),26.0) -> 26 | G3: =IFERROR(__xludf.DUMMYFUNCTION("IFERROR(ROWS(UNIQUE(FILTER(job_status!D:D, job_status!C:C=A28, job_status!E:E=""up:Submitted""))), 0)"),78.0) -> 78 | H3: =IFERROR(__xludf.DUMMYFUNCTION("IFERROR(ROWS(UNIQUE(FILTER(job_status!D:D, job_status!C:C=A28, job_status!E:E=""up:InReview"", job_status!F:F=0))), 0)"),78.0) -> 78 | I3: =COUNTIFS(job_status!C:C, A28, job_status!E:E, "up:Reviewed", job_status!F:F,0) -> 78 | J3: =H3 - I3 -> 0 | K3: =IFERROR(__xludf.DUMMYFUNCTION("IFERROR(ROWS(UNIQUE(FILTER(job_status!D:D, job_status!C:C=A28, job_status!E:E=""up:Success"", job_status!F:F=0))), 0)"),23.0) -> 23 | L3: =K3/I3 -> 0.29487179 | M3: =(I3 - K3) - N3 -> 0 | N3: =IFERROR(__xludf.DUMMYFUNCTION("IFERROR(ROWS(UNIQUE(FILTER(job_status!D:D, job_status!C:C=A28, job_status!E:E=""up:ChangeRequested"", job_status!F:F=1))), 0)"),55.0) -> 55 | O3: =IFERROR(__xludf.DUMMYFUNCTION("IFERROR(ROWS(UNIQUE(FILTER(job_status!D:D, job_status!C:C=A28, job_status!E:E=""up:InReview"", job_status!F:F=1))), 0)"),55.0) -> 55 | P3: =COUNTIFS(job_status!C:C, A28, job_status!E:E, "up:Reviewed", job_status!F:F,1) -> 55 | Q3: =IFERROR(__xludf.DUMMYFUNCTION("IFERROR(ROWS(UNIQUE(FILTER(job_status!D:D, job_status!C:C=A28, job_status!E:E=""up:Success"", job_status!F:F=1))), 0)"),15.0) -> 15 | R3: =Q3/P3 -> 0.27272727 | S3: =IFERROR(__xludf.DUMMYFUNCTION("IFERROR(ROWS(UNIQUE(FILTER(job_status!D:D, job_status!C:C=A28, job_status!E:E=""up:ChangeRequested"", job_status!F:F=2))), 0)"),40.0) -> 40 | T3: =IFERROR(__xludf.DUMMYFUNCTION("IFERROR(ROWS(UNIQUE(FILTER(job_status!D:D, job_status!C:C=A28, job_status!E:E=""up:InReview"", job_status!F:F=2))), 0)"),40.0) -> 40 | U3: =COUNTIFS(job_status!C:C, A28, job_status!E:E, "up:Reviewed", job_status!F:F,2) -> 40 | V3: =IFERROR(__xludf.DUMMYFUNCTION("IFERROR(ROWS(UNIQUE(FILTER(job_status!D:D, job_status!C:C=A28, job_status!E:E=""up:Success"", job_status!F:F=2))), 0)"),17.0) -> 17
A4: Solomon | B4: =COUNTIF(assignments!B:B, A4) -> 30 | C4: =IFERROR(__xludf.DUMMYFUNCTION("IFERROR(COUNTUNIQUE(FILTER(job_status!A:A, job_status!C:C=A29)),0)"),28.0) -> 28 | D4: =B4-C4 -> 2 | E4: 0 | F4: =IFERROR(__xludf.DUMMYFUNCTION("COUNTUNIQUE(FILTER(job_status!A:A, job_status!C:C = A29, job_status!E:E = ""up:Reviewed""))"),27.0) -> 27 | G4: =IFERROR(__xludf.DUMMYFUNCTION("IFERROR(ROWS(UNIQUE(FILTER(job_status!D:D, job_status!C:C=A29, job_status!E:E=""up:Submitted""))), 0)"),84.0) -> 84 | H4: =IFERROR(__xludf.DUMMYFUNCTION("IFERROR(ROWS(UNIQUE(FILTER(job_status!D:D, job_status!C:C=A29, job_status!E:E=""up:InReview"", job_status!F:F=0))), 0)"),81.0) -> 81 | I4: =COUNTIFS(job_status!C:C, A29, job_status!E:E, "up:Reviewed", job_status!F:F,0) -> 81 | J4: =H4 - I4 -> 0 | K4: =IFERROR(__xludf.DUMMYFUNCTION("IFERROR(ROWS(UNIQUE(FILTER(job_status!D:D, job_status!C:C=A29, job_status!E:E=""up:Success"", job_status!F:F=0))), 0)"),47.0) -> 47 | L4: =K4/I4 -> 0.58024691 | M4: =(I4 - K4) - N4 -> 0 | N4: =IFERROR(__xludf.DUMMYFUNCTION("IFERROR(ROWS(UNIQUE(FILTER(job_status!D:D, job_status!C:C=A29, job_status!E:E=""up:ChangeRequested"", job_status!F:F=1))), 0)"),34.0) -> 34 | O4: =IFERROR(__xludf.DUMMYFUNCTION("IFERROR(ROWS(UNIQUE(FILTER(job_status!D:D, job_status!C:C=A29, job_status!E:E=""up:InReview"", job_status!F:F=1))), 0)"),34.0) -> 34 | P4: =COUNTIFS(job_status!C:C, A29, job_status!E:E, "up:Reviewed", job_status!F:F,1) -> 34 | Q4: =IFERROR(__xludf.DUMMYFUNCTION("IFERROR(ROWS(UNIQUE(FILTER(job_status!D:D, job_status!C:C=A29, job_status!E:E=""up:Success"", job_status!F:F=1))), 0)"),23.0) -> 23 | R4: =Q4/P4 -> 0.67647059 | S4: =IFERROR(__xludf.DUMMYFUNCTION("IFERROR(ROWS(UNIQUE(FILTER(job_status!D:D, job_status!C:C=A29, job_status!E:E=""up:ChangeRequested"", job_status!F:F=2))), 0)"),11.0) -> 11 | T4: =IFERROR(__xludf.DUMMYFUNCTION("IFERROR(ROWS(UNIQUE(FILTER(job_status!D:D, job_status!C:C=A29, job_status!E:E=""up:InReview"", job_status!F:F=2))), 0)"),11.0) -> 11 | U4: =COUNTIFS(job_status!C:C, A29, job_status!E:E, "up:Reviewed", job_status!F:F,2) -> 11 | V4: =IFERROR(__xludf.DUMMYFUNCTION("IFERROR(ROWS(UNIQUE(FILTER(job_status!D:D, job_status!C:C=A29, job_status!E:E=""up:Success"", job_status!F:F=2))), 0)"),6.0) -> 6
A5: Ghulam | B5: =COUNTIF(assignments!B:B, A5) -> 28 | C5: =IFERROR(__xludf.DUMMYFUNCTION("IFERROR(COUNTUNIQUE(FILTER(job_status!A:A, job_status!C:C=A30)),0)"),28.0) -> 28 | D5: =B5-C5 -> 0 | E5: 0 | F5: =IFERROR(__xludf.DUMMYFUNCTION("COUNTUNIQUE(FILTER(job_status!A:A, job_status!C:C = A30, job_status!E:E = ""up:Reviewed""))"),28.0) -> 28 | G5: =IFERROR(__xludf.DUMMYFUNCTION("IFERROR(ROWS(UNIQUE(FILTER(job_status!D:D, job_status!C:C=A30, job_status!E:E=""up:Submitted""))), 0)"),84.0) -> 84 | H5: =IFERROR(__xludf.DUMMYFUNCTION("IFERROR(ROWS(UNIQUE(FILTER(job_status!D:D, job_status!C:C=A30, job_status!E:E=""up:InReview"", job_status!F:F=0))), 0)"),84.0) -> 84 | I5: =COUNTIFS(job_status!C:C, A30, job_status!E:E, "up:Reviewed", job_status!F:F,0) -> 84 | J5: =H5 - I5 -> 0 | K5: =IFERROR(__xludf.DUMMYFUNCTION("IFERROR(ROWS(UNIQUE(FILTER(job_status!D:D, job_status!C:C=A30, job_status!E:E=""up:Success"", job_status!F:F=0))), 0)"),23.0) -> 23 | L5: =K5/I5 -> 0.27380952 | M5: =(I5 - K5) - N5 -> 0 | N5: =IFERROR(__xludf.DUMMYFUNCTION("IFERROR(ROWS(UNIQUE(FILTER(job_status!D:D, job_status!C:C=A30, job_status!E:E=""up:ChangeRequested"", job_status!F:F=1))), 0)"),61.0) -> 61 | O5: =IFERROR(__xludf.DUMMYFUNCTION("IFERROR(ROWS(UNIQUE(FILTER(job_status!D:D, job_status!C:C=A30, job_status!E:E=""up:InReview"", job_status!F:F=1))), 0)"),61.0) -> 61 | P5: =COUNTIFS(job_status!C:C, A30, job_status!E:E, "up:Reviewed", job_status!F:F,1) -> 61 | Q5: =IFERROR(__xludf.DUMMYFUNCTION("IFERROR(ROWS(UNIQUE(FILTER(job_status!D:D, job_status!C:C=A30, job_status!E:E=""up:Success"", job_status!F:F=1))), 0)"),25.0) -> 25 | R5: =Q5/P5 -> 0.40983607 | S5: =IFERROR(__xludf.DUMMYFUNCTION("IFERROR(ROWS(UNIQUE(FILTER(job_status!D:D, job_status!C:C=A30, job_status!E:E=""up:ChangeRequested"", job_status!F:F=2))), 0)"),36.0) -> 36 | T5: =IFERROR(__xludf.DUMMYFUNCTION("IFERROR(ROWS(UNIQUE(FILTER(job_status!D:D, job_status!C:C=A30, job_status!E:E=""up:InReview"", job_status!F:F=2))), 0)"),36.0) -> 36 | U5: =COUNTIFS(job_status!C:C, A30, job_status!E:E, "up:Reviewed", job_status!F:F,2) -> 36 | V5: =IFERROR(__xludf.DUMMYFUNCTION("IFERROR(ROWS(UNIQUE(FILTER(job_status!D:D, job_status!C:C=A30, job_status!E:E=""up:Success"", job_status!F:F=2))), 0)"),12.0) -> 12
A6: Youssef | B6: =COUNTIF(assignments!B:B, A6) -> 23 | C6: =IFERROR(__xludf.DUMMYFUNCTION("IFERROR(COUNTUNIQUE(FILTER(job_status!A:A, job_status!C:C=A31)),0)"),23.0) -> 23 | D6: =B6-C6 -> 0 | E6: 0 | F6: =IFERROR(__xludf.DUMMYFUNCTION("COUNTUNIQUE(FILTER(job_status!A:A, job_status!C:C = A31, job_status!E:E = ""up:Reviewed""))"),23.0) -> 23 | G6: =IFERROR(__xludf.DUMMYFUNCTION("IFERROR(ROWS(UNIQUE(FILTER(job_status!D:D, job_status!C:C=A31, job_status!E:E=""up:Submitted""))), 0)"),69.0) -> 69 | H6: =IFERROR(__xludf.DUMMYFUNCTION("IFERROR(ROWS(UNIQUE(FILTER(job_status!D:D, job_status!C:C=A31, job_status!E:E=""up:InReview"", job_status!F:F=0))), 0)"),69.0) -> 69 | I6: =COUNTIFS(job_status!C:C, A31, job_status!E:E, "up:Reviewed", job_status!F:F,0) -> 69 | J6: =H6 - I6 -> 0 | K6: =IFERROR(__xludf.DUMMYFUNCTION("IFERROR(ROWS(UNIQUE(FILTER(job_status!D:D, job_status!C:C=A31, job_status!E:E=""up:Success"", job_status!F:F=0))), 0)"),33.0) -> 33 | L6: =K6/I6 -> 0.47826087 | M6: =(I6 - K6) - N6 -> 0 | N6: =IFERROR(__xludf.DUMMYFUNCTION("IFERROR(ROWS(UNIQUE(FILTER(job_status!D:D, job_status!C:C=A31, job_status!E:E=""up:ChangeRequested"", job_status!F:F=1))), 0)"),36.0) -> 36 | O6: =IFERROR(__xludf.DUMMYFUNCTION("IFERROR(ROWS(UNIQUE(FILTER(job_status!D:D, job_status!C:C=A31, job_status!E:E=""up:InReview"", job_status!F:F=1))), 0)"),36.0) -> 36 | P6: =COUNTIFS(job_status!C:C, A31, job_status!E:E, "up:Reviewed", job_status!F:F,1) -> 36 | Q6: =IFERROR(__xludf.DUMMYFUNCTION("IFERROR(ROWS(UNIQUE(FILTER(job_status!D:D, job_status!C:C=A31, job_status!E:E=""up:Success"", job_status!F:F=1))), 0)"),12.0) -> 12 | R6: =Q6/P6 -> 0.33333333 | S6: =IFERROR(__xludf.DUMMYFUNCTION("IFERROR(ROWS(UNIQUE(FILTER(job_status!D:D, job_status!C:C=A31, job_status!E:E=""up:ChangeRequested"", job_status!F:F=2))), 0)"),24.0) -> 24 | T6: =IFERROR(__xludf.DUMMYFUNCTION("IFERROR(ROWS(UNIQUE(FILTER(job_status!D:D, job_status!C:C=A31, job_status!E:E=""up:InReview"", job_status!F:F=2))), 0)"),24.0) -> 24 | U6: =COUNTIFS(job_status!C:C, A31, job_status!E:E, "up:Reviewed", job_status!F:F,2) -> 24 | V6: =IFERROR(__xludf.DUMMYFUNCTION("IFERROR(ROWS(UNIQUE(FILTER(job_status!D:D, job_status!C:C=A31, job_status!E:E=""up:Success"", job_status!F:F=2))), 0)"),13.0) -> 13
A8: Totals | B8: =sum(B3:B6) -> 107 | C8: =sum(C3:C6) -> 105 | D8: =sum(D3:D6) -> 2 | E8: =sum(E3:E6) -> 0 | F8: =sum(F3:F6) -> 104 | G8: =sum(G3:G6) -> 315 | H8: =sum(H3:H6) -> 312 | I8: =sum(I3:I6) -> 312 | ... K8: =sum(K3:K6) -> 126 | L8: =K8/I8 -> 0.40384615 | M8: =sum(M3:M6) -> 0 | N8: =sum(N3:N6) -> 186 | O8: =sum(O3:O6) -> 186 | P8: =sum(P3:P6) -> 186 | Q8: =sum(Q3:Q6) -> 75 | R8: =Q8/P8 -> 0.40322581 | S8: =sum(S3:S6) -> 111 | T8: =sum(T3:T6) -> 111 | U8: =sum(U3:U6) -> 111 | V8: =sum(V3:V6) -> 48
E9: =E8/B8 -> 0
K12: Assignments Faling M1 | L12: Name | M12: Turn 1 Reviews Pending | N12: Turn 2 Reviews Pending
K13: =COUNTIF(M5_submission_fails!F:F, "No") -> 0 | L13: Sanjeev | M13: =(O3 - P3) -> 0 | N13: =(T3 - U3) -> 0
L14: Solomon | M14: =(O4 - P4) -> 0 | N14: =(T4 - U4) -> 0
L15: Ghulam | M15: =(O5 - P5) -> 0 | N15: =(T5 - U5) -> 0
L16: Youssef | M16: =(O6 - P6) -> 0 | N16: =(T6 - U6) -> 0
L17: Remaining | M17: =sum(M13:M16) -> 0 | N17: =sum(N13:N16) -> 0
L18: Assuming all remaining turn 1 reviews fail, they will have to be reviewed in turn 2. That will add to the existing pending reviews in turn 2 | M18: =2*M17 + N17 -> 0
L19: Assuming same remaining succes percentage | M19: =R8*M17*2 + N17 -> 0
L20: Time per review (in minutes) | M20: =67*0.6*2 + N17 -> 80.4
L21: Max Time (hours) | M21: =M18*20/60 -> 0
L22: Max Time percentage(hours) | M22: =M19*20/60 -> 0
L23: Sanjeev | M23: =(2*M13+N13)*20/60 -> 0 | N23: =(2*M13*0.69+N13)*20/60 -> 0
L24: Solomon | M24: =(2*M14+N14)*20/60 -> 0 | N24: =(2*M14*0.69+N14)*20/60 -> 0
L25: Ghulam | M25: =(2*M15+N15)*20/60 -> 0 | N25: =(2*M15*0.69+N15)*20/60 -> 0
L26: Youssef | M26: =(2*M16+N16)*20/60 -> 0 | N26: =(2*M16*0.69+N16)*20/60 -> 0
A27: Slack Helper for assigned DO NOT TOUCH | M27: =sum(M23:M26) -> 0 | N27: =(2*M17*0.69+N17)*20/60 -> 0
A28: {=INDEX(assignments!C:C, MATCH(A3, assignments!B:B, 0))} -> U0ARQUUJXBM | L28: Darvin (assuming 3 hours and 4 reviews per hour) | M28: 12
A29: {=INDEX(assignments!C:C, MATCH(A4, assignments!B:B, 0))} -> U0ASA7SCECR | L29: Karthik (assuming 9 hours and 4 reveiws per hour) | M29: 36
A30: {=INDEX(assignments!C:C, MATCH(A5, assignments!B:B, 0))} -> U0ASRJTQSPJ | L30: Nikhil (assuming 4 hours at 4 reviews per hour) | M30: 16
A31: {=INDEX(assignments!C:C, MATCH(A6, assignments!B:B, 0))} -> U0ARV8X2JDU | M31: =sum(M28:M30) -> 64
L32: New Eval load | M32: =M18 - M31 -> -64 | N32: =M19 - M31 -> -64
L33: Reduced time | M33: =64*20/60 -> 21.333333 | N33: =64*20/60 -> 21.333333
L34: New Time | M34: =136*20/60 -> 45.333333 | N34: =N32*20/60 -> -21.333333
K36: Threads with critical skip marked as fail - Turn 0 | L36: Count Critical Fail | M36: Count of Critical Skip
K37: =IFERROR(__xludf.DUMMYFUNCTION("UNIQUE(FILTER(evals_turn0!E:E, evals_turn0!T:T=0, evals_turn0!G:G=""fail"", evals_turn0!U:U > 0))"),"32064128:anthropic:U0ARV8X2JDU") -> 32064128:anthropic:U0ARV8X2JDU | L37: =IFERROR(__xludf.DUMMYFUNCTION("FILTER(evals_turn0!T:T, evals_turn0!T:T=0, evals_turn0!G:G=""fail"", evals_turn0!U:U > 0)"),0.0) -> 0 | M37: =IFERROR(__xludf.DUMMYFUNCTION("FILTER(evals_turn0!U:U, evals_turn0!T:T=0, evals_turn0!G:G=""fail"", evals_turn0!U:U > 0)"),1.0) -> 1
K38: =IFERROR(__xludf.DUMMYFUNCTION("""COMPUTED_VALUE"""),"28590549:google:U0ARV8X2JDU") -> 28590549:google:U0ARV8X2JDU | L38: =IFERROR(__xludf.DUMMYFUNCTION("""COMPUTED_VALUE"""),0.0) -> 0 | M38: =IFERROR(__xludf.DUMMYFUNCTION("""COMPUTED_VALUE"""),4.0) -> 4
K39: =IFERROR(__xludf.DUMMYFUNCTION("""COMPUTED_VALUE"""),"28590549:anthropic:U0ARV8X2JDU") -> 28590549:anthropic:U0ARV8X2JDU | L39: =IFERROR(__xludf.DUMMYFUNCTION("""COMPUTED_VALUE"""),0.0) -> 0 | M39: =IFERROR(__xludf.DUMMYFUNCTION("""COMPUTED_VALUE"""),4.0) -> 4
K40: =IFERROR(__xludf.DUMMYFUNCTION("""COMPUTED_VALUE"""),"36277294:anthropic:U0ARQUUJXBM") -> 36277294:anthropic:U0ARQUUJXBM | L40: =IFERROR(__xludf.DUMMYFUNCTION("""COMPUTED_VALUE"""),0.0) -> 0 | M40: =IFERROR(__xludf.DUMMYFUNCTION("""COMPUTED_VALUE"""),3.0) -> 3
K41: =IFERROR(__xludf.DUMMYFUNCTION("""COMPUTED_VALUE"""),"36277294:openai:U0ARQUUJXBM") -> 36277294:openai:U0ARQUUJXBM | L41: =IFERROR(__xludf.DUMMYFUNCTION("""COMPUTED_VALUE"""),0.0) -> 0 | M41: =IFERROR(__xludf.DUMMYFUNCTION("""COMPUTED_VALUE"""),3.0) -> 3
K42: =IFERROR(__xludf.DUMMYFUNCTION("""COMPUTED_VALUE"""),"34581102:google:U0ASRJTQSPJ") -> 34581102:google:U0ASRJTQSPJ | L42: =IFERROR(__xludf.DUMMYFUNCTION("""COMPUTED_VALUE"""),0.0) -> 0 | M42: =IFERROR(__xludf.DUMMYFUNCTION("""COMPUTED_VALUE"""),1.0) -> 1
K44: Threads with critical skip marked as fail - Turn 1 | L44: Count Critical Fail | M44: Count of Critical Skip
K45: =IFERROR(__xludf.DUMMYFUNCTION("UNIQUE(FILTER(evals_turn1!E:E, evals_turn1!T:T=0, evals_turn1!G:G=""fail"", evals_turn1!U:U > 0))"),"25506763:openai:U0ASA7SCECR") -> 25506763:openai:U0ASA7SCECR | L45: =IFERROR(__xludf.DUMMYFUNCTION("FILTER(evals_turn1!T:T, evals_turn1!T:T=0, evals_turn1!G:G=""fail"", evals_turn1!U:U > 0)"),0.0) -> 0 | M45: =IFERROR(__xludf.DUMMYFUNCTION("FILTER(evals_turn1!U:U, evals_turn1!T:T=0, evals_turn1!G:G=""fail"", evals_turn1!U:U > 0)"),5.0) -> 5
K46: =IFERROR(__xludf.DUMMYFUNCTION("""COMPUTED_VALUE"""),"30054640:google:U0ARQUUJXBM") -> 30054640:google:U0ARQUUJXBM | L46: =IFERROR(__xludf.DUMMYFUNCTION("""COMPUTED_VALUE"""),0.0) -> 0 | M46: =IFERROR(__xludf.DUMMYFUNCTION("""COMPUTED_VALUE"""),4.0) -> 4
K47: =IFERROR(__xludf.DUMMYFUNCTION("""COMPUTED_VALUE"""),"30054640:anthropic:U0ARQUUJXBM") -> 30054640:anthropic:U0ARQUUJXBM | L47: =IFERROR(__xludf.DUMMYFUNCTION("""COMPUTED_VALUE"""),0.0) -> 0 | M47: =IFERROR(__xludf.DUMMYFUNCTION("""COMPUTED_VALUE"""),4.0) -> 4
K48: =IFERROR(__xludf.DUMMYFUNCTION("""COMPUTED_VALUE"""),"30054640:openai:U0ARQUUJXBM") -> 30054640:openai:U0ARQUUJXBM | L48: =IFERROR(__xludf.DUMMYFUNCTION("""COMPUTED_VALUE"""),0.0) -> 0 | M48: =IFERROR(__xludf.DUMMYFUNCTION("""COMPUTED_VALUE"""),4.0) -> 4
K49: =IFERROR(__xludf.DUMMYFUNCTION("""COMPUTED_VALUE"""),"29557774:google:U0ASRJTQSPJ") -> 29557774:google:U0ASRJTQSPJ | L49: =IFERROR(__xludf.DUMMYFUNCTION("""COMPUTED_VALUE"""),0.0) -> 0 | M49: =IFERROR(__xludf.DUMMYFUNCTION("""COMPUTED_VALUE"""),2.0) -> 2
K50: =IFERROR(__xludf.DUMMYFUNCTION("""COMPUTED_VALUE"""),"28590549:openai:U0ARV8X2JDU") -> 28590549:openai:U0ARV8X2JDU | L50: =IFERROR(__xludf.DUMMYFUNCTION("""COMPUTED_VALUE"""),0.0) -> 0 | M50: =IFERROR(__xludf.DUMMYFUNCTION("""COMPUTED_VALUE"""),5.0) -> 5
K51: =IFERROR(__xludf.DUMMYFUNCTION("""COMPUTED_VALUE"""),"36277294:anthropic:U0ARQUUJXBM") -> 36277294:anthropic:U0ARQUUJXBM | L51: =IFERROR(__xludf.DUMMYFUNCTION("""COMPUTED_VALUE"""),0.0) -> 0 | M51: =IFERROR(__xludf.DUMMYFUNCTION("""COMPUTED_VALUE"""),3.0) -> 3
K52: =IFERROR(__xludf.DUMMYFUNCTION("""COMPUTED_VALUE"""),"36277294:google:U0ARQUUJXBM") -> 36277294:google:U0ARQUUJXBM | L52: =IFERROR(__xludf.DUMMYFUNCTION("""COMPUTED_VALUE"""),0.0) -> 0 | M52: =IFERROR(__xludf.DUMMYFUNCTION("""COMPUTED_VALUE"""),3.0) -> 3
K53: =IFERROR(__xludf.DUMMYFUNCTION("""COMPUTED_VALUE"""),"36277294:openai:U0ARQUUJXBM") -> 36277294:openai:U0ARQUUJXBM | L53: =IFERROR(__xludf.DUMMYFUNCTION("""COMPUTED_VALUE"""),0.0) -> 0 | M53: =IFERROR(__xludf.DUMMYFUNCTION("""COMPUTED_VALUE"""),3.0) -> 3
K54: =IFERROR(__xludf.DUMMYFUNCTION("""COMPUTED_VALUE"""),"34057595:google:U0ASA7SCECR") -> 34057595:google:U0ASA7SCECR | L54: =IFERROR(__xludf.DUMMYFUNCTION("""COMPUTED_VALUE"""),0.0) -> 0 | M54: =IFERROR(__xludf.DUMMYFUNCTION("""COMPUTED_VALUE"""),1.0) -> 1
K55: =IFERROR(__xludf.DUMMYFUNCTION("""COMPUTED_VALUE"""),"30054886:google:U0ASRJTQSPJ") -> 30054886:google:U0ASRJTQSPJ | L55: =IFERROR(__xludf.DUMMYFUNCTION("""COMPUTED_VALUE"""),0.0) -> 0 | M55: =IFERROR(__xludf.DUMMYFUNCTION("""COMPUTED_VALUE"""),1.0) -> 1
K56: =IFERROR(__xludf.DUMMYFUNCTION("""COMPUTED_VALUE"""),"30054886:openai:U0ASRJTQSPJ") -> 30054886:openai:U0ASRJTQSPJ | L56: =IFERROR(__xludf.DUMMYFUNCTION("""COMPUTED_VALUE"""),0.0) -> 0 | M56: =IFERROR(__xludf.DUMMYFUNCTION("""COMPUTED_VALUE"""),5.0) -> 5
K57: =IFERROR(__xludf.DUMMYFUNCTION("""COMPUTED_VALUE"""),"35459600:google:U0ASRJTQSPJ") -> 35459600:google:U0ASRJTQSPJ | L57: =IFERROR(__xludf.DUMMYFUNCTION("""COMPUTED_VALUE"""),0.0) -> 0 | M57: =IFERROR(__xludf.DUMMYFUNCTION("""COMPUTED_VALUE"""),1.0) -> 1

Sheet agent_traces
A1: job_id | B1: agent | C1: job_status | D1: initial_request | E1: agent_response:turn_0 | F1: evaluation:turn_0
A2: 23829182 | B2: anthropic | C2: up:Success | D2: job_name: Need JavaScript component: extended FAB button triggering an action menu job_description: I am looking for an experienced freelance frontend dev to create the following JavaScript component: An extended floating action button that opens an action menu on click, according to the Material specs. Extended FAB = A FAB with icon and label. Here's a description: https://material.io/components/buttons-floating-action-button/#extended-fab (see also screenshot). On click, it should overlay an action menu (like in the video/screenshot attached). Important is that the FAB can be put in the bottom right corner of the page (position fixed) and that the menu opens above the FAB, to the top. So that if you click twice (without moving the cursor), you end up clicking the last option of the action menu. The implementation should be in pure CSS, HTML and JavaScript (you can also use TypeScript and/or SCSS for styling). Colors and texts don't matter, but should be easy to change. Performance is important: it should be smoothly implemented, much like in the examples of the Material docs. It's not important to make it as a highly configurable web component. Just the HTML, CSS (and if necessary, the JavaScript/TypeScript) is needed. **NO usage of 3th party libraries or frameworks. So no jQuery, bootstrap, Material frameworks, React, etc... You can base the code of existing FAB implementations (there are some on Codepen and many other websites) if the license allows it, but the deliverable should be pure HTML+CSS(+JS) without dependencies** Thank you, looking forward to working together! | E2: # hapi-v2-benchmark Repo to collect HAPI v2 benchmark agent deliverable | F2: { "job_id": "23829182", "agent_name": "anthropic", "turn": 0, "evaluator": "U0ASA7SCECR", "overall_judgement": "pass", "submission_feedback": [ { "id": 1, "label": "critical", "judgement": "pass", "reasoning": "The index.html includes a <button class=\"fab\"> containing both a Material icon SVG and a text label \"Actions\", following the extended FAB design." }, { "id": 2, "label": "critical", "judgement": "pass", "reasoning": "The action menu is positioned within a flex container that stacks elements vertically, ensuring the fab-menu overlays directly above the FAB when opened." }, { "id": 3, "label": "critical", "judgement": "pass", "reasoning": "The implementation uses only native HTML5, CSS3 (with custom properties), and vanilla JavaScript without any external libraries or frameworks." }, { "id": 4, "label": "critical", "judgement": "pass", "reasoning": "The implementation uses only native HTML5, CSS3 (with custom properties), and vanilla JavaScript without any external libraries or frameworks." }, { "id": 5, "label": "critical", "judgement": "pass", "reasoning": "Animations use the standard Material Design cubic-bezier(0.4, 0, 0.2, 1) easing and staggered delays to provide a smooth, performant expansion effect." }, { "id": 6, "label": "optional", "judgement": "pass", "reasoning": "All primary colors, dimensions, and animation timings are defined as CSS variables in the @root selector, making them easy to modify." } ] }
A4: 23829182 | B4: google | C4: up:Success | D4: job_name: Need JavaScript component: extended FAB button triggering an action menu job_description: I am looking for an experienced freelance frontend dev to create the following JavaScript component: An extended floating action button that opens an action menu on click, according to the Material specs. Extended FAB = A FAB with icon and label. Here's a description: https://material.io/components/buttons-floating-action-button/#extended-fab (see also screenshot). On click, it should overlay an action menu (like in the video/screenshot attached). Important is that the FAB can be put in the bottom right corner of the page (position fixed) and that the menu opens above the FAB, to the top. So that if you click twice (without moving the cursor), you end up clicking the last option of the action menu. The implementation should be in pure CSS, HTML and JavaScript (you can also use TypeScript and/or SCSS for styling). Colors and texts don't matter, but should be easy to change. Performance is important: it should be smoothly implemented, much like in the examples of the Material docs. It's not important to make it as a highly configurable web component. Just the HTML, CSS (and if necessary, the JavaScript/TypeScript) is needed. **NO usage of 3th party libraries or frameworks. So no jQuery, bootstrap, Material frameworks, React, etc... You can base the code of existing FAB implementations (there are some on Codepen and many other websites) if the license allows it, but the deliverable should be pure HTML+CSS(+JS) without dependencies** Thank you, looking forward to working together! | E4: # Extended Floating Action Button (FAB) Component This project provides a pure HTML, CSS, and JavaScript implementation of an Extended Floating Action Button that opens an Action Menu, built according to the Material Design specifications. ## Features - **Pure Implementation**: Zero external dependencies, libraries, or frameworks (no jQuery, Bootstrap, React, etc.). - **Material Specs**: Uses standard Material Design sizing, elevations, typography (Roboto), and icons. - **Fixed Position**: The FAB is positioned in the bottom right corner. - **Click-to-Action Alignment**: The action menu opens above the FAB. Its bottom-right origin perfectly aligns with the FAB such that clicking the FAB and then immediately clicking again without moving the cursor will trigger the last option in the menu. - **Ripple Effect**: Includes a custom JavaScript-based Material ripple effect for both the FAB and menu items. - **Keyboard Accessibility**: Supports keyboard navigation (`Enter` / `Space` to activate, `Escape` to close, `ArrowUp` / `ArrowDown` to navigate menu items). ## Files - `index.html`: Contains the markup for the FAB and the action menu. - `styles.css`: Contains the CSS for layout, styling, animations, and shadows. - `script.js`: Contains the logic for toggling the menu, handling clicks, keyboard accessibility, and the ripple effect. ## How to Run Since this is pure HTML/CSS/JS, no build step or installation is required: 1. Open `index.html` in any modern web browser. 2. Click the extended FAB in the bottom right corner to see the menu animate in. 3. Click again to trigger the last item, or click elsewhere to close it. | F4: { "job_id": "23829182", "agent_name": "google", "turn": 0, "evaluator": "U0ASA7SCECR", "overall_judgement": "pass", "submission_feedback": [ { "id": 1, "label": "critical", "judgement": "pass", "reasoning": "The button matches Material specs with a 56px height, rounded corners, and includes both a Material icon and a text label." }, { "id": 2, "label": "critical", "judgement": "pass", "reasoning": "The menu overlays the FAB on the Z-axis and extends upwards, fulfilling the requirement for immediate selection on a second click." }, { "id": 3, "label": "critical", "judgement": "pass", "reasoning": "The FAB container is appropriately fixed at the bottom-right of the page with standard 24px offsets from the viewport edges." }, { "id": 4, "label": "critical", "judgement": "pass", "reasoning": "The project uses only pure HTML, CSS, and vanilla JavaScript without any third-party libraries or frameworks." }, { "id": 5, "label": "critical", "judgement": "pass", "reasoning": "Open/close transitions use hardware-accelerated transforms and standard Material Design cubic-bezier easing for smooth performance." }, { "id": 6, "label": "optional", "judgement": "pass", "reasoning": "Centralized CSS variables and semantic HTML structure allow for easy modification of colors and text content without touching logic." } ] }
A6: 23829182 | B6: openai | C6: up:Success | D6: job_name: Need JavaScript component: extended FAB button triggering an action menu job_description: I am looking for an experienced freelance frontend dev to create the following JavaScript component: An extended floating action button that opens an action menu on click, according to the Material specs. Extended FAB = A FAB with icon and label. Here's a description: https://material.io/components/buttons-floating-action-button/#extended-fab (see also screenshot). On click, it should overlay an action menu (like in the video/screenshot attached). Important is that the FAB can be put in the bottom right corner of the page (position fixed) and that the menu opens above the FAB, to the top. So that if you click twice (without moving the cursor), you end up clicking the last option of the action menu. The implementation should be in pure CSS, HTML and JavaScript (you can also use TypeScript and/or SCSS for styling). Colors and texts don't matter, but should be easy to change. Performance is important: it should be smoothly implemented, much like in the examples of the Material docs. It's not important to make it as a highly configurable web component. Just the HTML, CSS (and if necessary, the JavaScript/TypeScript) is needed. **NO usage of 3th party libraries or frameworks. So no jQuery, bootstrap, Material frameworks, React, etc... You can base the code of existing FAB implementations (there are some on Codepen and many other websites) if the license allows it, but the deliverable should be pure HTML+CSS(+JS) without dependencies** Thank you, looking forward to working together! | E6: # Extended FAB Action Menu This deliverable is a dependency-free implementation of an extended floating action button that opens an overlay action menu upward from the bottom-right corner of the page. ## What Was Built - A fixed extended FAB with icon and label - An upward-opening action menu anchored to the same bottom-right origin - Pure HTML, CSS, and JavaScript with no third-party libraries - Keyboard and pointer interactions for opening, closing, and selecting actions - Styling via CSS custom properties so colors and spacing are easy to change ## Files - `index.html` contains the demo markup and the component structure - `styles.css` contains all component and page styling - `script.js` contains the menu toggle and interaction logic ## Run No build step is required. 1. Open `index.html` directly in a browser. 2. Or serve the folder with a static server, for example: ```bash python3 -m http.server 8000 ``` Then visit `http://localhost:8000`. ## Customization - Update the action labels directly in `index.html` - Change colors, shadows, and sizing in the `:root` variables in `styles.css` - Move the component by editing `.fab-controller` in `styles.css` ## Behavior Notes - The menu surface is positioned from the same bottom-right anchor as the FAB - When the menu opens, it overlays the FAB so a second click without moving the pointer activates the last action - Motion uses lightweight opacity and transform transitions for smooth rendering | F6: { "job_id": "23829182", "agent_name": "openai", "turn": 0, "evaluator": "U0ASA7SCECR", "overall_judgement": "pass", "submission_feedback": [ { "id": 1, "label": "critical", "judgement": "pass", "reasoning": "The implementation includes a properly structured Extended FAB in index.html with both a SVG icon and a text label, consistent with Material Design specifications." }, { "id": 2, "label": "critical", "judgement": "pass", "reasoning": "The menu is positioned at the same anchor point as the FAB and expands upwards, ensuring the last action overlays the trigger for immediate accessibility upon a second click." }, { "id": 3, "label": "critical", "judgement": "pass", "reasoning": "The .fab-controller in styles.css uses position: fixed with clamp-based offsets to reliably anchor the component in the bottom-right corner of the viewport." }, { "id": 4, "label": "critical", "judgement": "pass", "reasoning": "The project strictly utilizes vanilla HTML, CSS (using modern features like color-mix and variables), and JavaScript without any external dependencies or frameworks" }, { "id": 5, "label": "critical", "judgement": "pass", "reasoning": "Transitions are optimized using transform and opacity properties with a custom cubic-bezier easing, resulting in a smooth, high-performance animation." }, { "id": 6, "label": "optional", "judgement": "pass", "reasoning": "A comprehensive set of CSS variables in the :root pseudo-class allows for effortless customization of the color palette, shadows, and layout dimensions." } ] }
A8: 24294313 | B8: anthropic | C8: up:Success | D8: job_name: Create a 3-page web application job_description: Create a 3-page web application in C # using ASP.NET MVC Framework. Layouts (first three attached files) DB structure (fourth file, additions / suggestions are accepted) The database can be filled with random values 1 page: The values â€‹â€‹in the table are updated with a frequency of 1 second (without reloading the page) "Time" corresponds to the value of trainingtime in the control_panel table "Position" corresponds to the value of current_position in the control_panel table "Angle" 1 corresponds to the bending value in the control_panel table "Angle" 2 corresponds to the extension value in the control_panel table "Limits" corresponds to the extension value in the control_panel table Pause 1 corresponds to the pausebending value in the control_panel table Pause 2 corresponds to the pauseextension value in the control_panel table "Speed" corresponds to the value of speed in the control_panel table 2 page: Data from the tables sens_positiondata and sens_resistancemotordata, which are updated with a frequency of 2 seconds (without reloading the page) 3 page Depending on the values â€‹â€‹of positionsel in sens_positiondata and resistdel in sens_resistancemotordata (for example, less than a certain one. It does not matter what the condition is) to output data (any, one if / esle will be enough) !!NOTE: I need web-application to be done in 2 days. | E8: # hapi-v2-benchmark Repo to collect HAPI v2 benchmark agent deliverable | F8: { "job_id": "24294313", "agent_name": "anthropic", "turn": 0, "evaluator": "U0ASA7SCECR", "overall_judgement": "pass", "submission_feedback": [ { "id": 1, "label": "critical", "judgement": "pass", "reasoning": "The application is built with the ASP.NET MVC Framework in C# and implements the required database schema using SQLite." }, { "id": 2, "label": "critical", "judgement": "pass", "reasoning": "Page 1 correctly maps and displays all required fields from the control_panel and trainingtime tables with a 1-second AJAX auto-update interval." }, { "id": 3, "label": "critical", "judgement": "pass", "reasoning": "Page 2 successfully displays data from sens_positiondata and sens_resistancemotordata in separate sections with a 2-second AJAX auto-update interval." }, { "id": 4, "label": "critical", "judgement": "pass", "reasoning": "Page 3 implements a logical condition evaluated against sensor deviations to display diagnostic messages and solutions." }, { "id": 5, "label": "critical", "judgement": "pass", "reasoning": "The visual layout and component structure (tables, sections, and navigation) align with the provided mockup images." }, { "id": 6, "label": "optional", "judgement": "pass", "reasoning": "The database is automatically initialized and pre-filled with randomized values during the first application startup." } ] }
A10: 24294313 | B10: google | C10: up:InReview | D10: job_name: Create a 3-page web application job_description: Create a 3-page web application in C # using ASP.NET MVC Framework. Layouts (first three attached files) DB structure (fourth file, additions / suggestions are accepted) The database can be filled with random values 1 page: The values â€‹â€‹in the table are updated with a frequency of 1 second (without reloading the page) "Time" corresponds to the value of trainingtime in the control_panel table "Position" corresponds to the value of current_position in the control_panel table "Angle" 1 corresponds to the bending value in the control_panel table "Angle" 2 corresponds to the extension value in the control_panel table "Limits" corresponds to the extension value in the control_panel table Pause 1 corresponds to the pausebending value in the control_panel table Pause 2 corresponds to the pauseextension value in the control_panel table "Speed" corresponds to the value of speed in the control_panel table 2 page: Data from the tables sens_positiondata and sens_resistancemotordata, which are updated with a frequency of 2 seconds (without reloading the page) 3 page Depending on the values â€‹â€‹of positionsel in sens_positiondata and resistdel in sens_resistancemotordata (for example, less than a certain one. It does not matter what the condition is) to output data (any, one if / esle will be enough) !!NOTE: I need web-application to be done in 2 days. | E10: # ASP.NET Core MVC 3-Page Web Application ## Overview This is a 3-page web application built with C# and ASP.NET Core MVC framework. It fulfills the requirements provided in the job description, using an Entity Framework Core In-Memory database filled with randomized data to simulate the dynamic behavior. ### Features * **Page 1 (Control Panel Data):** Displays live values from the `control_panel` table. The data is polled and updated on the frontend every 1 second without reloading the page. * **Page 2 (Sensor Data):** Displays live values from the `sens_positiondata` and `sens_resistancemotordata` tables. The data is polled and updated every 2 seconds without reloading the page. * **Page 3 (Condition Status):** Evaluates a simple IF/ELSE condition based on `positionsel` and `resistdel` values and outputs the result. The condition evaluation updates every 2 seconds without a page reload. ## Architecture & Implementation * **Backend:** ASP.NET Core 10.0 MVC * **Database:** Entity Framework Core with In-Memory Database (`Microsoft.EntityFrameworkCore.InMemory`) * **Data Simulation:** A Background Service (`RandomizeDataService`) runs continuously and randomizes the database values every second to simulate a live changing environment. * **Frontend Updates:** JavaScript `fetch` API is used with `setInterval` to poll the API endpoints (`/api/data/page1`, `/api/data/page2`, `/api/data/page3`) and update the HTML DOM dynamically. ## How to Run the Application ### Prerequisites * [.NET 10.0 SDK](https://dotnet.microsoft.com/en-us/download/dotnet/10.0) (or a compatible .NET SDK) installed on your machine. ### Instructions 1. Open your terminal or command prompt. 2. Navigate to the `src` folder inside the project root: ```bash cd src ``` 3. Run the application using the .NET CLI: ```bash dotnet run ``` 4. Open your web browser and navigate to the local URL provided in the console output (usually `http://localhost:5000` or `https://localhost:5001`). You can navigate between the three pages using the navigation bar at the top of the application. | F10: { "job_id": "24294313", "agent_name": "google", "turn": 0, "evaluator": "U0ASA7SCECR", "overall_judgement": "fail", "submission_feedback": [ { "id": 1, "label": "critical", "judgement": "pass", "reasoning": "The application is correctly built using the ASP.NET Core MVC framework in C# and implements the required database schema via Entity Framework Core." }, { "id": 2, "label": "critical", "judgement": "fail", "reasoning": " Page 1 uses a vertical table layout and generic labels that do not match the horizontal structure and specific headers (e.g., \"Current position\") shown in mockup 11.png." }, { "id": 3, "label": "critical", "judgement": "pass", "reasoning": "Page 2 lacks the separate sections and the ID/Time/Value columns required by mockup 2.png, displaying only single raw data points instead of a data list." }, { "id": 4, "label": "critical", "judgement": "pass", "reasoning": "Page 3 successfully implements a logical condition check on positionsel and resistdel values and updates the UI message accordingly without a page reload." }, { "id": 5, "label": "critical", "judgement": "fail", "reasoning": "The visual layout fails to match the mockups, specifically regarding the navigation bar labels (\"Page 1\" vs. \"Monitoring\") and the overall page hierarchy." }, { "id": 6, "label": "optional", "judgement": "pass", "reasoning": "The application correctly pre-fills the in-memory database with random values upon startup through a seed routine in Program.cs." } ] }
A12: 24294313 | B12: openai | C12: up:Reviewed | D12: job_name: Create a 3-page web application job_description: Create a 3-page web application in C # using ASP.NET MVC Framework. Layouts (first three attached files) DB structure (fourth file, additions / suggestions are accepted) The database can be filled with random values 1 page: The values â€‹â€‹in the table are updated with a frequency of 1 second (without reloading the page) "Time" corresponds to the value of trainingtime in the control_panel table "Position" corresponds to the value of current_position in the control_panel table "Angle" 1 corresponds to the bending value in the control_panel table "Angle" 2 corresponds to the extension value in the control_panel table "Limits" corresponds to the extension value in the control_panel table Pause 1 corresponds to the pausebending value in the control_panel table Pause 2 corresponds to the pauseextension value in the control_panel table "Speed" corresponds to the value of speed in the control_panel table 2 page: Data from the tables sens_positiondata and sens_resistancemotordata, which are updated with a frequency of 2 seconds (without reloading the page) 3 page Depending on the values â€‹â€‹of positionsel in sens_positiondata and resistdel in sens_resistancemotordata (for example, less than a certain one. It does not matter what the condition is) to output data (any, one if / esle will be enough) !!NOTE: I need web-application to be done in 2 days. | E12: # Motion Monitor ASP.NET Core MVC web application that implements the requested three-page monitoring dashboard in C#. ## What Was Built - `Home`: a control-panel summary table that refreshes every 1 second without reloading. - `Monitoring`: live position and resistance tables sourced from `sens_positiondata` and `sens_resistancemotordata`, refreshed every 2 seconds. - `Error`: a rule-based diagnostic page that evaluates `positionsel` and `resistdel` and outputs a problem, cause, and solution. - SQLite-backed persistence with seeded random telemetry and a hosted simulator that keeps the values changing while the app runs. ## Stack - .NET 8 - ASP.NET Core MVC - Entity Framework Core with SQLite - Vanilla JavaScript polling with `fetch` ## Project Structure - `src/MonitoringDashboard`: MVC application - `src/MonitoringDashboard/Data`: EF Core context and database seeding - `src/MonitoringDashboard/Services`: background telemetry simulator - `src/MonitoringDashboard/ViewModels`: page and API response models ## Run Locally ```bash dotnet restore MonitoringDashboard.slnx dotnet run --project src/MonitoringDashboard/MonitoringDashboard.csproj ``` Then open the local URL printed by ASP.NET Core. ## Notes - The original schema image was simplified into the tables required by the issue so the requested screens can map directly to persisted values. - The SQLite database file is created automatically on first run and is ignored by git. | F12: { "job_id": "24294313", "agent_name": "openai", "turn": 0, "evaluator": "U0ASA7SCECR", "overall_judgement": "pass", "submission_feedback": [ { "id": 1, "label": "critical", "judgement": "pass", "reasoning": "The application is built using the ASP.NET MVC Framework in C#, and the database models (ControlPanelState, PositionSensorReading, ResistanceMotorReading) correctly map to the specified schema tables." }, { "id": 2, "label": "critical", "judgement": "pass", "reasoning": "The Home page (Page 1) displays a summary table with values from the control_panel table, including the trainingtime mapping, and uses AJAX polling in site.js to auto-update every 1 second." }, { "id": 3, "label": "critical", "judgement": "pass", "reasoning": "The Monitoring page (Page 2) features separate sections for position and resistance sensor data, which auto-update every 2 seconds without a page reload using background fetch calls." }, { "id": 4, "label": "critical", "judgement": "pass", "reasoning": "The Error page (Page 3) implements a diagnostic logic in the HomeController that evaluates the positionsel and resistdel fields against defined thresholds to display conditional error messages." }, { "id": 5, "label": "critical", "judgement": "pass", "reasoning": "The user interface structure and telemetry table layouts in the Razor views (Index.cshtml, Monitoring.cshtml, Error.cshtml) align with the visual organization shown in the provided mockup images." }, { "id": 6, "label": "optional", "judgement": "pass", "reasoning": "The database is pre-filled during application startup by the AppDbInitializer class, which seeds the SQLite tables with initial random values for immediately functional monitoring." } ] }
A14: 24766666 | B14: anthropic | C14: up:Success | D14: job_name: Vue.js Express MEVN Google Drive API wrapper interface & Web App development job_description: Initial project which could lead to more work Mongo if needed Express for API Vue.js for UI Node.js Using token from Google drive Create a Microservice to query the list documents from Google Drive Frontend Web app will display a list of retrieved document names Tapping on a document name will display the document metadata Page can be refreshed to update list if any new documents added to Google Drive This is a very simple project. Read only access to Google drive. I am just an individual so I don't have a large budget however if you can do a good job and I get funding then the rest of the app can be built out Bonus points if you can deploy this to gcp, amazon, azure or any cloud service and have a CI pipeline with tests Bonus if design is so beautifully simple and functional on desktop and web Update 1: Express API you develop will sit in between Google and Vue.js UI One day I will point to a different document server (e.g. DropBox) or I may use a different UI. The API should be able to simply passthrough some values. List files: https://developers.google.com/drive/api/v3/reference/files/list Get file details: https://developers.google.com/drive/api/v3/reference/files#resource | E14: # hapi-v2-benchmark Repo to collect HAPI v2 benchmark agent deliverable | F14: { "job_id": "24766666", "agent_name": "anthropic", "turn": 0, "evaluator": "U0ASA7SCECR", "overall_judgement": "pass", "submission_feedback": [ { "id": 1, "label": "critical", "judgement": "pass", "reasoning": "The backend is built with Express and uses the googleapis library to authenticate via an OAuth2 refresh token flow defined in api/src/services/googleDrive.js." }, { "id": 2, "label": "critical", "judgement": "pass", "reasoning": "The /api/files endpoint in api/src/routes/files.js invokes the drive.files.list operation to fetch and return the user's document list." }, { "id": 3, "label": "critical", "judgement": "pass", "reasoning": "The frontend is a Vue 3 application that utilizes a FileList.vue component to render the names of retrieved files in a selectable list." }, { "id": 4, "label": "critical", "judgement": "pass", "reasoning": "Tapping a file name triggers the selectFile method, which fetches full metadata via the API and displays it in the FileDetail.vue component." }, { "id": 5, "label": "critical", "judgement": "pass", "reasoning": "A \"Refresh\" button is implemented in the application header (App.vue) that clears the current view and re-executes the loadFiles query." } ] }
A16: 24766666 | B16: google | C16: up:Success | D16: job_name: Vue.js Express MEVN Google Drive API wrapper interface & Web App development job_description: Initial project which could lead to more work Mongo if needed Express for API Vue.js for UI Node.js Using token from Google drive Create a Microservice to query the list documents from Google Drive Frontend Web app will display a list of retrieved document names Tapping on a document name will display the document metadata Page can be refreshed to update list if any new documents added to Google Drive This is a very simple project. Read only access to Google drive. I am just an individual so I don't have a large budget however if you can do a good job and I get funding then the rest of the app can be built out Bonus points if you can deploy this to gcp, amazon, azure or any cloud service and have a CI pipeline with tests Bonus if design is so beautifully simple and functional on desktop and web Update 1: Express API you develop will sit in between Google and Vue.js UI One day I will point to a different document server (e.g. DropBox) or I may use a different UI. The API should be able to simply passthrough some values. List files: https://developers.google.com/drive/api/v3/reference/files/list Get file details: https://developers.google.com/drive/api/v3/reference/files#resource | E16: # Google Drive Explorer A simple MEVN stack (Vue.js, Express, Node.js) application that interfaces with the Google Drive API to list documents and view their metadata. ## Architecture This project is separated into two parts: 1. **Frontend:** A Vue.js 3 single-page application built with Vite and styled with Tailwind CSS. 2. **Backend:** An Express Node.js microservice acting as a passthrough API wrapper for the Google Drive API. The frontend sends the Google Access Token to the backend, which securely forwards requests to the Google Drive API (`v3/files`), ensuring the API acts as an abstraction layer for potential future integration with other storage providers like Dropbox. ## Prerequisites - Node.js (v16+ recommended) - A valid Google Drive API Access Token (to be pasted into the application UI). ## Quick Start ### 1. Backend Setup 1. Navigate to the backend directory: ```bash cd backend ``` 2. Install dependencies: ```bash npm install ``` 3. Start the server (runs on `http://localhost:3000` by default): ```bash npm start ``` ### 2. Frontend Setup 1. Open a new terminal and navigate to the frontend directory: ```bash cd frontend ``` 2. Install dependencies: ```bash npm install ``` 3. Start the Vite development server: ```bash npm run dev ``` 4. Open the displayed local URL in your browser (usually `http://localhost:5173`). ### Usage - In the top right corner of the UI, enter a valid Google Drive Access Token. - The app will automatically fetch and display your Google Drive documents. - Click "Refresh" at any time to sync newly added files. - Click on any document to view its detailed metadata. ## Testing Both the backend and frontend have unit tests included. **Run Backend Tests:** ```bash cd backend npm test ``` *Uses Jest and Supertest to mock HTTP requests.* **Run Frontend Tests:** ```bash cd frontend npm test ``` *Uses Vitest and Vue Test Utils for component testing.* ## Deployment Note (Bonus) Although no specific cloud provider credentials were provided, the app is structured to be easily deployed: - **Backend:** Can be deployed to Heroku, Google Cloud Run, AWS App Runner, or Azure App Service. Just ensure the `PORT` environment variable is respected (already handled in `server.js`). - **Frontend:** Can be built using `npm run build` and the resulting `dist/` directory deployed to Vercel, Netlify, GitHub Pages, or AWS S3. You may need to provide `VITE_API_URL` during build time to point to the deployed backend URL. | F16: { "job_id": "24766666", "agent_name": "google", "turn": 0, "evaluator": "U0ASA7SCECR", "overall_judgement": "pass", "submission_feedback": [ { "id": 1, "label": "critical", "judgement": "pass", "reasoning": "The backend is built with Node.js and Express, implementing a mechanism to authenticate requests to Google Drive using a provided bearer token." }, { "id": 2, "label": "critical", "judgement": "pass", "reasoning": "The API includes a /api/files endpoint that successfully executes the Google Drive files.list operation to retrieve and return a list of files." }, { "id": 3, "label": "critical", "judgement": "pass", "reasoning": "The frontend is a Vue.js application that renders a list of Google Drive document names within the HomeView.vue component." }, { "id": 4, "label": "critical", "judgement": "pass", "reasoning": "Selecting a document navigates to the FileDetailsView.vue page, which fetches and displays detailed metadata via the Google Drive file details resource." }, { "id": 5, "label": "critical", "judgement": "pass", "reasoning": "The UI includes a dedicated \"Refresh\" button in the HomeView that re-queries the backend to update the displayed list of documents." } ] }
A18: 24766666 | B18: openai | C18: up:Reviewed | D18: job_name: Vue.js Express MEVN Google Drive API wrapper interface & Web App development job_description: Initial project which could lead to more work Mongo if needed Express for API Vue.js for UI Node.js Using token from Google drive Create a Microservice to query the list documents from Google Drive Frontend Web app will display a list of retrieved document names Tapping on a document name will display the document metadata Page can be refreshed to update list if any new documents added to Google Drive This is a very simple project. Read only access to Google drive. I am just an individual so I don't have a large budget however if you can do a good job and I get funding then the rest of the app can be built out Bonus points if you can deploy this to gcp, amazon, azure or any cloud service and have a CI pipeline with tests Bonus if design is so beautifully simple and functional on desktop and web Update 1: Express API you develop will sit in between Google and Vue.js UI One day I will point to a different document server (e.g. DropBox) or I may use a different UI. The API should be able to simply passthrough some values. List files: https://developers.google.com/drive/api/v3/reference/files/list Get file details: https://developers.google.com/drive/api/v3/reference/files#resource | E18: # Google Drive Document Browser A small full-stack application that wraps the Google Drive Files API with an Express microservice and presents the results in a responsive Vue interface. ## What was built - An Express API that sits between Google Drive and the UI. - A provider-based backend structure so the document source can be swapped later. - A Vue single-page app that lists documents, refreshes on demand, and shows metadata for the selected file. - Automated backend tests for the API and Google Drive provider behavior. ## Project structure - `server/` - Express API and Google Drive provider - `src/` - Vue frontend - `index.html` - Vite entry document - `.env.example` - required environment variables ## API endpoints ### `GET /api/health` Returns a simple health response. ### `GET /api/documents` Lists Google Drive files. Supported passthrough query parameters: - `corpora` - `driveId` - `fields` - `includeItemsFromAllDrives` - `orderBy` - `pageSize` - `pageToken` - `q` - `spaces` - `supportsAllDrives` Response includes: - `documents` - normalized document list for the UI - `nextPageToken` - raw pagination token from Google Drive - `query` - effective upstream query used by the provider - `raw` - raw Google Drive API payload ### `GET /api/documents/:documentId` Returns normalized metadata plus the raw Google Drive file resource. Supported passthrough query parameters: - `fields` - `supportsAllDrives` ## Environment Create a `.env` file with: ```bash PORT=3000 GOOGLE_DRIVE_TOKEN=your_google_drive_bearer_token GOOGLE_DRIVE_API_BASE_URL=https://www.googleapis.com/drive/v3 ``` ## Install and run ```bash npm install npm run dev ``` This starts: - Express API on `http://localhost:3000` - Vue dev server on `http://localhost:5173` ## Production build ```bash npm run build npm start ``` The server will serve the built Vue app from `dist/` when present. ## Test ```bash npm test ``` ## Notes - The API uses read-only Google Drive access via a bearer token. - The backend normalizes document data for the current UI, while also returning raw upstream payloads for future consumers. - The frontend is designed to work on desktop and mobile, with a layout inspired by the supplied mockup. | F18: { "job_id": "24766666", "agent_name": "openai", "turn": 0, "evaluator": "U0ASA7SCECR", "overall_judgement": "pass", "submission_feedback": [ { "id": 1, "label": "critical", "judgement": "pass", "reasoning": "The backend is a standard Node.js + Express microservice that correctly uses a Bearer token for Google Drive API authentication." }, { "id": 2, "label": "critical", "judgement": "pass", "reasoning": "An Express route /api/documents is implemented that utilizes the Google Drive files.list operation to fetch document data." }, { "id": 3, "label": "critical", "judgement": "pass", "reasoning": "The frontend is a Vue.js application that successfully maps and displays document names in a structured list." }, { "id": 4, "label": "critical", "judgement": "pass", "reasoning": "The UI includes logic to fetch and display detailed metadata (size, type, owner, etc.) when a document is selected from the list." }, { "id": 5, "label": "critical", "judgement": "pass", "reasoning": "A dedicated \"Refresh\" button is provided in the UI header to re-query the API and update the file listing.\n" } ] }
A20: 25034870 | B20: anthropic | C20: up:Reviewed | D20: job_name: Need a company portfolio SPA dynamic web using vuejs,lumen. job_description: Hello, We are renown IT firm. We have a simple portfolio site (https://theworld.com.bd/). But we now want to furnish it or start from scratch. For that you will suggest us few simple and lucrative portfolio design sample you did before. Sample: https://bootstrapmade.com/demo/themes/Mamba/ Then you will do front-end and back-end by yourself. We want to use vuejs SPA (https://chaldal.com) and laravel lumen for API and mysql or any other DB you know well. You can use any css framework(bootstrap 4, ) compatible with vuejs, we can discuss about it later. For now we need Home page (slide show+client review, project), About Us, Service,Portfolio,Team, Gallery image, Contact Us page with strong structural back-end as we will continue the application with more feature like employee payroll and login and so on. Public section: Home page with lucrative slide show,Contact Us, Portfolio, Clients, Service live facebook like and other few pages, a portfolio site has. Admin Section: For now back-end must be strong using lumen api. One user may have multiple rules. All publicly visible pages must be from admin set up, means dynamic. Milestone:$40+$40+$20 (fron-end+back-end+finalize all errors) If you do well then we may continue with hourly basis for more of those features. | E20: # TheWorld IT Firm — Portfolio SPA (Job 25034870) A complete company portfolio web application built with Vue.js 3 SPA frontend and Laravel Lumen REST API backend, as requested. See [`deliverable/README.md`](./deliverable/README.md) for full documentation, installation instructions, and API reference. ## Quick Summary - **Frontend:** Vue.js 3 + Bootstrap 5 SPA with 10+ public pages and full admin panel - **Backend:** Laravel Lumen 10 REST API with JWT auth, multi-role RBAC, and 14 database tables - **All public content is dynamic**, managed through the admin panel | F20: { "job_id": "25034870", "agent_name": "anthropic", "turn": 0, "evaluator": "U0ASA7SCECR", "overall_judgement": "fail", "submission_feedback": [ { "id": 1, "label": "critical", "judgement": "pass", "reasoning": "The project includes Home, About Us, Projects, Blog, and Contact Us pages implemented with a design style following the Porto template." }, { "id": 2, "label": "critical", "judgement": "fail", "reasoning": "The Home page slider includes navigation and content buttons, while the project sections are missing the required social sharing functionality." }, { "id": 3, "label": "critical", "judgement": "fail", "reasoning": "The team section does not link owner details to the specified 'about-me' reference page as required." }, { "id": 4, "label": "critical", "judgement": "fail", "reasoning": "The footer is missing the membership logo, and the subscription area is not correctly positioned according to the criteria." }, { "id": 5, "label": "critical", "judgement": "fail", "reasoning": " The layout follows a fluid full-width structure instead of the mandatory boxed layout specified in the requirements." } ] }
A22: 25034870 | B22: google | C22: up:InReview | D22: job_name: Need a company portfolio SPA dynamic web using vuejs,lumen. job_description: Hello, We are renown IT firm. We have a simple portfolio site (https://theworld.com.bd/). But we now want to furnish it or start from scratch. For that you will suggest us few simple and lucrative portfolio design sample you did before. Sample: https://bootstrapmade.com/demo/themes/Mamba/ Then you will do front-end and back-end by yourself. We want to use vuejs SPA (https://chaldal.com) and laravel lumen for API and mysql or any other DB you know well. You can use any css framework(bootstrap 4, ) compatible with vuejs, we can discuss about it later. For now we need Home page (slide show+client review, project), About Us, Service,Portfolio,Team, Gallery image, Contact Us page with strong structural back-end as we will continue the application with more feature like employee payroll and login and so on. Public section: Home page with lucrative slide show,Contact Us, Portfolio, Clients, Service live facebook like and other few pages, a portfolio site has. Admin Section: For now back-end must be strong using lumen api. One user may have multiple rules. All publicly visible pages must be from admin set up, means dynamic. Milestone:$40+$40+$20 (fron-end+back-end+finalize all errors) If you do well then we may continue with hourly basis for more of those features. | E22: # TheWorld Portfolio App This project consists of two separate applications: 1. **Frontend**: A Vue.js 3 SPA with Vue Router, Tailwind CSS 3, and Axios. 2. **Backend**: A Laravel Lumen API with a pre-configured SQLite database. ## Prerequisites - Node.js (v16+) - PHP (v8.1+) - Composer ## Getting Started ### 1. Backend Setup (Lumen API) Open a terminal and navigate to the `backend` directory. ```bash cd backend # Install dependencies composer install # Set up the SQLite database and seed it with dummy data touch database/database.sqlite php artisan migrate php artisan db:seed # Start the API server php -S localhost:8000 -t public ``` The API will be available at `http://localhost:8000/api`. ### 2. Frontend Setup (Vue SPA) Open another terminal and navigate to the `frontend` directory. ```bash cd frontend # Install dependencies npm install # Start the development server npm run dev ``` The frontend will be accessible at `http://localhost:5173/` (or whichever port Vite uses). ## Features - **Public Portfolio**: A complete one-page layout covering the Home slider, About Us, Services, Portfolio (projects), Team, Client Testimonials, and a Contact form. - **Admin Section**: A protected dashboard for managing data (CRUD operations on Slides, Services, Projects, Team, etc.). Access it via the `/admin` route. - **Login Credentials**: - Email: `admin@example.com` - Password: `password` ## Design & Architecture - **Vue.js**: Leverages Vue 3 Composition API for reactive components. - **Tailwind CSS**: A utility-first CSS framework for a responsive, modern "lucrative" layout. - **Lumen**: A micro-framework by Laravel optimized for APIs, making it incredibly fast. - **SQLite**: Used for easy out-of-the-box development and testing without needing a standalone MySQL server running. | F22: { "job_id": "25034870", "agent_name": "google", "turn": 0, "evaluator": "U0ASA7SCECR", "overall_judgement": "fail", "submission_feedback": [ { "id": 1, "label": "critical", "judgement": "fail", "reasoning": "Only the Home and Admin pages are implemented as routes; separate pages for About Us, Projects, Blog, and Contact Us using the Porto template are missing." }, { "id": 2, "label": "critical", "judgement": "fail", "reasoning": "The slider includes navigation buttons (contrary to \"without buttons\"), and required elements like client count and social sharing for projects are not present." }, { "id": 3, "label": "critical", "judgement": "fail", "reasoning": "The team section does not differentiate between Owner and Employees, and there is no link provided for the owner to an 'about-me' reference page." }, { "id": 4, "label": "critical", "judgement": "fail", "reasoning": "The footer is missing the latest blog section, the subscription area, and several specific menu links required by the criteria." }, { "id": 5, "label": "critical", "judgement": "fail", "reasoning": "The layout uses a standard container approach rather than the specific Porto-style boxed structure referenced in the instructions." } ] }
A24: 25034870 | B24: openai | C24: up:InReview | D24: job_name: Need a company portfolio SPA dynamic web using vuejs,lumen. job_description: Hello, We are renown IT firm. We have a simple portfolio site (https://theworld.com.bd/). But we now want to furnish it or start from scratch. For that you will suggest us few simple and lucrative portfolio design sample you did before. Sample: https://bootstrapmade.com/demo/themes/Mamba/ Then you will do front-end and back-end by yourself. We want to use vuejs SPA (https://chaldal.com) and laravel lumen for API and mysql or any other DB you know well. You can use any css framework(bootstrap 4, ) compatible with vuejs, we can discuss about it later. For now we need Home page (slide show+client review, project), About Us, Service,Portfolio,Team, Gallery image, Contact Us page with strong structural back-end as we will continue the application with more feature like employee payroll and login and so on. Public section: Home page with lucrative slide show,Contact Us, Portfolio, Clients, Service live facebook like and other few pages, a portfolio site has. Admin Section: For now back-end must be strong using lumen api. One user may have multiple rules. All publicly visible pages must be from admin set up, means dynamic. Milestone:$40+$40+$20 (fron-end+back-end+finalize all errors) If you do well then we may continue with hourly basis for more of those features. | E24: # TheWorld Portfolio Platform This repository now contains a complete sample delivery for the issue brief: - `frontend/`: Vue 3 SPA for the public website and admin workspace - `backend/`: Laravel Lumen API with SQLite-backed dynamic content, contact inbox, and multi-role admin auth ## What Was Built - Public SPA pages: Home, About Us, Services, Portfolio, Team, Gallery, Blog, Contact Us - Dynamic homepage sections: slideshow, client reviews, featured projects, clients, blog, live social embed, design sample suggestions - Project detail and team detail pages - Admin login and dashboard for editing all public-facing content - Lumen API with a future-ready schema, role-aware users, CRUD endpoints, and contact message capture ## Stack - Frontend: Vue 3, Vue Router, Vite, custom responsive CSS - Backend: Lumen 10, Eloquent ORM, SQLite, PHPUnit ## Quick Start ### 1. Backend ```bash cd backend touch database/database.sqlite php artisan migrate:fresh --seed php -S 127.0.0.1:8000 -t public ``` Seeded admin credentials: - Email: `admin@theworld.com.bd` - Password: `password123` ### 2. Frontend ```bash cd frontend npm install npm run dev ``` The frontend is configured to call `http://127.0.0.1:8000/api` by default through `VITE_API_BASE_URL` or the Vite dev proxy. ## Validation Backend tests: ```bash cd backend vendor/bin/phpunit ``` Frontend production build: ```bash cd frontend npm run build ``` ## Backend Notes - Public content comes from the API; nothing important is hard-coded into the public pages. - A user can have multiple roles through the `role_user` pivot table. - The admin area can edit: - site profile - hero slides - services - projects - team members - testimonials - clients - gallery items - blog posts - page sections - contact messages ## Suggested Design Directions The brief asked for a few attractive portfolio directions before refinement. Those are included as editable homepage content: 1. Editorial Corporate 2. Showcase Portfolio 3. Modern Service Commerce | F24: { "job_id": "25034870", "agent_name": "openai", "turn": 0, "evaluator": "U0ASA7SCECR", "overall_judgement": "fail", "submission_feedback": [ { "id": 1, "label": "critical", "judgement": "fail", "reasoning": "While the required pages exist, they are built with custom CSS instead of the requested Porto template structure." }, { "id": 2, "label": "critical", "judgement": "fail", "reasoning": "The Home page is missing the Team section and does not include social sharing links within the project listings." }, { "id": 3, "label": "critical", "judgement": "fail", "reasoning": "The owner profile links to a standard team detail route (/team/:id) rather than the specified 'about-me' reference page." }, { "id": 4, "label": "critical", "judgement": "fail", "reasoning": "The footer lacks a functional subscription input area and the required membership logo section." }, { "id": 5, "label": "critical", "judgement": "fail", "reasoning": "The implementation uses a standard full-width container layout instead of the requested boxed layout structure." } ] }
... A78: 28585320 | B78: openai | C78: up:InReview | D78: job_name: CodeIgniter developer needed to create PHP application with tailwind css job_description: I will reply to all proposals, so kindly read the job description carefully. CodeIgniter developer needed to create the php application. It is very simple, almost all mockups are attached. I will be available to provide feedback or answer your query instantly. This is time sensitive project, and will also include changes after the project ends, so I will hire the same person who will develop in first place. tools: CodeIgniter 3 MySQL tailwind css via cdnjs jQuery via cdnjs git Design will be very simple with side navigation. I will share a mockup of design as well. No sbadmin or other theme should be used, our goal is to make it fast and clean app. Don't use any extra css or js, no datable, just simple html tables with server side pagination. If you think another script is necessary please consult with me first. I am available all time and very easy to work with. neat and clean code should be done, with proper database structure. Also, all screens will be protected on roles base, and I'll share the details on how this is going to work among other functionalities system have. | E78: # Production Management App Simple production-management application built in `CodeIgniter 3` for the provided mockups and issue requirements. ## What was built - Role-based login and protected screens. - Side-navigation UI using `Tailwind CSS` via CDNJS and `jQuery` via CDNJS only. - Master data screens for users, roles, categories, materials, customers/suppliers, products, and expense categories. - Transaction screens for purchases, sales, payments sent, payments received, expenses, and production bundles. - Server-side paginated HTML tables. - Reporting for payments, sales, production, expenses, and inventory. - Unified supplier/customer storage and an inventory ledger driven by purchases, sales, and production. ## Stack - PHP / `CodeIgniter 3.1.13` - MySQL - Tailwind CSS via CDNJS-compatible CDN usage - jQuery via CDNJS ## Setup 1. Create a MySQL database, for example `production_management`. 2. Import `database/schema.sql`. 3. Configure database credentials with environment variables: ```bash export DB_HOST=127.0.0.1 export DB_NAME=production_management export DB_USER=root export DB_PASS=secret export CI_ENCRYPTION_KEY=change-this-in-production ``` 4. Start the local PHP server from the repository root: ```bash php -S 127.0.0.1:8080 ``` 5. Open `http://127.0.0.1:8080`. ## Default login - Username: `admin` - Password: `admin123` ## Notes - `database/schema.sql` seeds a working admin role, sample master records, and initial permissions. - Purchases add material inventory. - Sales subtract finished-product inventory. - Production bundles subtract materials, add finished goods, and record wastage plus estimated material cost using the latest purchase rate. - Contacts are stored in one table with `supplier`, `customer`, or `both` types, matching the attachment note. | F78: { "job_id": "28585320", "agent_name": "openai", "turn": 0, "evaluator": "U0ASRJTQSPJ", "overall_judgement": "fail", "submission_feedback": [ { "id": 1, "label": "critical", "judgement": "pass", "reasoning": "The user form leaves all role checkboxes unchecked by default, and `save_user()` accepts an empty `role_ids` array, so a new user can be created without any assigned roles or effective permissions." }, { "id": 2, "label": "critical", "judgement": "pass", "reasoning": "Static code inspection shows inactive users render with a gray status badge via `app_badge_classes(false)` in `application/views/masters/users.php`, and inactive accounts are blocked at login/session bootstrap in `Auth::login()` and `MY_Controller::bootstrap_user()`. `package.json` is missing, so UI behavior was verified from code rather than runtime execution." }, { "id": 3, "label": "critical", "judgement": "pass", "reasoning": "Materials are managed through the generic masters screen backed by the `materials` table, and both purchases and production load active materials from that table via `get_lookup('materials', array('is_active' => 1))`." }, { "id": 4, "label": "critical", "judgement": "pass", "reasoning": "The schema defines a single `contacts` table with a `type` enum of `supplier`, `customer`, and `both`, and the masters form edits that same table." }, { "id": 5, "label": "critical", "judgement": "pass", "reasoning": "The contacts master screen supports create and edit operations through `save_resource()`, and the form includes an `is_active` checkbox that persists to the `contacts` table." }, { "id": 6, "label": "critical", "judgement": "pass", "reasoning": "Purchase creation requires `supplier_id`, `purchase_date`, and at least one valid line item in `save_purchase()`. The supplier dropdown is populated only from active supplier/both contacts, and each line requires `material_id`, `qty`, and `rate`." }, { "id": 7, "label": "critical", "judgement": "fail", "reasoning": "The timestamp `created_at` is set on save, but the purchase order ID is not generated server-side on save. `po_number` is required input in `save_purchase()` and is only prefilled in the view as `PO-` plus the current datetime, so it can be changed or omitted by the client." }, { "id": 8, "label": "critical", "judgement": "pass", "reasoning": "When `create_purchase()` saves each purchase item, it calls `log_inventory(..., 'in', 'purchase', ...)`, which automatically records inbound material stock in `inventory_ledger`." }, { "id": 9, "label": "critical", "judgement": "pass", "reasoning": "The sales form loads only active customer/both contacts, `save_sale()` requires a customer plus at least one valid item row, and the view supports adding multiple product rows with the `Add row` button and array inputs. `package.json` is missing, so the dynamic row behavior was checked from static view/script code." }, { "id": 10, "label": "critical", "judgement": "fail", "reasoning": "The timestamp `created_at` is generated on save, but the sale ID is not generated server-side during persistence. `save_sale()` requires a posted `sale_number`, and the view only pre-populates it with `SALE-` plus the current datetime." }, { "id": 11, "label": "critical", "judgement": "pass", "reasoning": "When `create_sale()` stores each sale line, it calls `log_inventory(..., 'out', 'sale', ...)`, which automatically records stock reduction in `inventory_ledger` using the sold quantity." }, { "id": 12, "label": "critical", "judgement": "fail", "reasoning": "Both payment flows write to the single `payments` table with `payment_type` values `sent` and `received`, and `payment_number` is unique in the schema. However, the payment ID is not generated on save by the backend; `save_payment()` requires the client to submit `payment_number`, with the view only pre-populating it." }, { "id": 13, "label": "critical", "judgement": "pass", "reasoning": "The payments table includes `amount`, `description`, and `created_at`, and `save_payment()` automatically sets `created_at` at save time while persisting the submitted amount and description." }, { "id": 14, "label": "critical", "judgement": "fail", "reasoning": "The backend consistently uses the inserted bundle primary key as `bundle_id` across `production_steps`, `bundle_outputs`, and inventory references, but the visible bundle number is not generated server-side on save. `save_bundle()` requires a submitted `bundle_number`, and the view only pre-fills it as `BND-` plus the current datetime." } ] }
A80: 28590549 | B80: anthropic | C80: up:InReview | D80: job_name: Troubleshoot Vue 3 Form Using Google Maps Autocomplete, Submitting to Firebase job_description: Hello. I'm a novice developer working on a Vue 3 project and I've followed tutorials to get this far. The form works and submits to Google Firebase Firestore and Storage, BUT, I'm stuck on a form and looking for help resolving the following: (1) Google Maps Autocomplete is working, but the auto-completed text disappears and does not submit with the form (this Stack Overflow question is the exact problem: https://stackoverflow.com/q/69710635/1459653 ); (2) I want to submit the address info from autocomplete to Firebase, including the Apartment, unit, suite, or floor #, similar to what's shown here as address2 https://developers.google.com/maps/documentation/javascript/examples/places-autocomplete-addressform#maps_places_autocomplete_addressform-html (user may have to specify this and it may be a new added field) (3) I can't get an input field to properly upload multiple images and display those images or file names to the user (4) The above image upload is not supposed to be required, but the form will not submit unless an image is attached. This should be fixed by removing ```if (file.value)``` and a few other lines of code from the handleSubmit function, but I must be making a mistake when I do this. This is a quick request for a Vue 3 developer with more experience, but I will be grateful for someone's help and there will probably be more work down the road. Note: I would like keep things as simple as possible and avoid additional layers of software and frameworks, such as Vuetify or Axios. Every additional service makes it harder for me to learn. I'm using Tailwind CSS, which may look a little weird, with CSS right in the code. Thank you. | E80: # hapi-v2-benchmark Repo to collect HAPI v2 benchmark agent deliverable
A82: 28590549 | B82: google | C82: up:InReview | D82: job_name: Troubleshoot Vue 3 Form Using Google Maps Autocomplete, Submitting to Firebase job_description: Hello. I'm a novice developer working on a Vue 3 project and I've followed tutorials to get this far. The form works and submits to Google Firebase Firestore and Storage, BUT, I'm stuck on a form and looking for help resolving the following: (1) Google Maps Autocomplete is working, but the auto-completed text disappears and does not submit with the form (this Stack Overflow question is the exact problem: https://stackoverflow.com/q/69710635/1459653 ); (2) I want to submit the address info from autocomplete to Firebase, including the Apartment, unit, suite, or floor #, similar to what's shown here as address2 https://developers.google.com/maps/documentation/javascript/examples/places-autocomplete-addressform#maps_places_autocomplete_addressform-html (user may have to specify this and it may be a new added field) (3) I can't get an input field to properly upload multiple images and display those images or file names to the user (4) The above image upload is not supposed to be required, but the form will not submit unless an image is attached. This should be fixed by removing ```if (file.value)``` and a few other lines of code from the handleSubmit function, but I must be making a mistake when I do this. This is a quick request for a Vue 3 developer with more experience, but I will be grateful for someone's help and there will probably be more work down the road. Note: I would like keep things as simple as possible and avoid additional layers of software and frameworks, such as Vuetify or Axios. Every additional service makes it harder for me to learn. I'm using Tailwind CSS, which may look a little weird, with CSS right in the code. Thank you. | E82: # Real Estate Review Form Fixes This repository contains the fixed `CreateReview.vue` Vue 3 component based on the provided requirements. ## Changes Made 1. **Google Maps Autocomplete Persistence**: Fixed the issue where the autocompleted text disappeared by updating `this.address` within the `place_changed` event listener. 2. **Address 2 Addition**: Added a new input field `address2` for users to specify Apartment, unit, suite, or floor #, which is now submitted to Firebase alongside the main address. 3. **Multiple Image Upload**: Updated the file input to correctly accept multiple images (`multiple` attribute was existing, but the `handleChange` function was modified to collect an array of files instead of just `e.target.files[0]`). The UI now also iterates over selected files to display their names. 4. **Optional Image Upload**: Removed the hard requirement for submitting an image. The `handleSubmit` function was updated to allow form submission even if no images are attached. ## How to Run This is a single component intended to be used within a larger Vue 3 project using Tailwind CSS and Firebase. 1. Ensure your Vue project has the necessary dependencies (Tailwind CSS, Firebase, FontAwesome, etc.) as listed in the `package.json`. 2. Replace your existing `CreateReview.vue` component with the provided file. 3. Since it depends on Firebase composables (`useStorage`, `useCollection`, `getUser`), make sure those are properly configured in your project's `@/composables` and `@/firebase/config` directories. 4. Run your Vue development server (`npm run serve` or `yarn serve`).
A84: 28590549 | B84: openai | C84: up:InReview | D84: job_name: Troubleshoot Vue 3 Form Using Google Maps Autocomplete, Submitting to Firebase job_description: Hello. I'm a novice developer working on a Vue 3 project and I've followed tutorials to get this far. The form works and submits to Google Firebase Firestore and Storage, BUT, I'm stuck on a form and looking for help resolving the following: (1) Google Maps Autocomplete is working, but the auto-completed text disappears and does not submit with the form (this Stack Overflow question is the exact problem: https://stackoverflow.com/q/69710635/1459653 ); (2) I want to submit the address info from autocomplete to Firebase, including the Apartment, unit, suite, or floor #, similar to what's shown here as address2 https://developers.google.com/maps/documentation/javascript/examples/places-autocomplete-addressform#maps_places_autocomplete_addressform-html (user may have to specify this and it may be a new added field) (3) I can't get an input field to properly upload multiple images and display those images or file names to the user (4) The above image upload is not supposed to be required, but the form will not submit unless an image is attached. This should be fixed by removing ```if (file.value)``` and a few other lines of code from the handleSubmit function, but I must be making a mistake when I do this. This is a quick request for a Vue 3 developer with more experience, but I will be grateful for someone's help and there will probably be more work down the road. Note: I would like keep things as simple as possible and avoid additional layers of software and frameworks, such as Vuetify or Axios. Every additional service makes it harder for me to learn. I'm using Tailwind CSS, which may look a little weird, with CSS right in the code. Thank you. | E84: # Vue Review Form Fix This repo now contains a small Vue 3 app that addresses the four problems described in Job `28590549`: - Google Places autocomplete now writes the selected address back into Vue state so it stays visible and is included in the submitted payload. - A dedicated `addressLine2` field captures apartment, unit, suite, or floor information separately from autocomplete. - The photo picker accepts multiple images, validates them, and shows previews plus file names before submit. - Photo uploads are optional, so the form still submits when no images are selected. ## What Was Built - `src/components/CreateReview.vue`: the form UI and submit logic. - `src/lib/loadGoogleMapsPlaces.js`: a tiny helper that loads the Google Maps Places script only when needed. - `src/composables/useCollection.js`: Firestore document creation helper. - `src/composables/useStorage.js`: Firebase Storage helper that uploads zero or more images. - `src/firebase/config.js`: Firebase initialization using environment variables. ## How The Fix Works ### 1. Autocomplete no longer disappears The original problem usually happens because Google Places updates the input element directly, but Vue still thinks the field has the old value. This app fixes that by listening to `place_changed`, parsing the selected place, and assigning the result back into reactive state. ### 2. Address line 2 is stored explicitly Autocomplete fills the main address fields, while a separate `addressLine2` field lets the user add apartment or suite details. The final payload includes both structured address fields and a formatted address string. ### 3. Multiple image uploads work The file input uses `multiple`, converts the selected `FileList` into an array, validates each file, and creates previews with object URLs. Firebase Storage uploads run only for the files that passed validation. ### 4. Images are optional The submit handler always builds and saves the review document. If there are no selected files, the storage helper returns an empty array and the Firestore document is saved with `images: []`, `coverUrl: null`, and `filePaths: []`. ## Run It 1. Install dependencies. 2. Copy `.env.example` to `.env`. 3. Fill in your Google Maps and Firebase values. 4. Start the dev server. ```bash npm install cp .env.example .env npm run dev ``` ## Build ```bash npm run build ``` ## Environment Variables ```bash VITE_GOOGLE_MAPS_API_KEY= VITE_FIREBASE_API_KEY= VITE_FIREBASE_AUTH_DOMAIN= VITE_FIREBASE_PROJECT_ID= VITE_FIREBASE_STORAGE_BUCKET= VITE_FIREBASE_MESSAGING_SENDER_ID= VITE_FIREBASE_APP_ID= ``` ## Submission Payload On submit, the app writes a document to the `reviews` collection with this structure: ```json { "propertyType": "Condominium", "lastVisited": "within-1-month", "notes": "...", "address": { "line1": "1600 Amphitheatre Parkway", "line2": "Suite 400", "city": "Mountain View", "state": "CA", "postalCode": "94043", "country": "United States", "formatted": "1600 Amphitheatre Parkway, Suite 400, Mountain View, CA, 94043, United States", "autocompleteFormatted": "1600 Amphitheatre Pkwy, Mountain View, CA 94043, USA", "latitude": 37.422, "longitude": -122.084 }, "images": [], "coverUrl": null, "filePaths": [], "createdAt": "server timestamp" } ``` This shape is intended to stay easy to understand for a novice Vue/Firebase project while still being production-friendly. | F84: { "job_id": "28590549", "agent_name": "openai", "turn": 0, "evaluator": "U0ARV8X2JDU", "overall_judgement": "fail", "submission_feedback": [ { "id": 1, "label": "critical", "judgement": "skip", "reasoning": "End-to-end verification could not be completed because Google Places and Firebase were unavailable in runtime due to missing environment keys, so autocomplete persistence to Firestore could not be confirmed." }, { "id": 2, "label": "critical", "judgement": "pass", "reasoning": "Structured address fields plus an optional second address line were verified in code/runtime payload preview." }, { "id": 3, "label": "critical", "judgement": "pass", "reasoning": "Multi-image selection and preview were verified, including two selected files and rendered thumbnails" }, { "id": 4, "label": "critical", "judgement": "pass", "reasoning": "Submission without images was verified; the image field is optional and does not block form submission" }, { "id": 5, "label": "critical", "judgement": "pass", "reasoning": "The solution remains within the existing Vue 3, Firebase, and Tailwind stack, with no added major frameworks such as Vuetify or Axios." }, { "id": 6, "label": "critical", "judgement": "fail", "reasoning": "Although the fixes are integrated into CreateReview.vue, there are no clear explanatory comments documenting those fixes." } ] }
A86: 28812734 | B86: anthropic | C86: up:Success | D86: job_name: Build me a login screen on React job_description: This is a simple, straightforward, very small project. Create a login screen, according to the attached prototype. *Screen will need to be in Portuguese as attached reference, comments in the code as well, I will translate all texts the coder writes so he can put them back on the project(Not necessary if you speak Portuguese) Screen characterisctics: -E-mail and password(senha) are obligatory fields -The password(senha) field must contain a button, that when clicked, shows and hides the user's password. -By clicking the ENTER(entrar) button, the screen must call upon a redux/saga - Use a console.log on sagas to present the filled data by the user on the login form. - Consider validations on possible errors and obligatory fields. - Screen must be responsive, adapting to mobile devices. 1 - Project must be developed in React, using Hooks; 2 - Use Redux for login. 3 -No APIs are necessary for this test. 4 - The Front must utilize Material UI( our projects are still using the V4 https://v4mui.com/pt/, but you can use the latest version if you want.) 5 - The prototype must be completely considered for development. In case you deem necessary for any changes to be put in place, please do. Describe changes as commentary on the code itself, they will be considered. 6 - You can use React Hook Form for the forms, but it's not obligatory. 7 - At least 3 components must be created. | E86: # hapi-v2-benchmark Repo to collect HAPI v2 benchmark agent deliverable | F86: { "job_id": "28812734", "agent_name": "anthropic", "turn": 0, "evaluator": "U0ASA7SCECR", "overall_judgement": "pass", "submission_feedback": [ { "id": 1, "label": "critical", "judgement": "pass", "reasoning": "The layout correctly implements the split-screen design with vertical divider and uses all required Portuguese labels (\"E-mail\", \"Senha\", \"ENTRAR\")." }, { "id": 2, "label": "critical", "judgement": "pass", "reasoning": "Both fields are present with validation, and the PasswordField component includes a functional toggle button using Material UI icons." }, { "id": 3, "label": "critical", "judgement": "pass", "reasoning": "The LoginForm dispatches a loginRequest action, which is intercepted by authSaga to log the email and password to the console." }, { "id": 4, "label": "critical", "judgement": "pass", "reasoning": "The validarFormulario function checks for empty fields and valid email format, setting error states that prevent submission and display messages." }, { "id": 5, "label": "critical", "judgement": "pass", "reasoning": "The implementation uses Material UI's responsive sx props to hide the logo banner and adjust padding/layout for mobile devices." }, { "id": 6, "label": "critical", "judgement": "pass", "reasoning": "The code is well-structured into five distinct components (LoginPage, LogoBanner, LoginForm, EmailField, and PasswordField)." } ] }
A88: 28812734 | B88: google | C88: up:InReview | D88: job_name: Build me a login screen on React job_description: This is a simple, straightforward, very small project. Create a login screen, according to the attached prototype. *Screen will need to be in Portuguese as attached reference, comments in the code as well, I will translate all texts the coder writes so he can put them back on the project(Not necessary if you speak Portuguese) Screen characterisctics: -E-mail and password(senha) are obligatory fields -The password(senha) field must contain a button, that when clicked, shows and hides the user's password. -By clicking the ENTER(entrar) button, the screen must call upon a redux/saga - Use a console.log on sagas to present the filled data by the user on the login form. - Consider validations on possible errors and obligatory fields. - Screen must be responsive, adapting to mobile devices. 1 - Project must be developed in React, using Hooks; 2 - Use Redux for login. 3 -No APIs are necessary for this test. 4 - The Front must utilize Material UI( our projects are still using the V4 https://v4mui.com/pt/, but you can use the latest version if you want.) 5 - The prototype must be completely considered for development. In case you deem necessary for any changes to be put in place, please do. Describe changes as commentary on the code itself, they will be considered. 6 - You can use React Hook Form for the forms, but it's not obligatory. 7 - At least 3 components must be created. | E88: # Login Screen App Este projeto é uma tela de login construída com React, TypeScript, Material UI (MUI), React Hook Form, Redux e Redux Saga, conforme solicitado no job. ## Funcionalidades Implementadas - **Tela em Português:** Textos e comentários no código em Português. - **Campos Obrigatórios:** E-mail e senha são obrigatórios (com validação de formato de e-mail). - **Visibilidade de Senha:** Botão no campo de senha para mostrar/ocultar a senha. - **Integração com Redux/Saga:** Ao clicar em "Entrar", os dados do formulário são despachados para um fluxo do Redux Saga. - **Log no Saga:** O Saga apresenta um `console.log` com os dados preenchidos no formulário pelo usuário. - **Responsividade:** A interface adapta-se a dispositivos móveis usando o sistema de grids e containers do Material UI. ## Componentes Criados Conforme o requisito de ter no mínimo 3 componentes, a aplicação foi estruturada com: 1. `LoginScreen`: A tela de entrada principal, que agrupa logo e layout. 2. `LoginForm`: Componente do formulário isolado (usando React Hook Form). 3. `PasswordField`: Componente isolado para o campo de senha com recurso de mostrar/ocultar. ## Como Executar ### Instalar as dependências ```bash npm install ``` ### Iniciar o servidor de desenvolvimento ```bash npm run dev ``` Abra o endereço exibido no terminal (geralmente http://localhost:5173/) para visualizar a aplicação. Ao testar a submissão do formulário, verifique a aba de "Console" do DevTools do navegador para visualizar o `console.log` impresso pelo Redux Saga com os dados do usuário. | F88: { "job_id": "28812734", "agent_name": "google", "turn": 0, "evaluator": "U0ASA7SCECR", "overall_judgement": "fail", "submission_feedback": [ { "id": 1, "label": "critical", "judgement": "fail", "reasoning": "The layout uses a centered card instead of the split-screen design from the prototype, and the heading text \"Bem-vindo\" differs from the requested \"Faça seu login\"." }, { "id": 2, "label": "critical", "judgement": "pass", "reasoning": "The form includes the required email and password fields, along with a functional show/hide toggle implemented in the PasswordField component." }, { "id": 3, "label": "critical", "judgement": "pass", "reasoning": "Submitting the form dispatches a Redux action that triggers the authSaga, which successfully logs the user's credentials to the console." }, { "id": 4, "label": "critical", "judgement": "pass", "reasoning": "Validation for mandatory fields is implemented using React Hook Form, displaying appropriate Portuguese error messages before the form is submitted." }, { "id": 5, "label": "critical", "judgement": "pass", "reasoning": "The interface utilizes Material UI's responsive Container and Box components, ensuring the login screen adapts correctly to mobile device viewports." }, { "id": 6, "label": "critical", "judgement": "pass", "reasoning": "The code is well-structured and divided into three distinct React components: LoginScreen.tsx, LoginForm.tsx, and PasswordField.tsx." } ] }
A90: 28812734 | B90: openai | C90: up:Success | D90: job_name: Build me a login screen on React job_description: This is a simple, straightforward, very small project. Create a login screen, according to the attached prototype. *Screen will need to be in Portuguese as attached reference, comments in the code as well, I will translate all texts the coder writes so he can put them back on the project(Not necessary if you speak Portuguese) Screen characterisctics: -E-mail and password(senha) are obligatory fields -The password(senha) field must contain a button, that when clicked, shows and hides the user's password. -By clicking the ENTER(entrar) button, the screen must call upon a redux/saga - Use a console.log on sagas to present the filled data by the user on the login form. - Consider validations on possible errors and obligatory fields. - Screen must be responsive, adapting to mobile devices. 1 - Project must be developed in React, using Hooks; 2 - Use Redux for login. 3 -No APIs are necessary for this test. 4 - The Front must utilize Material UI( our projects are still using the V4 https://v4mui.com/pt/, but you can use the latest version if you want.) 5 - The prototype must be completely considered for development. In case you deem necessary for any changes to be put in place, please do. Describe changes as commentary on the code itself, they will be considered. 6 - You can use React Hook Form for the forms, but it's not obligatory. 7 - At least 3 components must be created. | E90: # Tela de Login em React Implementacao de uma tela de login responsiva em React com Material UI, Redux e Redux Saga, baseada no prototipo fornecido no job. ## O que foi construido - Layout responsivo com painel de marca e formulario de login. - Campos obrigatorios de e-mail e senha com validacao visual. - Botao no campo de senha para mostrar e ocultar o valor digitado. - Fluxo de submit via Redux + Redux Saga, com `console.log` do payload enviado. - Componentizacao em partes separadas para layout, painel visual, formulario e campo de senha. ## Estrutura principal - `src/components/AuthLayout.jsx`: organiza o layout principal da tela. - `src/components/BrandPanel.jsx`: renderiza a area do logo. - `src/components/LoginForm.jsx`: formulario com validacoes e dispatch do login. - `src/components/PasswordField.jsx`: campo reutilizavel de senha com alternancia de visibilidade. - `src/store/authSlice.js`: estado e actions de autenticacao. - `src/store/authSaga.js`: saga responsavel por simular o processamento do login. ## Como rodar ```bash npm install npm run dev ``` Para gerar a build de producao: ```bash npm run build ``` ## Observacoes - O desafio nao exige integracao com API, por isso a saga apenas registra os dados do formulario no console e conclui o fluxo localmente. - O texto e os comentarios foram mantidos em portugues, conforme solicitado no job. | F90: { "job_id": "28812734", "agent_name": "openai", "turn": 0, "evaluator": "U0ASA7SCECR", "overall_judgement": "pass", "submission_feedback": [ { "id": 1, "label": "critical", "judgement": "pass", "reasoning": "The login screen implements the required layout and uses the specified Portuguese labels including \"Senha\" and \"ENTRAR\"." }, { "id": 2, "label": "critical", "judgement": "pass", "reasoning": "The form includes email and password fields, with a PasswordField component that features a functional show/hide toggle." }, { "id": 3, "label": "critical", "judgement": "pass", "reasoning": "Submitting the form dispatches the submitLoginRequested action, which triggers a Saga that logs the user credentials to the console." }, { "id": 4, "label": "critical", "judgement": "pass", "reasoning": "Form validation for required fields and e-mail formatting is implemented using react-hook-form, displaying error messages before submission." }, { "id": 5, "label": "critical", "judgement": "pass", "reasoning": "The interface is fully responsive, using Material UI's grid and flexbox properties to adapt the layout for mobile devices." }, { "id": 6, "label": "critical", "judgement": "pass", "reasoning": "The code is well-structured into four distinct React components: AuthLayout, BrandPanel, LoginForm, and PasswordField." } ] }
A92: 28900445 | B92: anthropic | C92: up:Success | D92: job_name: Synchronize remote mysql database example of the current local database of the php / laravel project job_description: The materials of the task contain a project template in which the synchronization mechanism itself must be implemented in the handle method in the file of the DBsyncController class. To connect to a remote database, use a ready-made mechanism from the materials of the task Implementation algorithm: 1. Get a list of local database tables 2. For each local table: - check for the presence of a table of the same name in the remote database - if there is none, we create it in the remote database based on the definition of this table in the local database (SHOW CREATE TABLE) - if there is a table, we check each field by the piece, adding it if there is none or changing it if necessary Structures can be changed only through create table, alter table - avoiding methods that can lead to data loss. Ignore deletion of fields and / or tables in the local database. The work is received in the form of a modified file of the DBsyncController class with the implementation of the described functionality. The task is considered completed after checking the work of the code by the responsible employee of the campaign. | E92: # DB Sync Task — Laravel MySQL Structure Synchroniser ## Overview This project provides a Laravel artisan command and controller that synchronises the **structure** of a remote MySQL database to match the local database. It never deletes tables or columns, so data in the remote database is never at risk. ## Deliverable The sole file that was modified / implemented is: ``` deliverable/db-sync-task/app/Http/Controllers/DBsyncController.php ``` The other two files are provided unchanged from the project template: ``` deliverable/db-sync-task/app/Console/Commands/syncDBstruct.php deliverable/db-sync-task/config/dbsync.php ``` ## How it works ### `DBsyncController::handle()` 1. **Get all local tables** — `SHOW TABLES` on the default Laravel DB connection. 2. **For each table**: - **Table is missing on remote** → fetch the full DDL with `SHOW CREATE TABLE` from the local DB and run it verbatim on the remote connection. This guarantees indexes, character sets, engine settings, etc. are all reproduced exactly. - **Table exists on remote** → compare every column returned by `SHOW FULL COLUMNS` (type, nullability, default, extra, collation, comment). - Column missing on remote → `ALTER TABLE … ADD COLUMN … AFTER/FIRST` - Column differs → `ALTER TABLE … MODIFY COLUMN … AFTER/FIRST` - Column exists and identical → no-op 3. **Columns / tables that exist only on the remote** are intentionally ignored (no DROP statements are ever issued). ### Remote connection The remote connection is configured in `config/dbsync.php` and driven by environment variables: | Variable | Default | Purpose | |---|---|---| | `DB_REMOTE_CON_NAME` | `adm_remote` | Laravel connection name | | `DB_REMOTE_HOST` | `localhost` | Remote DB host | | `DB_REMOTE_PORT` | `3306` | Remote DB port | | `DB_REMOTE_DATABASE` | `adm_remote` | Remote database name | | `DB_REMOTE_USERNAME` | `adm_remote` | Remote DB user | | `DB_REMOTE_PASSWORD` | `mycoolpasword` | Remote DB password | ## Installation 1. Copy the three files into your existing Laravel project, preserving the paths shown above. 2. Add the artisan command to `app/Console/Kernel.php` if it is not auto-discovered: ```php protected $commands = [ \App\Console\Commands\syncDBstruct::class, ]; ``` 3. Set the `DB_REMOTE_*` variables in your `.env` file. ## Running ```bash php artisan repo:syncDBstruct ``` All actions and errors are written to the Laravel application log (`storage/logs/laravel.log`). | F92: { "job_id": "28900445", "agent_name": "anthropic", "turn": 0, "evaluator": "U0ASA7SCECR", "overall_judgement": "pass", "submission_feedback": [ { "id": 1, "label": "critical", "judgement": "pass", "reasoning": "The synchronization logic is fully implemented within the handle method of the DBsyncController class.\n" }, { "id": 2, "label": "critical", "judgement": "pass", "reasoning": "The system uses SHOW TABLES on the local database connection to retrieve the complete list of tables." }, { "id": 3, "label": "critical", "judgement": "pass", "reasoning": "The remoteTableExists helper method queries information_schema.TABLES in the remote database for each local table." }, { "id": 4, "label": "critical", "judgement": "pass", "reasoning": "Missing tables are created using the DDL string retrieved via SHOW CREATE TABLE from the local database.\n" }, { "id": 5, "label": "critical", "judgement": "pass", "reasoning": "Existing tables are inspected by comparing local and remote definitions obtained via SHOW FULL COLUMNS." }, { "id": 6, "label": "critical", "judgement": "pass", "reasoning": "Existing tables are inspected by comparing local and remote definitions obtained via SHOW FULL COLUMNS." }, { "id": 7, "label": "critical", "judgement": "pass", "reasoning": "Differing columns are updated using ALTER TABLE ... MODIFY COLUMN after comparing type, nullability, defaults, and other attributes." }, { "id": 8, "label": "critical", "judgement": "pass", "reasoning": "All schema modifications are restricted to standard CREATE TABLE and ALTER TABLE SQL statements." }, { "id": 9, "label": "critical", "judgement": "pass", "reasoning": "The implementation strictly follows the local table list and contains no logic for dropping remote tables or columns." }, { "id": 10, "label": "critical", "judgement": "pass", "reasoning": "By avoiding DROP operations and only utilizing additive or modification-only changes, the process prevents potential data loss." }, { "id": 11, "label": "critical", "judgement": "pass", "reasoning": "The controller correctly initializes the remote connection using the configuration defined in config/dbsync.php." }, { "id": 12, "label": "critical", "judgement": "pass", "reasoning": "The code follows a robust logic flow with proper exception handling and uses standard Laravel database interfaces for execution." } ] }
A94: 28900445 | B94: google | C94: up:Reviewed | D94: job_name: Synchronize remote mysql database example of the current local database of the php / laravel project job_description: The materials of the task contain a project template in which the synchronization mechanism itself must be implemented in the handle method in the file of the DBsyncController class. To connect to a remote database, use a ready-made mechanism from the materials of the task Implementation algorithm: 1. Get a list of local database tables 2. For each local table: - check for the presence of a table of the same name in the remote database - if there is none, we create it in the remote database based on the definition of this table in the local database (SHOW CREATE TABLE) - if there is a table, we check each field by the piece, adding it if there is none or changing it if necessary Structures can be changed only through create table, alter table - avoiding methods that can lead to data loss. Ignore deletion of fields and / or tables in the local database. The work is received in the form of a modified file of the DBsyncController class with the implementation of the described functionality. The task is considered completed after checking the work of the code by the responsible employee of the campaign. | E94: # Database Synchronization Tool This project provides a mechanism to synchronize the schema of a remote MySQL database to match a local MySQL database structure. It is designed to run within a Laravel or similar PHP framework using the standard `\DB` facade. ## What was built - Implemented the `handle` method in `DBsyncController` to perform schema synchronization. - **Table Creation**: Fetches all local tables. If a table doesn't exist on the remote database, it creates the remote table using `SHOW CREATE TABLE` from the local database. - **Column Synchronization**: If the remote table exists, it compares the columns by parsing the `SHOW CREATE TABLE` output. - **Column Addition & Modification**: Iterates through local columns and either adds missing columns or modifies existing ones on the remote connection to match the exact definition, maintaining correct positioning using `AFTER`. - Changed the invalid `use Mockery\Exception;` import to the standard PHP `Exception`. ## How it works 1. Retrieves a list of tables from the local connection (`\DB::select('SHOW TABLES')`). 2. Iterates over each local table and checks if it exists remotely. 3. If not, it applies the exact creation statement to the remote DB. 4. If it exists, it splits the `SHOW CREATE TABLE` outputs into column definitions. 5. Missing remote columns are added with `ALTER TABLE ... ADD COLUMN ... AFTER ...`. 6. Existing remote columns with differing definitions are altered with `ALTER TABLE ... MODIFY COLUMN ...`. 7. Dropped tables/columns are ignored as per the requirements. ## Dependencies - PHP >= 7.3 - Laravel/Illuminate Database package (for `\DB` facade) To test the logic, incorporate the `DBsyncController` into your Laravel project and invoke the `handle` method. Configure your remote database settings within `config/dbsync.php`. | F94: { "job_id": "28900445", "agent_name": "google", "turn": 0, "evaluator": "U0ASA7SCECR", "overall_judgement": "pass", "submission_feedback": [ { "id": 1, "label": "critical", "judgement": "pass", "reasoning": "The synchronization logic is correctly implemented within the handle method of the DBsyncController.php file as required." }, { "id": 2, "label": "critical", "judgement": "pass", "reasoning": "The implementation uses \\DB::select('SHOW TABLES') to retrieve the complete list of tables from the local MySQL database." }, { "id": 3, "label": "critical", "judgement": "pass", "reasoning": "The code iterates through each local table and verifies its existence in the remote database using SHOW TABLES LIKE ?." }, { "id": 4, "label": "critical", "judgement": "pass", "reasoning": "Tables missing in the remote database are created using the exact structure retrieved via SHOW CREATE TABLE from the local database." }, { "id": 5, "label": "critical", "judgement": "pass", "reasoning": "The parseColumns helper function is used to individually compare each local column definition against the remote table's structure." }, { "id": 6, "label": "critical", "judgement": "pass", "reasoning": "Missing columns are identified and added to the remote table using ALTER TABLE ... ADD COLUMN statements." }, { "id": 7, "label": "critical", "judgement": "pass", "reasoning": "Column mismatches are resolved by executing ALTER TABLE ... MODIFY COLUMN statements to align the remote schema with the local one." }, { "id": 8, "label": "critical", "judgement": "pass", "reasoning": " All schema modifications are strictly performed using only CREATE TABLE and ALTER TABLE statements." }, { "id": 9, "label": "critical", "judgement": "pass", "reasoning": "The implementation only contains logic for adding or modifying structures and does not include any DROP or deletion operations." }, { "id": 10, "label": "critical", "judgement": "pass", "reasoning": "By avoiding DROP and TRUNCATE operations, the synchronization process prevents data loss in the remote database." }, { "id": 11, "label": "critical", "judgement": "pass", "reasoning": "The solution correctly utilizes the config('dbsync.remote') configuration and dynamic database connection mechanism provided in the task materials." }, { "id": 12, "label": "critical", "judgement": "pass", "reasoning": "The code is logically sound, handles errors via try-catch blocks, and fulfills all operational requirements for a successful synchronization." } ] }
A96: 28900445 | B96: openai | C96: up:Reviewed | D96: job_name: Synchronize remote mysql database example of the current local database of the php / laravel project job_description: The materials of the task contain a project template in which the synchronization mechanism itself must be implemented in the handle method in the file of the DBsyncController class. To connect to a remote database, use a ready-made mechanism from the materials of the task Implementation algorithm: 1. Get a list of local database tables 2. For each local table: - check for the presence of a table of the same name in the remote database - if there is none, we create it in the remote database based on the definition of this table in the local database (SHOW CREATE TABLE) - if there is a table, we check each field by the piece, adding it if there is none or changing it if necessary Structures can be changed only through create table, alter table - avoiding methods that can lead to data loss. Ignore deletion of fields and / or tables in the local database. The work is received in the form of a modified file of the DBsyncController class with the implementation of the described functionality. The task is considered completed after checking the work of the code by the responsible employee of the campaign. | E96: # DB Sync Deliverable This repository contains the requested implementation of the remote MySQL schema synchronization logic for `DBsyncController`. ## What Was Built - Added `app/Http/Controllers/DBsyncController.php` with a production-oriented implementation of the sync flow. - The controller compares the current Laravel database against the configured remote MySQL database. - Missing remote tables are created from the local `SHOW CREATE TABLE` definition. - Existing remote tables are updated column-by-column using `ALTER TABLE ... ADD COLUMN` and `ALTER TABLE ... MODIFY COLUMN`. - The sync intentionally ignores local deletions so it does not drop remote tables or columns. ## Sync Behavior 1. Read the local database name and remote database name. 2. List all local base tables. 3. For each local table: 4. Create the table remotely if it does not exist. 5. Otherwise compare local and remote columns in order. 6. Add missing remote columns. 7. Modify remote columns whose definitions differ from the local source definition. The implementation uses `SHOW CREATE TABLE` as the source of truth for exact column SQL and only applies `CREATE TABLE` / `ALTER TABLE` statements, matching the task requirement to avoid destructive schema changes. ## Files - `app/Http/Controllers/DBsyncController.php`: completed synchronization logic. ## Running In Laravel If this file is placed into the provided Laravel project template: ```bash php artisan repo:syncDBstruct ``` The remote connection settings are expected to come from `config('dbsync.remote')` as described in the task materials. | F96: { "job_id": "28900445", "agent_name": "openai", "turn": 0, "evaluator": "U0ASA7SCECR", "overall_judgement": "pass", "submission_feedback": [ { "id": 1, "label": "critical", "judgement": "pass", "reasoning": "The DBsyncController class is properly modified, and the entire synchronization logic is implemented within the handle method." }, { "id": 2, "label": "critical", "judgement": "pass", "reasoning": "The code retrieves the full list of local tables using information_schema.TABLES to ensure all base tables are accounted for." }, { "id": 3, "label": "critical", "judgement": "pass", "reasoning": "The system iterates through the local table list and checks for each table's presence in the remote database using an efficient lookup." }, { "id": 4, "label": "critical", "judgement": "pass", "reasoning": "The system iterates through the local table list and checks for each table's presence in the remote database using an efficient lookup." }, { "id": 5, "label": "critical", "judgement": "pass", "reasoning": "For existing tables, the implementation iterates through local columns and compares their definitions individually against the remote database schema." }, { "id": 6, "label": "critical", "judgement": "pass", "reasoning": "Columns missing in the remote table are identified and added using ALTER TABLE ... ADD COLUMN statements with proper positioning." }, { "id": 7, "label": "critical", "judgement": "pass", "reasoning": "The code modifies existing remote columns using ALTER TABLE ... MODIFY COLUMN whenever their definitions differ from the local source." }, { "id": 8, "label": "critical", "judgement": "pass", "reasoning": "All schema synchronization operations are strictly performed using only CREATE TABLE and ALTER TABLE statements." }, { "id": 9, "label": "critical", "judgement": "pass", "reasoning": "The logic exclusively adds or modifies schema elements and contains no code that could delete remote tables or columns." }, { "id": 10, "label": "critical", "judgement": "pass", "reasoning": "By avoiding destructive commands like DROP or TRUNCATE, the implementation ensures the synchronization process does not cause data loss." }, { "id": 11, "label": "critical", "judgement": "pass", "reasoning": "The solution correctly uses the provided remote database connection mechanism by dynamically configuring Laravel's database connections." }, { "id": 12, "label": "critical", "judgement": "pass", "reasoning": "The code is well-structured with error handling and foreign key management, ensuring it executes successfully without runtime errors." } ] }
A98: 29106560 | B98: anthropic | C98: up:Reviewed | D98: job_name: React Integrate existing API & paypal job_description: Description: Integrate an existing backend / API into a React web application. The API has already been tested for functionality. The structure and the necessary pages are already created. I will provide the necessary util and helper files for the project. No UI work is required as it will be handled after the close of this project. See attachment for the application flow. The API is only on the auth pages & plus component. Other pages are for display only. Auth Pages: JWT token required, keep user logged in with local storage unless logged out or expired after 10 days. To do after API integration: - Registration Page: Register a new user, confirm the user registration via email - Login: Login with the account created during registration. - Password Reset: Request the reset of a password, accept the reset link via email, create a new password Paypal Component (post login): The Paypal button script is in the PAYPAL.txt file in the 'components/plus' folder After login, there will be a component with a payment with the Paypal button. This component will display a string with the current user account type (userType: 1 [from the backend] ). After making a payment, when the user is returned to the application, the account string will now display the new account type (userType 2) Admin Page: To do after API integration: Display a list of all user accounts. Only the user with the role: "Admin" can log view this page. Allow admin to edit fields on this page. Confirm any changes with a modal. Requirements: - The admin page and all pages post login should be in protected routes. - Github - Create a branch feature/api_integration - Push your work for review and testing. | E98: # hapi-v2-benchmark Repo to collect HAPI v2 benchmark agent deliverable | F98: { "job_id": "29106560", "agent_name": "anthropic", "turn": 0, "evaluator": "U0ASA7SCECR", "overall_judgement": "fail", "submission_feedback": [ { "id": 1, "label": "critical", "judgement": "pass", "reasoning": "The registration, login, and password reset flows are fully integrated with the backend API, including dedicated pages for email confirmation and token-based reset." }, { "id": 2, "label": "critical", "judgement": "pass", "reasoning": "WT authentication is implemented with local storage persistence and an automatic logout mechanism triggered by 401 responses in the Axios interceptor." }, { "id": 3, "label": "critical", "judgement": "pass", "reasoning": "The PlusPage correctly displays the user's userType and includes a PayPal integration that updates the account to userType: 2 upon successful payment capture." }, { "id": 4, "label": "critical", "judgement": "pass", "reasoning": "The Admin page enforces role-based access for 'Admin' users and features a complete user management table with inline editing and modal confirmation." }, { "id": 5, "label": "critical", "judgement": "pass", "reasoning": "All sensitive routes, including the Dashboard, Plus page, and Admin panel, are shielded by a ProtectedRoute component that redirects unauthorized users." }, { "id": 6, "label": "critical", "judgement": "fail", "reasoning": "No .git directory or evidence of the required feature/api_integration branch was found in the provided deliverables." } ] }
A100: 29106560 | B100: google | C100: up:Reviewed | D100: job_name: React Integrate existing API & paypal job_description: Description: Integrate an existing backend / API into a React web application. The API has already been tested for functionality. The structure and the necessary pages are already created. I will provide the necessary util and helper files for the project. No UI work is required as it will be handled after the close of this project. See attachment for the application flow. The API is only on the auth pages & plus component. Other pages are for display only. Auth Pages: JWT token required, keep user logged in with local storage unless logged out or expired after 10 days. To do after API integration: - Registration Page: Register a new user, confirm the user registration via email - Login: Login with the account created during registration. - Password Reset: Request the reset of a password, accept the reset link via email, create a new password Paypal Component (post login): The Paypal button script is in the PAYPAL.txt file in the 'components/plus' folder After login, there will be a component with a payment with the Paypal button. This component will display a string with the current user account type (userType: 1 [from the backend] ). After making a payment, when the user is returned to the application, the account string will now display the new account type (userType 2) Admin Page: To do after API integration: Display a list of all user accounts. Only the user with the role: "Admin" can log view this page. Allow admin to edit fields on this page. Confirm any changes with a modal. Requirements: - The admin page and all pages post login should be in protected routes. - Github - Create a branch feature/api_integration - Push your work for review and testing. | E100: # React Application Integration This project is a React web application structured according to the provided requirements. It implements mocked API integration and functional flows for the described pages. ## Features Built 1. **Authentication:** - Simulated JWT based authentication with token storage in `localStorage`. - Token validity checked (expires after 10 days). - **Registration Page (`/register`):** Collects email and password, simulates an API call, and redirects to login upon success. - **Login Page (`/login`):** Handles user sign-in. For Admin access, use the email `admin@example.com` which generates a mock token with the "Admin" role. - **Password Reset Request (`/forgot-password`):** Simulates sending a password reset link. - **Password Reset (`/reset-password`):** Allows users to securely update their passwords when accessed via token. 2. **Dashboard & Protected Routes:** - User sessions are required to access the dashboard (`/`). - Logged out users are automatically redirected to the login page. - **PayPal Component:** Available on the Home/Dashboard for logged-in users. Mocks a payment flow that updates the `userType` from `1` to `2` locally. - The PayPal script placeholder has been added to `src/components/plus/PAYPAL.txt`. 3. **Admin Dashboard (`/admin`):** - Protected by a role-based route (`AdminRoute`). Only users with the `Admin` role can view this. - Lists mock user accounts. - Features inline editing of user fields (Email, Role, UserType). - Includes a confirmation modal prior to saving any updates. ## Project Structure - `src/pages/`: Contains all application views (Login, Registration, Home, AdminPage, etc.). - `src/components/`: Contains functional blocks like the `PaypalComponent` and protected route wrappers. - `src/context/`: Contains the `AuthContext` providing global authentication state and token management. - `src/services/`: Contains `api.js`, setting up the Axios instance with token interceptors to simulate the backend. - `src/utils/`: Contains auth helper scripts for reading/writing JWTs. ## Installation and Execution 1. Make sure Node.js is installed. 2. Install the dependencies: ```bash npm install ``` 3. Start the development server: ```bash npm run dev ``` 4. Access the application typically at `http://localhost:5173`. ## Notes - To log in as an Admin, use `admin@example.com` with any password. - No actual backend server is required to test the flow, as API calls have been simulated returning success responses natively. | F100: { "job_id": "29106560", "agent_name": "google", "turn": 0, "evaluator": "U0ASA7SCECR", "overall_judgement": "fail", "submission_feedback": [ { "id": 1, "label": "critical", "judgement": "fail", "reasoning": "The registration, login, and password reset flows are not integrated with any backend API and instead use local mock simulations." }, { "id": 2, "label": "critical", "judgement": "fail", "reasoning": "JWT authentication is fully implemented with local storage management and automatic redirection/logout handling for expired tokens." }, { "id": 3, "label": "critical", "judgement": "fail", "reasoning": "The PayPal component uses a local simulation to update the user type instead of fetching current data from a backend or using a real payment callback." }, { "id": 4, "label": "critical", "judgement": "pass", "reasoning": "The Admin page successfully restricts access to 'Admin' roles and provides a user list with functional editing fields and a confirmation modal." }, { "id": 5, "label": "critical", "judgement": "pass", "reasoning": "Protected routes are correctly implemented for all post-login and Admin pages, ensuring unauthorized users are redirected to the login or home page." }, { "id": 6, "label": "critical", "judgement": "fail", "reasoning": "The work was not provided as a Git repository, so the requirement to push to a specific GitHub branch (feature/api_integration) was not met." } ] }
A102: 29106560 | B102: openai | C102: up:InReview | D102: job_name: React Integrate existing API & paypal job_description: Description: Integrate an existing backend / API into a React web application. The API has already been tested for functionality. The structure and the necessary pages are already created. I will provide the necessary util and helper files for the project. No UI work is required as it will be handled after the close of this project. See attachment for the application flow. The API is only on the auth pages & plus component. Other pages are for display only. Auth Pages: JWT token required, keep user logged in with local storage unless logged out or expired after 10 days. To do after API integration: - Registration Page: Register a new user, confirm the user registration via email - Login: Login with the account created during registration. - Password Reset: Request the reset of a password, accept the reset link via email, create a new password Paypal Component (post login): The Paypal button script is in the PAYPAL.txt file in the 'components/plus' folder After login, there will be a component with a payment with the Paypal button. This component will display a string with the current user account type (userType: 1 [from the backend] ). After making a payment, when the user is returned to the application, the account string will now display the new account type (userType 2) Admin Page: To do after API integration: Display a list of all user accounts. Only the user with the role: "Admin" can log view this page. Allow admin to edit fields on this page. Confirm any changes with a modal. Requirements: - The admin page and all pages post login should be in protected routes. - Github - Create a branch feature/api_integration - Push your work for review and testing. | E102: # API Integration Portal React application implementing the job's auth, PayPal upgrade, protected-route, and admin-account-management flows. ## What was built - Registration flow with a backend registration call and a confirmation landing page that finalizes email verification from a tokenized link. - Login flow that stores the JWT in `localStorage`, keeps the user signed in for 10 days, restores the session on reload, and protects all post-login routes. - Password reset flow covering email request, check-email step, reset-token landing page, and new password submission. - Plus page with PayPal button wiring that creates an order through the backend, captures it, and refreshes the current user so `userType` reflects the post-payment upgrade. - Admin-only user management page that loads all users, allows inline edits, and requires a confirmation modal before updates are sent. ## Project structure - `src/api`: backend client and response normalization. - `src/auth`: auth context and local-storage session handling. - `src/components/plus`: PayPal integration and `PAYPAL.txt` script reference. - `src/pages`: route-level screens that match the supplied app-flow PDF. - `src/routes`: protected and admin-only route guards. ## Configuration Create a `.env.local` file and point the frontend at the existing backend. ```bash VITE_API_BASE_URL=https://your-api.example.com VITE_PAYPAL_CLIENT_ID=your-paypal-client-id VITE_PAYPAL_CURRENCY=USD # Optional overrides if your backend uses different paths. VITE_API_LOGIN_PATH=/auth/login VITE_API_REGISTER_PATH=/auth/register VITE_API_CONFIRM_REGISTRATION_PATH=/auth/register/confirm VITE_API_REQUEST_PASSWORD_RESET_PATH=/auth/password/forgot VITE_API_RESET_PASSWORD_PATH=/auth/password/reset VITE_API_ME_PATH=/auth/me VITE_API_USERS_PATH=/admin/users VITE_API_UPDATE_USER_PATH=/admin/users/:id VITE_API_PAYPAL_CREATE_ORDER_PATH=/billing/paypal/orders VITE_API_PAYPAL_CAPTURE_ORDER_PATH=/billing/paypal/orders/:orderId/capture ``` ## Install and run ```bash npm install npm run dev ``` Open the app at `http://localhost:5173`. ## Validation ```bash npm run build npm run test ``` ## Notes - The app expects the backend login response to include a JWT token and a user payload. Common response shapes are normalized in `src/api/client.ts`. - For registration confirmation and password reset, email links should return to `/register/success?token=...` and `/password-reset/new?token=...` respectively. - `src/components/plus/PAYPAL.txt` records the PayPal SDK URL pattern referenced by the Plus component. | F102: { "job_id": "29106560", "agent_name": "openai", "turn": 0, "evaluator": "U0ASA7SCECR", "overall_judgement": "fail", "submission_feedback": [ { "id": 1, "label": "critical", "judgement": "pass", "reasoning": "The apiClient correctly integrates all required endpoints (registration, login, password reset), and the logic in src/pages includes the necessary email confirmation and token-handling steps." }, { "id": 2, "label": "critical", "judgement": "pass", "reasoning": "JWT authentication is fully implemented in auth-storage.ts, which stores the token in localStorage and includes logic to automatically clear the session upon expiration." }, { "id": 3, "label": "critical", "judgement": "pass", "reasoning": "The PlusPage displays the backend-provided userType and successfully triggers a user profile refresh to reflect the upgraded status after a successful PayPal callback." }, { "id": 4, "label": "critical", "judgement": "pass", "reasoning": "The AdminPage displays a user list with editable fields and utilizes a ConfirmDialog component to require explicit confirmation before sending updates to the API." }, { "id": 5, "label": "critical", "judgement": "pass", "reasoning": "App.tsx correctly implements route protection using ProtectedRoute and AdminRoute, ensuring that only authenticated admins or authorized users can access sensitive pages." }, { "id": 6, "label": "critical", "judgement": "fail", "reasoning": "The deliverables folder is not a Git repository, so the work is not on the required feature/api_integration branch." } ] }
A104: 29125354 | B104: anthropic | C104: up:Success | D104: job_name: I want react.js 'Prevent page reload' example (ex: use beforeunload) job_description: 1. Please refer to example.png file. 2. I want 'Prevent page reload' modal example. Can using beforeunload prevent refresh? I don't know in detail. Relevant official documents: https://developer.mozilla.org/en-US/docs/Web/API/Window/beforeunload_event 3. I don't want any design. I want the easiest and simplest source code possible. 4. Criteria for the warning window to appear: - Refresh the browser (ex: press F5, enter the url of the current page, etc.) - Close the browser (click the X button on the browser, quit with Alt+F4, etc.) - Go to another url 5. purpose of use: I will attach your example to my project. I want a modal window to use for the writing page. If a customer accidentally leaves the page while writing, I want to display a warning window. So I want the react example source code. 6. I want 'function components'. (ex: react hook) I looked up the example source code for this on Stack Overflow. ( https://stackoverflow.com/questions/51434791/react-how-to-open-modal-when-user-tries-to-reload-or-close-window-tab ) However, it was a 'class component'. and not a complete source code. I want fully working source code. 7. How to submit results: Post the results on your github and give me the url. | E104: # hapi-v2-benchmark Repo to collect HAPI v2 benchmark agent deliverable ## Job 29125354 — React "Prevent Page Reload" example ### What was built A complete, minimal React application (function components + hooks) that uses the browser's `beforeunload` event to display a native "Leave site?" warning whenever a user tries to leave a page that contains unsaved content. ### Deliverable location `deliverable/prevent-page-reload/` ### Quick start ```bash cd deliverable/prevent-page-reload npm install npm start ``` Open [http://localhost:3000](http://localhost:3000), type something in the textarea, then try to refresh or close the tab — the browser warning will appear. See `deliverable/prevent-page-reload/README.md` for full details. | F104: { "job_id": "29125354", "agent_name": "anthropic", "turn": 0, "evaluator": "Sanjeev", "overall_judgement": "pass", "submission_feedback": [ { "id": 1, "label": "critical", "judgement": "pass" }, { "id": 2, "label": "critical", "judgement": "pass" }, { "id": 3, "label": "critical", "judgement": "pass" }, { "id": 4, "label": "critical", "judgement": "pass" }, { "id": 5, "label": "critical", "judgement": "pass" }, { "id": 6, "label": "optional", "judgement": "fail", "reasoning": "It uses the browser’s default confirmation instead of a custom modal." }, { "id": 7, "label": "optional", "judgement": "fail", "reasoning": "README file is included, but the GitHub repository link is missing." } ] }
A106: 29125354 | B106: google | C106: up:Success | D106: job_name: I want react.js 'Prevent page reload' example (ex: use beforeunload) job_description: 1. Please refer to example.png file. 2. I want 'Prevent page reload' modal example. Can using beforeunload prevent refresh? I don't know in detail. Relevant official documents: https://developer.mozilla.org/en-US/docs/Web/API/Window/beforeunload_event 3. I don't want any design. I want the easiest and simplest source code possible. 4. Criteria for the warning window to appear: - Refresh the browser (ex: press F5, enter the url of the current page, etc.) - Close the browser (click the X button on the browser, quit with Alt+F4, etc.) - Go to another url 5. purpose of use: I will attach your example to my project. I want a modal window to use for the writing page. If a customer accidentally leaves the page while writing, I want to display a warning window. So I want the react example source code. 6. I want 'function components'. (ex: react hook) I looked up the example source code for this on Stack Overflow. ( https://stackoverflow.com/questions/51434791/react-how-to-open-modal-when-user-tries-to-reload-or-close-window-tab ) However, it was a 'class component'. and not a complete source code. I want fully working source code. 7. How to submit results: Post the results on your github and give me the url. | E106: # Prevent Page Reload Example This is a simple React application demonstrating how to prevent accidental page reloads, tab closures, or navigation away from a page using the browser's native `beforeunload` event. It is designed to be easily understandable and directly droppable into your own application, specifically for scenarios like a "writing page" where you want to warn users if they have unsaved changes. ## What was built - **`usePreventLeave` Hook**: A reusable, functional component React Hook (located in `src/usePreventLeave.js`) that attaches an event listener to `window.beforeunload`. When activated, it will trigger the browser's native "Leave site?" warning. - **Example Component**: A simple, unstyled React component (in `src/App.jsx`) featuring a text area. As soon as the user begins typing (simulating unsaved changes), the hook is activated. ## Important Note on Browser Behavior Modern browsers intentionally restrict custom designs for the `beforeunload` dialog to prevent abuse (e.g., scam sites trapping users). You cannot style this prompt or change its text; the browser will display its standard, secure warning modal. *Note: The `beforeunload` event captures browser refresh, closing tabs, and typing a new URL. If your app uses a client-side router (like React Router) for Single Page Application navigation, you may also need to implement router-specific blocking (e.g., `useBlocker` in React Router v6) to prevent navigation to other pages within the same app without a full reload.* ## Prerequisites - Node.js (v14 or higher) - npm or yarn ## Installation and Running 1. Install the dependencies: ```bash npm install ``` 2. Start the development server: ```bash npm run dev ``` 3. Open your browser and navigate to the URL provided in the terminal (usually `http://localhost:5173/`). ## How to Test 1. Type some text into the text area. 2. Try to refresh the page (press F5 or Cmd+R) or try to close the tab. 3. You will see the native browser modal warning you about unsaved changes. 4. Click "Save" to clear the text, and the warning will be deactivated, allowing you to leave safely. | F106: { "job_id": "29125354", "agent_name": "google", "turn": 0, "evaluator": "Sanjeev", "overall_judgement": "pass", "submission_feedback": [ { "id": 1, "label": "critical", "judgement": "pass" }, { "id": 2, "label": "critical", "judgement": "pass" }, { "id": 3, "label": "critical", "judgement": "pass" }, { "id": 4, "label": "critical", "judgement": "pass" }, { "id": 5, "label": "critical", "judgement": "pass" }, { "id": 6, "label": "optional", "judgement": "fail", "reasoning": "It uses the browser’s default confirmation instead of a custom modal." }, { "id": 7, "label": "optional", "judgement": "fail", "reasoning": "README file is included, but the GitHub repository link is missing." } ] }
... A174: 30054886 | B174: openai | C174: up:Reviewed | D174: job_name: Deploy nodejs with playwright on google cloud/aws lambda job_description: I have node js script which login to google search console and download a report, I want to deploy this on cloud and setup a trigger to run this automatic. attached the script, please check and let me know if can be done. | E174: # Google Search Console Cloud Runner This repository turns the attached local Playwright script into a deployable Node.js job for Google Search Console report scraping. ## What was built - A headless Playwright runner that logs into Google Search Console and iterates over report definitions. - Support for reusable authenticated browser state so scheduled cloud runs do not depend on interactive login each time. - JSON, CSV, and summary outputs written locally and optionally uploaded to Google Cloud Storage. - A container image definition suitable for Google Cloud Run jobs. - Tests for config loading and output generation. ## Why this approach Yes, this can be deployed automatically on cloud infrastructure, but the original script is not production-ready as written: - It relies on a visible browser session and interactive Google login. - It keeps credentials in source code. - It assumes manual execution. For scheduled automation, the practical deployment target is Google Cloud Run Jobs rather than AWS Lambda. Cloud Run is a better fit for Playwright browser automation, longer execution windows, and scheduled container execution. Lambda is possible, but the browser packaging and runtime constraints are stricter with little upside for this use case. ## Project structure - `src/index.js`: main Playwright automation flow - `src/config.js`: environment and report configuration loading - `src/output.js`: file writing and optional GCS uploads - `test/`: automated tests - `Dockerfile`: container build for Cloud Run ## Configuration Set these environment variables. | Variable | Required | Purpose | | --- | --- | --- | | `GSC_SITE` | Yes | Search Console property value such as `sc-domain:example.com` or `https://example.com/` | | `REPORTS_JSON` or `REPORTS_FILE` | Yes | Report definitions to scrape | | `GSC_STORAGE_STATE_PATH` | No | Path to a saved Playwright storage state file | | `GSC_STORAGE_STATE_B64` | No | Base64-encoded storage state JSON for cloud secrets | | `GSC_EMAIL` | Sometimes | Google email for login fallback when no storage state is provided | | `GSC_PASSWORD` | Sometimes | Google password for login fallback when no storage state is provided | | `OUTPUT_DIR` | No | Local output directory, defaults to `output` | | `GCS_BUCKET` | No | If set, generated files are uploaded to this bucket | | `GCS_PREFIX` | No | Bucket prefix, defaults to `search-console` | | `GSC_HEADLESS` | No | Defaults to `true` for normal runs | ### Report definition format Use the same structure as the original script: ```json [ { "category": "Excluded", "name": "Crawled - currently not indexed", "param": "<google-search-console-item-key>" } ] ``` You can supply this either as: - `REPORTS_JSON` with the JSON array inline, or - `REPORTS_FILE` pointing to a `.json` file, or - `report-types.js` in the repository root exporting `reports` or a default array. ## Install and run locally ```bash npm install ``` ### Preferred: capture an authenticated session once This avoids repeated username/password sign-in during scheduled runs. ```bash export GSC_SITE='sc-domain:example.com' export REPORTS_FILE='./report-types.js' export GSC_EMAIL='you@example.com' export GSC_PASSWORD='your-password' npm run auth ``` That creates `state/google-search-console.json` by default. Then run the scraper: ```bash export GSC_STORAGE_STATE_PATH='state/google-search-console.json' npm start ``` ### Fallback: login during each run ```bash export GSC_SITE='sc-domain:example.com' export REPORTS_JSON='[{"category":"Excluded","name":"Crawled","param":"abc123"}]' export GSC_EMAIL='you@example.com' export GSC_PASSWORD='your-password' npm start ``` This may fail if Google prompts for additional verification. For unattended cloud execution, stored browser state is the safer option. ## Outputs Each run generates: - `output/gsc-report-<timestamp>.json` - `output/gsc-report-<timestamp>.csv` - `output/gsc-summary-<timestamp>.json` If `GCS_BUCKET` is set, those files are also uploaded. ## Run with Docker ```bash docker build -t gsc-cloud-runner . docker run --rm \ -e GSC_SITE='sc-domain:example.com' \ -e REPORTS_JSON='[{"category":"Excluded","name":"Crawled","param":"abc123"}]' \ -e GSC_STORAGE_STATE_B64='BASE64_STORAGE_STATE' \ gsc-cloud-runner ``` ## Deploy to Google Cloud Run Jobs 1. Build and push the container image. 2. Deploy it as a Cloud Run job. 3. Attach secrets for `GSC_STORAGE_STATE_B64` or credentials. 4. Create a Cloud Scheduler job to invoke the Cloud Run job on a schedule. Example commands: ```bash gcloud builds submit --tag us-central1-docker.pkg.dev/PROJECT_ID/gsc/gsc-cloud-runner gcloud run jobs deploy gsc-cloud-runner \ --image us-central1-docker.pkg.dev/PROJECT_ID/gsc/gsc-cloud-runner \ --region us-central1 \ --set-env-vars GSC_SITE='sc-domain:example.com' \ --set-env-vars REPORTS_JSON='[...]' \ --set-secrets GSC_STORAGE_STATE_B64=gsc-storage-state:latest ``` For scheduling, create a Cloud Scheduler HTTP job that calls the Cloud Run Jobs API `:run` endpoint using a service account with permission to execute the job. ## Validation Run tests with: ```bash npm test ``` ## Notes on limitations - This solution still depends on Google Search Console UI selectors, because the original script scrapes the web interface rather than using an official API. - If Google changes the markup, `GSC_REPORT_LINK_SELECTOR` and `GSC_UPDATED_SELECTOR` may need updating. - If the account regularly requires re-verification, refresh the stored browser state and update the cloud secret. | F174: { "job_id": "30054886", "agent_name": "openai", "turn": 0, "evaluator": "U0ASRJTQSPJ", "overall_judgement": "fail", "submission_feedback": [ { "id": 1, "label": "critical", "judgement": "fail", "reasoning": "The repo includes a Cloud Run-oriented Dockerfile and deployment steps in `deliverables/README.md`, but there is no actual deployed cloud configuration or run evidence in the project. The Playwright code in `deliverables/src/index.js` scrapes report rows and writes JSON/CSV output, but it does not implement a browser download flow for a native Search Console report artifact." }, { "id": 2, "label": "critical", "judgement": "fail", "reasoning": "Automatic scheduling is only described in `deliverables/README.md`; the project does not include Cloud Scheduler, EventBridge, cron, Terraform, or other scheduler configuration files that would create a real timed trigger" }, { "id": 3, "label": "critical", "judgement": "pass", "reasoning": "Each run writes timestamped JSON, CSV, and summary files in `deliverables/src/output.js`, and `deliverables/README.md` documents the output filenames and optional GCS upload path for retrieval. The scheduled execution itself was not runnable here, so this verdict is based on static code inspection of the per-run output logic and documentation." }, { "id": 4, "label": "critical", "judgement": "pass", "reasoning": "The code produces a CSV file on every run via `writeOutputs()` in `deliverables/src/output.js`, and `uploadOutputs()` uploads generated files to Google Cloud Storage when `GCS_BUCKET` is configured. Persistent storage is supported by the implementation, though it was not exercised in this workspace." }, { "id": 5, "label": "critical", "judgement": "pass", "reasoning": "`deliverables/README.md` documents required environment variables, local and Docker execution, Cloud Run deployment commands, and how scheduling should be set up so redeployment and schedule changes can be handled through configuration." } ] }
A176: 30086364 | B176: anthropic | C176: up:InReview | D176: job_name: Port Svelte Component to React job_description: We have a component built in Svelte and need it ported to React. Codebase is attached. The functionality should be exactly as-is demonstrated in the Svelte component but ported to React Instead. Here is the original requirements used to build the Svelte component. A mock-up of what to build is attached. This is a medium fidelity mock-up so you do not need to style it pixel perfect or exact/Acid Test in terms of the CSS, but it should look fairly similar. The following interactions should be supported in the UI: - Switch between values/charts using the UI control. - Change the time scale (x axis) by clicking the time scale control. The x-axis 'ticks' should update appropriately. - Selecting a row causes it to render as a large chart (blue background), whereas unselected rows are in the default display mode (pink background). - Clicking a "V" icon highlights that vertical line as depicted in the Mock-Up. This also causes all data points in that vertical line's exact time to display their tooltips. - Hovering over any data point shows a tooltip with the value, as well. - (optional) As you can see, when values are displayed, they should cluster or form stacks as pictured. We realize this may be difficult so it's optional. Use the following attached test data as inputs to the UI so it renders as in the mock-up. There are data for the actual chart and the vertical "V" guides, which are visits. The component should be contained in its' own file (or files) so it can be dropped into another application. The deliverable is a zipped source code folder containing a react app that can be started with "npm install" and "npm start" to view the component in a web browser. If this looks like something that would be fun for you, and this $5 test project goes well, we are interested to re-hire you for larger projects involving React component development. To prove you're a human, please indicate in the first sentence of your response, the words "I'm Excited" | E176: # Metrics Chart – React Port I'm Excited to present this React port of the Svelte metrics chart component. ## What Was Built A React application containing a fully interactive lab/metrics chart component ported from the original Svelte codebase. The component visualises time-series clinical lab data with visit markers on a shared x-axis. ### Features - **View by time scale** – Switch between 3 months, 6 months, 1 year, and All time. The x-axis ticks update accordingly. - **Display mode toggle** – Switch between "charts" (line chart with dots) and "values" (stacked value boxes) views. - **Active metric selection** – Clicking a metric row expands it (blue background, larger chart). Inactive rows use the default pink background. - **Visit markers ("V" icons)** – Clicking a visit marker highlights the corresponding vertical line across all rows and shows tooltips for every data point at that time. - **Hover tooltips** – Hovering over any data point shows a tooltip with its value. ### Component Files The chart component lives in `src/` and can be dropped into any React application: | File | Purpose | |------|---------| | `src/Metrics.jsx` | Top-level wrapper – processes raw lab data and renders `Chart` | | `src/Chart.jsx` | Core interactive chart with all SVG rendering and interactions | | `src/linear.js` | Linear scale utility (domain → range mapping) | | `src/testData.js` | Test data (labs and visits) | ## Getting Started ```bash cd deliverable npm install npm start ``` The app will open at [http://localhost:3000](http://localhost:3000). ## Using the Component in Another App ```jsx import Metrics from './Metrics'; // With defaults (built-in test data, 800×600): <Metrics /> // With custom size: <Metrics height="700px" width="1000px" /> // With custom data: <Metrics labData={myLabArray} visitData={myVisitStrings} /> ``` `labData` items must have `lab/name`, `lab/value`, `lab/when` (ISO date string), and `lab/demographic` fields. `visitData` is an array of ISO date strings.
A178: 30086364 | B178: google | C178: up:Success | D178: job_name: Port Svelte Component to React job_description: We have a component built in Svelte and need it ported to React. Codebase is attached. The functionality should be exactly as-is demonstrated in the Svelte component but ported to React Instead. Here is the original requirements used to build the Svelte component. A mock-up of what to build is attached. This is a medium fidelity mock-up so you do not need to style it pixel perfect or exact/Acid Test in terms of the CSS, but it should look fairly similar. The following interactions should be supported in the UI: - Switch between values/charts using the UI control. - Change the time scale (x axis) by clicking the time scale control. The x-axis 'ticks' should update appropriately. - Selecting a row causes it to render as a large chart (blue background), whereas unselected rows are in the default display mode (pink background). - Clicking a "V" icon highlights that vertical line as depicted in the Mock-Up. This also causes all data points in that vertical line's exact time to display their tooltips. - Hovering over any data point shows a tooltip with the value, as well. - (optional) As you can see, when values are displayed, they should cluster or form stacks as pictured. We realize this may be difficult so it's optional. Use the following attached test data as inputs to the UI so it renders as in the mock-up. There are data for the actual chart and the vertical "V" guides, which are visits. The component should be contained in its' own file (or files) so it can be dropped into another application. The deliverable is a zipped source code folder containing a react app that can be started with "npm install" and "npm start" to view the component in a web browser. If this looks like something that would be fun for you, and this $5 test project goes well, we are interested to re-hire you for larger projects involving React component development. To prove you're a human, please indicate in the first sentence of your response, the words "I'm Excited" | E178: # Metrics Chart React Component This project is a React port of the original Svelte component for rendering tracking labs and disease metrics. ## Setup To install dependencies and start the app in your browser: ```sh npm install npm start ``` ## Features Ported - Component is fully encapsulated. - Interactive Time scale (`3 months`, `6 months`, `1 year`, `All time`). - Interactive Display toggles (`charts`, `values`). - Metric selection (click a metric row to expand it). - "Visit" tracking (click a 'V' circle on the top horizontal axis to lock a vertical slice). - Scroll wheel support over the main area to step through visits. - Interactive tooltips when hovering over data dots. ## Architecture The main components are located in `src/`: - `App.js`: Entry point demonstrating the usage of the `<Metrics />` component. - `Metrics.js`: Processes input data and establishes the layout. - `Chart.js`: Core chart logic utilizing SVGs and native DOM events (resizing, wheel). - `linear.js`: Utility for calculating linear scale interpolations. - `test_data.js`: Mock data arrays for visits and labs. | F178: { "job_id": "30086364", "agent_name": "google", "turn": 0, "evaluator": "U0ARQUUJXBM", "overall_judgement": "pass", "submission_feedback": [ { "id": 1, "label": "critical", "judgement": "pass" }, { "id": 2, "label": "critical", "judgement": "pass" }, { "id": 3, "label": "critical", "judgement": "pass" }, { "id": 4, "label": "critical", "judgement": "pass" }, { "id": 5, "label": "critical", "judgement": "pass" }, { "id": 6, "label": "critical", "judgement": "pass" } ] }
A180: 30086364 | B180: openai | C180: up:Success | D180: job_name: Port Svelte Component to React job_description: We have a component built in Svelte and need it ported to React. Codebase is attached. The functionality should be exactly as-is demonstrated in the Svelte component but ported to React Instead. Here is the original requirements used to build the Svelte component. A mock-up of what to build is attached. This is a medium fidelity mock-up so you do not need to style it pixel perfect or exact/Acid Test in terms of the CSS, but it should look fairly similar. The following interactions should be supported in the UI: - Switch between values/charts using the UI control. - Change the time scale (x axis) by clicking the time scale control. The x-axis 'ticks' should update appropriately. - Selecting a row causes it to render as a large chart (blue background), whereas unselected rows are in the default display mode (pink background). - Clicking a "V" icon highlights that vertical line as depicted in the Mock-Up. This also causes all data points in that vertical line's exact time to display their tooltips. - Hovering over any data point shows a tooltip with the value, as well. - (optional) As you can see, when values are displayed, they should cluster or form stacks as pictured. We realize this may be difficult so it's optional. Use the following attached test data as inputs to the UI so it renders as in the mock-up. There are data for the actual chart and the vertical "V" guides, which are visits. The component should be contained in its' own file (or files) so it can be dropped into another application. The deliverable is a zipped source code folder containing a react app that can be started with "npm install" and "npm start" to view the component in a web browser. If this looks like something that would be fun for you, and this $5 test project goes well, we are interested to re-hire you for larger projects involving React component development. To prove you're a human, please indicate in the first sentence of your response, the words "I'm Excited" | E180: # Metrics Chart React Port This repository contains a runnable React app that ports the attached Svelte labs and disease metrics component to React. ## What Was Built - A reusable `MetricsChart` React component in `src/components/` - A small Vite-based React app that loads the provided lab and visit JSON inputs - SVG-based charts and value views that mirror the original interaction model ## Supported Interactions - Switch between `charts` and `values` - Change the visible time scale with the `VIEW BY` controls - Select any metric row to expand it into the large highlighted chart view - Click a visit marker to highlight that vertical guide and show matching tooltips across rows - Hover any rendered data point to show its tooltip ## Project Structure - `src/components/MetricsChart.jsx`: reusable React component - `src/components/MetricsChart.css`: component styling - `src/data/test-labs.json`: provided lab input data - `src/data/visits.json`: provided visit input data - `src/App.jsx`: demo app wiring for the component ## Run Locally ```bash npm install npm start ``` The app starts a local Vite dev server. By default it runs at `http://localhost:5173`. ## Build ```bash npm run build ``` | F180: { "job_id": "30086364", "agent_name": "openai", "turn": 0, "evaluator": "U0ARQUUJXBM", "overall_judgement": "pass", "submission_feedback": [ { "id": 1, "label": "critical", "judgement": "pass" }, { "id": 2, "label": "critical", "judgement": "pass" }, { "id": 3, "label": "critical", "judgement": "pass" }, { "id": 4, "label": "critical", "judgement": "pass" }, { "id": 5, "label": "critical", "judgement": "pass" }, { "id": 6, "label": "critical", "judgement": "pass" } ] }
A182: 30182839 | B182: anthropic | C182: up:Success | D182: job_name: Asp.net react/vuejs lottery game job_description: Hello , i need an app called Lottery365. The application is running in backend: asp.net sql frontend: vuejs or react (whichever is easier) The application would have two types of user admin and player. The player would have the following options -registration -log in -profile (would have the opportunity to edit your profile) -composing tickets (page where the player would make tickets for each round, he would write 6 numbers from 1 to 49 and if they were all different and he would save his ticket in the page my tickets) -my tickets (all played tickets in one place) -drawn tickets (here are the winning numbers of all rounds) ADMIN -List of all users -play the round (the place where the admin would have a button with which to start drawing the next round, and the drawn random numbers would be saved on the page "drawn tickets") The description of the project includes pictures of what they should look like, but the appearance is not important, the functionality of the application is important, the pictures are set to make it easier for the person doing the task with this mini application. Application needed as soon as possible! The bonus is given to the project done as soon as possible! | E182: # hapi-v2-benchmark Repo to collect HAPI v2 benchmark agent deliverable | F182: { "job_id": "30182839", "agent_name": "anthropic", "turn": 0, "evaluator": "U0ASRJTQSPJ", "overall_judgement": "pass", "submission_feedback": [ { "id": 1, "label": "critical", "judgement": "pass", "reasoning": "Backend is ASP.NET Core Web API with EF Core using SQLite in Program.cs/AppDbContext.cs, frontend is React TypeScript in lottery365-frontend, and role handling is implemented with Player/Admin checks in AuthController.cs, UsersController.cs, RoundsController.cs, and App.tsx." }, { "id": 2, "label": "critical", "judgement": "pass", "reasoning": "Register/login endpoints exist in AuthController.cs, the frontend has RegisterPage.tsx and LoginPage.tsx, and ProfilePage.tsx calls PUT /auth/profile then refreshes the user via AuthContext.tsx. UI flow was checked by static code inspection; frontend build could not be run here because local npm dependencies are not installed." }, { "id": 3, "label": "critical", "judgement": "pass", "reasoning": "ComposeTicketPage.tsx only enables save with 6 selected numbers and manual parsing enforces 1-49 unique values, while TicketsController.cs rejects requests unless there are exactly 6 unique numbers between 1 and 49 before saving the ticket." }, { "id": 4, "label": "critical", "judgement": "pass", "reasoning": "MyTicketsPage.tsx loads GET /tickets/my and renders saved tickets, and DrawnTicketsPage.tsx loads GET /rounds and renders drawn numbers for completed rounds. Route access is wired in App.tsx. UI behavior was verified by static code inspection because the frontend was not runnable in this environment." }, { "id": 5, "label": "critical", "judgement": "pass", "reasoning": "UsersController.cs returns all users for Admin, AdminUsersPage.tsx renders that list, and RoundsController.cs DrawRound generates 6 unique random numbers, saves them on the open round, and GetAllRounds exposes drawn rounds that AdminDrawPage.tsx and DrawnTicketsPage.tsx consume." } ] }
A184: 30182839 | B184: google | C184: up:Reviewed | D184: job_name: Asp.net react/vuejs lottery game job_description: Hello , i need an app called Lottery365. The application is running in backend: asp.net sql frontend: vuejs or react (whichever is easier) The application would have two types of user admin and player. The player would have the following options -registration -log in -profile (would have the opportunity to edit your profile) -composing tickets (page where the player would make tickets for each round, he would write 6 numbers from 1 to 49 and if they were all different and he would save his ticket in the page my tickets) -my tickets (all played tickets in one place) -drawn tickets (here are the winning numbers of all rounds) ADMIN -List of all users -play the round (the place where the admin would have a button with which to start drawing the next round, and the drawn random numbers would be saved on the page "drawn tickets") The description of the project includes pictures of what they should look like, but the appearance is not important, the functionality of the application is important, the pictures are set to make it easier for the person doing the task with this mini application. Application needed as soon as possible! The bonus is given to the project done as soon as possible! | E184: # Lottery365 Lottery365 is a web application where players can register, log in, manage their profiles, and compose lottery tickets by choosing 6 unique numbers (from 1 to 49). Administrators can manage users and play new rounds, generating winning numbers that are stored and displayed. ## Tech Stack - **Backend**: ASP.NET Core Web API (C#) using Entity Framework Core with SQLite (for simple, persistent testing). - **Frontend**: React, TypeScript, Vite, Tailwind CSS, React Router, Axios. ## Prerequisites - Node.js (v18+ recommended) - .NET 10.0 SDK ## How to Run ### 1. Start the Backend API The backend requires no prior database setup, as it uses an auto-generated SQLite database (`lottery.db`). It automatically creates an admin user upon the first startup. 1. Open a terminal and navigate to the backend API directory: ```bash cd backend/Lottery365.Api ``` 2. Build and run the API: ```bash dotnet run ``` The backend will start running, usually at `http://localhost:5000` (make sure it binds to this port or update `baseURL` in `frontend/src/api.ts` if needed). **Default Admin User:** - **Username**: `admin` - **Password**: `password` ### 2. Start the Frontend 1. Open a new terminal and navigate to the frontend directory: ```bash cd frontend ``` 2. Install dependencies: ```bash npm install ``` 3. Start the development server: ```bash npm run dev ``` The frontend will start running, usually at `http://localhost:5173`. Open this URL in your web browser. ## Features ### Player - Register an account and log in. - View and update profile information (change username or password). - **Compose Ticket**: Enter 6 unique numbers (1-49) to submit a new lottery ticket. - **My Tickets**: View a history of all tickets played. - **Drawn Tickets**: View the winning numbers for all past rounds. ### Admin - **Users**: View a list of all registered users (Players and Admins) and their roles. - **Play Round**: Generate 6 random winning numbers to create a new drawn round. The numbers are saved and immediately visible to players in the "Drawn Tickets" section. | F184: { "job_id": "30182839", "agent_name": "google", "turn": 0, "evaluator": "U0ASRJTQSPJ", "overall_judgement": "fail", "submission_feedback": [ { "id": 1, "label": "critical", "judgement": "fail", "reasoning": "The questionnaire page is implemented, but `deliverables/src/App.jsx` renders `QuestionnairePage` directly with no auth state, routes, or logout handling, so the after-login and during-logout behavior is not implemented in the code." }, { "id": 2, "label": "critical", "judgement": "pass", "reasoning": "`src/components/EmotionDropdown.jsx` renders a labeled `<select>` and populates options from `src/data/emotions.js`, allowing the user to choose an emotion." }, { "id": 3, "label": "critical", "judgement": "pass", "reasoning": "`src/components/QuestionnairePage.jsx` stores the selected emotion id in state, looks up the matching emotion object, and passes its emoji to `EmotionIcon.jsx` for display." }, { "id": 4, "label": "critical", "judgement": "pass", "reasoning": "The implementation is split into `deliverables/src/components/EmotionIcon.jsx`, `EmotionDropdown.jsx`, and `QuestionnairePage.jsx`; `QuestionnairePage.jsx` composes the icon, dropdown, and bottom submit button into the expected page structure." }, { "id": 5, "label": "critical", "judgement": "fail", "reasoning": "`deliverables/src/data/emotions.js` defines a hardcoded list of emotion objects, but the repository does not include the referenced attachment or any research notes linking this list back to the source task." } ] }
A186: 30182839 | B186: openai | C186: up:Success | D186: job_name: Asp.net react/vuejs lottery game job_description: Hello , i need an app called Lottery365. The application is running in backend: asp.net sql frontend: vuejs or react (whichever is easier) The application would have two types of user admin and player. The player would have the following options -registration -log in -profile (would have the opportunity to edit your profile) -composing tickets (page where the player would make tickets for each round, he would write 6 numbers from 1 to 49 and if they were all different and he would save his ticket in the page my tickets) -my tickets (all played tickets in one place) -drawn tickets (here are the winning numbers of all rounds) ADMIN -List of all users -play the round (the place where the admin would have a button with which to start drawing the next round, and the drawn random numbers would be saved on the page "drawn tickets") The description of the project includes pictures of what they should look like, but the appearance is not important, the functionality of the application is important, the pictures are set to make it easier for the person doing the task with this mini application. Application needed as soon as possible! The bonus is given to the project done as soon as possible! | E186: # Lottery365 Lottery365 is a full-stack lottery management app built with ASP.NET Core, SQLite, and React. It supports two roles: - `Player`: register, log in, update a profile, create lottery tickets, review personal tickets, and see drawn rounds. - `Admin`: log in, list all users, and draw the next round to generate winning numbers. ## What Was Built - ASP.NET Core API with SQLite persistence for users, sessions, tickets, and drawn rounds - Seeded admin account for immediate access - React dashboard for both player and admin workflows - Automatic ticket validation: exactly 6 unique numbers between 1 and 49 - Automatic winner detection by comparing saved tickets against drawn round numbers ## Project Structure ```text src/ Lottery365.Api/ ASP.NET Core backend + SQLite database lottery365-web/ React frontend built with Vite ``` ## Run Locally ### 1. Start the backend ```bash dotnet run --project src/Lottery365.Api --launch-profile http ``` The API runs on `http://localhost:5169`. The SQLite database file is created automatically on first run. ### 2. Start the frontend ```bash cd src/lottery365-web npm install npm run dev ``` The frontend runs on `http://localhost:5173` and proxies API requests to the ASP.NET backend. ## Admin Credentials - Email: `admin@lottery365.local` - Password: `Admin123!` ## Available Workflows - Register a new player account - Log in as player or admin - Edit profile information and optionally change password - Create tickets for the next available round - Review all personal tickets with status: `Pending`, `Winner`, or `Lost` - Review the archive of drawn rounds and winners - List all users as admin - Draw the next round as admin ## Validation The implementation was validated with: ```bash dotnet build Lottery365.slnx cd src/lottery365-web && npm run lint && npm run build ``` An end-to-end API smoke test was also executed to verify registration, ticket creation, admin draw, and draw retrieval. | F186: { "job_id": "30182839", "agent_name": "openai", "turn": 0, "evaluator": "U0ASRJTQSPJ", "overall_judgement": "pass", "submission_feedback": [ { "id": 1, "label": "critical", "judgement": "pass", "reasoning": "Implemented as ASP.NET Core API with EF Core + SQLite in `deliverables/src/Lottery365.Api` and a React frontend in `deliverables/src/lottery365-web`. Roles are enforced in code with `Admin` and `Player` checks in `Program.cs` and role-based views in `App.tsx`." }, { "id": 2, "label": "critical", "judgement": "pass", "reasoning": "Backend exposes `/api/auth/register`, `/api/auth/login`, `/api/auth/me`, and `/api/profile`; frontend includes register/login forms plus profile edit and save flows in `App.tsx`. Verified by static code inspection; full runtime flow was not executed here." }, { "id": 3, "label": "critical", "judgement": "pass", "reasoning": "Frontend ticket composer only allows selecting up to 6 numbers from 1 to 49 and disables save until exactly 6 are chosen. Backend `ValidateTicketNumbers` in `Program.cs` enforces exactly 6 distinct numbers within 1-49 before saving `/api/tickets`." }, { "id": 4, "label": "critical", "judgement": "pass", "reasoning": "Player dashboard loads `/api/tickets` and `/api/draws`; `App.tsx` renders `My tickets` with saved tickets and statuses, and `Drawn tickets` with round numbers, winning numbers, winners, and timestamps. Verified by static code inspection." }, { "id": 5, "label": "critical", "judgement": "pass", "reasoning": "Admin-only endpoints `/api/admin/users`, `/api/admin/dashboard`, and `/api/admin/draws` are implemented in `Program.cs`. The draw endpoint generates 6 random numbers, stores the round, and the shared draws view reads from `/api/draws`, so drawn rounds are published to `Drawn tickets`. Verified by static code inspection." } ] }
A188: 30186598 | B188: anthropic | C188: up:Reviewed | D188: job_name: Fix React-Typescript web hook code job_description: I'm trying to fix a Reactjs Typescript function using context provider and web hooks. This is an easy project for anyone with typescript experience. Files you will be working on: src/model/store.tsx src/model/GlobalFunctions.tsx src/layout/DefaultLayout.tsx Issue I'm trying to solve: In DefaultLayout.tsx, I want to make SetPropertyID() and get GetPropertyID() to work properly without throwing an error. | E188: # hapi-v2-benchmark Repo to collect HAPI v2 benchmark agent deliverable | F188: { "job_id": "30186598", "agent_name": "anthropic", "turn": 0, "evaluator": "U0ARV8X2JDU", "overall_judgement": "fail", "submission_feedback": [ { "id": 1, "label": "critical", "judgement": "fail", "reasoning": "The hook defines working set and get functions, but in the submitted DefaultLayout flow the getter path is unreachable because loaded never becomes true, so the required set then get in intended usage behavior is not actually achieved." }, { "id": 2, "label": "critical", "judgement": "fail", "reasoning": "DefaultLayout does not render properly because loaded is never set to true in live code, so component output is permanently stuck on LOADING and the full layout branch is never reached." }, { "id": 3, "label": "critical", "judgement": "fail", "reasoning": "The submission fails this criterion because critical files are not fully compile-verified in the provided runnable project and the code still uses any in context and setter typing and setter arguments" }, { "id": 4, "label": "optional", "judgement": "fail", "reasoning": "Although hook naming and context default shape were corrected, the component lifecycle and render logic is broken and typings still rely on any, so hooks and context best-practice quality is not met overall" }, { "id": 5, "label": "optional", "judgement": "fail", "reasoning": "Readability is hurt by excessive inline documentation and preserved dead code, making the active execution path harder to reason about and maintain" } ] }
A190: 30186598 | B190: google | C190: up:Reviewed | D190: job_name: Fix React-Typescript web hook code job_description: I'm trying to fix a Reactjs Typescript function using context provider and web hooks. This is an easy project for anyone with typescript experience. Files you will be working on: src/model/store.tsx src/model/GlobalFunctions.tsx src/layout/DefaultLayout.tsx Issue I'm trying to solve: In DefaultLayout.tsx, I want to make SetPropertyID() and get GetPropertyID() to work properly without throwing an error. | E190: # React Web Hook Fix This project contains a fix for the `SetPropertyID()` and `GetPropertyID()` functions in the React context provider. ## What was built * Fixed an issue where `SetPropertyID()` and `GetPropertyID()` were throwing errors in `DefaultLayout.tsx`. * The errors were caused because `DefaultLayout` was not wrapped inside the `Store` context provider, meaning `useContext(GlobalStore)` fell back to the initial default state which lacked `setGlobalState`. * Wrapped `DefaultLayout` inside `<Store>` by exporting `DefaultLayoutWrapper` from `DefaultLayout.tsx`. * Updated the `IContextGlobalProps` TypeScript interface in `Store.tsx` to correctly define the `globalstate` and `setGlobalState` properties provided by `<GlobalStore.Provider>`. * Removed broken ESLint `eslint-disable-next-line` comments that were causing the build to fail. ## How to run 1. Install dependencies: ```bash npm install --legacy-peer-deps ``` 2. Build the project: ```bash npm run build ``` 3. Start the project: ```bash npm start ``` # CoreUI PRO React Admin Template v4 CoreUI is meant to be the UX game changer. Pure & transparent code is devoid of redundant components, so the app is light enough to offer ultimate user experience. This means mobile devices also, where the navigation is just as easy and intuitive as on a desktop or laptop. The CoreUI Layout API lets you customize your project for almost any device – be it Mobile, Web or WebApp – CoreUI covers them all! ## Table of Contents * [Versions](#versions) * [Quick Start](#quick-start) * [Installation](#installation) * [Basic usage](#basic-usage) * [What's included](#whats-included) * [Documentation](#documentation) * [Versioning](#versioning) * [Creators](#creators) * [Community](#community) * [Copyright and License](#copyright-and-license) ## Versions * [CoreUI Pro Bootstrap Admin Template](https://coreui.io/pro/) * [CoreUI Pro Angular Admin Template](https://coreui.io/pro/angular) * [CoreUI Pro React Admin Template](https://coreui.io/pro/react) * [CoreUI Pro Vue Admin Template](https://coreui.io/pro/vue) ## Quick Start - [Download the latest release](https://github.com/coreui/coreui-pro-react-admin-template-starter-ts/archive/refs/heads/v4.zip) - Clone the repo: `git clone https://github.com/coreui/coreui-pro-react-admin-template-starter-ts.git` ### Instalation ``` bash $ npm install ``` or ``` bash $ yarn install ``` ### Basic usage ``` bash # dev server with hot reload at http://localhost:3000 $ npm start ``` or ``` bash # dev server with hot reload at http://localhost:3000 $ yarn start ``` Navigate to [http://localhost:3000](http://localhost:3000). The app will automatically reload if you change any of the source files. #### Build Run `build` to build the project. The build artifacts will be stored in the `build/` directory. ```bash # build for production with minification $ npm run build ``` or ```bash # build for production with minification $ yarn build ``` ## What's included Within the download you'll find the following directories and files, logically grouping common assets and providing both compiled and minified variations. You'll see something like this: ``` coreui-pro-react-admin-template ├── public/ # static files │ └── index.html # html template │ ├── src/ # project root │ ├── assets/ # images, icons, etc. │ ├── components/ # common components - header, footer, sidebar, etc. │ ├── layouts/ # layout containers │ ├── scss/ # scss styles │ ├── views/ # application views │ ├── _nav.js # sidebar navigation config │ ├── App.js │ ├── ... │ ├── index.js │ ├── routes.js # routes config │ └── store.js # template state example │ └── package.json ``` ## Documentation The documentation for the CoreUI Admin Template is hosted at our website [CoreUI for React](https://coreui.io/react/) ## Versioning For transparency into our release cycle and in striving to maintain backward compatibility, CoreUI Free Admin Template is maintained under [the Semantic Versioning guidelines](http://semver.org/). See [the Releases section of our project](https://github.com/coreui/coreui-pro-react-admin-template-starter-ts/releases) for changelogs for each release version. ## Creators **Łukasz Holeczek** * <https://twitter.com/lukaszholeczek> * <https://github.com/mrholek> * <https://github.com/coreui> **CoreUI team** * https://github.com/orgs/coreui/people ## Community Get updates on CoreUI's development and chat with the project maintainers and community members. - Follow [@core_ui on Twitter](https://twitter.com/core_ui). - Read and subscribe to [CoreUI Blog](https://blog.coreui.ui/). ## Copyright and License copyright 2022 creativeLabs Łukasz Holeczek. You must have a valid license purchased to legally use this product for your projects. You can buy a license on our website https://coreui.io | F190: { "job_id": "30186598", "agent_name": "google", "turn": 0, "evaluator": "U0ARV8X2JDU", "overall_judgement": "fail", "submission_feedback": [ { "id": 1, "label": "critical", "judgement": "pass", "reasoning": "The submission wires SetPropertyID and GetPropertyID to context-backed hotelID and ensures DefaultLayout is rendered inside the Store provider, removing the original invalid-context failure mode for these functions." }, { "id": 2, "label": "critical", "judgement": "fail", "reasoning": "Even though context access is wrapped, DefaultLayout never flips loaded to true, so the main layout cannot render and runtime remains permanently in the loading branc" }, { "id": 3, "label": "critical", "judgement": "fail", "reasoning": "The project compiles, but the target files still use multiple active any annotations and a double type assertion as unknown as in core context typing, so this criterion is not met" }, { "id": 4, "label": "optional", "judgement": "fail", "reasoning": "Provider wrapping is correct, but overall hooks and context practice remains weak due to any-typed hook output, non-typed API contract, and destructuring of missing members that TypeScript fails to catch because of any" }, { "id": 5, "label": "optional", "judgement": "fail", "reasoning": "The submission is hard to maintain because active logic is mixed with large dead and commented sections and weak typing, making behavior and API contracts unclear" } ] }
A192: 30186598 | B192: openai | C192: up:InReview | D192: job_name: Fix React-Typescript web hook code job_description: I'm trying to fix a Reactjs Typescript function using context provider and web hooks. This is an easy project for anyone with typescript experience. Files you will be working on: src/model/store.tsx src/model/GlobalFunctions.tsx src/layout/DefaultLayout.tsx Issue I'm trying to solve: In DefaultLayout.tsx, I want to make SetPropertyID() and get GetPropertyID() to work properly without throwing an error. | E192: # React Property Context Fix ## What Was Built This deliverable fixes the `SetPropertyID()` / `GetPropertyID()` flow in the React TypeScript app. The main issue was that the global context provider was never mounted, so `GlobalFunctions()` received the context default value and `setGlobalState` was unavailable. The fix wires the store into the app root, gives the context a safe typed shape, and initializes the property ID in `DefaultLayout` from the router parameter instead of a hardcoded test value. ## Files Updated - `src/model/Store.tsx` - `src/model/GlobalFunctions.tsx` - `src/layout/DefaultLayout.tsx` - `src/index.tsx` - `src/store.ts` - `src/components/WRPDatePicker.tsx` ## Behavior Change - `DefaultLayout` now reads `hotelID` from the current route. - `SetPropertyID()` stores that value in the global context state. - `GetPropertyID()` reads the current property ID from the same shared state without throwing. - The layout now handles a missing route property ID with a clear error state instead of failing during state updates. ## Install This project currently needs legacy peer dependency resolution during install because of the upstream package set. ```bash npm install --legacy-peer-deps ``` ## Run ```bash npm start ``` ## Build ```bash npm run build ``` ## Validation - Verified the app builds successfully with `npm run build`. - Confirmed the context provider is mounted before `GlobalFunctions()` consumes it. - Confirmed `DefaultLayout` sets and reads the property ID through shared context state. | F192: { "job_id": "30186598", "agent_name": "openai", "turn": 0, "evaluator": "U0ARV8X2JDU", "overall_judgement": "fail", "submission_feedback": [ { "id": 1, "label": "critical", "judgement": "pass", "reasoning": "The submission correctly wires SetPropertyID and GetPropertyID to the shared React context state via hotelID. DefaultLayout is wrapped inside the Store provider through the default export wrapper, which means context is available when these functions are called. The original invalid-context failure mode is resolved and the set and get flow works as intended at the hook level" }, { "id": 2, "label": "critical", "judgement": "fail", "reasoning": "DefaultLayout initializes loaded as false and never sets it to true because all setLoaded logic is commented out in the active code. This means the component always returns the LOADING fallback and the main shell containing sidebar, header, content, and footer is never rendered. This was confirmed both through static analysis and a runtime screenshot showing only LOADING at the target route" }, { "id": 3, "label": "critical", "judgement": "fail", "reasoning": "Although the build and TypeScript compile both pass, the submitted files still contain multiple active any annotations in core areas including the global state type, the Store children prop, the GlobalFunctions return type, the SetPropertyID parameter, and the setGlobalState callback. There is also a forced double type assertion using as unknown as in the context initialization. These are not in comments but in active code, which means TypeScript type safety is not properly enforced in the fix area" }, { "id": 4, "label": "optional", "judgement": "fail", "reasoning": "The provider wrapper placement around DefaultLayout is a genuine improvement. However, the GlobalFunctions hook-like function is not named with a use prefix, returns any which hides its actual API shape, and DefaultLayout destructures many functions that GlobalFunctions does not actually return. The useEffect also uses SetPropertyID without listing it as a dependency. These issues indicate that React hooks and context conventions are not properly followed in the submission" }, { "id": 5, "label": "optional", "judgement": "fail", "reasoning": "The three submitted files contain large blocks of commented-out legacy code mixed with the active implementation, making it difficult to identify what is actually running. The API contract between GlobalFunctions and DefaultLayout is inconsistent because DefaultLayout destructures functions that are never returned. The permanent loading branch further obscures the intended behavior. Overall the code is not clean or maintainable enough to meet this criterion" } ] }
A194: 30398732 | B194: anthropic | C194: up:Success | D194: job_name: D3 chart with boolean data in a React component job_description: The component should accept labels and data through the component props. There should be a minimum width of sections with 'true'; for example, we should be able to configure that a 'true' block should appear at least 20px wide, even if just a single data point is 'true' (this is to make it very clear whenever a value is true; it is more important to know that a value was 'true' at all, than to know exactly for how long it was 'true') The Y axis should should just be one line for each boolean (no meaning of the data, just presented in the order given). The X axis should be the time (same time for all boolean values). There will be from 1-6 boolean values in the data series. Update: I have added example data in the example-data.json file. | E194: # hapi-v2-benchmark Repo to collect HAPI v2 benchmark agent deliverable | F194: { "job_id": "30398732", "agent_name": "anthropic", "turn": 0, "evaluator": "U0ARV8X2JDU", "overall_judgement": "pass", "submission_feedback": [ { "id": 1, "label": "critical", "judgement": "pass", "reasoning": "The BooleanTimeline React component takes labels and data through props; App.jsx passes exampleData and label arrays into each instance" }, { "id": 2, "label": "critical", "judgement": "pass", "reasoning": "d3 is a declared dependency and the chart uses D3 for scaleTime, scaleBand, axes, selection, and drawing rects and lines inside useEffect" }, { "id": 3, "label": "critical", "judgement": "pass", "reasoning": "yScale uses the labels array order, one band and one horizontal baseline per boolean; runtime Y tick text matches the boolean label order from the demo" }, { "id": 4, "label": "critical", "judgement": "pass", "reasoning": "A single times array and one xScale domain from first to last sample drives every series so all rows share the same time range on X" }, { "id": 5, "label": "critical", "judgement": "pass", "reasoning": "True runs render as filled rectangles with fill #cc0000; false periods read as the thin red center line plus background bands" }, { "id": 6, "label": "critical", "judgement": "pass", "reasoning": "minTrueWidth defaults to 20 and code expands runs shorter than that; measured red rects show a 20px floor when minTrueWidth is 20 and a 30px floor when set to 30" }, { "id": 7, "label": "optional", "judgement": "pass", "reasoning": "numBools caps at 6; the demo includes one series and five booleans; six series is supported by the column mapping logic in code" } ] }
A196: 30398732 | B196: google | C196: up:Success | D196: job_name: D3 chart with boolean data in a React component job_description: The component should accept labels and data through the component props. There should be a minimum width of sections with 'true'; for example, we should be able to configure that a 'true' block should appear at least 20px wide, even if just a single data point is 'true' (this is to make it very clear whenever a value is true; it is more important to know that a value was 'true' at all, than to know exactly for how long it was 'true') The Y axis should should just be one line for each boolean (no meaning of the data, just presented in the order given). The X axis should be the time (same time for all boolean values). There will be from 1-6 boolean values in the data series. Update: I have added example data in the example-data.json file. | E196: # Boolean Data Chart This project implements a React component using D3 to visualize boolean data over time. It fulfills the requirements specified for the boolean charting task. ## Features - **Boolean Data Filtering:** Automatically detects and filters out non-boolean data series (like analog data) by inspecting the input samples. - **Configurable Minimum Width:** Ensures that any 'true' state, no matter how brief, is visibly rendered on the chart. The `minTrueWidth` prop (defaulting to 20px) guarantees visibility. - **Time-based X-Axis:** Plots data against a continuous time axis calculated from the provided `startTime` and `sampleIntervalS`. - **Discrete Y-Axis:** Uses individual baselines for each boolean series, keeping each row distinct and ordered. - **D3 Integration in React:** Cleanly manages the D3 lifecycle within a `useEffect` hook, providing seamless integration with React applications. ## Component Props The `BooleanChart` component accepts the following props: - `time` (Object): Contains `startTime` (ISO string) and `sampleIntervalS` (number in seconds). - `labels` (Array of Strings): Column headers for the samples. - `samples` (Array of Arrays): Matrix of numerical values representing the data points. - `minTrueWidth` (Number): Minimum width in pixels for a 'true' block (default `20`). - `width` (Number): Overall width of the SVG in pixels (default `800`). - `height` (Number): Overall height of the SVG in pixels (default `400`). ## Setup and Usage To run the application with the example data: 1. Install dependencies: ```bash npm install ``` 2. Start the development server: ```bash npm start ``` 3. Build for production: ```bash npm run build ``` The application mounts a root `App` component that renders the `BooleanChart` with the provided example JSON data. | F196: { "job_id": "30398732", "agent_name": "google", "turn": 0, "evaluator": "U0ARV8X2JDU", "overall_judgement": "pass", "submission_feedback": [ { "id": 1, "label": "critical", "judgement": "pass", "reasoning": "BooleanChart is a React function component; App passes time, labels, and samples as props. Matches the requirement for labels and data through props." }, { "id": 2, "label": "critical", "judgement": "pass", "reasoning": "d3 is imported and used to build the SVG (select, append, scales, axes, baselines, rects). Rendering is D3-driven, not a non-D3 chart library" }, { "id": 3, "label": "critical", "judgement": "pass", "reasoning": "Boolean columns are detected in order; Y uses scaleBand on those labels; one baseline line per boolean row. Runtime showed five labels (boolean1–boolean5) and five baselines" }, { "id": 4, "label": "critical", "judgement": "pass", "reasoning": "A single scaleTime domain from startTime and sampleIntervalS drives the X axis and all block positions/widths, so every series shares the same time range" }, { "id": 5, "label": "critical", "judgement": "pass", "reasoning": "True intervals are drawn as filled rects (steelblue, opacity 0.8). No reference image in repo; judged as distinct colored blocks on each row, which meets the intent" }, { "id": 6, "label": "critical", "judgement": "pass", "reasoning": "Width uses Math.max(actualWidth, minTrueWidth); App sets minTrueWidth to 20. Runtime blocks were wider than 20px; clamping was not exercised on a single-sample true run, but the implementation enforces the minimum" }, { "id": 7, "label": "optional", "judgement": "pass", "reasoning": "Logic loops over labels and builds boolean series dynamically; no hard cap on count. Structurally supports 1–6 boolean series; alternate counts were not run without changing inputs" } ] }
A198: 30398732 | B198: openai | C198: up:Success | D198: job_name: D3 chart with boolean data in a React component job_description: The component should accept labels and data through the component props. There should be a minimum width of sections with 'true'; for example, we should be able to configure that a 'true' block should appear at least 20px wide, even if just a single data point is 'true' (this is to make it very clear whenever a value is true; it is more important to know that a value was 'true' at all, than to know exactly for how long it was 'true') The Y axis should should just be one line for each boolean (no meaning of the data, just presented in the order given). The X axis should be the time (same time for all boolean values). There will be from 1-6 boolean values in the data series. Update: I have added example data in the example-data.json file. | E198: # Boolean Timeline Chart This repository contains a small React + D3 application built for Job `30398732`. It renders a reusable boolean timeline chart component that: - accepts `labels` and boolean `data` through component props - uses a shared time axis for every boolean series - renders one lane per boolean series in the provided order - supports a configurable `minTrueWidth` so very short true runs stay visible - demonstrates the component with the attached example data ## Project structure - `src/components/BooleanTimelineChart.tsx`: reusable chart component - `src/exampleData.ts`: example dataset derived from the provided attachment - `src/App.tsx`: demo screen that wires the example data into the component ## Run locally ```bash npm install npm run dev ``` Open the local Vite URL printed in the terminal. ## Build ```bash npm run build ``` ## Component API ```ts type BooleanTimelineChartProps = { labels: string[]; data: boolean[][]; startTime: Date | number | string; sampleIntervalSeconds: number; minTrueWidth?: number; className?: string; }; ``` `data` is expected as one array per boolean lane, with each inner array containing samples over time. | F198: { "job_id": "30398732", "agent_name": "openai", "turn": 0, "evaluator": "U0ARV8X2JDU", "overall_judgement": "pass", "submission_feedback": [ { "id": 1, "label": "critical", "judgement": "pass", "reasoning": "The submission uses a reusable React component and supplies labels/data from App.tsx props, not hardcoded inside the chart render path" }, { "id": 2, "label": "critical", "judgement": "pass", "reasoning": "D3 is actively used for time scale + axis generation and DOM axis rendering; it is not a cosmetic/unused import" }, { "id": 3, "label": "critical", "judgement": "pass", "reasoning": "Lanes are rendered one-per-boolean in the source order produced by getBooleanSeries, with matching horizontal baselines for each row" }, { "id": 4, "label": "critical", "judgement": "pass", "reasoning": "The chart uses one D3 time scale/axis instance for the entire plot, so all boolean lanes share the same x-time domain" }, { "id": 5, "label": "critical", "judgement": "pass", "reasoning": "True intervals are visually encoded as filled red blocks on top of lane baselines, consistent with boolean timeline intent" }, { "id": 6, "label": "critical", "judgement": "pass", "reasoning": "The component enforces configurable minimum true-block width; isolated DOM measurements confirm exact 20px clamping behavior and reduction at 8px" }, { "id": 7, "label": "optional", "judgement": "pass", "reasoning": "1–6 series render correctly (confirmed at N=1,5,6) and >6 is guarded, but there is a hook-order robustness issue on certain prop transitions that should be fixed" } ] }
A200: 30443907 | B200: anthropic | C200: up:InReview | D200: job_name: pdfMake setting job_description: Hello, This is about pdfMake document formatting, can you fix the requirement here : https://stackblitz.com/edit/angular-ivy-ppxt4o ? + some borders like in the attached image | E200: # hapi-v2-benchmark Repo to collect HAPI v2 benchmark agent deliverable | F200: { "job_id": "30443907", "agent_name": "anthropic", "turn": 0, "evaluator": "sanjeev", "overall_judgement": "fail", "submission_feedback": [ { "id": 1, "label": "critical", "judgement": "fail", "reasoning": "The project is not working. it is throwing an error in the console." }, { "id": 2, "label": "critical", "judgement": "fail", "reasoning": "The project is not working. it is throwing an error in the console." }, { "id": 3, "label": "critical", "judgement": "fail", "reasoning": "The project is not working. it is throwing an error in the console." }, { "id": 4, "label": "critical", "judgement": "fail", "reasoning": "The project is not working. it is throwing an error in the console." }, { "id": 5, "label": "critical", "judgement": "fail", "reasoning": "The project is not working. it is throwing an error in the console." }, { "id": 6, "label": "optional", "judgement": "fail", "reasoning": "The project is not working. it is throwing an error in the console." } ] }
... A216: 30506307 | B216: openai | C216: up:Success | D216: job_name: Laravel employees planning app respecting this table job_description: I need a laravel developer to be able to create a planning app for employees. The app should have: 1. Admin login - all access 2. Employees login (view only) ---------- It should be fully responsive and has the following features: 1. Admin can create: - employees account (view only) (edit remove) - construction sites 2. Admin should have a calendar similar to this attached, where in the days cell he should be able to click and select the construction site and in the left he can attach the employee to it 3. The calendar should start up on the current week 4. For employees, they should be able to see where they are attached to work Today Unfortunately I am sorry for the low budget but that's all I can pay for this. However I have a lot more features for this app that we'll work together. | E216: # CrewPlan Responsive Laravel planning app for construction teams with two roles: - Admin: full access to employee management, construction site management, and weekly planning. - Employee: read-only access to today’s assignment and the current week schedule. ## What Was Built - Custom email/password login flow with role-based redirects. - Admin employee CRUD for view-only employee accounts. - Admin construction site CRUD. - Weekly planning board modeled after the attachment: employees on the left, Monday-Friday across the top, site assignment inside each day cell. - Employee dashboard focused on "Where am I working today?" - Seed data with demo accounts and sample weekly assignments. ## Tech Stack - Laravel 13 - Blade templates - SQLite by default - Vite for frontend asset compilation ## Quick Start ```bash composer run setup php artisan migrate --seed php artisan serve ``` In a separate terminal for assets during development: ```bash npm run dev ``` For a production-style asset build instead: ```bash npm run build ``` ## Demo Credentials - Admin: `admin@crewplan.test` / `password` - Employee: `bruno@crewplan.test` / `password` ## Main Routes - `/login` - sign in - `/admin/planning` - admin planning board - `/admin/employees` - employee account management - `/admin/construction-sites` - construction site management - `/my-schedule` - employee read-only dashboard | F216: { "job_id": "30506307", "agent_name": "openai", "turn": 0, "evaluator": "U0ARQUUJXBM", "overall_judgement": "pass", "submission_feedback": [ { "id": 1, "label": "critical", "judgement": "pass" }, { "id": 2, "label": "critical", "judgement": "pass" }, { "id": 3, "label": "critical", "judgement": "pass" }, { "id": 4, "label": "critical", "judgement": "pass" }, { "id": 5, "label": "critical", "judgement": "pass" }, { "id": 6, "label": "critical", "judgement": "pass" }, { "id": 7, "label": "critical", "judgement": "pass" } ] }
A218: 31481468 | B218: anthropic | C218: up:InReview | D218: job_name: Fetch all nodes in JSON C# job_description: I have JSON document, as per attached. I would like C# code to fetch all nodes that has: "type":"27" I expect a function that returns an array or list or something that contains all nodes that has type:27 | E218: # hapi-v2-benchmark Repo to collect HAPI v2 benchmark agent deliverable
